Workbook

Sheet Synthèse
A1: DOSSIER COMPTABLE PAIE & CNAS 2026 — SARL D.P.R. COMPAGNY
A2: Arrêté au 01/10/2026 — période couverte : janvier à août 2026 — montants en DA.
A4: Établissement | B4: IMPORT | C4: TPM | D4: Total
A5: N° cotisant CNAS | B5: =Paramètres!B10 | C5: =Paramètres!B11
A6: Masse salariale soumise (R500) jan–août | B6: ='Paie IMPORT'!K19 | C6: ='Paie TPM'!K19 | D6: =B6+C6
A7: Retenues sécurité sociale (9 %) | B7: ='Paie IMPORT'!K21 | C7: ='Paie TPM'!K21 | D7: =B7+C7
A8: IRG retenu | B8: ='Paie IMPORT'!K25 | C8: ='Paie TPM'!K25 | D8: =B8+C8
A9: Net à payer | B9: ='Paie IMPORT'!K28 | C9: ='Paie TPM'!K28 | D9: =B9+C9
A10: Frais de mission | B10: ='Paie IMPORT'!K26 | C10: ='Paie TPM'!K26 | D10: =B10+C10
A11: Cotisations CNAS déclarées (pièces reçues) | B11: =SUMIFS('Rappro CNAS'!K5:K12,'Rappro CNAS'!B5:B12,"IMPORT*") | C11: =SUMIFS('Rappro CNAS'!K5:K12,'Rappro CNAS'!B5:B12,"TPM*") | D11: =B11+C11
A12: Cotisations CNAS calculées sur paie (hors mars IMPORT, T3 partiel) | B12: =SUMIFS('Rappro CNAS'!J5:J12,'Rappro CNAS'!B5:B12,"IMPORT*") | C12: =SUMIFS('Rappro CNAS'!J5:J12,'Rappro CNAS'!B5:B12,"TPM*") | D12: =B12+C12
A13: Effectif fin août | B13: ='Paie IMPORT'!J5 | C13: ='Paie TPM'!J5 | D13: =B13+C13
A15: Situation des déclarations CNAS
A16: Indicateur | B16: Nombre
A17: Déclarations attendues (jan–T3) | B17: =COUNTA('Rappro CNAS'!A5:A12)
A18: Déclarations conformes | B18: =COUNTIF('Rappro CNAS'!T5:T12,"Conforme")
A19: Déclarations avec écart | B19: =COUNTIF('Rappro CNAS'!T5:T12,"ÉCART")
A20: Déclarations à déposer / à fournir | B20: =COUNTIF('Rappro CNAS'!T5:T12,"À DÉPOSER*")
A22: Anomalies
A23: Priorité | B23: Nombre | C23: Ouvertes
A24: 1 — Critique | B24: =COUNTIF('Anomalies & actions'!B5:B40,1) | C24: =COUNTIFS('Anomalies & actions'!B5:B40,1,'Anomalies & actions'!I5:I40,"Ouvert")
A25: 2 — À corriger | B25: =COUNTIF('Anomalies & actions'!B5:B40,2) | C25: =COUNTIFS('Anomalies & actions'!B5:B40,2,'Anomalies & actions'!I5:I40,"Ouvert")
A26: 3 — À vérifier | B26: =COUNTIF('Anomalies & actions'!B5:B40,3) | C26: =COUNTIFS('Anomalies & actions'!B5:B40,3,'Anomalies & actions'!I5:I40,"Ouvert")
A28: Contrôles de cohérence
A29: Contrôle | B29: Résultat
A30: Journal équilibré (débit = crédit) | B30: =IF(ABS('Journal paie'!F142)<0.01,"OK","ERREUR")
A31: Paie IMPORT : gains = retenues (8 mois) | B31: =IF(ABS('Paie IMPORT'!K33)<0.01,"OK","ERREUR")
A32: Paie TPM : gains = retenues (8 mois) | B32: =IF(ABS('Paie TPM'!K33)<0.01,"OK","ERREUR")
A33: Paie IMPORT : éléments soumis hors assiette | B33: =IF(ABS('Paie IMPORT'!K37)<0.01,"OK","ÉCART (voir A03)")
A34: Balance 2024-2025 équilibrée | B34: =IF(AND(ABS('Balance 2024-2025'!C105)<0.01,ABS('Balance 2024-2025'!D105)<0.01),"OK","ERREUR")
A35: États : résultat = −(classes 6+7) et bilan bouclé | B35: =IF(AND(ABS('États 2024-2025'!C17)<0.01,ABS('États 2024-2025'!D17)<0.01,ABS('États 2024-2025'!C46)<0.01,ABS('États 2024-2025'!D46)<0.01),"OK","ERREUR")
A36: G50 IMPORT janv.–août : totaux et report de précompte | B36: =IF(AND(SUMPRODUCT(ABS('G50 2026'!B29:I29))<1,SUMPRODUCT(ABS('G50 2026'!C16:I16))<1),"OK","ÉCART")
A37: G50 TPM janv.–août : totaux | B37: =IF(SUMPRODUCT(ABS('G50 TPM 2026'!B20:I20))<1,"OK","ÉCART")
A38: Paie TPM : éléments soumis hors assiette | B38: =IF(ABS('Paie TPM'!K37)<0.01,"OK","ÉCART")
A39: Contenu du classeur
A40: Paramètres | B40: Taux, identifiants, plan de comptes
A41: Paie IMPORT / Paie TPM | B41: Récapitulatif mensuel par rubrique + contrôles
A42: Rappro CNAS | B42: Rapprochement paie ↔ chaque déclaration CNAS
A43: Journal paie | B43: Écritures comptables proposées (SCF)
A44: Balance comptes | B44: Cumul par compte et établissement
A45: Échéancier IRG-CNAS | B45: IRG mensuel à rapprocher des G50
A46: Anomalies & actions | B46: Constats, impact, actions, suivi
A47: Pièces | B47: Pièces reçues / manquantes
A48: G50 2026 | B48: Contrôle TVA / IRG / timbre / TA des G50 IMPORT janv.–août
A49: G50 TPM 2026 | B49: Contrôle des G50 TPM et location (janv.–août)
A50: Contrôle 2023 | B50: Journal 2023 vs à-nouveaux 2024 ; historique TVA TPM
A51: Clients & fournisseurs | B51: Soldes par tiers au 31/12/2025, catégories de risque, décision 2026
... A54: États 2024-2025 | B54: Compte de résultat et bilan simplifiés, indicateurs
A57: Légende : bleu = saisie depuis une pièce ; vert = lien vers une autre feuille ; noir = calcul ; fond jaune = à compléter.
A59: Exercices comptables
A60: Indicateur | B60: 2024 | C60: 2025 | D60: Variation
A61: Chiffre d'affaires | B61: ='États 2024-2025'!C5 | C61: ='États 2024-2025'!D5 | D61: =IF(B61=0,"",C61/B61-1)
A62: Charges de personnel | B62: ='États 2024-2025'!C10 | C62: ='États 2024-2025'!D10 | D62: =IF(B62=0,"",C62/B62-1)
A63: Résultat net | B63: ='États 2024-2025'!C16 | C63: ='États 2024-2025'!D16 | D63: =IF(B63=0,"",C63/B63-1)

Sheet Paramètres
A1: Paramètres et hypothèses
A2: Cellules en bleu sur fond jaune = hypothèses modifiables. Toutes les feuilles y renvoient.
A4: Paramètre | B4: Valeur | C4: Source / commentaire
A5: Taux CNAS régime général (R22) | B5: 0.345 | C5: Déclarations CNAS 2026 fournies (code R22)
A6: Taux FNPOS (R98) | B6: 0.005 | C6: Déclarations CNAS 2026 fournies (code R98)
A7: Part salariale sécurité sociale | B7: 0.09 | C7: Rubrique R510 des centralisateurs de paie (9 % du salaire de poste)
A8: Part patronale (= R22 + R98 − part salariale) | B8: =B5+B6-B7 | C8: Calculée — charge employeur compte 635
A9: Raison sociale | B9: SARL D.P.R. COMPAGNY | C9: Déclarations CNAS
A10: Établissement IMPORT — n° cotisant CNAS | B10: 06713395 46 | C10: VGE TIZI, CNE SEMAOUN, BEJAIA
A11: Établissement TPM — n° cotisant CNAS | B11: 06736613 53 | C11: TISSA, CNE DE SMAOUN, W. BEJAIA
A12: Agence CNAS | B12: 10600 — CNAS BEJAIA | C12: Déclarations CNAS
A13: Date d'arrêté du dossier | B13: 01/10/2026 | C13: Date de constitution
A15: Plan de comptes utilisé (SCF algérien)
A16: Compte | B16: Intitulé | C16: Contenu
A17: 631 | B17: Rémunérations du personnel | C17: Salaire de poste (R500) + prime de ponctualité (R540)
A18: 638 | B18: Autres charges de personnel | C18: Indemnités de panier (R522) et de transport (R532)
A19: 625 | B19: Déplacements, missions et réceptions | C19: Frais de mission (R670), à justifier par ordres de mission
A20: 635 | B20: Cotisations aux organismes sociaux | C20: Part patronale CNAS (26 % de l'assiette)
A21: 431 | B21: Organismes sociaux — CNAS | C21: Parts salariale + patronale à reverser ; salaire unique avancé (à valider)
A22: 442 | B22: État, impôts et taxes recouvrables sur tiers | C22: IRG retenu à la source (R660), à reverser via G50
A23: 421 | B23: Personnel, rémunérations dues | C23: Net à payer (R770)

Sheet Paie IMPORT
A1: Récapitulatif mensuel de la paie — IMPORT (centralisateurs 2026)
A2: Source : PAIE_2026_DPR_COMPANY_IMPORT.xlsx — montants en DA. Valeurs en bleu = saisies depuis les centralisateurs.
A4: Code | B4: Libellé | C4: Janv 2026 | D4: Févr 2026 | E4: Mars 2026 | F4: Avr 2026 | G4: Mai 2026 | H4: Juin 2026 | I4: Juil 2026 | J4: Août 2026 | K4: Cumul Jan–Août
A5: EFF | B5: Effectif (en-tête du centralisateur) | C5: 12 | D5: 12 | F5: 5 | G5: 5 | H5: 5 | I5: 5 | J5: 5
A6: R030 | B6: Salaire de base | C6: 446760 | D6: 446760 | F6: 242000 | G6: 242000 | H6: 242000 | I6: 215325 | J6: 215325 | K6: =SUM(C6:J6)
A7: R065 | B7: Heures d'absence (retenue) | C7: 12207.85 | D7: 185066.01 | H7: 48000 | I7: 15492.09 | J7: 36892.47 | K7: =SUM(C7:J7)
A8: R061 | B8: Jours reprise / congé (retenue) | I8: 194000 | K8: =SUM(C8:J8)
A9: R100 | B9: Congé | I9: 289141.68 | K9: =SUM(C9:J9)
A10: R112 | B10: Heures supp. 50 % | C10: 100947.33 | D10: 28662.09 | F10: 42370.04 | G10: 54187.96 | H10: 37779.96 | I10: 1494.83 | J10: 34373.73 | K10: =SUM(C10:J10)
A11: R122 | B11: Heures supp. 75 % | C11: 89206.9 | D11: 20483.47 | F11: 26451.42 | G11: 33519.37 | H11: 22111 | I11: 3444.87 | J11: 21594.57 | K11: =SUM(C11:J11)
A12: R261 | B12: I.E.P. | C12: 13842.47 | D12: 8092.77 | F12: 8130 | G12: 8130 | H12: 5250 | J12: 4228.39 | K12: =SUM(C12:J12)
A13: R281 | B13: Nuisance | C13: 61544.89 | D13: 39262.19 | F13: 37680 | G13: 37680 | H13: 30000 | I13: 583.29 | J13: 27013 | K13: =SUM(C13:J13)
A14: R291 | B14: Responsabilité | C14: 5 | D14: 1.14 | K14: =SUM(C14:J14)
A15: R301 | B15: P.R.I. | C15: 62673.03 | D15: 38872.02 | F15: 36780 | G15: 36780 | H15: 29100 | I15: 349.97 | J15: 26327.06 | K15: =SUM(C15:J15)
A16: R320 | B16: Prime de performance | C16: 55590 | D16: 21100 | F16: 17970 | G16: 23470 | H16: 15000 | I16: 9500 | J16: 15000 | K16: =SUM(C16:J16)
A17: STC | B17: Solde de tout compte (R546 / R040) | D17: 534308.14 | J17: 2237.4 | K17: =SUM(C17:J17)
A18: R540 | B18: Prime de ponctualité | C18: 17500 | D18: 8000 | F18: 7500 | G18: 7500 | H18: 5500 | I18: 3000 | J18: 3000 | K18: =SUM(C18:J18)
A19: R500 | B19: SALAIRE DE POSTE (assiette CNAS) | C19: 818361.77 | D19: 952475.81 | F19: 411381.46 | G19: 435767.33 | H19: 333240.96 | I19: 310347.55 | J19: 309206.68 | K19: =SUM(C19:J19)
A20: R500E | B20: Effectif cotisant (R500) | C20: 12 | D20: 12 | F20: 5 | G20: 5 | H20: 4 | I20: 5 | J20: 5
A21: R510 | B21: Retenue sécurité sociale 9 % | C21: 73652.56 | D21: 85722.83 | F21: 37024.34 | G21: 39219.06 | H21: 29991.69 | I21: 27931.28 | J21: 27828.6 | K21: =SUM(C21:J21)
A22: R522 | B22: Panier | C22: 36036 | D22: 19188 | F22: 13728 | G22: 13728 | H22: 10296 | I22: 936 | J22: 9516 | K22: =SUM(C22:J22)
A23: R532 | B23: Transport | C23: 20845.62 | D23: 11811.16 | F23: 8800 | G23: 8800 | H23: 6600 | I23: 601.74 | J23: 6102.95 | K23: =SUM(C23:J23)
A24: R650 | B24: Base imposable IRG | C24: 819090.83 | D24: 905752.15 | F24: 404385.13 | G24: 426576.27 | H24: 325645.27 | I24: 286954.01 | J24: 299997.03 | K24: =SUM(C24:J24)
A25: R660 | B25: Retenue IRG | C25: 132616.39 | D25: 162285.9 | F25: 72478 | G25: 79138 | H25: 59017.5 | I25: 42612.3 | J25: 49667.4 | K25: =SUM(C25:J25)
A26: R670 | B26: Frais de mission | C26: 67580 | D26: 14280 | F26: 7775 | G26: 3640 | H26: 3350 | I26: 4165 | K26: =SUM(C26:J26)
A27: R714 | B27: Salaire unique | C27: 1500 | D27: 1500 | F27: 2500 | G27: 2500 | H27: 2500 | I27: 2500 | J27: 2500 | K27: =SUM(C27:J27)
A28: R770 | B28: NET À PAYER | C28: 755554.44 | D28: 759246.24 | F28: 342182.12 | G28: 353578.27 | H28: 272477.77 | I28: 251006.71 | J28: 252829.63 | K28: =SUM(C28:J28)
A29: TGG | B29: Total général — gains | C29: 974031.24 | D29: 1192321 | F29: 451684.46 | G29: 471935.33 | H29: 409486.96 | I29: 531042.38 | J29: 367218.1 | K29: =SUM(C29:J29)
A30: TGR | B30: Total général — retenues | C30: 974031.24 | D30: 1192321 | F30: 451684.46 | G30: 471935.33 | H30: 409486.96 | I30: 531042.38 | J30: 367218.1 | K30: =SUM(C30:J30)
A32: CONTRÔLES (doivent être à zéro, sauf mention)
A33: C1 | B33: Équilibre : total gains − total retenues | C33: =C29-C30 | D33: =D29-D30 | E33: =E29-E30 | F33: =F29-F30 | G33: =G29-G30 | H33: =H29-H30 | I33: =I29-I30 | J33: =J29-J30 | K33: =SUM(C33:J33)
A34: C2 | B34: Équilibre comptable : R500+R540+R522+R532+R670+R714 − R510 − R660 − R770 | C34: =C19+C18+C22+C23+C26+C27-C21-C25-C28 | D34: =D19+D18+D22+D23+D26+D27-D21-D25-D28 | E34: =E19+E18+E22+E23+E26+E27-E21-E25-E28 | F34: =F19+F18+F22+F23+F26+F27-F21-F25-F28 | G34: =G19+G18+G22+G23+G26+G27-G21-G25-G28 | H34: =H19+H18+H22+H23+H26+H27-H21-H25-H28 | I34: =I19+I18+I22+I23+I26+I27-I21-I25-I28 | J34: =J19+J18+J22+J23+J26+J27-J21-J25-J28 | K34: =SUM(C34:J34)
A35: C3 | B35: Retenue SS − 9 % × salaire de poste (écart d'arrondi ≤ 0,02 admis) | C35: =C21-ROUND(C19*Paramètres!$B$7,2) | D35: =D21-ROUND(D19*Paramètres!$B$7,2) | E35: =E21-ROUND(E19*Paramètres!$B$7,2) | F35: =F21-ROUND(F19*Paramètres!$B$7,2) | G35: =G21-ROUND(G19*Paramètres!$B$7,2) | H35: =H21-ROUND(H19*Paramètres!$B$7,2) | I35: =I21-ROUND(I19*Paramètres!$B$7,2) | J35: =J21-ROUND(J19*Paramètres!$B$7,2) | K35: =SUM(C35:J35)
A36: C4 | B36: Base IRG − (R500 − R510 + R522 + R532 + R540) | C36: =C24-(C19-C21+C22+C23+C18) | D36: =D24-(D19-D21+D22+D23+D18) | E36: =E24-(E19-E21+E22+E23+E18) | F36: =F24-(F19-F21+F22+F23+F18) | G36: =G24-(G19-G21+G22+G23+G18) | H36: =H24-(H19-H21+H22+H23+H18) | I36: =I24-(I19-I21+I22+I23+I18) | J36: =J24-(J19-J21+J22+J23+J18) | K36: =SUM(C36:J36)
A37: C5 | B37: Éléments soumis NON inclus dans l'assiette CNAS (≠ 0 = anomalie A03) | C37: =(C6-C7-C8+C9+C10+C11+C12+C13+C14+C15+C16+C17+C18)-C19 | D37: =(D6-D7-D8+D9+D10+D11+D12+D13+D14+D15+D16+D17+D18)-D19 | E37: =(E6-E7-E8+E9+E10+E11+E12+E13+E14+E15+E16+E17+E18)-E19 | F37: =(F6-F7-F8+F9+F10+F11+F12+F13+F14+F15+F16+F17+F18)-F19 | G37: =(G6-G7-G8+G9+G10+G11+G12+G13+G14+G15+G16+G17+G18)-G19 | H37: =(H6-H7-H8+H9+H10+H11+H12+H13+H14+H15+H16+H17+H18)-H19 | I37: =(I6-I7-I8+I9+I10+I11+I12+I13+I14+I15+I16+I17+I18)-I19 | J37: =(J6-J7-J8+J9+J10+J11+J12+J13+J14+J15+J16+J17+J18)-J19 | K37: =SUM(C37:J37)
A39: Mars 2026 : centralisateur absent du fichier source (colonne grisée). Voir anomalie A02.

Sheet Paie TPM
A1: Récapitulatif mensuel de la paie — TPM (centralisateurs 2026)
A2: Source : PAIE_2026_DPR_COMPANY_TPM.xlsx — montants en DA. Valeurs en bleu = saisies depuis les centralisateurs.
A4: Code | B4: Libellé | C4: Janv 2026 | D4: Févr 2026 | E4: Mars 2026 | F4: Avr 2026 | G4: Mai 2026 | H4: Juin 2026 | I4: Juil 2026 | J4: Août 2026 | K4: Cumul Jan–Août
A5: EFF | B5: Effectif (en-tête du centralisateur) | C5: 3 | D5: 3 | E5: 3 | F5: 3 | G5: 3 | H5: 3 | I5: 2 | J5: 1
A6: R030 | B6: Salaire de base | C6: 90700 | D6: 90700 | E6: 90700 | F6: 90700 | G6: 90700 | H6: 90700 | I6: 58200 | J6: 29100 | K6: =SUM(C6:J6)
A7: R065 | B7: Heures d'absence (retenue) | C7: 57135.54 | D7: 46807.84 | E7: 36459.52 | F7: 32051.31 | G7: 32051.31 | H7: 61600 | I7: 29100 | K7: =SUM(C7:J7)
A8: R061 | B8: Jours reprise / congé (retenue) | K8: =SUM(C8:J8)
A9: R100 | B9: Congé | K9: =SUM(C9:J9)
A10: R112 | B10: Heures supp. 50 % | E10: 8360.81 | F10: 8360.81 | G10: 8360.81 | H10: 7303.12 | I10: 1473.22 | J10: 1473.22 | K10: =SUM(C10:J10)
A11: R122 | B11: Heures supp. 75 % | K11: =SUM(C11:J11)
A12: R261 | B12: I.E.P. | C12: 446.45 | D12: 1479.22 | E12: 2514.05 | F12: 2954.87 | G12: 2954.87 | K12: =SUM(C12:J12)
A13: R281 | B13: Nuisance | C13: 5705.96 | D13: 7461.67 | E13: 9220.88 | F13: 9970.28 | G13: 9970.28 | H13: 4947 | I13: 4947 | J13: 4947 | K13: =SUM(C13:J13)
A14: R291 | B14: Responsabilité | K14: =SUM(C14:J14)
A15: R301 | B15: P.R.I. | C15: 5325.67 | D15: 6874.82 | E15: 8427.07 | F15: 9088.3 | G15: 9088.3 | H15: 4656 | I15: 4656 | J15: 4656 | K15: =SUM(C15:J15)
A16: R320 | B16: Prime de performance | K16: =SUM(C16:J16)
A17: STC | B17: Solde de tout compte (R546 / R040) | H17: 87785.02 | K17: =SUM(C17:J17)
A18: R540 | B18: Prime de ponctualité | K18: =SUM(C18:J18)
A19: R500 | B19: SALAIRE DE POSTE (assiette CNAS) | C19: 45042.54 | D19: 59707.87 | E19: 82763.29 | F19: 89022.95 | G19: 89022.95 | H19: 133791.14 | I19: 40176.22 | J19: 40176.22 | K19: =SUM(C19:J19)
A20: R500E | B20: Effectif cotisant (R500) | C20: 2 | D20: 2 | E20: 2 | F20: 2 | G20: 2 | H20: 2 | I20: 1 | J20: 1
A21: R510 | B21: Retenue sécurité sociale 9 % | C21: 4053.83 | D21: 5373.71 | E21: 7448.69 | F21: 8012.06 | G21: 8012.06 | H21: 12041.2 | I21: 3615.86 | J21: 3615.86 | K21: =SUM(C21:J21)
A22: R522 | B22: Panier | C22: 3900 | D22: 4992 | E22: 6084 | F22: 6552 | G22: 6552 | H22: 3432 | I22: 3432 | J22: 3432 | K22: =SUM(C22:J22)
A23: R532 | B23: Transport | C23: 2502.21 | D23: 3201.31 | E23: 3901.81 | F23: 4200.22 | G23: 4200.22 | H23: 2200 | I23: 2200 | J23: 2200 | K23: =SUM(C23:J23)
A24: R650 | B24: Base imposable IRG | C24: 47390.92 | D24: 62527.47 | E24: 85300.4 | F24: 91763.1 | G24: 91763.1 | H24: 127381.94 | I24: 42192.36 | J24: 42192.36 | K24: =SUM(C24:J24)
A25: R660 | B25: Retenue IRG | C25: 3329.5 | D25: 3329.5 | E25: 7757.4 | F25: 9375.2 | G25: 9375.2 | H25: 18989.9 | I25: 3691.3 | J25: 3691.3 | K25: =SUM(C25:J25)
A26: R670 | B26: Frais de mission | C26: 16210 | D26: 21145 | E26: 34960 | F26: 41615 | G26: 49115 | H26: 625 | K26: =SUM(C26:J26)
A27: R714 | B27: Salaire unique | C27: 1000 | D27: 1000 | E27: 1000 | F27: 1000 | G27: 1000 | H27: 500 | I27: 500 | J27: 500 | K27: =SUM(C27:J27)
A28: R770 | B28: NET À PAYER | C28: 61271.42 | D28: 81342.97 | E28: 113503.01 | F28: 125002.91 | G28: 132502.91 | H28: 109517.04 | I28: 39001.06 | J28: 39001.06 | K28: =SUM(C28:J28)
A29: TGG | B29: Total général — gains | C29: 125790.29 | D29: 136854.02 | E29: 165168.62 | F29: 174441.48 | G29: 181941.48 | H29: 202148.14 | I29: 75408.22 | J29: 46308.22 | K29: =SUM(C29:J29)
A30: TGR | B30: Total général — retenues | C30: 125790.29 | D30: 136854.02 | E30: 165168.62 | F30: 174441.48 | G30: 181941.48 | H30: 202148.14 | I30: 75408.22 | J30: 46308.22 | K30: =SUM(C30:J30)
A32: CONTRÔLES (doivent être à zéro, sauf mention)
A33: C1 | B33: Équilibre : total gains − total retenues | C33: =C29-C30 | D33: =D29-D30 | E33: =E29-E30 | F33: =F29-F30 | G33: =G29-G30 | H33: =H29-H30 | I33: =I29-I30 | J33: =J29-J30 | K33: =SUM(C33:J33)
A34: C2 | B34: Équilibre comptable : R500+R540+R522+R532+R670+R714 − R510 − R660 − R770 | C34: =C19+C18+C22+C23+C26+C27-C21-C25-C28 | D34: =D19+D18+D22+D23+D26+D27-D21-D25-D28 | E34: =E19+E18+E22+E23+E26+E27-E21-E25-E28 | F34: =F19+F18+F22+F23+F26+F27-F21-F25-F28 | G34: =G19+G18+G22+G23+G26+G27-G21-G25-G28 | H34: =H19+H18+H22+H23+H26+H27-H21-H25-H28 | I34: =I19+I18+I22+I23+I26+I27-I21-I25-I28 | J34: =J19+J18+J22+J23+J26+J27-J21-J25-J28 | K34: =SUM(C34:J34)
A35: C3 | B35: Retenue SS − 9 % × salaire de poste (écart d'arrondi ≤ 0,02 admis) | C35: =C21-ROUND(C19*Paramètres!$B$7,2) | D35: =D21-ROUND(D19*Paramètres!$B$7,2) | E35: =E21-ROUND(E19*Paramètres!$B$7,2) | F35: =F21-ROUND(F19*Paramètres!$B$7,2) | G35: =G21-ROUND(G19*Paramètres!$B$7,2) | H35: =H21-ROUND(H19*Paramètres!$B$7,2) | I35: =I21-ROUND(I19*Paramètres!$B$7,2) | J35: =J21-ROUND(J19*Paramètres!$B$7,2) | K35: =SUM(C35:J35)
A36: C4 | B36: Base IRG − (R500 − R510 + R522 + R532 + R540) | C36: =C24-(C19-C21+C22+C23+C18) | D36: =D24-(D19-D21+D22+D23+D18) | E36: =E24-(E19-E21+E22+E23+E18) | F36: =F24-(F19-F21+F22+F23+F18) | G36: =G24-(G19-G21+G22+G23+G18) | H36: =H24-(H19-H21+H22+H23+H18) | I36: =I24-(I19-I21+I22+I23+I18) | J36: =J24-(J19-J21+J22+J23+J18) | K36: =SUM(C36:J36)
A37: C5 | B37: Éléments soumis NON inclus dans l'assiette CNAS (≠ 0 = anomalie A03) | C37: =(C6-C7-C8+C9+C10+C11+C12+C13+C14+C15+C16+C17+C18)-C19 | D37: =(D6-D7-D8+D9+D10+D11+D12+D13+D14+D15+D16+D17+D18)-D19 | E37: =(E6-E7-E8+E9+E10+E11+E12+E13+E14+E15+E16+E17+E18)-E19 | F37: =(F6-F7-F8+F9+F10+F11+F12+F13+F14+F15+F16+F17+F18)-F19 | G37: =(G6-G7-G8+G9+G10+G11+G12+G13+G14+G15+G16+G17+G18)-G19 | H37: =(H6-H7-H8+H9+H10+H11+H12+H13+H14+H15+H16+H17+H18)-H19 | I37: =(I6-I7-I8+I9+I10+I11+I12+I13+I14+I15+I16+I17+I18)-I19 | J37: =(J6-J7-J8+J9+J10+J11+J12+J13+J14+J15+J16+J17+J18)-J19 | K37: =SUM(C37:J37)

Sheet Rappro CNAS
A1: Rapprochement paie ↔ déclarations CNAS 2026
A2: Assiette paie = somme des salaires de poste (R500) des mois couverts. Colonnes bleues = valeurs lues sur les déclarations CNAS (vides = déclaration non reçue).
A4: Réf | B4: Établissement | C4: Période | D4: Mois couverts | E4: Assiette paie (R500) | F4: Assiette déclarée | G4: Écart assiette | H4: R22 calculé | I4: R98 calculé | J4: Total calculé | K4: Total déclaré | L4: Écart cotisations | M4: Effectif fin période (paie) | N4: Effectif déclaré | O4: Entrées déclarées | P4: Sorties déclarées | Q4: STC payés (paie) | R4: Date dépôt | S4: Échéance | T4: Statut | U4: Ponctualité non soumise | V4: Cotisations sur ponctualité (35 %) | W4: Observation
A5: D01 | B5: IMPORT — 06713395 46 | C5: Janvier 2026 (mensuelle) | D5: Janv | E5: ='Paie IMPORT'!C19 | F5: 818361.77 | G5: =IF(F5="","",E5-F5) | H5: =ROUND(E5*Paramètres!$B$5,2) | I5: =ROUND(E5*Paramètres!$B$6,2) | J5: =H5+I5 | K5: 286426.62 | L5: =IF(K5="","",J5-K5) | M5: ='Paie IMPORT'!C5 | N5: 12 | O5: 0 | P5: 0 | Q5: =IF('Paie IMPORT'!C17>0,1,0) | R5: 28/02/2026 | S5: 28/02/2026 | T5: =IF(K5="","À DÉPOSER / À FOURNIR",IF(AND(ABS(G5)<1,ABS(L5)<1),"Conforme","ÉCART")) | U5: ='Paie IMPORT'!C18 | V5: =ROUND(U5*(Paramètres!$B$5+Paramètres!$B$6),2) | W5: Conforme. Effectif 12 = paie.
A6: D02 | B6: IMPORT — 06713395 46 | C6: Février 2026 (mensuelle) | D6: Févr | E6: ='Paie IMPORT'!D19 | G6: =IF(F6="","",E6-F6) | H6: =ROUND(E6*Paramètres!$B$5,2) | I6: =ROUND(E6*Paramètres!$B$6,2) | J6: =H6+I6 | L6: =IF(K6="","",J6-K6) | M6: ='Paie IMPORT'!D5 | Q6: =IF('Paie IMPORT'!D17>0,7,0) | S6: 31/03/2026 | T6: =IF(K6="","À DÉPOSER / À FOURNIR",IF(AND(ABS(G6)<1,ABS(L6)<1),"Conforme","ÉCART")) | U6: ='Paie IMPORT'!D18 | V6: =ROUND(U6*(Paramètres!$B$5+Paramètres!$B$6),2) | W6: DÉCLARATION NON FOURNIE. 7 STC payés en février : l'EMS doit déclarer 7 sorties (effectif 12 → 5).
A7: D03 | B7: IMPORT — 06713395 46 | C7: Mars 2026 (mensuelle) | D7: Mars | E7: ='Paie IMPORT'!E19 | F7: 368389.93 | G7: =IF(F7="","",E7-F7) | H7: =ROUND(E7*Paramètres!$B$5,2) | I7: =ROUND(E7*Paramètres!$B$6,2) | J7: =H7+I7 | K7: 128936.48 | L7: =IF(K7="","",J7-K7) | M7: ='Paie IMPORT'!E5 | N7: 5 | O7: 0 | P7: 0 | Q7: =IF('Paie IMPORT'!E17>0,1,0) | R7: 28/04/2026 | S7: 30/04/2026 | T7: =IF(K7="","À DÉPOSER / À FOURNIR",IF(AND(ABS(G7)<1,ABS(L7)<1),"Conforme","ÉCART")) | U7: ='Paie IMPORT'!E18 | V7: =ROUND(U7*(Paramètres!$B$5+Paramètres!$B$6),2) | W7: Centralisateur de mars ABSENT : assiette déclarée non justifiable par la paie.
A8: D04 | B8: IMPORT — 06713395 46 | C8: T2 2026 (avr–juin) | D8: Avr, Mai, Juin | E8: =SUM('Paie IMPORT'!F19:H19) | F8: 1180389.8 | G8: =IF(F8="","",E8-F8) | H8: =ROUND(E8*Paramètres!$B$5,2) | I8: =ROUND(E8*Paramètres!$B$6,2) | J8: =H8+I8 | K8: 413136.41 | L8: =IF(K8="","",J8-K8) | M8: ='Paie IMPORT'!H5 | N8: 5 | O8: 0 | P8: 0 | Q8: =IF('Paie IMPORT'!F17>0,1,0)+IF('Paie IMPORT'!G17>0,1,0)+IF('Paie IMPORT'!H17>0,1,0) | R8: 06/07/2026 | S8: 30/07/2026 | T8: =IF(K8="","À DÉPOSER / À FOURNIR",IF(AND(ABS(G8)<1,ABS(L8)<1),"Conforme","ÉCART")) | U8: =SUM('Paie IMPORT'!F18:H18) | V8: =ROUND(U8*(Paramètres!$B$5+Paramètres!$B$6),2) | W8: Conforme sur l'assiette R500. EMS néant cohérent.
A9: D05 | B9: IMPORT — 06713395 46 | C9: T3 2026 (juil–sept) | D9: Juil, Août (+ sept. à venir) | E9: =SUM('Paie IMPORT'!I19:J19) | G9: =IF(F9="","",E9-F9) | H9: =ROUND(E9*Paramètres!$B$5,2) | I9: =ROUND(E9*Paramètres!$B$6,2) | J9: =H9+I9 | L9: =IF(K9="","",J9-K9) | M9: ='Paie IMPORT'!J5 | Q9: =IF('Paie IMPORT'!I17>0,1,0)+IF('Paie IMPORT'!J17>0,1,0) | S9: 30/10/2026 | T9: =IF(K9="","À DÉPOSER / À FOURNIR",IF(AND(ABS(G9)<1,ABS(L9)<1),"Conforme","ÉCART")) | U9: =SUM('Paie IMPORT'!I18:J18) | V9: =ROUND(U9*(Paramètres!$B$5+Paramètres!$B$6),2) | W9: À ÉTABLIR. Septembre non fourni (cumul juil–août seulement). 1 STC en août → 1 sortie à déclarer.
A10: D06 | B10: TPM — 06736613 53 | C10: T1 2026 (janv–mars) | D10: Janv, Févr, Mars | E10: =SUM('Paie TPM'!C19:E19) | F10: 187513.7 | G10: =IF(F10="","",E10-F10) | H10: =ROUND(E10*Paramètres!$B$5,2) | I10: =ROUND(E10*Paramètres!$B$6,2) | J10: =H10+I10 | K10: 65629.8 | L10: =IF(K10="","",J10-K10) | M10: ='Paie TPM'!E5 | N10: 2 | O10: 0 | P10: 0 | Q10: =IF('Paie TPM'!C17>0,1,0)+IF('Paie TPM'!D17>0,1,0)+IF('Paie TPM'!E17>0,1,0) | R10: 28/04/2026 | S10: 30/04/2026 | T10: =IF(K10="","À DÉPOSER / À FOURNIR",IF(AND(ABS(G10)<1,ABS(L10)<1),"Conforme","ÉCART")) | U10: =SUM('Paie TPM'!C18:E18) | V10: =ROUND(U10*(Paramètres!$B$5+Paramètres!$B$6),2) | W10: Assiette conforme. Effectif déclaré 2, paie = 3 salariés (1 absent non rémunéré) : T2 = 2 après 1 sortie ⇒ T1 aurait dû être 3.
A11: D07 | B11: TPM — 06736613 53 | C11: T2 2026 (avr–juin) | D11: Avr, Mai, Juin | E11: =SUM('Paie TPM'!F19:H19) | F11: 311837.04 | G11: =IF(F11="","",E11-F11) | H11: =ROUND(E11*Paramètres!$B$5,2) | I11: =ROUND(E11*Paramètres!$B$6,2) | J11: =H11+I11 | K11: 109142.97 | L11: =IF(K11="","",J11-K11) | M11: ='Paie TPM'!H5 | N11: 2 | O11: 0 | P11: 1 | Q11: =IF('Paie TPM'!F17>0,1,0)+IF('Paie TPM'!G17>0,1,0)+IF('Paie TPM'!H17>0,1,0) | R11: 23/07/2026 | S11: 30/07/2026 | T11: =IF(K11="","À DÉPOSER / À FOURNIR",IF(AND(ABS(G11)<1,ABS(L11)<1),"Conforme","ÉCART")) | U11: =SUM('Paie TPM'!F18:H18) | V11: =ROUND(U11*(Paramètres!$B$5+Paramètres!$B$6),2) | W11: Conforme. Sortie ELHOUANNES Boualem (SS 630003079056) au 01/06/2026, STC 87 785,02 en juin.
A12: D08 | B12: TPM — 06736613 53 | C12: T3 2026 (juil–sept) | D12: Juil, Août (+ sept. à venir) | E12: =SUM('Paie TPM'!I19:J19) | G12: =IF(F12="","",E12-F12) | H12: =ROUND(E12*Paramètres!$B$5,2) | I12: =ROUND(E12*Paramètres!$B$6,2) | J12: =H12+I12 | L12: =IF(K12="","",J12-K12) | M12: ='Paie TPM'!J5 | Q12: =IF('Paie TPM'!I17>0,1,0)+IF('Paie TPM'!J17>0,1,0) | S12: 30/10/2026 | T12: =IF(K12="","À DÉPOSER / À FOURNIR",IF(AND(ABS(G12)<1,ABS(L12)<1),"Conforme","ÉCART")) | U12: =SUM('Paie TPM'!I18:J18) | V12: =ROUND(U12*(Paramètres!$B$5+Paramètres!$B$6),2) | W12: À ÉTABLIR. Effectif 2 en juillet → 1 en août sans STC : 1 sortie + STC à régulariser.
A13: TOTAL | E13: =SUM(E5:E12) | F13: =SUM(F5:F12) | H13: =SUM(H5:H12) | I13: =SUM(I5:I12) | J13: =SUM(J5:J12) | K13: =SUM(K5:K12) | U13: =SUM(U5:U12) | V13: =SUM(V5:V12)
A15: Note : D03 (mars IMPORT) — l'assiette paie ressort à 0 car le centralisateur de mars est absent ; l'écart affiché disparaîtra dès sa saisie dans « Paie IMPORT », colonne E.
A16: Note : les bordereaux de versement portent « Montant de versement 0,00 » : joindre les preuves de paiement (reçus CNAS / virements).

Sheet Journal paie
A1: Journal de paie 2026 — écritures proposées (SCF)
A2: Une écriture de paie + une écriture de charges patronales par mois et par établissement. Montants liés aux feuilles « Paie ».
A4: Pièce | B4: Mois | C4: Établissement | D4: Compte | E4: Libellé | F4: Débit | G4: Crédit
A5: PAIE-IMP-01 | B5: Janv 2026 | C5: IMPORT | D5: 631 | E5: Rémunérations (salaire de poste + ponctualité) | F5: ='Paie IMPORT'!C19+'Paie IMPORT'!C18
A6: PAIE-IMP-01 | B6: Janv 2026 | C6: IMPORT | D6: 638 | E6: Indemnités panier et transport | F6: ='Paie IMPORT'!C22+'Paie IMPORT'!C23
A7: PAIE-IMP-01 | B7: Janv 2026 | C7: IMPORT | D7: 625 | E7: Frais de mission | F7: ='Paie IMPORT'!C26
A8: PAIE-IMP-01 | B8: Janv 2026 | C8: IMPORT | D8: 431 | E8: Salaire unique avancé pour compte CNAS (à valider) | F8: ='Paie IMPORT'!C27
A9: PAIE-IMP-01 | B9: Janv 2026 | C9: IMPORT | D9: 431 | E9: CNAS — retenue salariale 9 % | G9: ='Paie IMPORT'!C21
A10: PAIE-IMP-01 | B10: Janv 2026 | C10: IMPORT | D10: 442 | E10: IRG retenu à la source | G10: ='Paie IMPORT'!C25
A11: PAIE-IMP-01 | B11: Janv 2026 | C11: IMPORT | D11: 421 | E11: Net à payer au personnel | G11: ='Paie IMPORT'!C28
A12: CNAS-IMP-01 | B12: Janv 2026 | C12: IMPORT | D12: 635 | E12: Charges patronales CNAS (26 %) | F12: =ROUND('Paie IMPORT'!C19*Paramètres!$B$8,2)
A13: CNAS-IMP-01 | B13: Janv 2026 | C13: IMPORT | D13: 431 | E13: CNAS — part patronale à reverser | G13: =ROUND('Paie IMPORT'!C19*Paramètres!$B$8,2)
A14: PAIE-IMP-02 | B14: Févr 2026 | C14: IMPORT | D14: 631 | E14: Rémunérations (salaire de poste + ponctualité) | F14: ='Paie IMPORT'!D19+'Paie IMPORT'!D18
A15: PAIE-IMP-02 | B15: Févr 2026 | C15: IMPORT | D15: 638 | E15: Indemnités panier et transport | F15: ='Paie IMPORT'!D22+'Paie IMPORT'!D23
A16: PAIE-IMP-02 | B16: Févr 2026 | C16: IMPORT | D16: 625 | E16: Frais de mission | F16: ='Paie IMPORT'!D26
A17: PAIE-IMP-02 | B17: Févr 2026 | C17: IMPORT | D17: 431 | E17: Salaire unique avancé pour compte CNAS (à valider) | F17: ='Paie IMPORT'!D27
A18: PAIE-IMP-02 | B18: Févr 2026 | C18: IMPORT | D18: 431 | E18: CNAS — retenue salariale 9 % | G18: ='Paie IMPORT'!D21
A19: PAIE-IMP-02 | B19: Févr 2026 | C19: IMPORT | D19: 442 | E19: IRG retenu à la source | G19: ='Paie IMPORT'!D25
A20: PAIE-IMP-02 | B20: Févr 2026 | C20: IMPORT | D20: 421 | E20: Net à payer au personnel | G20: ='Paie IMPORT'!D28
A21: CNAS-IMP-02 | B21: Févr 2026 | C21: IMPORT | D21: 635 | E21: Charges patronales CNAS (26 %) | F21: =ROUND('Paie IMPORT'!D19*Paramètres!$B$8,2)
A22: CNAS-IMP-02 | B22: Févr 2026 | C22: IMPORT | D22: 431 | E22: CNAS — part patronale à reverser | G22: =ROUND('Paie IMPORT'!D19*Paramètres!$B$8,2)
A23: PAIE-IMP-03 | B23: Mars 2026 | C23: IMPORT | E23: CENTRALISATEUR ABSENT — écriture impossible (anomalie A02)
A24: PAIE-IMP-04 | B24: Avr 2026 | C24: IMPORT | D24: 631 | E24: Rémunérations (salaire de poste + ponctualité) | F24: ='Paie IMPORT'!F19+'Paie IMPORT'!F18
A25: PAIE-IMP-04 | B25: Avr 2026 | C25: IMPORT | D25: 638 | E25: Indemnités panier et transport | F25: ='Paie IMPORT'!F22+'Paie IMPORT'!F23
A26: PAIE-IMP-04 | B26: Avr 2026 | C26: IMPORT | D26: 625 | E26: Frais de mission | F26: ='Paie IMPORT'!F26
A27: PAIE-IMP-04 | B27: Avr 2026 | C27: IMPORT | D27: 431 | E27: Salaire unique avancé pour compte CNAS (à valider) | F27: ='Paie IMPORT'!F27
A28: PAIE-IMP-04 | B28: Avr 2026 | C28: IMPORT | D28: 431 | E28: CNAS — retenue salariale 9 % | G28: ='Paie IMPORT'!F21
A29: PAIE-IMP-04 | B29: Avr 2026 | C29: IMPORT | D29: 442 | E29: IRG retenu à la source | G29: ='Paie IMPORT'!F25
A30: PAIE-IMP-04 | B30: Avr 2026 | C30: IMPORT | D30: 421 | E30: Net à payer au personnel | G30: ='Paie IMPORT'!F28
A31: CNAS-IMP-04 | B31: Avr 2026 | C31: IMPORT | D31: 635 | E31: Charges patronales CNAS (26 %) | F31: =ROUND('Paie IMPORT'!F19*Paramètres!$B$8,2)
A32: CNAS-IMP-04 | B32: Avr 2026 | C32: IMPORT | D32: 431 | E32: CNAS — part patronale à reverser | G32: =ROUND('Paie IMPORT'!F19*Paramètres!$B$8,2)
A33: PAIE-IMP-05 | B33: Mai 2026 | C33: IMPORT | D33: 631 | E33: Rémunérations (salaire de poste + ponctualité) | F33: ='Paie IMPORT'!G19+'Paie IMPORT'!G18
A34: PAIE-IMP-05 | B34: Mai 2026 | C34: IMPORT | D34: 638 | E34: Indemnités panier et transport | F34: ='Paie IMPORT'!G22+'Paie IMPORT'!G23
A35: PAIE-IMP-05 | B35: Mai 2026 | C35: IMPORT | D35: 625 | E35: Frais de mission | F35: ='Paie IMPORT'!G26
A36: PAIE-IMP-05 | B36: Mai 2026 | C36: IMPORT | D36: 431 | E36: Salaire unique avancé pour compte CNAS (à valider) | F36: ='Paie IMPORT'!G27
A37: PAIE-IMP-05 | B37: Mai 2026 | C37: IMPORT | D37: 431 | E37: CNAS — retenue salariale 9 % | G37: ='Paie IMPORT'!G21
A38: PAIE-IMP-05 | B38: Mai 2026 | C38: IMPORT | D38: 442 | E38: IRG retenu à la source | G38: ='Paie IMPORT'!G25
A39: PAIE-IMP-05 | B39: Mai 2026 | C39: IMPORT | D39: 421 | E39: Net à payer au personnel | G39: ='Paie IMPORT'!G28
A40: CNAS-IMP-05 | B40: Mai 2026 | C40: IMPORT | D40: 635 | E40: Charges patronales CNAS (26 %) | F40: =ROUND('Paie IMPORT'!G19*Paramètres!$B$8,2)
A41: CNAS-IMP-05 | B41: Mai 2026 | C41: IMPORT | D41: 431 | E41: CNAS — part patronale à reverser | G41: =ROUND('Paie IMPORT'!G19*Paramètres!$B$8,2)
A42: PAIE-IMP-06 | B42: Juin 2026 | C42: IMPORT | D42: 631 | E42: Rémunérations (salaire de poste + ponctualité) | F42: ='Paie IMPORT'!H19+'Paie IMPORT'!H18
A43: PAIE-IMP-06 | B43: Juin 2026 | C43: IMPORT | D43: 638 | E43: Indemnités panier et transport | F43: ='Paie IMPORT'!H22+'Paie IMPORT'!H23
A44: PAIE-IMP-06 | B44: Juin 2026 | C44: IMPORT | D44: 625 | E44: Frais de mission | F44: ='Paie IMPORT'!H26
A45: PAIE-IMP-06 | B45: Juin 2026 | C45: IMPORT | D45: 431 | E45: Salaire unique avancé pour compte CNAS (à valider) | F45: ='Paie IMPORT'!H27
A46: PAIE-IMP-06 | B46: Juin 2026 | C46: IMPORT | D46: 431 | E46: CNAS — retenue salariale 9 % | G46: ='Paie IMPORT'!H21
A47: PAIE-IMP-06 | B47: Juin 2026 | C47: IMPORT | D47: 442 | E47: IRG retenu à la source | G47: ='Paie IMPORT'!H25
A48: PAIE-IMP-06 | B48: Juin 2026 | C48: IMPORT | D48: 421 | E48: Net à payer au personnel | G48: ='Paie IMPORT'!H28
A49: CNAS-IMP-06 | B49: Juin 2026 | C49: IMPORT | D49: 635 | E49: Charges patronales CNAS (26 %) | F49: =ROUND('Paie IMPORT'!H19*Paramètres!$B$8,2)
A50: CNAS-IMP-06 | B50: Juin 2026 | C50: IMPORT | D50: 431 | E50: CNAS — part patronale à reverser | G50: =ROUND('Paie IMPORT'!H19*Paramètres!$B$8,2)
A51: PAIE-IMP-07 | B51: Juil 2026 | C51: IMPORT | D51: 631 | E51: Rémunérations (salaire de poste + ponctualité) | F51: ='Paie IMPORT'!I19+'Paie IMPORT'!I18
A52: PAIE-IMP-07 | B52: Juil 2026 | C52: IMPORT | D52: 638 | E52: Indemnités panier et transport | F52: ='Paie IMPORT'!I22+'Paie IMPORT'!I23
A53: PAIE-IMP-07 | B53: Juil 2026 | C53: IMPORT | D53: 625 | E53: Frais de mission | F53: ='Paie IMPORT'!I26
A54: PAIE-IMP-07 | B54: Juil 2026 | C54: IMPORT | D54: 431 | E54: Salaire unique avancé pour compte CNAS (à valider) | F54: ='Paie IMPORT'!I27
A55: PAIE-IMP-07 | B55: Juil 2026 | C55: IMPORT | D55: 431 | E55: CNAS — retenue salariale 9 % | G55: ='Paie IMPORT'!I21
A56: PAIE-IMP-07 | B56: Juil 2026 | C56: IMPORT | D56: 442 | E56: IRG retenu à la source | G56: ='Paie IMPORT'!I25
A57: PAIE-IMP-07 | B57: Juil 2026 | C57: IMPORT | D57: 421 | E57: Net à payer au personnel | G57: ='Paie IMPORT'!I28
A58: CNAS-IMP-07 | B58: Juil 2026 | C58: IMPORT | D58: 635 | E58: Charges patronales CNAS (26 %) | F58: =ROUND('Paie IMPORT'!I19*Paramètres!$B$8,2)
A59: CNAS-IMP-07 | B59: Juil 2026 | C59: IMPORT | D59: 431 | E59: CNAS — part patronale à reverser | G59: =ROUND('Paie IMPORT'!I19*Paramètres!$B$8,2)
A60: PAIE-IMP-08 | B60: Août 2026 | C60: IMPORT | D60: 631 | E60: Rémunérations (salaire de poste + ponctualité) | F60: ='Paie IMPORT'!J19+'Paie IMPORT'!J18
A61: PAIE-IMP-08 | B61: Août 2026 | C61: IMPORT | D61: 638 | E61: Indemnités panier et transport | F61: ='Paie IMPORT'!J22+'Paie IMPORT'!J23
A62: PAIE-IMP-08 | B62: Août 2026 | C62: IMPORT | D62: 625 | E62: Frais de mission | F62: ='Paie IMPORT'!J26
A63: PAIE-IMP-08 | B63: Août 2026 | C63: IMPORT | D63: 431 | E63: Salaire unique avancé pour compte CNAS (à valider) | F63: ='Paie IMPORT'!J27
A64: PAIE-IMP-08 | B64: Août 2026 | C64: IMPORT | D64: 431 | E64: CNAS — retenue salariale 9 % | G64: ='Paie IMPORT'!J21
A65: PAIE-IMP-08 | B65: Août 2026 | C65: IMPORT | D65: 442 | E65: IRG retenu à la source | G65: ='Paie IMPORT'!J25
A66: PAIE-IMP-08 | B66: Août 2026 | C66: IMPORT | D66: 421 | E66: Net à payer au personnel | G66: ='Paie IMPORT'!J28
A67: CNAS-IMP-08 | B67: Août 2026 | C67: IMPORT | D67: 635 | E67: Charges patronales CNAS (26 %) | F67: =ROUND('Paie IMPORT'!J19*Paramètres!$B$8,2)
A68: CNAS-IMP-08 | B68: Août 2026 | C68: IMPORT | D68: 431 | E68: CNAS — part patronale à reverser | G68: =ROUND('Paie IMPORT'!J19*Paramètres!$B$8,2)
A69: PAIE-TPM-01 | B69: Janv 2026 | C69: TPM | D69: 631 | E69: Rémunérations (salaire de poste + ponctualité) | F69: ='Paie TPM'!C19+'Paie TPM'!C18
A70: PAIE-TPM-01 | B70: Janv 2026 | C70: TPM | D70: 638 | E70: Indemnités panier et transport | F70: ='Paie TPM'!C22+'Paie TPM'!C23
A71: PAIE-TPM-01 | B71: Janv 2026 | C71: TPM | D71: 625 | E71: Frais de mission | F71: ='Paie TPM'!C26
A72: PAIE-TPM-01 | B72: Janv 2026 | C72: TPM | D72: 431 | E72: Salaire unique avancé pour compte CNAS (à valider) | F72: ='Paie TPM'!C27
A73: PAIE-TPM-01 | B73: Janv 2026 | C73: TPM | D73: 431 | E73: CNAS — retenue salariale 9 % | G73: ='Paie TPM'!C21
A74: PAIE-TPM-01 | B74: Janv 2026 | C74: TPM | D74: 442 | E74: IRG retenu à la source | G74: ='Paie TPM'!C25
A75: PAIE-TPM-01 | B75: Janv 2026 | C75: TPM | D75: 421 | E75: Net à payer au personnel | G75: ='Paie TPM'!C28
A76: CNAS-TPM-01 | B76: Janv 2026 | C76: TPM | D76: 635 | E76: Charges patronales CNAS (26 %) | F76: =ROUND('Paie TPM'!C19*Paramètres!$B$8,2)
A77: CNAS-TPM-01 | B77: Janv 2026 | C77: TPM | D77: 431 | E77: CNAS — part patronale à reverser | G77: =ROUND('Paie TPM'!C19*Paramètres!$B$8,2)
A78: PAIE-TPM-02 | B78: Févr 2026 | C78: TPM | D78: 631 | E78: Rémunérations (salaire de poste + ponctualité) | F78: ='Paie TPM'!D19+'Paie TPM'!D18
A79: PAIE-TPM-02 | B79: Févr 2026 | C79: TPM | D79: 638 | E79: Indemnités panier et transport | F79: ='Paie TPM'!D22+'Paie TPM'!D23
A80: PAIE-TPM-02 | B80: Févr 2026 | C80: TPM | D80: 625 | E80: Frais de mission | F80: ='Paie TPM'!D26
A81: PAIE-TPM-02 | B81: Févr 2026 | C81: TPM | D81: 431 | E81: Salaire unique avancé pour compte CNAS (à valider) | F81: ='Paie TPM'!D27
A82: PAIE-TPM-02 | B82: Févr 2026 | C82: TPM | D82: 431 | E82: CNAS — retenue salariale 9 % | G82: ='Paie TPM'!D21
A83: PAIE-TPM-02 | B83: Févr 2026 | C83: TPM | D83: 442 | E83: IRG retenu à la source | G83: ='Paie TPM'!D25
A84: PAIE-TPM-02 | B84: Févr 2026 | C84: TPM | D84: 421 | E84: Net à payer au personnel | G84: ='Paie TPM'!D28
A85: CNAS-TPM-02 | B85: Févr 2026 | C85: TPM | D85: 635 | E85: Charges patronales CNAS (26 %) | F85: =ROUND('Paie TPM'!D19*Paramètres!$B$8,2)
A86: CNAS-TPM-02 | B86: Févr 2026 | C86: TPM | D86: 431 | E86: CNAS — part patronale à reverser | G86: =ROUND('Paie TPM'!D19*Paramètres!$B$8,2)
A87: PAIE-TPM-03 | B87: Mars 2026 | C87: TPM | D87: 631 | E87: Rémunérations (salaire de poste + ponctualité) | F87: ='Paie TPM'!E19+'Paie TPM'!E18
A88: PAIE-TPM-03 | B88: Mars 2026 | C88: TPM | D88: 638 | E88: Indemnités panier et transport | F88: ='Paie TPM'!E22+'Paie TPM'!E23
A89: PAIE-TPM-03 | B89: Mars 2026 | C89: TPM | D89: 625 | E89: Frais de mission | F89: ='Paie TPM'!E26
A90: PAIE-TPM-03 | B90: Mars 2026 | C90: TPM | D90: 431 | E90: Salaire unique avancé pour compte CNAS (à valider) | F90: ='Paie TPM'!E27
A91: PAIE-TPM-03 | B91: Mars 2026 | C91: TPM | D91: 431 | E91: CNAS — retenue salariale 9 % | G91: ='Paie TPM'!E21
A92: PAIE-TPM-03 | B92: Mars 2026 | C92: TPM | D92: 442 | E92: IRG retenu à la source | G92: ='Paie TPM'!E25
A93: PAIE-TPM-03 | B93: Mars 2026 | C93: TPM | D93: 421 | E93: Net à payer au personnel | G93: ='Paie TPM'!E28
A94: CNAS-TPM-03 | B94: Mars 2026 | C94: TPM | D94: 635 | E94: Charges patronales CNAS (26 %) | F94: =ROUND('Paie TPM'!E19*Paramètres!$B$8,2)
A95: CNAS-TPM-03 | B95: Mars 2026 | C95: TPM | D95: 431 | E95: CNAS — part patronale à reverser | G95: =ROUND('Paie TPM'!E19*Paramètres!$B$8,2)
A96: PAIE-TPM-04 | B96: Avr 2026 | C96: TPM | D96: 631 | E96: Rémunérations (salaire de poste + ponctualité) | F96: ='Paie TPM'!F19+'Paie TPM'!F18
A97: PAIE-TPM-04 | B97: Avr 2026 | C97: TPM | D97: 638 | E97: Indemnités panier et transport | F97: ='Paie TPM'!F22+'Paie TPM'!F23
A98: PAIE-TPM-04 | B98: Avr 2026 | C98: TPM | D98: 625 | E98: Frais de mission | F98: ='Paie TPM'!F26
A99: PAIE-TPM-04 | B99: Avr 2026 | C99: TPM | D99: 431 | E99: Salaire unique avancé pour compte CNAS (à valider) | F99: ='Paie TPM'!F27
A100: PAIE-TPM-04 | B100: Avr 2026 | C100: TPM | D100: 431 | E100: CNAS — retenue salariale 9 % | G100: ='Paie TPM'!F21
A101: PAIE-TPM-04 | B101: Avr 2026 | C101: TPM | D101: 442 | E101: IRG retenu à la source | G101: ='Paie TPM'!F25
...

Sheet Balance comptes
A1: Balance des comptes de paie — cumul janvier–août 2026
A2: Calculée par SUMIFS sur le journal de paie.
A4: Compte | B4: Intitulé | C4: Débit IMPORT | D4: Crédit IMPORT | E4: Débit TPM | F4: Crédit TPM | G4: Débit total | H4: Crédit total | I4: Solde (D − C)
A5: 631 | B5: Rémunérations du personnel | C5: =SUMIFS('Journal paie'!$F$5:$F$140,'Journal paie'!$D$5:$D$140,A5,'Journal paie'!$C$5:$C$140,"IMPORT") | D5: =SUMIFS('Journal paie'!$G$5:$G$140,'Journal paie'!$D$5:$D$140,A5,'Journal paie'!$C$5:$C$140,"IMPORT") | E5: =SUMIFS('Journal paie'!$F$5:$F$140,'Journal paie'!$D$5:$D$140,A5,'Journal paie'!$C$5:$C$140,"TPM") | F5: =SUMIFS('Journal paie'!$G$5:$G$140,'Journal paie'!$D$5:$D$140,A5,'Journal paie'!$C$5:$C$140,"TPM") | G5: =C5+E5 | H5: =D5+F5 | I5: =G5-H5
A6: 638 | B6: Autres charges de personnel | C6: =SUMIFS('Journal paie'!$F$5:$F$140,'Journal paie'!$D$5:$D$140,A6,'Journal paie'!$C$5:$C$140,"IMPORT") | D6: =SUMIFS('Journal paie'!$G$5:$G$140,'Journal paie'!$D$5:$D$140,A6,'Journal paie'!$C$5:$C$140,"IMPORT") | E6: =SUMIFS('Journal paie'!$F$5:$F$140,'Journal paie'!$D$5:$D$140,A6,'Journal paie'!$C$5:$C$140,"TPM") | F6: =SUMIFS('Journal paie'!$G$5:$G$140,'Journal paie'!$D$5:$D$140,A6,'Journal paie'!$C$5:$C$140,"TPM") | G6: =C6+E6 | H6: =D6+F6 | I6: =G6-H6
A7: 625 | B7: Déplacements, missions et réceptions | C7: =SUMIFS('Journal paie'!$F$5:$F$140,'Journal paie'!$D$5:$D$140,A7,'Journal paie'!$C$5:$C$140,"IMPORT") | D7: =SUMIFS('Journal paie'!$G$5:$G$140,'Journal paie'!$D$5:$D$140,A7,'Journal paie'!$C$5:$C$140,"IMPORT") | E7: =SUMIFS('Journal paie'!$F$5:$F$140,'Journal paie'!$D$5:$D$140,A7,'Journal paie'!$C$5:$C$140,"TPM") | F7: =SUMIFS('Journal paie'!$G$5:$G$140,'Journal paie'!$D$5:$D$140,A7,'Journal paie'!$C$5:$C$140,"TPM") | G7: =C7+E7 | H7: =D7+F7 | I7: =G7-H7
A8: 635 | B8: Cotisations aux organismes sociaux | C8: =SUMIFS('Journal paie'!$F$5:$F$140,'Journal paie'!$D$5:$D$140,A8,'Journal paie'!$C$5:$C$140,"IMPORT") | D8: =SUMIFS('Journal paie'!$G$5:$G$140,'Journal paie'!$D$5:$D$140,A8,'Journal paie'!$C$5:$C$140,"IMPORT") | E8: =SUMIFS('Journal paie'!$F$5:$F$140,'Journal paie'!$D$5:$D$140,A8,'Journal paie'!$C$5:$C$140,"TPM") | F8: =SUMIFS('Journal paie'!$G$5:$G$140,'Journal paie'!$D$5:$D$140,A8,'Journal paie'!$C$5:$C$140,"TPM") | G8: =C8+E8 | H8: =D8+F8 | I8: =G8-H8
A9: 431 | B9: Organismes sociaux — CNAS | C9: =SUMIFS('Journal paie'!$F$5:$F$140,'Journal paie'!$D$5:$D$140,A9,'Journal paie'!$C$5:$C$140,"IMPORT") | D9: =SUMIFS('Journal paie'!$G$5:$G$140,'Journal paie'!$D$5:$D$140,A9,'Journal paie'!$C$5:$C$140,"IMPORT") | E9: =SUMIFS('Journal paie'!$F$5:$F$140,'Journal paie'!$D$5:$D$140,A9,'Journal paie'!$C$5:$C$140,"TPM") | F9: =SUMIFS('Journal paie'!$G$5:$G$140,'Journal paie'!$D$5:$D$140,A9,'Journal paie'!$C$5:$C$140,"TPM") | G9: =C9+E9 | H9: =D9+F9 | I9: =G9-H9
A10: 442 | B10: État, impôts et taxes recouvrables sur tiers | C10: =SUMIFS('Journal paie'!$F$5:$F$140,'Journal paie'!$D$5:$D$140,A10,'Journal paie'!$C$5:$C$140,"IMPORT") | D10: =SUMIFS('Journal paie'!$G$5:$G$140,'Journal paie'!$D$5:$D$140,A10,'Journal paie'!$C$5:$C$140,"IMPORT") | E10: =SUMIFS('Journal paie'!$F$5:$F$140,'Journal paie'!$D$5:$D$140,A10,'Journal paie'!$C$5:$C$140,"TPM") | F10: =SUMIFS('Journal paie'!$G$5:$G$140,'Journal paie'!$D$5:$D$140,A10,'Journal paie'!$C$5:$C$140,"TPM") | G10: =C10+E10 | H10: =D10+F10 | I10: =G10-H10
A11: 421 | B11: Personnel, rémunérations dues | C11: =SUMIFS('Journal paie'!$F$5:$F$140,'Journal paie'!$D$5:$D$140,A11,'Journal paie'!$C$5:$C$140,"IMPORT") | D11: =SUMIFS('Journal paie'!$G$5:$G$140,'Journal paie'!$D$5:$D$140,A11,'Journal paie'!$C$5:$C$140,"IMPORT") | E11: =SUMIFS('Journal paie'!$F$5:$F$140,'Journal paie'!$D$5:$D$140,A11,'Journal paie'!$C$5:$C$140,"TPM") | F11: =SUMIFS('Journal paie'!$G$5:$G$140,'Journal paie'!$D$5:$D$140,A11,'Journal paie'!$C$5:$C$140,"TPM") | G11: =C11+E11 | H11: =D11+F11 | I11: =G11-H11
B12: TOTAL | C12: =SUM(C5:C11) | D12: =SUM(D5:D11) | E12: =SUM(E5:E11) | F12: =SUM(F5:F11) | G12: =SUM(G5:G11) | H12: =SUM(H5:H11) | I12: =SUM(I5:I11)
A14: Le solde du 431 représente les cotisations CNAS générées par la paie (hors mars IMPORT) ; il doit être soldé par les règlements CNAS. Les soldes 442 et 421 sont soldés par les G50 et les virements de salaires.

Sheet Échéancier IRG-CNAS
A1: Échéancier mensuel — IRG (G50) et masse salariale
A2: IRG retenu à reverser par G50 avant le 20 du mois suivant. À rapprocher des G50 déposées (non fournies).
A4: Mois | B4: Assiette CNAS IMPORT | C4: Assiette CNAS TPM | D4: Assiette totale | E4: IRG IMPORT | F4: IRG TPM | G4: IRG total à reverser (G50) | H4: Échéance G50 | I4: IRG IMPORT déclaré G50 | J4: Écart IRG | K4: Net payé IMPORT | L4: Net payé TPM | M4: Effectif IMPORT | N4: Effectif TPM
A5: Janv 2026 | B5: ='Paie IMPORT'!C19 | C5: ='Paie TPM'!C19 | D5: =B5+C5 | E5: ='Paie IMPORT'!C25 | F5: ='Paie TPM'!C25 | G5: =E5+F5 | H5: 20/02/2026 | I5: ='G50 2026'!B19 | J5: =IF(I5="","",IF(E5=0,"paie absente",I5-E5)) | K5: ='Paie IMPORT'!C28 | L5: ='Paie TPM'!C28 | M5: ='Paie IMPORT'!C5 | N5: ='Paie TPM'!C5
A6: Févr 2026 | B6: ='Paie IMPORT'!D19 | C6: ='Paie TPM'!D19 | D6: =B6+C6 | E6: ='Paie IMPORT'!D25 | F6: ='Paie TPM'!D25 | G6: =E6+F6 | H6: 20/03/2026 | I6: ='G50 2026'!C19 | J6: =IF(I6="","",IF(E6=0,"paie absente",I6-E6)) | K6: ='Paie IMPORT'!D28 | L6: ='Paie TPM'!D28 | M6: ='Paie IMPORT'!D5 | N6: ='Paie TPM'!D5
A7: Mars 2026 | B7: ='Paie IMPORT'!E19 | C7: ='Paie TPM'!E19 | D7: =B7+C7 | E7: ='Paie IMPORT'!E25 | F7: ='Paie TPM'!E25 | G7: =E7+F7 | H7: 20/04/2026 | I7: ='G50 2026'!D19 | J7: =IF(I7="","",IF(E7=0,"paie absente",I7-E7)) | K7: ='Paie IMPORT'!E28 | L7: ='Paie TPM'!E28 | M7: ='Paie IMPORT'!E5 | N7: ='Paie TPM'!E5
A8: Avr 2026 | B8: ='Paie IMPORT'!F19 | C8: ='Paie TPM'!F19 | D8: =B8+C8 | E8: ='Paie IMPORT'!F25 | F8: ='Paie TPM'!F25 | G8: =E8+F8 | H8: 20/05/2026 | I8: ='G50 2026'!E19 | J8: =IF(I8="","",IF(E8=0,"paie absente",I8-E8)) | K8: ='Paie IMPORT'!F28 | L8: ='Paie TPM'!F28 | M8: ='Paie IMPORT'!F5 | N8: ='Paie TPM'!F5
A9: Mai 2026 | B9: ='Paie IMPORT'!G19 | C9: ='Paie TPM'!G19 | D9: =B9+C9 | E9: ='Paie IMPORT'!G25 | F9: ='Paie TPM'!G25 | G9: =E9+F9 | H9: 20/06/2026 | I9: ='G50 2026'!F19 | J9: =IF(I9="","",IF(E9=0,"paie absente",I9-E9)) | K9: ='Paie IMPORT'!G28 | L9: ='Paie TPM'!G28 | M9: ='Paie IMPORT'!G5 | N9: ='Paie TPM'!G5
A10: Juin 2026 | B10: ='Paie IMPORT'!H19 | C10: ='Paie TPM'!H19 | D10: =B10+C10 | E10: ='Paie IMPORT'!H25 | F10: ='Paie TPM'!H25 | G10: =E10+F10 | H10: 20/07/2026 | I10: ='G50 2026'!G19 | J10: =IF(I10="","",IF(E10=0,"paie absente",I10-E10)) | K10: ='Paie IMPORT'!H28 | L10: ='Paie TPM'!H28 | M10: ='Paie IMPORT'!H5 | N10: ='Paie TPM'!H5
A11: Juil 2026 | B11: ='Paie IMPORT'!I19 | C11: ='Paie TPM'!I19 | D11: =B11+C11 | E11: ='Paie IMPORT'!I25 | F11: ='Paie TPM'!I25 | G11: =E11+F11 | H11: 20/08/2026 | I11: ='G50 2026'!H19 | J11: =IF(I11="","",IF(E11=0,"paie absente",I11-E11)) | K11: ='Paie IMPORT'!I28 | L11: ='Paie TPM'!I28 | M11: ='Paie IMPORT'!I5 | N11: ='Paie TPM'!I5
A12: Août 2026 | B12: ='Paie IMPORT'!J19 | C12: ='Paie TPM'!J19 | D12: =B12+C12 | E12: ='Paie IMPORT'!J25 | F12: ='Paie TPM'!J25 | G12: =E12+F12 | H12: 20/09/2026 | I12: ='G50 2026'!I19 | J12: =IF(I12="","",IF(E12=0,"paie absente",I12-E12)) | K12: ='Paie IMPORT'!J28 | L12: ='Paie TPM'!J28 | M12: ='Paie IMPORT'!J5 | N12: ='Paie TPM'!J5
A13: TOTAL | B13: =SUM(B5:B12) | C13: =SUM(C5:C12) | D13: =SUM(D5:D12) | E13: =SUM(E5:E12) | F13: =SUM(F5:F12) | G13: =SUM(G5:G12) | I13: =SUM(I5:I12) | K13: =SUM(K5:K12) | L13: =SUM(L5:L12)
A15: Colonne I : G50 IMPORT janvier à août reçues (liées à « G50 2026 »). Écart IRG = G50 − IRG paie IMPORT. L'IRG TPM (colonne F) doit figurer sur une G50 TPM distincte (non fournie).

Sheet G50 2026
A1: Contrôle des G50 IMPORT 2026 (NIF 000306018423274 — art. 06120024511)
A2: Sources : fichiers G50_ARL_DPR_COMPANY_IMPORT_01 à 08-2026.xls (feuilles G.50-1/2/3). Valeurs en bleu = lues sur les G50.
A4: Taux de TVA (revente en l'état) | B4: 0.19 | C4: Taux porté sur les G50 (ligne E3B22)
A6: Rubrique | B6: Janv 2026 | C6: Févr 2026 | D6: Mars 2026 | E6: Avr 2026 | F6: Mai 2026 | G6: Juin 2026 | H6: Juil 2026 | I6: Août 2026 | J6: Cumul | K6: Commentaire
A7: CA imposable déclaré (E3B22) | B7: 11994522 | C7: 27783649 | D7: 3445200 | E7: 23988307 | F7: 16671298 | G7: 10479294 | H7: 7604135 | I7: 4413684 | J7: =SUM(B7:I7) | K7: Revente en l'état
A8: TVA collectée déclarée | B8: 2278959 | C8: 5278893 | D8: 654588 | E8: 4557778 | F8: 3167547 | G8: 1991066 | H8: 1444786 | I8: 838600 | J8: =SUM(B8:I8)
A9: TVA recalculée (CA × taux) | B9: =ROUND(B7*$B$4,0) | C9: =ROUND(C7*$B$4,0) | D9: =ROUND(D7*$B$4,0) | E9: =ROUND(E7*$B$4,0) | F9: =ROUND(F7*$B$4,0) | G9: =ROUND(G7*$B$4,0) | H9: =ROUND(H7*$B$4,0) | I9: =ROUND(I7*$B$4,0) | J9: =SUM(B9:I9) | K9: Calcul
A10: Écart TVA déclarée − recalculée | B10: =B8-B9 | C10: =C8-C9 | D10: =D8-D9 | E10: =E8-E9 | F10: =F8-F9 | G10: =G8-G9 | H10: =H8-H9 | I10: =I8-I9 | J10: =SUM(B10:I10) | K10: Arrondi admis ±1
A11: Précompte antérieur (E3B91) | B11: 0 | C11: 0 | D11: 0 | E11: 0 | F11: 0 | G11: 386205 | H11: 178353 | I11: 0 | J11: =SUM(B11:I11)
A12: TVA déductible achats (E3B92) | B12: 1150880 | C12: 2199941 | D12: 0 | E12: 3919465 | F12: 3553752 | G12: 1783214 | H12: 0 | I12: 0 | J12: =SUM(B12:I12)
A13: Total déductions | B13: =B11+B12 | C13: =C11+C12 | D13: =D11+D12 | E13: =E11+E12 | F13: =F11+F12 | G13: =G11+G12 | H13: =H11+H12 | I13: =I11+I12 | J13: =SUM(B13:I13) | K13: Calcul
A14: TVA à payer (C − B) | B14: =MAX(0,B8-B13) | C14: =MAX(0,C8-C13) | D14: =MAX(0,D8-D13) | E14: =MAX(0,E8-E13) | F14: =MAX(0,F8-F13) | G14: =MAX(0,G8-G13) | H14: =MAX(0,H8-H13) | I14: =MAX(0,I8-I13) | J14: =SUM(B14:I14) | K14: Calcul
A15: Précompte à reporter (B − C) | B15: =MAX(0,B13-B8) | C15: =MAX(0,C13-C8) | D15: =MAX(0,D13-D8) | E15: =MAX(0,E13-E8) | F15: =MAX(0,F13-F8) | G15: =MAX(0,G13-G8) | H15: =MAX(0,H13-H8) | I15: =MAX(0,I13-I8) | K15: Calcul
A16: Contrôle report : précompte repris − reporté le mois précédent | C16: =C11-B15 | D16: =D11-C15 | E16: =E11-D15 | F16: =F11-E15 | G16: =G11-F15 | H16: =H11-G15 | I16: =I11-H15 | K16: Doit être 0 (chaîne mai → juin → juillet)
A17: IRG salaires — base déclarée (E1L20) | B17: 819091 | C17: 905752 | D17: 365763 | E17: 404385 | F17: 426576 | G17: 325645 | H17: 286954 | I17: 300000 | J17: =SUM(B17:I17)
A18: IRG salaires — base paie IMPORT (R650) | B18: ='Paie IMPORT'!C24 | C18: ='Paie IMPORT'!D24 | D18: ='Paie IMPORT'!E24 | E18: ='Paie IMPORT'!F24 | F18: ='Paie IMPORT'!G24 | G18: ='Paie IMPORT'!H24 | H18: ='Paie IMPORT'!I24 | I18: ='Paie IMPORT'!J24 | J18: =SUM(B18:I18) | K18: Lien paie (mars : centralisateur absent)
A19: IRG salaires — montant déclaré | B19: 132616 | C19: 162286 | D19: 60932 | E19: 72478 | F19: 79138 | G19: 59018 | H19: 42610 | I19: 49670 | J19: =SUM(B19:I19)
A20: IRG salaires — retenu en paie IMPORT (R660) | B20: ='Paie IMPORT'!C25 | C20: ='Paie IMPORT'!D25 | D20: ='Paie IMPORT'!E25 | E20: ='Paie IMPORT'!F25 | F20: ='Paie IMPORT'!G25 | G20: ='Paie IMPORT'!H25 | H20: ='Paie IMPORT'!I25 | I20: ='Paie IMPORT'!J25 | J20: =SUM(B20:I20) | K20: Lien paie
A21: Écart IRG déclaré − paie | B21: =IF(B20=0,"paie absente",B19-B20) | C21: =IF(C20=0,"paie absente",C19-C20) | D21: =IF(D20=0,"paie absente",D19-D20) | E21: =IF(E20=0,"paie absente",E19-E20) | F21: =IF(F20=0,"paie absente",F19-F20) | G21: =IF(G20=0,"paie absente",G19-G20) | H21: =IF(H20=0,"paie absente",H19-H20) | I21: =IF(I20=0,"paie absente",I19-I20) | K21: Négatif = IRG retenu non reversé
A22: IRG retenu en paie TPM (déclaré sur G50 TPM, voir onglet G50 TPM) | B22: ='Paie TPM'!C25 | C22: ='Paie TPM'!D25 | D22: ='Paie TPM'!E25 | E22: ='Paie TPM'!F25 | F22: ='Paie TPM'!G25 | G22: ='Paie TPM'!H25 | H22: ='Paie TPM'!I25 | I22: ='Paie TPM'!J25 | J22: =SUM(B22:I22) | K22: G50 TPM fournies : juillet et août seulement
A23: Droit de timbre — base | B23: 1526130 | C23: 6372000 | D23: 0 | E23: 177058 | F23: 177058 | G23: 0 | H23: 0 | I23: 0 | J23: =SUM(B23:I23)
A24: Droit de timbre — montant | B24: 30525 | C24: 63720 | D24: 0 | E24: 8944 | F24: 3173 | G24: 0 | H24: 0 | I24: 0 | J24: =SUM(B24:I24) | K24: Taux apparents incohérents (ligne 31)
A25: Taxe d'apprentissage — base | B25: 0 | C25: 8782828 | D25: 0 | E25: 0 | F25: 0 | G25: 0 | H25: 0 | I25: 4409079 | J25: =SUM(B25:I25)
A26: Taxe d'apprentissage — montant | B26: 0 | C26: 87828 | D26: 0 | E26: 0 | F26: 0 | G26: 0 | H26: 0 | I26: 44091 | J26: =SUM(B26:I26) | K26: 1 % ; payée en février ET en août : bases à justifier
A27: Total à payer déclaré | B27: 1291220 | C27: 3392786 | D27: 715520 | E27: 719735 | F27: 82311 | G27: 59018 | H27: 1309043 | I27: 932361 | J27: =SUM(B27:I27)
A28: Total recalculé (TVA + IRG + timbre + TA) | B28: =B14+B19+B24+B26 | C28: =C14+C19+C24+C26 | D28: =D14+D19+D24+D26 | E28: =E14+E19+E24+E26 | F28: =F14+F19+F24+F26 | G28: =G14+G19+G24+G26 | H28: =H14+H19+H24+H26 | I28: =I14+I19+I24+I26 | J28: =SUM(B28:I28) | K28: Calcul
A29: Écart total | B29: =B27-B28 | C29: =C27-C28 | D29: =D27-D28 | E29: =E27-E28 | F29: =F27-F28 | G29: =G27-G28 | H29: =H27-H28 | I29: =I27-I28 | J29: =SUM(B29:I29) | K29: Doit être 0
A30: Date de signature imprimée | B30: 18/02/2022 | C30: 19/03/2022 | D30: 17/04/2021 | E30: 18/05/2022 | F30: 18/06/2022 | G30: 28/07/2022 | H30: 19/08/2022 | I30: 19/08/2022 | K30: Dates obsolètes : modèle non mis à jour
A31: Taux apparent du droit de timbre (montant / base) | B31: =IF(B23=0,"",B24/B23) | C31: =IF(C23=0,"",C24/C23) | D31: =IF(D23=0,"",D24/D23) | E31: =IF(E23=0,"",E24/E23) | F31: =IF(F23=0,"",F24/F23) | G31: =IF(G23=0,"",G24/G23) | H31: =IF(H23=0,"",H24/H23) | I31: =IF(I23=0,"",I24/I23) | K31: Taux appliqués différents d'un mois à l'autre
A33: Annotations portées en marge des G50 (suivi du CA de mars 2026)
A34: Rubrique | B34: Montant | K34: Commentaire
A35: CA réalisé en mars 2026 (« TOTAL CA 03/2026 », G50 mars) | B35: 27006870 | K35: Annotation G50 mars et avril
A36: TVA correspondante (« TOTAL TVA 03/2026 ») | B36: 5131305
A37: TVA recalculée sur le CA de mars | B37: =ROUND(B35*$B$4,0) | K37: Contrôle
A38: CA de mars effectivement déclaré en mars | B38: =D7 | K38: G50 mars
A39: CA de mars reporté sur les mois suivants | B39: =B35-B38 | K39: Annoté « RESTE A DECLARER CA » 23 561 670
A40: TVA de mars payée en retard | B40: =ROUND(B39*$B$4,0) | K40: Annoté « RESTE A DECLARER TVA » 4 476 717
A41: « CA DECLARE 04/2026 » annoté en avril | B41: 13157895 | K41: Soit 2 500 000 / 19 % : CA calculé à partir d'un objectif de TVA
A42: TVA cible correspondante | B42: =ROUND(B41*$B$4,2) | K42: Contrôle
A43: « RESTE A DECLARER TVA » annoté en juillet et août | B43: 5417538 | K43: Montant restant selon le suivi interne
A45: Comparaison avec le CA IMPORT 2025 des mêmes mois (compte 70001, journal 2025)
A46: Rubrique | B46: Janv | C46: Févr | D46: Mars | E46: Avr | F46: Mai | G46: Juin | H46: Juil | I46: Août | J46: Cumul | K46: Commentaire
A47: CA 2025 (journal comptable) | B47: 17864580 | C47: 25568207 | D47: 31947529 | E47: 29534571 | F47: 41310810 | G47: 28042831 | H47: 23178604 | I47: 15524844 | J47: =SUM(B47:I47)
A48: CA 2026 déclaré sur G50 | B48: =B7 | C48: =C7 | D48: =D7 | E48: =E7 | F48: =F7 | G48: =G7 | H48: =H7 | I48: =I7 | J48: =SUM(B48:I48) | K48: Le CA 2026 déclaré mois par mois ne reflète pas le CA réalisé (voir annotations) : rapprocher avec le journal des ventes 2026.
A49: Variation 2026 / 2025 | B49: =IF(B47=0,"",B48/B47-1) | C49: =IF(C47=0,"",C48/C47-1) | D49: =IF(D47=0,"",D48/D47-1) | E49: =IF(E47=0,"",E48/E47-1) | F49: =IF(F47=0,"",F48/F47-1) | G49: =IF(G47=0,"",G48/G47-1) | H49: =IF(H47=0,"",H48/H47-1) | I49: =IF(I47=0,"",I48/I47-1) | J49: =J48/J47-1

Sheet Balance 2024-2025
A1: Balance générale des exercices 2024 et 2025 (avant clôture)
A2: Source : exports PCCOMPTA SARL_DPR_COMPAGNY_2024.xls / 2025.xls (feuille JOURNAL). Solde = débit − crédit (crédit négatif). Contrôles faits : journaux équilibrés ; ouvertures 2025 = clôtures 2024.
A4: Compte | B4: Libellé | C4: Solde 31/12/2024 | D4: Solde 31/12/2025 | E4: Variation
A5: 10100 | B5: CAPITAL EMIS | C5: -106000000 | D5: -106000000 | E5: =D5-C5
A6: 10500 | B6: Ecart de réévaluation | C6: -120163.5 | D6: -120163.5 | E6: =D6-C6
A7: 10610 | B7: RESERVES LEGALES | C7: -5546118.4 | D7: -7003771.4 | E7: =D7-C7
A8: 10611 | B8: BENEFICES A REINVESTIR | C8: -25922342 | D8: -25922342 | E8: =D8-C8
A9: 10620 | B9: RESERVES STATUTAIRES | C9: -211183 | D9: -211183 | E9: =D9-C9
A10: 10630 | B10: RESERVES FACULTATIVES | C10: -16395661 | D10: -44091060 | E10: =D10-C10
A11: 11000 | B11: REPORT A NOUVEAU | C11: 1508496.6 | D11: 1508496.6 | E11: =D11-C11
A12: 11001 | B12: AJUST RESUL CH METHODE CPTE | C12: 150790.11 | D12: 150790.11 | E12: =D12-C12
A13: 21100 | B13: TERRAINS | C13: 21600000 | D13: 21600000 | E13: =D13-C13
A14: 21300 | B14: Constructions | C14: 13891000 | D14: 13891000 | E14: =D14-C14
A15: 21301 | B15: CHARPENTE METALIQUE | C15: 20222222 | D15: 20222222 | E15: =D15-C15
A16: 21500 | B16: INSTALATIONS TECHNIQUES,MAERIE | C16: 2713848.8 | D16: 2713848.8 | E16: =D16-C16
... A104: 76800 | B104: Autres produits financiers | C104: -28106.95 | D104: 0 | E104: =D104-C104
B105: TOTAL (doit être 0 : balance équilibrée) | C105: =ROUND(SUM(C5:C104),2) | D105: =ROUND(SUM(D5:D104),2)

Sheet États 2024-2025
A1: Compte de résultat et bilan simplifiés — 2024 / 2025
A2: Calculés par préfixe de compte depuis « Balance 2024-2025 ».
A4: Compte de résultat (DA) | B4: Préfixes | C4: 2024 | D4: 2025 | E4: Variation %
A5: Chiffre d'affaires | B5: 70 | C5: =-(SUMPRODUCT((LEFT('Balance 2024-2025'!$A$5:$A$104,2)="70")*'Balance 2024-2025'!C$5:C$104)) | D5: =-(SUMPRODUCT((LEFT('Balance 2024-2025'!$A$5:$A$104,2)="70")*'Balance 2024-2025'!D$5:D$104)) | E5: =IF(C5=0,"",D5/C5-1)
A6: Autres produits opérationnels | B6: 75 | C6: =-(SUMPRODUCT((LEFT('Balance 2024-2025'!$A$5:$A$104,2)="75")*'Balance 2024-2025'!C$5:C$104)) | D6: =-(SUMPRODUCT((LEFT('Balance 2024-2025'!$A$5:$A$104,2)="75")*'Balance 2024-2025'!D$5:D$104)) | E6: =IF(C6=0,"",D6/C6-1)
A7: Produits financiers | B7: 76 | C7: =-(SUMPRODUCT((LEFT('Balance 2024-2025'!$A$5:$A$104,2)="76")*'Balance 2024-2025'!C$5:C$104)) | D7: =-(SUMPRODUCT((LEFT('Balance 2024-2025'!$A$5:$A$104,2)="76")*'Balance 2024-2025'!D$5:D$104)) | E7: =IF(C7=0,"",D7/C7-1)
A8: Achats consommés | B8: 60 | C8: =(SUMPRODUCT((LEFT('Balance 2024-2025'!$A$5:$A$104,2)="60")*'Balance 2024-2025'!C$5:C$104)) | D8: =(SUMPRODUCT((LEFT('Balance 2024-2025'!$A$5:$A$104,2)="60")*'Balance 2024-2025'!D$5:D$104)) | E8: =IF(C8=0,"",D8/C8-1)
A9: Services extérieurs et autres | B9: 61, 62 | C9: =(SUMPRODUCT((LEFT('Balance 2024-2025'!$A$5:$A$104,2)="61")*'Balance 2024-2025'!C$5:C$104)+SUMPRODUCT((LEFT('Balance 2024-2025'!$A$5:$A$104,2)="62")*'Balance 2024-2025'!C$5:C$104)) | D9: =(SUMPRODUCT((LEFT('Balance 2024-2025'!$A$5:$A$104,2)="61")*'Balance 2024-2025'!D$5:D$104)+SUMPRODUCT((LEFT('Balance 2024-2025'!$A$5:$A$104,2)="62")*'Balance 2024-2025'!D$5:D$104)) | E9: =IF(C9=0,"",D9/C9-1)
A10: Charges de personnel | B10: 63 | C10: =(SUMPRODUCT((LEFT('Balance 2024-2025'!$A$5:$A$104,2)="63")*'Balance 2024-2025'!C$5:C$104)) | D10: =(SUMPRODUCT((LEFT('Balance 2024-2025'!$A$5:$A$104,2)="63")*'Balance 2024-2025'!D$5:D$104)) | E10: =IF(C10=0,"",D10/C10-1)
A11: Impôts, taxes et versements assimilés | B11: 64 | C11: =(SUMPRODUCT((LEFT('Balance 2024-2025'!$A$5:$A$104,2)="64")*'Balance 2024-2025'!C$5:C$104)) | D11: =(SUMPRODUCT((LEFT('Balance 2024-2025'!$A$5:$A$104,2)="64")*'Balance 2024-2025'!D$5:D$104)) | E11: =IF(C11=0,"",D11/C11-1)
A12: Autres charges opérationnelles | B12: 65 | C12: =(SUMPRODUCT((LEFT('Balance 2024-2025'!$A$5:$A$104,2)="65")*'Balance 2024-2025'!C$5:C$104)) | D12: =(SUMPRODUCT((LEFT('Balance 2024-2025'!$A$5:$A$104,2)="65")*'Balance 2024-2025'!D$5:D$104)) | E12: =IF(C12=0,"",D12/C12-1)
A13: Charges financières | B13: 66 | C13: =(SUMPRODUCT((LEFT('Balance 2024-2025'!$A$5:$A$104,2)="66")*'Balance 2024-2025'!C$5:C$104)) | D13: =(SUMPRODUCT((LEFT('Balance 2024-2025'!$A$5:$A$104,2)="66")*'Balance 2024-2025'!D$5:D$104)) | E13: =IF(C13=0,"",D13/C13-1)
A14: Dotations aux amortissements | B14: 68 | C14: =(SUMPRODUCT((LEFT('Balance 2024-2025'!$A$5:$A$104,2)="68")*'Balance 2024-2025'!C$5:C$104)) | D14: =(SUMPRODUCT((LEFT('Balance 2024-2025'!$A$5:$A$104,2)="68")*'Balance 2024-2025'!D$5:D$104)) | E14: =IF(C14=0,"",D14/C14-1)
A15: Impôt sur les bénéfices (IBS) | B15: 69 | C15: =(SUMPRODUCT((LEFT('Balance 2024-2025'!$A$5:$A$104,2)="69")*'Balance 2024-2025'!C$5:C$104)) | D15: =(SUMPRODUCT((LEFT('Balance 2024-2025'!$A$5:$A$104,2)="69")*'Balance 2024-2025'!D$5:D$104)) | E15: =IF(C15=0,"",D15/C15-1)
A16: RÉSULTAT NET | C16: =SUM(C5:C7)-SUM(C8:C15) | D16: =SUM(D5:D7)-SUM(D8:D15) | E16: =IF(C16=0,"",D16/C16-1)
A17: Contrôle : −(classes 6 + 7) − résultat (doit être 0) | C17: =ROUND(-(SUMPRODUCT((LEFT('Balance 2024-2025'!$A$5:$A$104,1)="6")*'Balance 2024-2025'!C$5:C$104)+SUMPRODUCT((LEFT('Balance 2024-2025'!$A$5:$A$104,1)="7")*'Balance 2024-2025'!C$5:C$104))-C16,2) | D17: =ROUND(-(SUMPRODUCT((LEFT('Balance 2024-2025'!$A$5:$A$104,1)="6")*'Balance 2024-2025'!D$5:D$104)+SUMPRODUCT((LEFT('Balance 2024-2025'!$A$5:$A$104,1)="7")*'Balance 2024-2025'!D$5:D$104))-D16,2)
A19: Indicateurs | C19: 2024 | D19: 2025
A20: Résultat avant impôt | C20: =C16+C15 | D20: =D16+D15
A21: Taux effectif IBS | C21: =IF(C20=0,"",C15/C20) | D21: =IF(D20=0,"",D15/D20)
A22: Marge nette (résultat / CA) | C22: =C16/C5 | D22: =D16/D5
A23: Charges de personnel / CA | C23: =C10/C5 | D23: =D10/D5
A24: Primes « imposables non cotisables » (63120) | C24: =SUMPRODUCT((LEFT('Balance 2024-2025'!$A$5:$A$104,5)="63120")*'Balance 2024-2025'!C$5:C$104) | D24: =SUMPRODUCT((LEFT('Balance 2024-2025'!$A$5:$A$104,5)="63120")*'Balance 2024-2025'!D$5:D$104)
A25: Cotisations CNAS potentielles sur 63120 (35 %) | C25: =ROUND(C24*(Paramètres!$B$5+Paramètres!$B$6),2) | D25: =ROUND(D24*(Paramètres!$B$5+Paramètres!$B$6),2)
A27: Bilan — soldes par groupe (débit + / crédit −) | B27: Préfixes | C27: 31/12/2024 | D27: 31/12/2025 | E27: Variation
A28: Capitaux propres (capital, réserves, RAN) | B28: 10, 11 | C28: =SUMPRODUCT((LEFT('Balance 2024-2025'!$A$5:$A$104,2)="10")*'Balance 2024-2025'!C$5:C$104)+SUMPRODUCT((LEFT('Balance 2024-2025'!$A$5:$A$104,2)="11")*'Balance 2024-2025'!C$5:C$104) | D28: =SUMPRODUCT((LEFT('Balance 2024-2025'!$A$5:$A$104,2)="10")*'Balance 2024-2025'!D$5:D$104)+SUMPRODUCT((LEFT('Balance 2024-2025'!$A$5:$A$104,2)="11")*'Balance 2024-2025'!D$5:D$104) | E28: =D28-C28
A29: Résultat en instance d'affectation | B29: 12 | C29: =SUMPRODUCT((LEFT('Balance 2024-2025'!$A$5:$A$104,2)="12")*'Balance 2024-2025'!C$5:C$104) | D29: =SUMPRODUCT((LEFT('Balance 2024-2025'!$A$5:$A$104,2)="12")*'Balance 2024-2025'!D$5:D$104) | E29: =D29-C29
A30: Immobilisations nettes | B30: 2 | C30: =SUMPRODUCT((LEFT('Balance 2024-2025'!$A$5:$A$104,1)="2")*'Balance 2024-2025'!C$5:C$104) | D30: =SUMPRODUCT((LEFT('Balance 2024-2025'!$A$5:$A$104,1)="2")*'Balance 2024-2025'!D$5:D$104) | E30: =D30-C30
A31: Stocks | B31: 3 | C31: =SUMPRODUCT((LEFT('Balance 2024-2025'!$A$5:$A$104,1)="3")*'Balance 2024-2025'!C$5:C$104) | D31: =SUMPRODUCT((LEFT('Balance 2024-2025'!$A$5:$A$104,1)="3")*'Balance 2024-2025'!D$5:D$104) | E31: =D31-C31
A32: Fournisseurs | B32: 401, 404 | C32: =SUMPRODUCT((LEFT('Balance 2024-2025'!$A$5:$A$104,3)="401")*'Balance 2024-2025'!C$5:C$104)+SUMPRODUCT((LEFT('Balance 2024-2025'!$A$5:$A$104,3)="404")*'Balance 2024-2025'!C$5:C$104) | D32: =SUMPRODUCT((LEFT('Balance 2024-2025'!$A$5:$A$104,3)="401")*'Balance 2024-2025'!D$5:D$104)+SUMPRODUCT((LEFT('Balance 2024-2025'!$A$5:$A$104,3)="404")*'Balance 2024-2025'!D$5:D$104) | E32: =D32-C32
A33: Fournisseurs débiteurs (avances) | B33: 409 | C33: =SUMPRODUCT((LEFT('Balance 2024-2025'!$A$5:$A$104,3)="409")*'Balance 2024-2025'!C$5:C$104) | D33: =SUMPRODUCT((LEFT('Balance 2024-2025'!$A$5:$A$104,3)="409")*'Balance 2024-2025'!D$5:D$104) | E33: =D33-C33
A34: Clients | B34: 411 | C34: =SUMPRODUCT((LEFT('Balance 2024-2025'!$A$5:$A$104,3)="411")*'Balance 2024-2025'!C$5:C$104) | D34: =SUMPRODUCT((LEFT('Balance 2024-2025'!$A$5:$A$104,3)="411")*'Balance 2024-2025'!D$5:D$104) | E34: =D34-C34
A35: Clients créditeurs / avances reçues | B35: 419 | C35: =SUMPRODUCT((LEFT('Balance 2024-2025'!$A$5:$A$104,3)="419")*'Balance 2024-2025'!C$5:C$104) | D35: =SUMPRODUCT((LEFT('Balance 2024-2025'!$A$5:$A$104,3)="419")*'Balance 2024-2025'!D$5:D$104) | E35: =D35-C35
A36: Personnel | B36: 42 | C36: =SUMPRODUCT((LEFT('Balance 2024-2025'!$A$5:$A$104,2)="42")*'Balance 2024-2025'!C$5:C$104) | D36: =SUMPRODUCT((LEFT('Balance 2024-2025'!$A$5:$A$104,2)="42")*'Balance 2024-2025'!D$5:D$104) | E36: =D36-C36
A37: Organismes sociaux | B37: 43 | C37: =SUMPRODUCT((LEFT('Balance 2024-2025'!$A$5:$A$104,2)="43")*'Balance 2024-2025'!C$5:C$104) | D37: =SUMPRODUCT((LEFT('Balance 2024-2025'!$A$5:$A$104,2)="43")*'Balance 2024-2025'!D$5:D$104) | E37: =D37-C37
A38: IBS (dette 444 + acomptes 4441) | B38: 444 | C38: =SUMPRODUCT((LEFT('Balance 2024-2025'!$A$5:$A$104,3)="444")*'Balance 2024-2025'!C$5:C$104) | D38: =SUMPRODUCT((LEFT('Balance 2024-2025'!$A$5:$A$104,3)="444")*'Balance 2024-2025'!D$5:D$104) | E38: =D38-C38
A39: IRG retenu, TVA et autres impôts | B39: 442, 445, 447 | C39: =SUMPRODUCT((LEFT('Balance 2024-2025'!$A$5:$A$104,3)="442")*'Balance 2024-2025'!C$5:C$104)+SUMPRODUCT((LEFT('Balance 2024-2025'!$A$5:$A$104,3)="445")*'Balance 2024-2025'!C$5:C$104)+SUMPRODUCT((LEFT('Balance 2024-2025'!$A$5:$A$104,3)="447")*'Balance 2024-2025'!C$5:C$104) | D39: =SUMPRODUCT((LEFT('Balance 2024-2025'!$A$5:$A$104,3)="442")*'Balance 2024-2025'!D$5:D$104)+SUMPRODUCT((LEFT('Balance 2024-2025'!$A$5:$A$104,3)="445")*'Balance 2024-2025'!D$5:D$104)+SUMPRODUCT((LEFT('Balance 2024-2025'!$A$5:$A$104,3)="447")*'Balance 2024-2025'!D$5:D$104) | E39: =D39-C39
A40: Associés — comptes courants | B40: 455, 457 | C40: =SUMPRODUCT((LEFT('Balance 2024-2025'!$A$5:$A$104,3)="455")*'Balance 2024-2025'!C$5:C$104)+SUMPRODUCT((LEFT('Balance 2024-2025'!$A$5:$A$104,3)="457")*'Balance 2024-2025'!C$5:C$104) | D40: =SUMPRODUCT((LEFT('Balance 2024-2025'!$A$5:$A$104,3)="455")*'Balance 2024-2025'!D$5:D$104)+SUMPRODUCT((LEFT('Balance 2024-2025'!$A$5:$A$104,3)="457")*'Balance 2024-2025'!D$5:D$104) | E40: =D40-C40
A41: Autres débiteurs, attente, régularisation | B41: 458, 47, 48 | C41: =SUMPRODUCT((LEFT('Balance 2024-2025'!$A$5:$A$104,3)="458")*'Balance 2024-2025'!C$5:C$104)+SUMPRODUCT((LEFT('Balance 2024-2025'!$A$5:$A$104,2)="47")*'Balance 2024-2025'!C$5:C$104)+SUMPRODUCT((LEFT('Balance 2024-2025'!$A$5:$A$104,2)="48")*'Balance 2024-2025'!C$5:C$104) | D41: =SUMPRODUCT((LEFT('Balance 2024-2025'!$A$5:$A$104,3)="458")*'Balance 2024-2025'!D$5:D$104)+SUMPRODUCT((LEFT('Balance 2024-2025'!$A$5:$A$104,2)="47")*'Balance 2024-2025'!D$5:D$104)+SUMPRODUCT((LEFT('Balance 2024-2025'!$A$5:$A$104,2)="48")*'Balance 2024-2025'!D$5:D$104) | E41: =D41-C41
A42: Banques | B42: 512 | C42: =SUMPRODUCT((LEFT('Balance 2024-2025'!$A$5:$A$104,3)="512")*'Balance 2024-2025'!C$5:C$104) | D42: =SUMPRODUCT((LEFT('Balance 2024-2025'!$A$5:$A$104,3)="512")*'Balance 2024-2025'!D$5:D$104) | E42: =D42-C42
A43: Concours bancaires courants | B43: 519 | C43: =SUMPRODUCT((LEFT('Balance 2024-2025'!$A$5:$A$104,3)="519")*'Balance 2024-2025'!C$5:C$104) | D43: =SUMPRODUCT((LEFT('Balance 2024-2025'!$A$5:$A$104,3)="519")*'Balance 2024-2025'!D$5:D$104) | E43: =D43-C43
A44: Caisse | B44: 53 | C44: =SUMPRODUCT((LEFT('Balance 2024-2025'!$A$5:$A$104,2)="53")*'Balance 2024-2025'!C$5:C$104) | D44: =SUMPRODUCT((LEFT('Balance 2024-2025'!$A$5:$A$104,2)="53")*'Balance 2024-2025'!D$5:D$104) | E44: =D44-C44
A45: Accréditifs | B45: 54 | C45: =SUMPRODUCT((LEFT('Balance 2024-2025'!$A$5:$A$104,2)="54")*'Balance 2024-2025'!C$5:C$104) | D45: =SUMPRODUCT((LEFT('Balance 2024-2025'!$A$5:$A$104,2)="54")*'Balance 2024-2025'!D$5:D$104) | E45: =D45-C45
A46: Contrôle : somme des groupes − résultat (doit être 0) | C46: =ROUND(SUM(C28:C45)-C16,2) | D46: =ROUND(SUM(D28:D45)-D16,2)
A48: Le 2024 « Résultat en instance » est à 0 car la balance 2024 est avant affectation ; le résultat 2024 (29,15 M) a été affecté le 28/05/2025 (réserve légale 5 % + réserves facultatives).

Sheet G50 TPM 2026
A1: Contrôle des G50 « TPM et location » consolidées 2026 (même NIF 000306018423274)
A2: Sources : G50_01 à 08-2026_TPM_ET_LOCATION_CONSOLIDE.xls. Activité portée : transport et distribution de toutes marchandises.
A4: Rubrique | B4: Janv 2026 | C4: Févr 2026 | D4: Mars 2026 | E4: Avril 2026 | F4: Mai 2026 | G4: Juin 2026 | H4: Juil 2026 | I4: Août 2026 | J4: Cumul | K4: Commentaire
A5: Mois imprimé sur la G50 | B5: JANVIER | C5: FEVRIER | D5: MARS | E5: AVRIL | F5: AVRIL | G5: AVRIL | H5: AVRIL | I5: AOUT | K5: Avril à juillet : même G50 recopiée (mois « AVRIL »)
A6: CA imposable déclaré | B6: 0 | C6: 0 | D6: 0 | E6: 0 | F6: 0 | G6: 0 | H6: 0 | I6: 0 | J6: =SUM(B6:I6) | K6: Aucun CA TPM / location déclaré
A7: TVA collectée déclarée | B7: 0 | C7: 0 | D7: 0 | E7: 0 | F7: 0 | G7: 0 | H7: 0 | I7: 0 | J7: =SUM(B7:I7)
A8: Précompte antérieur (E3B91) | B8: 1714499 | C8: 1714499 | D8: 1714499 | E8: 1714499 | F8: 1714499 | G8: 1714499 | H8: 1714499 | I8: 1714499
A9: Précompte à reporter (E3B99) | B9: 1714499 | C9: 1714499 | D9: 1714499 | E9: 1714499 | F9: 1714499 | G9: 1714499 | H9: 1714499 | I9: 1714499
A10: Précompte au compte 44550 au 31/12/2025 (comptabilité) | B10: ='Balance 2024-2025'!D49 | C10: ='Balance 2024-2025'!D49 | D10: ='Balance 2024-2025'!D49 | E10: ='Balance 2024-2025'!D49 | F10: ='Balance 2024-2025'!D49 | G10: ='Balance 2024-2025'!D49 | H10: ='Balance 2024-2025'!D49 | I10: ='Balance 2024-2025'!D49 | K10: Identique : crédit reporté depuis 2025
A11: IRG salaires — base déclarée | B11: 47391 | C11: 62527 | D11: 85300 | E11: 91763 | F11: 91763 | G11: 91763 | H11: 91763 | I11: 42190 | J11: =SUM(B11:I11)
A12: IRG salaires — base paie TPM (R650) du mois | B12: ='Paie TPM'!C24 | C12: ='Paie TPM'!D24 | D12: ='Paie TPM'!E24 | E12: ='Paie TPM'!F24 | F12: ='Paie TPM'!G24 | G12: ='Paie TPM'!H24 | H12: ='Paie TPM'!I24 | I12: ='Paie TPM'!J24 | J12: =SUM(B12:I12) | K12: Lien paie
A13: IRG salaires — montant déclaré | B13: 3330 | C13: 3330 | D13: 7757 | E13: 9375 | F13: 9375 | G13: 9375 | H13: 9375 | I13: 3690 | J13: =SUM(B13:I13)
A14: IRG salaires — retenu en paie TPM (R660) du mois | B14: ='Paie TPM'!C25 | C14: ='Paie TPM'!D25 | D14: ='Paie TPM'!E25 | E14: ='Paie TPM'!F25 | F14: ='Paie TPM'!G25 | G14: ='Paie TPM'!H25 | H14: ='Paie TPM'!I25 | I14: ='Paie TPM'!J25 | J14: =SUM(B14:I14) | K14: Lien paie
A15: Écart IRG déclaré − paie | B15: =B13-B14 | C15: =C13-C14 | D15: =D13-D14 | E15: =E13-E14 | F15: =F13-F14 | G15: =G13-G14 | H15: =H13-H14 | I15: =I13-I14 | J15: =SUM(B15:I15) | K15: Négatif = IRG retenu non reversé
A16: Taxe d'apprentissage — base | B16: 0 | C16: 985118 | D16: 0 | E16: 0 | F16: 0 | G16: 0 | H16: 0 | I16: 680900 | J16: =SUM(B16:I16) | K16: Payée en février et en août : bases à justifier
A17: Taxe d'apprentissage — montant | B17: 0 | C17: 9851 | D17: 0 | E17: 0 | F17: 0 | G17: 0 | H17: 0 | I17: 6809 | J17: =SUM(B17:I17)
A18: Total à payer déclaré | B18: 3330 | C18: 13181 | D18: 7757 | E18: 9375 | F18: 9375 | G18: 9375 | H18: 9375 | I18: 10499 | J18: =SUM(B18:I18)
A19: Total recalculé (TVA + IRG + TA) | B19: =MAX(0,B7-B8)+B13+B17 | C19: =MAX(0,C7-C8)+C13+C17 | D19: =MAX(0,D7-D8)+D13+D17 | E19: =MAX(0,E7-E8)+E13+E17 | F19: =MAX(0,F7-F8)+F13+F17 | G19: =MAX(0,G7-G8)+G13+G17 | H19: =MAX(0,H7-H8)+H13+H17 | I19: =MAX(0,I7-I8)+I13+I17 | J19: =SUM(B19:I19) | K19: Calcul
A20: Écart total | B20: =B18-B19 | C20: =C18-C19 | D20: =D18-D19 | E20: =E18-E19 | F20: =F18-F19 | G20: =G18-G19 | H20: =H18-H19 | I20: =I18-I19 | J20: =SUM(B20:I20) | K20: Doit être 0
A23: Modèle G50 TPM : la feuille « Recap-TVA » porte encore la G50 de décembre 2025 (factures BOBOR PNEUS) et « Feuil1 » un extrait de journal 2019 ; à nettoyer avant dépôt.
A24: Janvier à mars : G50 conformes à la paie TPM (écarts d'arrondi < 1 DA).

Sheet Contrôle 2023
A1: Journal 2023 et historique de la TVA collectée TPM
A2: Source : DLG_COMPTAZ_SARL_DPR_COMPAGNY_2023.xls (3 365 lignes, équilibré) comparé aux à-nouveaux du journal 2024.
A4: Résultat 2023 selon le journal 2023 fourni | B4: 18539102 | C4: Journal 2023 sans écriture d'IBS (69) ni d'inventaire complète ; décembre 2023 : 31 lignes seulement
A5: Résultat 2023 repris en à-nouveau 2024 (compte 12000) | B5: 7260903.2
A6: Écart | B6: =B4-B5 | C6: Le fichier 2023 fourni est une version provisoire, antérieure aux écritures de clôture
A8: Compte | B8: Libellé | C8: Solde clôture 2023 (fichier) | D8: À-nouveau 2024 | E8: Écart
A9: 12000 | B9: RESULTAT DE L'EXERCICE | C9: 0 | D9: -7260903.2 | E9: =D9-C9
A10: 21805 | B10: INSTAL GEN,AGENC,AMENAG DIVERS | C10: 8403329.2 | D10: 9463661.1 | E10: =D10-C10
A11: 28150 | B11: AMORT MAT ET OUTILLAGES | C11: -1249096.2 | D11: -1416000.4 | E11: =D11-C11
A12: 28185 | B12: AMORT INST GEN AGENC ET AMENAG | C12: -3541844.1 | D12: -3612466 | E12: =D12-C12
A13: 30002 | B13: ST IMPORTATION | C13: 2.0201546e+08 | D13: 2.5372705e+08 | E13: =D13-C13
A14: 32201 | B14: ST PIECES DE RECHANGE | C14: 3509934.6 | D14: 0 | E14: =D14-C14
A15: 37000 | B15: STOCKS A L'EXTERIEUR | C15: 0 | D15: 47936182 | E15: =D15-C15
A16: 38002 | B16: ACHATS IMPORTATION | C16: 17544780 | D16: 0 | E16: =D16-C16
A17: 40100 | B17: Fournisseurs de stocks et serv | C17: -30009105 | D17: -69749176 | E17: =D17-C17
A18: 40102 | B18: FOURNSSEURS ETRANGERS | C18: -25535218 | D18: -57476812 | E18: =D18-C18
A19: 40130 | B19: FOUR. LOCAUX DE SERVICES | C19: -2957587.8 | D19: -1726194.4 | E19: =D19-C19
A20: 40400 | B20: Fournisseurs d'immobilisations | C20: -4045605 | D20: -5307400 | E20: =D20-C20
... A46: 53000 | B46: CAISSE | C46: 1432478 | D46: 760534.53 | E46: =D46-C46
B47: Nombre de comptes en écart | C47: =COUNTIF(E9:E46,"<>0") | D47: Somme des écarts en valeur absolue | E47: =SUMPRODUCT(ABS(E9:E46))
A49: Historique du compte 44537 « TVA collectée / ventes TPM » (crédit = dette de TVA)
A50: Exercice | B50: Solde d'ouverture | C50: TVA collectée de l'exercice | D50: Apurée par G50 (débits) | E50: Solde de clôture | F50: Contrôle
A51: 2023 | B51: 37267982 | C51: 7119300 | D51: 0 | E51: 44387282 | F51: =ROUND(B51+C51-D51-E51,2)
A52: 2024 | B52: 42352541 | C52: 6521750 | D52: 1147983 | E52: 47726308 | F52: =ROUND(B52+C52-D52-E52,2)
A53: 2025 | B53: 47726308 | C53: 4839300 | D53: 391208 | E53: 52174400 | F53: =ROUND(B53+C53-D53-E53,2)
A54: Total 2023–2025 | C54: =SUM(C51:C53) | D54: =SUM(D51:D53) | E54: =D54/C54 | F54: ← part de la TVA TPM apurée
A56: Ouverture 2024 (42,35 M) ≠ clôture 2023 du fichier (44,39 M) : écart de 2,03 M, voir tableau ci-dessus. La TVA TPM s'accumule au crédit depuis au moins 2022 (37,27 M à l'ouverture 2023).

Sheet Clients & fournisseurs
A1: Analyse des comptes clients et fournisseurs — situation au 31/12/2025 (base des à-nouveaux 2026)
A2: Source : journaux PCCOMPTA 2023, 2024, 2025 (comptes 401, 404, 409, 411, 419), regroupés par nom de tiers. Débit + / crédit −.
A4: Catégorie | B4: Nombre de tiers | C4: 411 au 31/12/2025 | D4: 419 au 31/12/2025 | E4: 401/404 au 31/12/2025 | F4: 409 au 31/12/2025 | G4: Solde net | H4: Action recommandée
A5: Partie liée | B5: =COUNTIF($B$22:$B$243,A5) | C5: =SUMIFS($D$22:$D$243,$B$22:$B$243,$A5) | D5: =SUMIFS($E$22:$E$243,$B$22:$B$243,$A5) | E5: =SUMIFS($F$22:$F$243,$B$22:$B$243,$A5) | F5: =SUMIFS($G$22:$G$243,$B$22:$B$243,$A5) | G5: =SUM(C5:F5) | H5: Convention écrite, reconnaissance de dette et échéancier ; confirmation de solde ; dépréciation à évaluer
A6: Associé en compte de tiers | B6: =COUNTIF($B$22:$B$243,A6) | C6: =SUMIFS($D$22:$D$243,$B$22:$B$243,$A6) | D6: =SUMIFS($E$22:$E$243,$B$22:$B$243,$A6) | E6: =SUMIFS($F$22:$F$243,$B$22:$B$243,$A6) | F6: =SUMIFS($G$22:$G$243,$B$22:$B$243,$A6) | G6: =SUM(C6:F6) | H6: Reclasser en compte courant d'associé (455/457) après justification
A7: Client 411 + avance 419 à compenser | B7: =COUNTIF($B$22:$B$243,A7) | C7: =SUMIFS($D$22:$D$243,$B$22:$B$243,$A7) | D7: =SUMIFS($E$22:$E$243,$B$22:$B$243,$A7) | E7: =SUMIFS($F$22:$F$243,$B$22:$B$243,$A7) | F7: =SUMIFS($G$22:$G$243,$B$22:$B$243,$A7) | G7: =SUM(C7:F7) | H7: Lettrer et compenser 419 / 411 à hauteur du plus petit montant
A8: Client 411 créditeur | B8: =COUNTIF($B$22:$B$243,A8) | C8: =SUMIFS($D$22:$D$243,$B$22:$B$243,$A8) | D8: =SUMIFS($E$22:$E$243,$B$22:$B$243,$A8) | E8: =SUMIFS($F$22:$F$243,$B$22:$B$243,$A8) | F8: =SUMIFS($G$22:$G$243,$B$22:$B$243,$A8) | G8: =SUM(C8:F8) | H8: Analyser : avoir, trop-perçu ou avance mal imputée ; reclasser en 419 ou rembourser
A9: Avance client dormante ≥ 3 ans | B9: =COUNTIF($B$22:$B$243,A9) | C9: =SUMIFS($D$22:$D$243,$B$22:$B$243,$A9) | D9: =SUMIFS($E$22:$E$243,$B$22:$B$243,$A9) | E9: =SUMIFS($F$22:$F$243,$B$22:$B$243,$A9) | F9: =SUMIFS($G$22:$G$243,$B$22:$B$243,$A9) | G9: =SUM(C9:F9) | H9: Dossier par client : facturer si livré (TVA + CA), rembourser si non livré, sinon justifier
A10: Avance client récente | B10: =COUNTIF($B$22:$B$243,A10) | C10: =SUMIFS($D$22:$D$243,$B$22:$B$243,$A10) | D10: =SUMIFS($E$22:$E$243,$B$22:$B$243,$A10) | E10: =SUMIFS($F$22:$F$243,$B$22:$B$243,$A10) | F10: =SUMIFS($G$22:$G$243,$B$22:$B$243,$A10) | G10: =SUM(C10:F10) | H10: Facturer à la livraison et lettrer
A11: Créance client sans mouvement en 2025 | B11: =COUNTIF($B$22:$B$243,A11) | C11: =SUMIFS($D$22:$D$243,$B$22:$B$243,$A11) | D11: =SUMIFS($E$22:$E$243,$B$22:$B$243,$A11) | E11: =SUMIFS($F$22:$F$243,$B$22:$B$243,$A11) | F11: =SUMIFS($G$22:$G$243,$B$22:$B$243,$A11) | G11: =SUM(C11:F11) | H11: Relance et confirmation de solde ; dépréciation (491) si non recouvrable
A12: Créance client active | B12: =COUNTIF($B$22:$B$243,A12) | C12: =SUMIFS($D$22:$D$243,$B$22:$B$243,$A12) | D12: =SUMIFS($E$22:$E$243,$B$22:$B$243,$A12) | E12: =SUMIFS($F$22:$F$243,$B$22:$B$243,$A12) | F12: =SUMIFS($G$22:$G$243,$B$22:$B$243,$A12) | G12: =SUM(C12:F12) | H12: Suivi normal ; lettrage mensuel
A13: Fournisseur débiteur (avance versée) | B13: =COUNTIF($B$22:$B$243,A13) | C13: =SUMIFS($D$22:$D$243,$B$22:$B$243,$A13) | D13: =SUMIFS($E$22:$E$243,$B$22:$B$243,$A13) | E13: =SUMIFS($F$22:$F$243,$B$22:$B$243,$A13) | F13: =SUMIFS($G$22:$G$243,$B$22:$B$243,$A13) | G13: =SUM(C13:F13) | H13: Obtenir facture ou remboursement ; lettrer avec 401
A14: Dette fournisseur sans mouvement en 2025 | B14: =COUNTIF($B$22:$B$243,A14) | C14: =SUMIFS($D$22:$D$243,$B$22:$B$243,$A14) | D14: =SUMIFS($E$22:$E$243,$B$22:$B$243,$A14) | E14: =SUMIFS($F$22:$F$243,$B$22:$B$243,$A14) | F14: =SUMIFS($G$22:$G$243,$B$22:$B$243,$A14) | G14: =SUM(C14:F14) | H14: Confirmation de solde ; régler ou constater en produit si dette éteinte et justifiée
A15: Fournisseur actif | B15: =COUNTIF($B$22:$B$243,A15) | C15: =SUMIFS($D$22:$D$243,$B$22:$B$243,$A15) | D15: =SUMIFS($E$22:$E$243,$B$22:$B$243,$A15) | E15: =SUMIFS($F$22:$F$243,$B$22:$B$243,$A15) | F15: =SUMIFS($G$22:$G$243,$B$22:$B$243,$A15) | G15: =SUM(C15:F15) | H15: Suivi normal ; lettrage mensuel
A16: TOTAL | B16: =SUM(B5:B15) | C16: =SUM(C5:C15) | D16: =SUM(D5:D15) | E16: =SUM(E5:E15) | F16: =SUM(F5:F15) | G16: =SUM(G5:G15)
A17: Contrôle : total 411 / 419 = balance 2025 | C17: =ROUND(C16-SUMPRODUCT((LEFT('Balance 2024-2025'!$A$5:$A$104,3)="411")*'Balance 2024-2025'!D$5:D$104),0) | D17: =ROUND(D16-SUMPRODUCT((LEFT('Balance 2024-2025'!$A$5:$A$104,3)="419")*'Balance 2024-2025'!D$5:D$104),0) | H17: Doit être 0
A20: Détail par tiers (colonne L à compléter : décision retenue pour chaque tiers)
A21: Tiers | B21: Catégorie | C21: 411 ouverture 2023 | D21: 411 au 31/12/2025 | E21: 419 au 31/12/2025 | F21: 401/404 au 31/12/2025 | G21: 409 au 31/12/2025 | H21: Solde net | I21: Débits 2025 | J21: Crédits 2025 | K21: Dernier mouvement 2025 | L21: Décision 2026
A22: SARL DPR AXXAM BRIQUETERIE | B22: Partie liée | C22: 2.776532e+08 | D22: 3.7101445e+08 | E22: 0 | F22: 0 | G22: 0 | H22: =SUM(D22:G22) | I22: 30309300 | J22: 2450200 | K22: 30/09/2025
A23: SARL DPR AXXAM | B23: Partie liée | C23: 0 | D23: 0 | E23: -9821942.2 | F23: -23812149 | G23: 45350000 | H23: =SUM(D23:G23) | I23: 62500000 | J23: 1815718.4 | K23: 14/12/2025
A24: DJENNADI REYAD | B24: Associé en compte de tiers | C24: 0 | D24: -4500000 | E24: -17609544 | F24: 0 | G24: 0 | H24: =SUM(D24:G24) | I24: 0 | J24: 4500000 | K24: 15/12/2025
A25: DJENNADI ABDELKRIM | B25: Associé en compte de tiers | C25: 0 | D25: -9700000 | E25: 0 | F25: 0 | G25: 0 | H25: =SUM(D25:G25) | I25: 4806900 | J25: 14506900 | K25: 25/12/2025
A26: DJENNADI ABD ELKADER | B26: Associé en compte de tiers | C26: 0 | D26: 0 | E26: 0 | F26: -2510665 | G26: 0 | H26: =SUM(D26:G26) | I26: 0 | J26: 0 | K26: aucun
A27: DJENNADI AHCENE | B27: Associé en compte de tiers | C27: 0 | D27: 0 | E27: -500000 | F27: 0 | G27: 0 | H27: =SUM(D27:G27) | I27: 0 | J27: 0 | K27: aucun
A28: AMEUR KHELLAF | B28: Client 411 + avance 419 à compenser | C28: 99837.81 | D28: 99837.81 | E28: -11034658 | F28: 0 | G28: 0 | H28: =SUM(D28:G28) | I28: 0 | J28: 0 | K28: aucun
A29: SAIDOUN YACINE | B29: Client 411 + avance 419 à compenser | C29: 0 | D29: 400000 | E29: -9857236.4 | F29: 0 | G29: 0 | H29: =SUM(D29:G29) | I29: 484277.89 | J29: 484277.89 | K29: 26/06/2025
A30: ABDOUNE RAFIK | B30: Client 411 + avance 419 à compenser | C30: 700700 | D30: 700700 | E30: -435515.5 | F30: 0 | G30: 0 | H30: =SUM(D30:G30) | I30: 0 | J30: 0 | K30: aucun
A31: GHENABZIA BELKACEM | B31: Client 411 + avance 419 à compenser | C31: 185540 | D31: 185540 | E31: -185540 | F31: 0 | G31: 0 | H31: =SUM(D31:G31) | I31: 0 | J31: 0 | K31: aucun
A32: BENAMARA AYOUB SAHARA MOTORS | B32: Client 411 créditeur | C32: 0 | D32: -1989648 | E32: 0 | F32: 0 | G32: 0 | H32: =SUM(D32:G32) | I32: 3918337 | J32: 5907985 | K32: 13/04/2025
A33: SNC AVI BOUDEDJA ET CIE | B33: Client 411 créditeur | C33: 0 | D33: -1361200 | E33: 0 | F33: 0 | G33: 0 | H33: =SUM(D33:G33) | I33: 789309.28 | J33: 2150509.3 | K33: 19/11/2025
... A243: CNRC | B243: Fournisseur actif | C243: 0 | D243: 0 | E243: 0 | F243: 30110 | G243: 0 | H243: =SUM(D243:G243) | I243: 30110 | J243: 0 | K243: 05/08/2025

Sheet Démarrage 2026
A1: Préparer les à-nouveaux 2026 : risques tiers et écritures de régularisation proposées
A2: Montants liés aux feuilles « Clients & fournisseurs » et « Balance 2024-2025 ». Toute écriture est à valider sur pièces avant passation.
A4: A. SARL DPR AXXAM BRIQUETERIE (client, partie liée) — historique du compte 411
A5: Exercice | B5: Solde d'ouverture | C5: Facturé | D5: Encaissé | E5: Solde de clôture | F5: Taux d'encaissement
A6: 2023 | B6: 2.776532e+08 | C6: 44589300 | D6: 16590000 | E6: 3.056525e+08 | F6: =IF(C6=0,"",D6/C6)
A7: 2024 | B7: 3.094986e+08 | C7: 40846750 | D7: 7190000 | E7: 3.4315535e+08 | F7: =IF(C7=0,"",D7/C7)
A8: 2025 | B8: 3.4315535e+08 | C8: 30309300 | D8: 2450200 | E8: 3.7101445e+08 | F8: =IF(C8=0,"",D8/C8)
A9: Total 2023–2025 | C9: =SUM(C6:C8) | D9: =SUM(D6:D8) | F9: =D9/C9
A10: Créance antérieure à 2023 encore due (encaissements imputés sur les plus anciennes) | E10: =MAX(0,B6-D9)
A11: Poids dans le total clients 411 au 31/12/2025 | E11: =E8/'Clients & fournisseurs'!C16
A12: Poids par rapport aux capitaux propres au 31/12/2025 | E12: =E8/(-'États 2024-2025'!D28-'États 2024-2025'!D29+'États 2024-2025'!D16)
A14: B. SARL DPR AXXAM (fournisseur / client, partie liée) — position au 31/12/2025
A15: Compte | B15: Solde | C15: Commentaire
A16: 401 fournisseur | B16: -1984749
A17: 404 fournisseur d'immobilisations | B17: -21827400 | C17: Sans mouvement en 2025
A18: 409 avances versées en 2025 | B18: 45350000 | C18: 7,0 M (avril) + 15,0 M (août) + 6,0 M + 9,35 M (nov.) + 8,0 M (déc.)
A19: 419 avance reçue | B19: -9821942.2 | C19: Dont remboursement de 6 800 000 en espèces le 06/12/2025
A20: Position nette (+ = DPR AXXAM nous doit) | B20: =SUM(B16:B19)
A21: Sorties de trésorerie vers DPR AXXAM en 2025 | B21: 62500000
A22: Exposition totale groupe DPR AXXAM (briqueterie + position nette) | B22: =E8+B20
A24: C. Écritures de régularisation proposées (à passer après justification, avant ou à l'ouverture 2026)
A25: N° | B25: Objet | C25: Débit | D25: Crédit | E25: Montant (DA) | F25: Condition / pièce requise
A26: R1 | B26: Reclasser les soldes des associés logés en 411 / 419 / 401 | C26: 411 / 419 / 401 | D26: 455 / 457 | E26: =-'Clients & fournisseurs'!G6 | F26: Attestation de chaque associé (apport, avance, ou achat personnel)
A27: R2 | B27: Compenser avances 419 et créances 411 d'un même client | C27: 419 | D27: 411 | E27: =MIN('Clients & fournisseurs'!C7,-'Clients & fournisseurs'!D7) | F27: Lettrage facture / avance par client
A28: R3 | B28: Reclasser les 411 créditeurs | C28: 411 | D28: 419 | E28: =-'Clients & fournisseurs'!C8 | F28: Analyse de chaque solde (avoir, trop-perçu)
A29: R4 | B29: Avances clients dormantes ≥ 3 ans : facturer les livraisons effectuées | C29: 419 | D29: 700 + 4457 | F29: Bons de livraison ; montant = part livrée (colonne L « Facturer »)
A30: R5 | B30: Avances clients dormantes ≥ 3 ans : rembourser les non-livrées | C30: 419 | D30: 512 | F30: Accord écrit du client ; montant = part « Rembourser »
A31: R6 | B31: Dépréciation créances clients sans mouvement en 2025 | C31: 685 | D31: 491 | E31: =ROUND('Clients & fournisseurs'!C11*$E$40,2) | F31: Relances restées sans effet ; taux en E40
A32: R7 | B32: Dépréciation de la créance DPR AXXAM BRIQUETERIE | C32: 685 | D32: 491 | E32: =ROUND(E10*$E$41,2) | F32: Analyse de la capacité de paiement ; taux en E41
A33: R8 | B33: Dettes fournisseurs sans mouvement en 2025 et éteintes | C33: 401 | D33: 758 | F33: Confirmation écrite ou prescription documentée
A35: Pour mémoire : avances clients dormantes ≥ 3 ans à traiter par R4 / R5 | E35: =-'Clients & fournisseurs'!D9
A36: Pour mémoire : dettes fournisseurs sans mouvement en 2025 (R8) | E36: =-'Clients & fournisseurs'!E14
A39: Hypothèses (à fixer avec le commissaire aux comptes)
A40: Taux de dépréciation des créances sans mouvement en 2025 | E40: 0 | F40: Mettre 0 % à 100 % selon le recouvrement attendu ; R6 se recalcule
A41: Taux de dépréciation de la créance briqueterie antérieure à 2023 | E41: 0 | F41: Idem pour R7
A43: D. Règles de tenue à appliquer dès janvier 2026
A44: 1. Un seul code tiers par client (aujourd'hui : un code C… pour la créance et un code AC… pour l'avance) ; lettrage mensuel 411 / 419 / 401 / 409.
A45: 2. Toute avance client donne lieu à une facture à la livraison ; aucune avance ne reste plus de 12 mois sans facture ni remboursement.
A46: 3. Balance âgée clients et fournisseurs à chaque fin de trimestre ; confirmation de solde annuelle des 20 premiers tiers.
A47: 4. Flux avec DPR AXXAM / DPR AXXAM BRIQUETERIE : convention écrite, factures et règlements par banque uniquement ; pas d'avance sans contrat.
A48: 5. Associés : uniquement en 455 / 457, jamais en comptes clients ou fournisseurs.
A49: 6. Ouverture 2026 : reprendre les à-nouveaux après passation de R1 à R8 et vérifier que la balance d'ouverture 2026 = balance de clôture 2025 ajustée.

Sheet Anomalies & actions
A1: Anomalies relevées et plan d'actions
A2: Priorité : 1 = critique (risque de redressement/pénalités), 2 = à corriger, 3 = à vérifier. Colonnes Responsable/Statut à compléter.
A4: N° | B4: Priorité | C4: Établissement | D4: Domaine | E4: Constat | F4: Impact estimé (DA) | G4: Action recommandée | H4: Responsable | I4: Statut
A5: A01 | B5: 1 | C5: IMPORT | D5: CNAS | E5: Déclaration CNAS de février 2026 non fournie (assiette paie 952 475,81 ; 7 STC payés). | F5: ='Rappro CNAS'!J6 | G5: Fournir la déclaration de février + EMS avec 7 sorties ; à défaut, la déposer (pénalités de retard). | I5: Ouvert
A6: A02 | B6: 1 | C6: IMPORT | D6: Paie | E6: Centralisateur de mars 2026 absent (onglet vide) alors que la CNAS de mars déclare 368 389,93 d'assiette, 5 salariés. | F6: ='Rappro CNAS'!K7 | G6: Obtenir le livre de paie de mars et le saisir dans « Paie IMPORT » col. E ; comptabiliser la paie de mars. | I6: Ouvert
A7: A03 | B7: 1 | C7: IMPORT | D7: CNAS | E7: Prime de ponctualité (R540) imposée à l'IRG mais exclue du salaire de poste (assiette CNAS) chaque mois. | F7: ='Rappro CNAS'!V13 | G7: Vérifier le paramétrage de la rubrique R540 (soumise SS) ; régulariser les déclarations concernées. | I7: Ouvert
A8: A04 | B8: 2 | C8: TPM | D8: CNAS | E8: Effectif déclaré au T1 = 2 alors que 3 salariés sont inscrits ; T2 déclare 1 sortie et un effectif final de 2 ⇒ T1 aurait dû être 3. | G8: Rectifier l'effectif du T1 auprès de la CNAS. | I8: Ouvert
A9: A05 | B9: 2 | C9: TPM | D9: Paie / CNAS | E9: Salarié totalement absent (non rémunéré) en juillet, disparu de la paie en août sans STC ni sortie déclarée. | G9: Établir le STC et déclarer la sortie dans l'EMS du T3 (échéance 30/10/2026). | I9: Ouvert
A10: A06 | B10: 2 | C10: IMPORT | D10: CNAS | E10: STC de 2 237,40 en août : une sortie à déclarer au T3. | G10: Déclarer la sortie dans l'EMS du T3. | I10: Ouvert
A11: A07 | B11: 2 | C11: Les deux | D11: CNAS | E11: Déclarations T3 2026 (juil–sept) à établir ; paie de septembre non fournie. | F11: ='Rappro CNAS'!J9+'Rappro CNAS'!J12 | G11: Transmettre les centralisateurs de septembre ; déposer et payer avant le 30/10/2026. | I11: Ouvert
A12: A08 | B12: 3 | C12: TPM | D12: Paie | E12: Avril = mai et juillet = août strictement identiques (mêmes absences, heures sup., IRG) : variables probablement non saisies. | G12: Contrôler les pointages et bulletins de mai et août. | I12: Ouvert
A13: A09 | B13: 3 | C13: TPM | D13: Paie | E13: Frais de mission élevés (avril 41 615 ; mai 49 115, soit 47–55 % de l'assiette), non soumis à cotisations. | F13: ='Paie TPM'!K26 | G13: Conserver ordres de mission et justificatifs ; risque de requalification en salaire. | I13: Ouvert
A14: A10 | B14: 3 | C14: IMPORT | D14: Paie | E14: Prime de responsabilité de 5,00 DA (janv.) et 1,14 DA (févr.) : paramètre vraisemblablement erroné (5 au lieu de 5 %). | G14: Corriger le paramètre B291 ; régulariser le rappel éventuel. | I14: Ouvert
A15: A11 | B15: 2 | C15: Les deux | D15: Trésorerie | E15: Bordereaux de versement CNAS à « 0,00 » : aucune preuve de paiement des cotisations dans le dossier. | F15: ='Rappro CNAS'!K13 | G15: Joindre les quittances CNAS / avis de virement ; comptabiliser les règlements (débit 431). | I15: Ouvert
A16: A12 | B16: 2 | C16: Les deux | D16: Fiscal | E16: IRG IMPORT : G50 de janvier à août conformes à la paie (écarts d'arrondi ≤ 3 DA ; juillet : 2,30 DA retenus non reversés). Mars non vérifiable (paie absente). | F16: ='Échéancier IRG-CNAS'!G13 | G16: Reverser l'IRG retenu au dinar près ; fournir la paie de mars. | I16: Ouvert
A17: A13 | B17: 3 | C17: Les deux | D17: BTPH | E17: Paie paramétrée CACOBATPH (taux X504) mais aucune déclaration CACOBATPH (congés payés / intempéries) dans le dossier. | G17: Fournir les déclarations et paiements CACOBATPH 2026. | I17: Ouvert
A18: A14 | B18: 3 | C18: Les deux | D18: Administratif | E18: Libellés divergents : « D.P.R.COMPAGNY » / « DPR COMPAGNY » ; en-tête de paie TPM à l'adresse VGE TIZI alors que l'affiliation TPM est à TISSA. | G18: Harmoniser raison sociale et adresse dans le logiciel de paie. | I18: Ouvert
A19: A15 | B19: 3 | C19: IMPORT | D19: CNAS | E19: Périodicité mixte : déclarations mensuelles (janv., mars) puis trimestrielle (T2). | G19: Confirmer auprès de la CNAS le passage au trimestriel après la baisse d'effectif (12 → 5). | I19: Ouvert
A20: A16 | B20: 3 | C20: Les deux | D20: Paie | E20: IRG non vérifiable salarié par salarié (centralisateurs uniquement). | G20: Fournir le livre de paie individuel / bulletins. | I20: Ouvert
A21: A17 | B21: 1 | C21: TPM | D21: Fiscal / TVA | E21: TVA collectée TPM (44537) et location (44527) jamais soldées : 58,9 M DA cumulés au 31/12/2025, accumulés depuis au moins 2022 (37,3 M à l'ouverture 2023) ; 2023–2025 : 18,5 M collectés, 1,5 M apurés. En 2025, 4 839 300 de TVA TPM générée, seuls 391 208 passés en G50 (déc.). Les G50 TPM 2026 (juil., août) ne déclarent aucun CA et reportent un précompte de 1 714 499 (= compte 44550). | F21: =-('Balance 2024-2025'!D48+'Balance 2024-2025'!D47) | G21: Rapprocher avec les G50 TPM 2023–2025 ; si TVA non déclarée, régulariser ; sinon passer les écritures de G50 manquantes. | I21: Ouvert
A22: A18 | B22: 1 | C22: IMPORT | D22: Fiscal / TVA | E22: CA de mars 2026 réalisé 27 006 870 (annotation G50), mais seulement 3 445 200 déclarés en mars « pour manque TVA à récupérer » : 23 561 670 de CA reportés sur avril–août. En avril, le CA annoté (13 157 894,74) est calculé pour obtenir 2 500 000 de TVA. Le CA déclaré mensuellement est ajusté à la TVA déductible disponible. | F22: ='G50 2026'!B40 | G22: Déclarer le CA au titre du mois de réalisation ; rapprocher le CA déclaré du journal des ventes 2026 ; chiffrer les pénalités de retard sur la TVA différée. | I22: Ouvert
A23: A19 | B23: 1 | C23: TPM | D23: Fiscal / IRG | E23: G50 TPM d'avril à juillet identiques (mois imprimé « AVRIL », IRG 9 375 chaque mois) : juin sous-déclaré de 9 614,90 (18 989,90 retenus), juillet sur-déclaré de 5 683,70. Janvier–mars et août conformes. | F23: =-'G50 TPM 2026'!G15 | G23: Déposer une G50 rectificative pour juin (IRG retenu non reversé) et régulariser juillet. | I23: Ouvert
A24: A20 | B24: 2 | C24: Les deux | D24: Comptabilité | E24: Écriture du 31/12/2025 « POUR SOLDE PRCT EXE 2025 » passée en sens inverse (D 44410 / C 444, 3 074 299) : dette IBS 9,79 M et acomptes 6,15 M au lieu d'un net de 3 642 951. | F24: 3074299 | G24: Contrepasser et compenser (D 444 / C 44410) ; vérifier le paiement du solde IBS 2025 en 2026. | I24: Ouvert
A25: A21 | B25: 2 | C25: Les deux | D25: Fiscal / IBS | E25: Solde IBS 2024 réglé le 03/07/2025 ; IBS 2025 net à liquider de 3 642 951 (précomptes douane déduits). | F25: 3642951 | G25: Vérifier les dates d'échéance de liquidation, les pénalités éventuelles et la preuve de paiement 2026. | I25: Ouvert
A26: A22 | B26: 2 | C26: Les deux | D26: Trésorerie | E26: Caisse de 12,1 M au 31/12/2025 (pic de 22,5 M) ; remboursement en espèces de 6 800 000 à SARL DPR AXXAM le 06/12/2025. | F26: ='Balance 2024-2025'!D67 | G26: PV de caisse au 31/12 ; respecter l'obligation de paiement scriptural au-delà des seuils réglementaires. | I26: Ouvert
A27: A23 | B27: 2 | C27: Les deux | D27: Parties liées | E27: 100 % du CA TPM 2025 (25,47 M) facturé à SARL DPR AXXAM BRIQUETERIE ; aucune facturation TPM d'oct. à déc. 2025 alors que du personnel TPM reste payé. | F27: =-'Balance 2024-2025'!D100 | G27: Documenter les conventions intra-groupe et la facturation d'oct.–déc. 2025. | I27: Ouvert
A28: A24 | B28: 2 | C28: Les deux | D28: Comptabilité | E28: Compte d'attente 47000 non soldé (« SARL FAHAS ?? », « TRESORERIE BEJAIA ?? », chèques). | F28: ='Balance 2024-2025'!D59 | G28: Identifier et apurer avant clôture. | I28: Ouvert
A29: A25 | B29: 2 | C29: Les deux | D29: CNAS | E29: Compte 63120 « prime imposable » non soumise à cotisation : 957 406 en 2025 et 1 139 275 en 2024 (même mécanisme que A03). | F29: ='États 2024-2025'!C24+'États 2024-2025'!D24 | G29: Analyser les primes concernées ; régulariser si elles sont cotisables. | I29: Ouvert
A30: A26 | B30: 3 | C30: Les deux | D30: Trésorerie | E30: Banque CPA El Kseur (51220) créditrice de 12,43 M au 31/12/2025 : découvert présenté en banque. | F30: =ABS('Balance 2024-2025'!D63) | G30: Reclasser en 519 ; vérifier les agios (aucune charge 661 en 2025). | I30: Ouvert
A31: A27 | B31: 3 | C31: Les deux | D31: Fiscal / CNAS | E31: Reversements IRG 2025 parfois partiels (févr., juin) et rattrapés le mois suivant ; amendes 2025 : douane 100 000, CNAS 1 746. | F31: ='Balance 2024-2025'!D93 | G31: Reverser l'IRG en totalité chaque mois. | I31: Ouvert
A32: A28 | B32: 3 | C32: IMPORT | D32: Fiscal | E32: Modèles G50 non mis à jour : dates de signature de 2021–2022 sur toutes les G50 2026, onglet de saisie figé (mai, TVA 17 %), G50 TPM contenant le récap TVA de déc. 2025 et un extrait de journal 2019 ; libellés de comptes de TVA à 17 %. | G32: Mettre à jour le modèle et les libellés (TVA 19 %). | I32: Ouvert
A33: A29 | B33: 3 | C33: Les deux | D33: Fiscal | E33: Taxe d'apprentissage payée deux fois en 2026 : février (87 828 IMPORT sur 8 782 828 + 9 851 TPM sur 985 118) et août (44 091 IMPORT sur 4 409 079 + 6 809 TPM sur 680 900). | F33: ='G50 2026'!J26+'G50 TPM 2026'!J17 | G33: Justifier les bases et la période couverte par chaque paiement (risque de double paiement). | I33: Ouvert
A34: A30 | B34: 3 | C34: IMPORT | D34: Fiscal / TVA | E34: Droit de timbre : taux apparents incohérents (janv. 2,0 %, févr. 1,0 %, avr. 5,05 %, mai 1,79 %) ; même base en avril et mai ; aucun timbre en mars et de juin à août. | F34: ='G50 2026'!J24 | G34: Justifier la base (ventes en espèces) et le taux appliqué. | I34: Ouvert
A35: A32 | B35: 1 | C35: Société | D35: Comptabilité | E35: Journal 2023 fourni provisoire : résultat 18,54 M contre 7,26 M repris en à-nouveau 2024 ; 38 comptes en écart avec les ouvertures 2024 (stocks, fournisseurs, banques, IBS, TVA). | F35: ='Contrôle 2023'!B6 | G35: Obtenir le journal 2023 définitif et la liasse fiscale 2023 ; documenter les écritures de clôture. | I35: Ouvert
A36: A33 | B36: 1 | C36: Société | D36: Clients / parties liées | E36: Créance SARL DPR AXXAM BRIQUETERIE : 371,0 M au 31/12/2025 (96 % du poste clients), en hausse continue depuis 2023 (277,7 M) ; 2023–2025 : 115,7 M facturés, 26,2 M encaissés (23 %). | F36: ='Démarrage 2026'!E8 | G36: Convention, reconnaissance de dette et échéancier ; confirmation de solde ; évaluer la dépréciation (Démarrage 2026, R7). | I36: Ouvert
A37: A34 | B37: 1 | C37: Société | D37: Clients / fiscal | E37: Avances clients (419) dormantes : 229,4 M sur 144 clients, inchangées depuis au moins le 01/01/2023 (hors associés et clients à compenser). Soit livraisons non facturées (CA et TVA non déclarés), soit dettes à rembourser. | F37: ='Démarrage 2026'!E35 | G37: Dossier par client ; facturer ou rembourser (R4 / R5) ; ne pas reprendre ces soldes tels quels en 2026. | I37: Ouvert
A38: A35 | B38: 1 | C38: Société | D38: Trésorerie / parties liées | E38: SARL DPR AXXAM : 62,5 M versés en 2025 (dont 45,35 M d'avances 409 sans facture) et 6,8 M remboursés en espèces, alors que la briqueterie du même groupe ne paie pas. | F38: ='Démarrage 2026'!B21 | G38: Justifier chaque avance (contrat, facture) ; stopper les avances sans convention. | I38: Ouvert
A39: A36 | B39: 2 | C39: Société | D39: Associés | E39: Associés (famille DJENNADI) logés en comptes clients / fournisseurs : soldes créditeurs en 411, 419 et 401. | F39: ='Démarrage 2026'!E26 | G39: Reclasser en 455 / 457 après attestation (R1). | I39: Ouvert
A40: A31 | B40: 3 | C40: Les deux | D40: Comptabilité | E40: Clients débiteurs 387,1 M et avances clients 314,6 M ; fournisseurs débiteurs 46,2 M au 31/12/2025. | G40: Lettrer les comptes clients/fournisseurs et compenser les avances soldées. | I40: Ouvert
A42: Impact : A01 = cotisations calculées de février ; A02 = cotisations de mars déclarées sans justificatif ; A03 = cotisations sur ponctualité ; A07 = cotisations T3 partielles (juil–août) ; A09 = frais de mission TPM cumulés ; A11 = cotisations déclarées sans preuve de paiement ; A12 = IRG cumulé à rapprocher.

Sheet Pièces
A1: Inventaire des pièces du dossier
A2: Reçues = transmises pour ce dossier ; Manquantes = à réclamer.
A4: N° | B4: Pièce | C4: Établissement | D4: Période | E4: Statut | F4: Remarque
A5: 1 | B5: PAIE_2026_DPR_COMPANY_IMPORT.xlsx — centralisateurs | C5: IMPORT | D5: Janv–août 2026 | E5: Reçue | F5: Onglet mars vide
A6: 2 | B6: PAIE_2026_DPR_COMPANY_TPM.xlsx — centralisateurs | C6: TPM | D6: Janv–août 2026 | E6: Reçue
A7: 3 | B7: CNAS_SARL_DPR_COMPANY_IMP_012026.pdf | C7: IMPORT | D7: Janvier 2026 | E7: Reçue | F7: Déposée 28/02/2026
A8: 4 | B8: CNAS_SARL_DPR_COMPANY_IMP_032026.pdf | C8: IMPORT | D8: Mars 2026 | E8: Reçue | F8: Déposée 28/04/2026
A9: 5 | B9: CNAS_T2_2026_SARL_DPR_COMPANY_IMPORT.pdf | C9: IMPORT | D9: T2 2026 | E9: Reçue | F9: Déposée 06/07/2026
A10: 6 | B10: CNAS_SARL_DPR_COMPANY_TPM_T1.pdf | C10: TPM | D10: T1 2026 | E10: Reçue | F10: Déposée 28/04/2026 (reçue en double, fichiers identiques)
A11: 7 | B11: CNAS_SARL_DPR_COMPANY_TPM_T2.pdf | C11: TPM | D11: T2 2026 | E11: Reçue | F11: Déposée 23/07/2026 ; EMS : 1 sortie
A12: 8 | B12: Déclaration CNAS + EMS février 2026 | C12: IMPORT | D12: Février 2026 | E12: Manquante | F12: 7 sorties attendues
A13: 9 | B13: Centralisateur / livre de paie mars 2026 | C13: IMPORT | D13: Mars 2026 | E13: Manquante
A14: 10 | B14: Centralisateurs septembre 2026 | C14: Les deux | D14: Septembre 2026 | E14: Manquante | F14: Nécessaires pour le T3
A15: 11 | B15: Déclarations CNAS T3 2026 | C15: Les deux | D15: T3 2026 | E15: Manquante | F15: Échéance 30/10/2026
A16: 12 | B16: Quittances / preuves de paiement CNAS | C16: Les deux | D16: 2026 | E16: Manquante | F16: Bordereaux à 0,00
A17: 13 | B17: G50_ARL_DPR_COMPANY_IMPORT_06-2026.xls | C17: IMPORT | D17: Juin 2026 | E17: Reçue | F17: TVA, IRG, précompte 178 353
A18: 14 | B18: G50_ARL_DPR_COMPANY_IMPORT_08-2026_.xls | C18: IMPORT | D18: Août 2026 | E18: Reçue | F18: TVA 838 600, IRG 49 670, TA 44 091
A19: 15 | B19: SARL_DPR_COMPAGNY_2024.xls — journal comptable PCCOMPTA | C19: Société | D19: Exercice 2024 | E19: Reçue | F19: 6 861 lignes, équilibré
A20: 16 | B20: SARL_DPR_COMPAGNY_2025.xls — journal comptable PCCOMPTA | C20: Société | D20: Exercice 2025 | E20: Reçue | F20: 5 774 lignes, équilibré
A21: 17 | B21: G50_ARL_DPR_COMPANY_IMPORT_03/04/05/07-2026.xls | C21: IMPORT | D21: Mars, avril, mai, juillet 2026 | E21: Reçue | F21: Série mars–août complète
A22: 18 | B22: G50_ARL_DPR_COMPANY_IMPORT_01/02-2026.xls | C22: IMPORT | D22: Janvier, février 2026 | E22: Reçue | F22: Série janv.–août complète
A23: 19 | B23: G50_07/08-2026_TPM_ET_LOCATION_CONSOLIDE.xls | C23: TPM | D23: Juillet, août 2026 | E23: Reçue | F23: Juillet : mois imprimé AVRIL
A24: 20 | B24: G50_04/05/06-2026_TPM_ET_LOCATION_CONSOLIDE.xls | C24: TPM | D24: Avril, mai, juin 2026 | E24: Reçue | F24: Identiques entre elles (mois AVRIL)
A25: 21 | B25: DLG_COMPTAZ_SARL_DPR_COMPAGNY_2023.xls — journal 2023 | C25: Société | D25: Exercice 2023 | E25: Reçue | F25: Version provisoire (voir A32)
... A33: 29 | B33: PV de caisse au 31/12/2025 | C33: Société | D33: 2025 | E33: Manquante | F33: Voir A22
A34: 30 | B34: Déclarations et paiements CACOBATPH | C34: Les deux | D34: 2026 | E34: Manquante
A35: 31 | B35: Livre de paie individuel / bulletins | C35: Les deux | D35: 2026 | E35: Manquante | F35: Pour contrôle IRG
A36: 32 | B36: Ordres de mission et justificatifs de frais | C36: TPM | D36: 2026 | E36: Manquante | F36: Frais de mission élevés
A37: 33 | B37: Relevés bancaires — virements de salaires | C37: Les deux | D37: 2026 | E37: Manquante | F37: Pour lettrage du 421
