Workbook

Sheet ECRITURES
A1: JOURNAL | B1: LIBELLE JOURNAL | C1: DATE | D1: N° PIECE | E1: REFERENCE | F1: COMPTE | G1: INTITULE COMPTE | H1: CODE TIERS | I1: NOM TIERS | J1: LIBELLE | K1: DEBIT | L1: CREDIT
A2: 01001 | B2: REOUVERTURE | C2: 46022 | F2: 10100 | G2: CAPITAL EMIS | J2: REOUVERTURE AU 01/01/26 | K2: 0 | L2: 106000000
A3: 01001 | B3: REOUVERTURE | C3: 46022 | F3: 10500 | G3: Ecart de réévaluation | J3: REOUVERTURE AU 01/01/26 | K3: 0 | L3: 120163.5
A4: 01001 | B4: REOUVERTURE | C4: 46022 | F4: 10610 | G4: RESERVES LEGALES | J4: REOUVERTURE AU 01/01/26 | K4: 0 | L4: 7003771.4
A5: 01001 | B5: REOUVERTURE | C5: 46022 | F5: 10611 | G5: BENEFICES A REINVESTIR | J5: REOUVERTURE AU 01/01/26 | K5: 0 | L5: 25922342
A6: 01001 | B6: REOUVERTURE | C6: 46022 | F6: 10620 | G6: RESERVES STATUTAIRES | J6: REOUVERTURE AU 01/01/26 | K6: 0 | L6: 211183
A7: 01001 | B7: REOUVERTURE | C7: 46022 | F7: 10630 | G7: RESERVES FACULTATIVES | J7: REOUVERTURE AU 01/01/26 | K7: 0 | L7: 44091060
A8: 01001 | B8: REOUVERTURE | C8: 46022 | F8: 11000 | G8: REPORT A NOUVEAU | J8: REOUVERTURE AU 01/01/26 | K8: 1508496.6 | L8: 0
A9: 01001 | B9: REOUVERTURE | C9: 46022 | F9: 11001 | G9: AJUST RESUL CH METHODE CPTE | J9: REOUVERTURE AU 01/01/26 | K9: 150790.11 | L9: 0
A10: 01001 | B10: REOUVERTURE | C10: 46022 | F10: 21100 | G10: TERRAINS | J10: REOUVERTURE AU 01/01/26 | K10: 21600000 | L10: 0
A11: 01001 | B11: REOUVERTURE | C11: 46022 | F11: 21300 | G11: Constructions | J11: REOUVERTURE AU 01/01/26 | K11: 13891000 | L11: 0
A12: 01001 | B12: REOUVERTURE | C12: 46022 | F12: 21301 | G12: CHARPENTE METALIQUE | J12: REOUVERTURE AU 01/01/26 | K12: 20222222 | L12: 0
A13: 01001 | B13: REOUVERTURE | C13: 46022 | F13: 21500 | G13: INSTALATIONS TECHNIQUES,MAERIE | J13: REOUVERTURE AU 01/01/26 | K13: 2713848.8 | L13: 0
... A25: 01001 | B25: REOUVERTURE | C25: 46022 | F25: 30002 | G25: ST IMPORTATION | J25: REOUVERTURE AU 01/01/26 | K25: 2.2873401e+08 | L25: 0
A26: 01001 | B26: REOUVERTURE | C26: 46022 | F26: 40100 | G26: Fournisseurs de stocks et serv | H26: FL001 | I26: DJENNADI ABD ELKADER | J26: REOUVERTURE AU 01/01/26 | K26: 0 | L26: 2510665
A27: 01001 | B27: REOUVERTURE | C27: 46022 | F27: 40100 | G27: Fournisseurs de stocks et serv | H27: FL002 | I27: EURL HAROUNE TRANSE | J27: REOUVERTURE AU 01/01/26 | K27: 0 | L27: 826173.63
A28: 01001 | B28: REOUVERTURE | C28: 46022 | F28: 40100 | G28: Fournisseurs de stocks et serv | H28: FL003 | I28: SARL CCI | J28: REOUVERTURE AU 01/01/26 | K28: 0 | L28: 3302997.5
A29: 01001 | B29: REOUVERTURE | C29: 46022 | F29: 40100 | G29: Fournisseurs de stocks et serv | H29: FL005 | I29: KARIM TRANS | J29: REOUVERTURE AU 01/01/26 | K29: 0 | L29: 177751.46
A30: 01001 | B30: REOUVERTURE | C30: 46022 | F30: 40100 | G30: Fournisseurs de stocks et serv | H30: FL025 | I30: SAIGH ABDEL KAMEL | J30: REOUVERTURE AU 01/01/26 | K30: 0 | L30: 142700
A31: 01001 | B31: REOUVERTURE | C31: 46022 | F31: 40100 | G31: Fournisseurs de stocks et serv | H31: FL031 | I31: SARL DPR AXXAM | J31: REOUVERTURE AU 01/01/26 | K31: 0 | L31: 1984749
A32: 01001 | B32: REOUVERTURE | C32: 46022 | F32: 40100 | G32: Fournisseurs de stocks et serv | H32: FL044 | I32: SNC AIT AISSA ET FILS | J32: REOUVERTURE AU 01/01/26 | K32: 0 | L32: 14832876
A33: 01001 | B33: REOUVERTURE | C33: 46022 | F33: 40100 | G33: Fournisseurs de stocks et serv | H33: FL045 | I33: GAMMA LUBRIFIANTS | J33: REOUVERTURE AU 01/01/26 | K33: 0 | L33: 926579.49
A34: 01001 | B34: REOUVERTURE | C34: 46022 | F34: 40100 | G34: Fournisseurs de stocks et serv | H34: FL051 | I34: DJERMOULI KAMAL ABDENNOUR | J34: REOUVERTURE AU 01/01/26 | K34: 0 | L34: 9100
A35: 01001 | B35: REOUVERTURE | C35: 46022 | F35: 40100 | G35: Fournisseurs de stocks et serv | H35: FL064 | I35: STATION GAMMA 4 | J35: REOUVERTURE AU 01/01/26 | K35: 0 | L35: 153309.95
A36: 01001 | B36: REOUVERTURE | C36: 46022 | F36: 40100 | G36: Fournisseurs de stocks et serv | H36: FL076 | I36: SNC DEBBOUZ ET FRERES | J36: REOUVERTURE AU 01/01/26 | K36: 0 | L36: 738432.49
A37: 01001 | B37: REOUVERTURE | C37: 46022 | F37: 40100 | G37: Fournisseurs de stocks et serv | H37: FL078 | I37: TRANSIT HAMMACHE DJAMEL | J37: REOUVERTURE AU 01/01/26 | K37: 0 | L37: 62000
... A95: 01001 | B95: REOUVERTURE | C95: 46022 | F95: 41100 | G95: Clients | H95: C978 | I95: SPA AGGLOMERES DE L'EST | J95: REOUVERTURE AU 01/01/26 | K95: 67830 | L95: 0
A96: 01001 | B96: REOUVERTURE | C96: 46022 | F96: 41170 | G96: CLIENTS-RETENUES DE GARANTIE | J96: REOUVERTURE AU 01/01/26 | K96: 490717.68 | L96: 0
A97: 01001 | B97: REOUVERTURE | C97: 46022 | F97: 41900 | G97: Clients créditeurs -avances re | H97: AC002 | I97: DJENNADI AHCENE | J97: REOUVERTURE AU 01/01/26 | K97: 0 | L97: 500000
A98: 01001 | B98: REOUVERTURE | C98: 46022 | F98: 41900 | G98: Clients créditeurs -avances re | H98: AC009 | I98: SARL DPR AXXAM | J98: REOUVERTURE AU 01/01/26 | K98: 0 | L98: 9821942.2
A99: 01001 | B99: REOUVERTURE | C99: 46022 | F99: 41900 | G99: Clients créditeurs -avances re | H99: AC014 | I99: SARL TRANS FAID | J99: REOUVERTURE AU 01/01/26 | K99: 0 | L99: 1843316.1
A100: 01001 | B100: REOUVERTURE | C100: 46022 | F100: 41900 | G100: Clients créditeurs -avances re | H100: AC048 | I100: MADI ALLAOUA | J100: REOUVERTURE AU 01/01/26 | K100: 0 | L100: 2660000
A101: 01001 | B101: REOUVERTURE | C101: 46022 | F101: 41900 | G101: Clients créditeurs -avances re | H101: AC067 | I101: DJENNADI REYAD | J101: REOUVERTURE AU 01/01/26 | K101: 0 | L101: 17609544
A102: 01001 | B102: REOUVERTURE | C102: 46022 | F102: 41900 | G102: Clients créditeurs -avances re | H102: AC111 | I102: SNC NASAF GALOUL ET CIE | J102: REOUVERTURE AU 01/01/26 | K102: 0 | L102: 1929169.5
A103: 01001 | B103: REOUVERTURE | C103: 46022 | F103: 41900 | G103: Clients créditeurs -avances re | H103: AC129 | I103: HAGROUD ABD ELAZIZE | J103: REOUVERTURE AU 01/01/26 | K103: 0 | L103: 48000
A104: 01001 | B104: REOUVERTURE | C104: 46022 | F104: 41900 | G104: Clients créditeurs -avances re | H104: AC144 | I104: SELLAH ABD ELGHANI | J104: REOUVERTURE AU 01/01/26 | K104: 0 | L104: 300000
A105: 01001 | B105: REOUVERTURE | C105: 46022 | F105: 41900 | G105: Clients créditeurs -avances re | H105: AC145 | I105: EURL CARRIER LES BIBIANS | J105: REOUVERTURE AU 01/01/26 | K105: 0 | L105: 800000
A106: 01001 | B106: REOUVERTURE | C106: 46022 | F106: 41900 | G106: Clients créditeurs -avances re | H106: AC189 | I106: MECHREF MOUHOUB | J106: REOUVERTURE AU 01/01/26 | K106: 0 | L106: 3509008.3
A107: 01001 | B107: REOUVERTURE | C107: 46022 | F107: 41900 | G107: Clients créditeurs -avances re | H107: AC191 | I107: OUKHALED YASSINE | J107: REOUVERTURE AU 01/01/26 | K107: 0 | L107: 5638.26
A108: 01001 | B108: REOUVERTURE | C108: 46022 | F108: 41900 | G108: Clients créditeurs -avances re | H108: AC206 | I108: CHEBBAH NACER | J108: REOUVERTURE AU 01/01/26 | K108: 0 | L108: 100000
... A256: 01001 | B256: REOUVERTURE | C256: 46022 | F256: 41900 | G256: Clients créditeurs -avances re | H256: AC475 | I256: KADOUR AMAR | J256: REOUVERTURE AU 01/01/26 | K256: 0 | L256: 240000
A257: 01001 | B257: REOUVERTURE | C257: 46022 | F257: 41910 | G257: AVANCES RECUES DES CLIENTS | J257: REOUVERTURE AU 01/01/26 | K257: 0 | L257: 1612881
A258: 01001 | B258: REOUVERTURE | C258: 46022 | F258: 42100 | G258: PERSONNEL,REMUNERATIONS DUES | H258: DCT006 | I258: BRAHMI SAID | J258: REOUVERTURE AU 01/01/26 | K258: 0 | L258: 46503.86
A259: 01001 | B259: REOUVERTURE | C259: 46022 | F259: 42100 | G259: PERSONNEL,REMUNERATIONS DUES | H259: DCT013 | I259: EL HOUANNES ZAHIR | J259: REOUVERTURE AU 01/01/26 | K259: 0 | L259: 73082.52
A260: 01001 | B260: REOUVERTURE | C260: 46022 | F260: 42100 | G260: PERSONNEL,REMUNERATIONS DUES | H260: DCT014 | I260: EL HOUANNES BOUALEM | J260: REOUVERTURE AU 01/01/26 | K260: 0 | L260: 51000.98
A261: 01001 | B261: REOUVERTURE | C261: 46022 | F261: 42100 | G261: PERSONNEL,REMUNERATIONS DUES | H261: SDC001 | I261: DJENNADI ABDELKRIM | J261: REOUVERTURE AU 01/01/26 | K261: 0 | L261: 68067
A262: 01001 | B262: REOUVERTURE | C262: 46022 | F262: 42100 | G262: PERSONNEL,REMUNERATIONS DUES | H262: SDC029 | I262: DJENNADI ZOUBIDA | J262: REOUVERTURE AU 01/01/26 | K262: 0 | L262: 27743
A263: 01001 | B263: REOUVERTURE | C263: 46022 | F263: 42100 | G263: PERSONNEL,REMUNERATIONS DUES | H263: SDC038 | I263: BOUDJEDIA DJILLALI | J263: REOUVERTURE AU 01/01/26 | K263: 0 | L263: 64000.71
A264: 01001 | B264: REOUVERTURE | C264: 46022 | F264: 42100 | G264: PERSONNEL,REMUNERATIONS DUES | H264: SDC041 | I264: CHILLAOUI ATMANE | J264: REOUVERTURE AU 01/01/26 | K264: 0 | L264: 93002.93
A265: 01001 | B265: REOUVERTURE | C265: 46022 | F265: 42100 | G265: PERSONNEL,REMUNERATIONS DUES | H265: SDC043 | I265: AIT MATEN SOUAD | J265: REOUVERTURE AU 01/01/26 | K265: 0 | L265: 65130.02
A266: 01001 | B266: REOUVERTURE | C266: 46022 | F266: 42100 | G266: PERSONNEL,REMUNERATIONS DUES | H266: SDC046 | I266: TIDJET SOFIANE | J266: REOUVERTURE AU 01/01/26 | K266: 0 | L266: 52875.62
A267: 01001 | B267: REOUVERTURE | C267: 46022 | F267: 42100 | G267: PERSONNEL,REMUNERATIONS DUES | H267: SDC053 | I267: KALI RYAD | J267: REOUVERTURE AU 01/01/26 | K267: 0 | L267: 68201.86
A268: 01001 | B268: REOUVERTURE | C268: 46022 | F268: 42100 | G268: PERSONNEL,REMUNERATIONS DUES | H268: SDC075 | I268: BENSEKHRI MAHDI | J268: REOUVERTURE AU 01/01/26 | K268: 0 | L268: 87000.35
A269: 01001 | B269: REOUVERTURE | C269: 46022 | F269: 42100 | G269: PERSONNEL,REMUNERATIONS DUES | H269: SDC077 | I269: BENMAMMAR NASSIM | J269: REOUVERTURE AU 01/01/26 | K269: 0 | L269: 88685.77
... A272: 01001 | B272: REOUVERTURE | C272: 46022 | F272: 42100 | G272: PERSONNEL,REMUNERATIONS DUES | H272: SDC085 | I272: BELHADI AHCENE ADEL | J272: REOUVERTURE AU 01/01/26 | K272: 0 | L272: 42903.07
A273: 01001 | B273: REOUVERTURE | C273: 46022 | F273: 43100 | G273: SECURITE SOCIALE | J273: REOUVERTURE AU 01/01/26 | K273: 0 | L273: 154771.05
A274: 01001 | B274: REOUVERTURE | C274: 46022 | F274: 43200 | G274: Autres organismes sociaux | J274: REOUVERTURE AU 01/01/26 | K274: 0 | L274: 447116.45
A275: 01001 | B275: REOUVERTURE | C275: 46022 | F275: 44210 | G275: RETENUES : IRG | J275: REOUVERTURE AU 01/01/26 | K275: 0 | L275: 139890.6
A276: 01001 | B276: REOUVERTURE | C276: 46022 | F276: 44400 | G276: Etat, impôts sur les résultats | J276: REOUVERTURE AU 01/01/26 | K276: 0 | L276: 9791549.2
A277: 01001 | B277: REOUVERTURE | C277: 46022 | F277: 44410 | G277: AVANCES ET ACOMPTES SUR IBS | J277: REOUVERTURE AU 01/01/26 | K277: 6148598 | L277: 0
A278: 01001 | B278: REOUVERTURE | C278: 46022 | F278: 44501 | G278: TVA DEDUCT S/INVEST. A 17 % | J278: REOUVERTURE AU 01/01/26 | K278: 541052 | L278: 0
A279: 01001 | B279: REOUVERTURE | C279: 46022 | F279: 44510 | G279: TVA A PAYER | J279: REOUVERTURE AU 01/01/26 | K279: 0 | L279: 5672989
A280: 01001 | B280: REOUVERTURE | C280: 46022 | F280: 44517 | G280: TVA COLLECTEE S/VENTES A 17 % | J280: REOUVERTURE AU 01/01/26 | K280: 100569.85 | L280: 0
A281: 01001 | B281: REOUVERTURE | C281: 46022 | F281: 44527 | G281: TVA COLLECTEE/VENTES LOCATION | J281: REOUVERTURE AU 01/01/26 | K281: 0 | L281: 6708151
A282: 01001 | B282: REOUVERTURE | C282: 46022 | F282: 44537 | G282: TVA COLLECTEE/VENTES TPM | J282: REOUVERTURE AU 01/01/26 | K282: 0 | L282: 52174400
A283: 01001 | B283: REOUVERTURE | C283: 46022 | F283: 44550 | G283: PRECOMPTE | J283: REOUVERTURE AU 01/01/26 | K283: 1714499 | L283: 0
A284: 01001 | B284: REOUVERTURE | C284: 46022 | F284: 44552 | G284: TVA RECUPERABLE LOCATION | J284: REOUVERTURE AU 01/01/26 | K284: 2822747 | L284: 0
... A303: 01001 | B303: REOUVERTURE | C303: 46022 | F303: 12000 | G303: RESULTAT DE L'EXERCICE | J303: REOUVERTURE AU 01/01/26 | K303: 0 | L303: 19112570
A304: 07001 | B304: JOURNAL DE REGULARISATION | C304: 46023 | D304: 00001 | E304: 00370-376984 | F304: 51220 | G304: CPA AGENCE EL KSEUR | J304: REGUL 31/12/25 DEGAGEMENT CAIS | K304: 10000000 | L304: 0
A305: 07001 | B305: JOURNAL DE REGULARISATION | C305: 46023 | D305: 00001 | E305: 00370-376984 | F305: 58100 | G305: VIREMENTS DE FONDS | J305: REGUL 31/12/25 DEGAGEMENT CAIS | K305: 0 | L305: 10000000
A306: 07001 | B306: JOURNAL DE REGULARISATION | C306: 46023 | D306: 00002 | E306: 00370-025250 | F306: 51220 | G306: CPA AGENCE EL KSEUR | J306: REGUL 31/12/25 EXTRAIT DE COMP | K306: 0 | L306: 249.9
A307: 07001 | B307: JOURNAL DE REGULARISATION | C307: 46023 | D307: 00002 | E307: 00370-025250 | F307: 62750 | G307: COMMISSIONS DIVERSES | J307: REGUL 31/12/25 EXTRAIT DE COMP | K307: 210 | L307: 0
A308: 07001 | B308: JOURNAL DE REGULARISATION | C308: 46023 | D308: 00002 | E308: 00370-025250 | F308: 44557 | G308: TVA RECUPERABLES | J308: REGUL 31/12/25 EXTRAIT DE COMP | K308: 39.9 | L308: 0
A309: 07001 | B309: JOURNAL DE REGULARISATION | C309: 46023 | D309: 00003 | E309: 00370-001038 | F309: 51220 | G309: CPA AGENCE EL KSEUR | J309: REGUL 31/12/25 COM.VRT EDI BQU | K309: 0 | L309: 35.7
A310: 07001 | B310: JOURNAL DE REGULARISATION | C310: 46023 | D310: 00003 | E310: 00370-001038 | F310: 62750 | G310: COMMISSIONS DIVERSES | J310: REGUL 31/12/25 COM.VRT EDI BQU | K310: 30 | L310: 0
A311: 07001 | B311: JOURNAL DE REGULARISATION | C311: 46023 | D311: 00003 | E311: 00370-001038 | F311: 44557 | G311: TVA RECUPERABLES | J311: REGUL 31/12/25 COM.VRT EDI BQU | K311: 5.7 | L311: 0
A312: 07001 | B312: JOURNAL DE REGULARISATION | C312: 46023 | D312: 00004 | E312: 00370-001038 | F312: 51220 | G312: CPA AGENCE EL KSEUR | J312: REGUL 31/12/25 VRT EDI SIMPLE | K312: 0 | L312: 800000
A313: 07001 | B313: JOURNAL DE REGULARISATION | C313: 46023 | D313: 00004 | E313: 00370-001038 | F313: 47000 | G313: Comptes transitoires ou d'atte | J313: REGUL 31/12/25 VRT EDI SIMPLE | K313: 800000 | L313: 0
A314: 07001 | B314: JOURNAL DE REGULARISATION | C314: 46023 | D314: 00005 | E314: 99000-057589 | F314: 51220 | G314: CPA AGENCE EL KSEUR | J314: REGUL 31/12/25 REMISE CHQ 5758 | K314: 252000 | L314: 0
A315: 07001 | B315: JOURNAL DE REGULARISATION | C315: 46023 | D315: 00005 | E315: 99000-057589 | F315: 47000 | G315: Comptes transitoires ou d'atte | J315: REGUL 31/12/25 REMISE CHQ 5758 | K315: 0 | L315: 252000
A316: 07001 | B316: JOURNAL DE REGULARISATION | C316: 46023 | D316: 00006 | E316: 99000-065346 | F316: 51220 | G316: CPA AGENCE EL KSEUR | J316: REGUL 31/12/25 SARL ATELIER SE | K316: 1154000 | L316: 0
A317: 07001 | B317: JOURNAL DE REGULARISATION | C317: 46023 | D317: 00006 | E317: 99000-065346 | F317: 41100 | G317: Clients | H317: C1047 | I317: SARL ATELIER SERVICES TRUCKS | J317: REGUL 31/12/25 SARL ATELIER SE | K317: 0 | L317: 1154000
A318: 07001 | B318: JOURNAL DE REGULARISATION | C318: 46023 | D318: 00007 | E318: 99000-065346 | F318: 51220 | G318: CPA AGENCE EL KSEUR | J318: REGUL 31/12/25 FRAIS REMISE CH | K318: 0 | L318: 238
A319: 07001 | B319: JOURNAL DE REGULARISATION | C319: 46023 | D319: 00007 | E319: 99000-065346 | F319: 62750 | G319: COMMISSIONS DIVERSES | J319: REGUL 31/12/25 FRAIS REMISE CH | K319: 200 | L319: 0
A320: 07001 | B320: JOURNAL DE REGULARISATION | C320: 46023 | D320: 00007 | E320: 99000-065346 | F320: 44557 | G320: TVA RECUPERABLES | J320: REGUL 31/12/25 FRAIS REMISE CH | K320: 38 | L320: 0
A321: 07001 | B321: JOURNAL DE REGULARISATION | C321: 46023 | D321: 00008 | E321: 00370-000198 | F321: 51220 | G321: CPA AGENCE EL KSEUR | J321: REGUL 31/12/25 ACCEPTA RE00370 | K321: 0 | L321: 4165
A322: 07001 | B322: JOURNAL DE REGULARISATION | C322: 46023 | D322: 00008 | E322: 00370-000198 | F322: 62750 | G322: COMMISSIONS DIVERSES | J322: REGUL 31/12/25 ACCEPTA RE00370 | K322: 3500 | L322: 0
A323: 07001 | B323: JOURNAL DE REGULARISATION | C323: 46023 | D323: 00008 | E323: 00370-000198 | F323: 44557 | G323: TVA RECUPERABLES | J323: REGUL 31/12/25 ACCEPTA RE00370 | K323: 665 | L323: 0
A324: 07001 | B324: JOURNAL DE REGULARISATION | C324: 46023 | D324: 00009 | E324: 00370-000331 | F324: 51220 | G324: CPA AGENCE EL KSEUR | J324: REGUL 31/12/25 OPERATION PROV | K324: 0 | L324: 1200000
A325: 07001 | B325: JOURNAL DE REGULARISATION | C325: 46023 | D325: 00009 | E325: 00370-000331 | F325: 54200 | G325: ACCREDITIFS | J325: REGUL 31/12/25 OPERATION PROV | K325: 1200000 | L325: 0
A326: 07001 | B326: JOURNAL DE REGULARISATION | C326: 46023 | D326: 00010 | E326: 99000-054075 | F326: 51220 | G326: CPA AGENCE EL KSEUR | J326: REGUL 31/12/25 FRAIS FIXE AU 3 | K326: 0 | L326: 375
A327: 07001 | B327: JOURNAL DE REGULARISATION | C327: 46023 | D327: 00010 | E327: 99000-054075 | F327: 62750 | G327: COMMISSIONS DIVERSES | J327: REGUL 31/12/25 FRAIS FIXE AU 3 | K327: 315.13 | L327: 0
A328: 07001 | B328: JOURNAL DE REGULARISATION | C328: 46023 | D328: 00010 | E328: 99000-054075 | F328: 44557 | G328: TVA RECUPERABLES | J328: REGUL 31/12/25 FRAIS FIXE AU 3 | K328: 59.87 | L328: 0
A329: 07001 | B329: JOURNAL DE REGULARISATION | C329: 46023 | D329: 00011 | E329: 99000-054075 | F329: 51220 | G329: CPA AGENCE EL KSEUR | J329: REGUL 31/12/25 INTERETS DEBITE | K329: 0 | L329: 88705.68
... A334: 07001 | B334: JOURNAL DE REGULARISATION | C334: 46023 | D334: 00013 | E334: 99000-054075 | F334: 44557 | G334: TVA RECUPERABLES | J334: REGUL 31/12/25 TAXE FRAIS FIXE | K334: 71.25 | L334: 0
A335: 07001 | B335: JOURNAL DE REGULARISATION | C335: 46023 | D335: 00014 | F335: 58100 | G335: VIREMENTS DE FONDS | J335: REGUL CAISSE VERST 31/12/25 | K335: 10000000 | L335: 0
A336: 07001 | B336: JOURNAL DE REGULARISATION | C336: 46023 | D336: 00014 | F336: 53000 | G336: CAISSE | J336: REGUL CAISSE VERST 31/12/25 | K336: 0 | L336: 10000000
A337: 02001 | B337: BANQUE CPA | C337: 46026 | D337: 000001 | E337: 00370-012760 | F337: 51220 | G337: CPA AGENCE EL KSEUR | J337: FRAIS VRT. | K337: 0 | L337: 59.5
A338: 02001 | B338: BANQUE CPA | C338: 46026 | D338: 000001 | E338: 00370-012760 | F338: 62750 | G338: COMMISSIONS DIVERSES | J338: FRAIS VRT. | K338: 50 | L338: 0
A339: 02001 | B339: BANQUE CPA | C339: 46026 | D339: 000001 | E339: 00370-012760 | F339: 44557 | G339: TVA RECUPERABLES | J339: FRAIS VRT. | K339: 9.5 | L339: 0
...

Sheet JOURNAUX
A1: JOURNAL | B1: LIBELLE | C1: NB LIGNES | D1: TOTAL DEBIT | E1: TOTAL CREDIT | F1: ECART
A2: 01001 | B2: REOUVERTURE | C2: =SUMPRODUCT((ECRITURES!$A$2:$A$3071=A2)*1) | D2: =SUMPRODUCT((ECRITURES!$A$2:$A$3071=A2)*ECRITURES!$K$2:$K$3071) | E2: =SUMPRODUCT((ECRITURES!$A$2:$A$3071=A2)*ECRITURES!$L$2:$L$3071) | F2: =D2-E2
A3: 07001 | B3: JOURNAL DE REGULARISATION | C3: =SUMPRODUCT((ECRITURES!$A$2:$A$3071=A3)*1) | D3: =SUMPRODUCT((ECRITURES!$A$2:$A$3071=A3)*ECRITURES!$K$2:$K$3071) | E3: =SUMPRODUCT((ECRITURES!$A$2:$A$3071=A3)*ECRITURES!$L$2:$L$3071) | F3: =D3-E3
A4: 02001 | B4: BANQUE CPA | C4: =SUMPRODUCT((ECRITURES!$A$2:$A$3071=A4)*1) | D4: =SUMPRODUCT((ECRITURES!$A$2:$A$3071=A4)*ECRITURES!$K$2:$K$3071) | E4: =SUMPRODUCT((ECRITURES!$A$2:$A$3071=A4)*ECRITURES!$L$2:$L$3071) | F4: =D4-E4
A5: 16001 | B5: BANQUE SOCIETE GENERALE | C5: =SUMPRODUCT((ECRITURES!$A$2:$A$3071=A5)*1) | D5: =SUMPRODUCT((ECRITURES!$A$2:$A$3071=A5)*ECRITURES!$K$2:$K$3071) | E5: =SUMPRODUCT((ECRITURES!$A$2:$A$3071=A5)*ECRITURES!$L$2:$L$3071) | F5: =D5-E5
A6: 05001 | B6: ACHATS IMPORTATION | C6: =SUMPRODUCT((ECRITURES!$A$2:$A$3071=A6)*1) | D6: =SUMPRODUCT((ECRITURES!$A$2:$A$3071=A6)*ECRITURES!$K$2:$K$3071) | E6: =SUMPRODUCT((ECRITURES!$A$2:$A$3071=A6)*ECRITURES!$L$2:$L$3071) | F6: =D6-E6
A7: 10001 | B7: STOCKS | C7: =SUMPRODUCT((ECRITURES!$A$2:$A$3071=A7)*1) | D7: =SUMPRODUCT((ECRITURES!$A$2:$A$3071=A7)*ECRITURES!$K$2:$K$3071) | E7: =SUMPRODUCT((ECRITURES!$A$2:$A$3071=A7)*ECRITURES!$L$2:$L$3071) | F7: =D7-E7
A8: 06002 | B8: VENTES | C8: =SUMPRODUCT((ECRITURES!$A$2:$A$3071=A8)*1) | D8: =SUMPRODUCT((ECRITURES!$A$2:$A$3071=A8)*ECRITURES!$K$2:$K$3071) | E8: =SUMPRODUCT((ECRITURES!$A$2:$A$3071=A8)*ECRITURES!$L$2:$L$3071) | F8: =D8-E8
A9: 15001 | B9: VENTES DETAIL FENAIA | C9: =SUMPRODUCT((ECRITURES!$A$2:$A$3071=A9)*1) | D9: =SUMPRODUCT((ECRITURES!$A$2:$A$3071=A9)*ECRITURES!$K$2:$K$3071) | E9: =SUMPRODUCT((ECRITURES!$A$2:$A$3071=A9)*ECRITURES!$L$2:$L$3071) | F9: =D9-E9
A10: 08002 | B10: OPPERATION DIVERS | C10: =SUMPRODUCT((ECRITURES!$A$2:$A$3071=A10)*1) | D10: =SUMPRODUCT((ECRITURES!$A$2:$A$3071=A10)*ECRITURES!$K$2:$K$3071) | E10: =SUMPRODUCT((ECRITURES!$A$2:$A$3071=A10)*ECRITURES!$L$2:$L$3071) | F10: =D10-E10
A11: 14002 | B11: OD TPM ET LOCATION | C11: =SUMPRODUCT((ECRITURES!$A$2:$A$3071=A11)*1) | D11: =SUMPRODUCT((ECRITURES!$A$2:$A$3071=A11)*ECRITURES!$K$2:$K$3071) | E11: =SUMPRODUCT((ECRITURES!$A$2:$A$3071=A11)*ECRITURES!$L$2:$L$3071) | F11: =D11-E11

Sheet BALANCE
A1: COMPTE | B1: INTITULE | C1: DEBIT | D1: CREDIT | E1: SOLDE DEBITEUR | F1: SOLDE CREDITEUR
A2: 10100 | B2: CAPITAL EMIS | C2: =SUMPRODUCT((ECRITURES!$F$2:$F$3071=A2)*ECRITURES!$K$2:$K$3071) | D2: =SUMPRODUCT((ECRITURES!$F$2:$F$3071=A2)*ECRITURES!$L$2:$L$3071) | E2: =MAX(C2-D2,0) | F2: =MAX(D2-C2,0)
A3: 10500 | B3: Ecart de réévaluation | C3: =SUMPRODUCT((ECRITURES!$F$2:$F$3071=A3)*ECRITURES!$K$2:$K$3071) | D3: =SUMPRODUCT((ECRITURES!$F$2:$F$3071=A3)*ECRITURES!$L$2:$L$3071) | E3: =MAX(C3-D3,0) | F3: =MAX(D3-C3,0)
A4: 10610 | B4: RESERVES LEGALES | C4: =SUMPRODUCT((ECRITURES!$F$2:$F$3071=A4)*ECRITURES!$K$2:$K$3071) | D4: =SUMPRODUCT((ECRITURES!$F$2:$F$3071=A4)*ECRITURES!$L$2:$L$3071) | E4: =MAX(C4-D4,0) | F4: =MAX(D4-C4,0)
A5: 10611 | B5: BENEFICES A REINVESTIR | C5: =SUMPRODUCT((ECRITURES!$F$2:$F$3071=A5)*ECRITURES!$K$2:$K$3071) | D5: =SUMPRODUCT((ECRITURES!$F$2:$F$3071=A5)*ECRITURES!$L$2:$L$3071) | E5: =MAX(C5-D5,0) | F5: =MAX(D5-C5,0)
A6: 10620 | B6: RESERVES STATUTAIRES | C6: =SUMPRODUCT((ECRITURES!$F$2:$F$3071=A6)*ECRITURES!$K$2:$K$3071) | D6: =SUMPRODUCT((ECRITURES!$F$2:$F$3071=A6)*ECRITURES!$L$2:$L$3071) | E6: =MAX(C6-D6,0) | F6: =MAX(D6-C6,0)
A7: 10630 | B7: RESERVES FACULTATIVES | C7: =SUMPRODUCT((ECRITURES!$F$2:$F$3071=A7)*ECRITURES!$K$2:$K$3071) | D7: =SUMPRODUCT((ECRITURES!$F$2:$F$3071=A7)*ECRITURES!$L$2:$L$3071) | E7: =MAX(C7-D7,0) | F7: =MAX(D7-C7,0)
A8: 11000 | B8: REPORT A NOUVEAU | C8: =SUMPRODUCT((ECRITURES!$F$2:$F$3071=A8)*ECRITURES!$K$2:$K$3071) | D8: =SUMPRODUCT((ECRITURES!$F$2:$F$3071=A8)*ECRITURES!$L$2:$L$3071) | E8: =MAX(C8-D8,0) | F8: =MAX(D8-C8,0)
A9: 11001 | B9: AJUST RESUL CH METHODE CPTE | C9: =SUMPRODUCT((ECRITURES!$F$2:$F$3071=A9)*ECRITURES!$K$2:$K$3071) | D9: =SUMPRODUCT((ECRITURES!$F$2:$F$3071=A9)*ECRITURES!$L$2:$L$3071) | E9: =MAX(C9-D9,0) | F9: =MAX(D9-C9,0)
A10: 12000 | B10: RESULTAT DE L'EXERCICE | C10: =SUMPRODUCT((ECRITURES!$F$2:$F$3071=A10)*ECRITURES!$K$2:$K$3071) | D10: =SUMPRODUCT((ECRITURES!$F$2:$F$3071=A10)*ECRITURES!$L$2:$L$3071) | E10: =MAX(C10-D10,0) | F10: =MAX(D10-C10,0)
A11: 21100 | B11: TERRAINS | C11: =SUMPRODUCT((ECRITURES!$F$2:$F$3071=A11)*ECRITURES!$K$2:$K$3071) | D11: =SUMPRODUCT((ECRITURES!$F$2:$F$3071=A11)*ECRITURES!$L$2:$L$3071) | E11: =MAX(C11-D11,0) | F11: =MAX(D11-C11,0)
A12: 21300 | B12: Constructions | C12: =SUMPRODUCT((ECRITURES!$F$2:$F$3071=A12)*ECRITURES!$K$2:$K$3071) | D12: =SUMPRODUCT((ECRITURES!$F$2:$F$3071=A12)*ECRITURES!$L$2:$L$3071) | E12: =MAX(C12-D12,0) | F12: =MAX(D12-C12,0)
A13: 21301 | B13: CHARPENTE METALIQUE | C13: =SUMPRODUCT((ECRITURES!$F$2:$F$3071=A13)*ECRITURES!$K$2:$K$3071) | D13: =SUMPRODUCT((ECRITURES!$F$2:$F$3071=A13)*ECRITURES!$L$2:$L$3071) | E13: =MAX(C13-D13,0) | F13: =MAX(D13-C13,0)
... A91: 76800 | B91: Autres produits financiers | C91: =SUMPRODUCT((ECRITURES!$F$2:$F$3071=A91)*ECRITURES!$K$2:$K$3071) | D91: =SUMPRODUCT((ECRITURES!$F$2:$F$3071=A91)*ECRITURES!$L$2:$L$3071) | E91: =MAX(C91-D91,0) | F91: =MAX(D91-C91,0)
B92: TOTAL | C92: =SUM(C2:C91) | D92: =SUM(D2:D91) | E92: =SUM(E2:E91) | F92: =SUM(F2:F91)

Sheet PLAN COMPTABLE
A1: COMPTE | B1: INTITULE
A2: 10100 | B2: CAPITAL EMIS
A3: 10500 | B3: Ecart de réévaluation
A4: 10610 | B4: RESERVES LEGALES
A5: 10611 | B5: BENEFICES A REINVESTIR
A6: 10620 | B6: RESERVES STATUTAIRES
A7: 10630 | B7: RESERVES FACULTATIVES
A8: 10700 | B8: Ecart d'équivalence
A9: 10800
A10: 11000 | B10: REPORT A NOUVEAU
A11: 11001 | B11: AJUST RESUL CH METHODE CPTE
A12: 12000 | B12: RESULTAT DE L'EXERCICE
A13: 13300 | B13: Impôts différés actif
A14: 16400 | B14: Emprunts auprès des établissem
A15: 16401 | B15: EMPRUNT ENGINS
A16: 16402 | B16: EMPRUNT 2016
A17: 18100 | B17: Comptes de liaison entre établ
A18: 21100 | B18: TERRAINS
A19: 21200 | B19: Agencements et aménagements de
A20: 21220 | B20: MATERIEL PROT. CONTRE INCENDIE
A21: 21300 | B21: Constructions
... A218: 76800 | B218: Autres produits financiers

Sheet TIERS
A1: CODE TIERS | B1: NOM
A2: 00X00 | B2: CODE DIVERS CREE PAR PCCOMPTAP
A3: AC | B3: ACOMPTES/SALAIRES
A4: AC001 | B4: SNC BAPIVAET CIE
A5: AC002 | B5: DJENNADI AHCENE
A6: AC003 | B6: KADRI REDOUANE
A7: AC004 | B7: MEGROUS HOCINE
A8: AC005 | B8: DJENNADI ABDELKRIM
A9: AC006 | B9: ISAADI LAID
A10: AC007 | B10: SNC FRERES CHABAT
A11: AC008 | B11: TEI AHMED
A12: AC009 | B12: SARL DPR AXXAM
... A421: AF40 | B421: ZHENJIANG AUTO
A422: C
A423: C001 | B423: BENKHELIFA CHEIKH
A424: C002 | B424: DJENNADI LYAZID
A425: C003 | B425: DJENNADI ABDELKADER
A426: C004 | B426: DJENNADI ABDELKRIM
A427: C005 | B427: EURL AMAD EDDINE SABLIERE
A428: C006 | B428: GUESSOUME MASSAOUD
A429: C007 | B429: KHALDI OMAR
A430: C008 | B430: NAFTAL GPL TIARET
A431: C009 | B431: NAFTAL DMR ORAN
A432: C010 | B432: NAFTAL SPA-BRANCHE GPL-DIRECTI
A433: C011 | B433: NAFTAL UNM EST CONSTANTINE
A434: C012 | B434: SARL HAMOUDI TRANS
... A1517: CD001 | B1517: CLIENTS COMPTOIR DETAIL
A1518: DC
A1519: DCT004 | B1519: BATROUNI MOKHTAR
A1520: DCT006 | B1520: BRAHMI SAID
A1521: DCT008 | B1521: TOUAZI HACENE
A1522: DCT013 | B1522: EL HOUANNES ZAHIR
A1523: DCT014 | B1523: EL HOUANNES BOUALEM
A1524: FE001 | B1524: BS MOTORS
A1525: FE002 | B1525: QINGDAO RULONG
A1526: FE003 | B1526: SAMPA OTOMOTIVE
A1527: FE004 | B1527: NINGGUO FEIYING AUTO SPARE
A1528: FE005 | B1528: UNION INTERNATIONAL
A1529: FE006 | B1529: SIPROF
A1530: FE007 | B1530: YPS DIS TICARET TURQUIE
... A1770: SDC088 | B1770: BOUDJEDIA DJILLALI

Sheet CODES JOURNAUX
A1: JOURNAL | B1: LIBELLE
A2: 01001 | B2: REOUVERTURE
A3: 02001 | B3: BANQUE CPA
A4: 03001 | B4: BANQUE EL BARAKA
A5: 04001 | B5: CAISSE
A6: 05001 | B6: ACHATS IMPORTATION
A7: 06002 | B7: VENTES
A8: 07001 | B8: JOURNAL DE REGULARISATION
A9: 08002 | B9: OPPERATION DIVERS
A10: 09001 | B10: INVESTISSEMENTS
A11: 10001 | B11: STOCKS
A12: 11001 | B12: ACHATS LOCAUX
... A18: 16001 | B18: BANQUE SOCIETE GENERALE
