Workbook

Sheet Lisez-moi
A1: Journal des ventes au détail — SARL DPR COMPAGNY, établissement de Fenaia Il Maten
A3: Rubrique | B3: Détail
A4: Établissement | B4: Lieu-dit Abadou, commune de Fenaia Il Maten, wilaya de Béjaïa (cachet « Pièces détachées et Réparation mécanique »)
A5: Registre de commerce | B5: Établissement secondaire 06/04-0184232 B 03, inscrit le 10/09/2024 (extrait n° 920064572 du 11/09/2024)
A6: Activités inscrites | B6: 506003 pièces détachées et accessoires auto, 506002 outillage, 506006 pneumatiques, 506007 batteries, 506008 huiles et graisses, 613204 réparation mécanique, 605024 salle d'exposition
A7: Fiscalité | B7: NIF 000306018423274 ; article d'imposition 06180778071 ; déclaration d'existence du 03/03/2026 (début d'activité déclaré 10/09/2024) ; IBS
A8: Ce qui change | B8: Un nouveau journal 15001 « VENTES DETAIL FENAIA » ; banque (51220) et caisse (53000) inchangées
A10: Contrôles
A11: Journal 15001 équilibré | B11: =IF(ABS('JOURNAL 15001'!L904)<0.01,"OK","ERREUR")
A12: Encaissements équilibrés | B12: =IF(ABS('Encaissements comptant'!L603-'Encaissements comptant'!M603)<0.01,"OK","ERREUR")
A13: CA HT du journal = brouillard | B13: =IF(ABS(SUMIFS('JOURNAL 15001'!M2:M901,'JOURNAL 15001'!G2:G901,Paramètres!$B$8)+SUMIFS('JOURNAL 15001'!M2:M901,'JOURNAL 15001'!G2:G901,Paramètres!$B$9)-'Brouillard ventes'!F306)<0.01,"OK","ERREUR")
A14: Récapitulatif = brouillard (année de suivi seule) | B14: =IF(ABS('Récap mensuel G50'!D17-SUMIFS('Brouillard ventes'!$F$6:$F$305,'Brouillard ventes'!$A$6:$A$305,">="&DATE('Récap mensuel G50'!B2,1,1),'Brouillard ventes'!$A$6:$A$305,"<"&DATE('Récap mensuel G50'!B2+1,1,1)))<0.01,"OK","ÉCART")
A16: Mode d'emploi
A17: 1. Créer dans PCCOMPTA le journal et les comptes listés dans « Paramètres » (lignes 17 à 24).
A18: 2. Saisir chaque jour les ventes dans « Brouillard ventes » (une ligne par facture ou ticket ; la ligne 6 est un exemple à remplacer).
A19: 3. Copier « JOURNAL 15001 » (lignes non vides) dans PCCOMPTA ; les règlements comptant sont dans « Encaissements comptant » (journaux 04001 / 02001).
A20: 4. En fin de mois, reporter « Récap mensuel G50 » sur la G50 de l'établissement et passer la constatation de TVA (Écritures types).
A21: 5. Régulariser les ventes au détail réalisées depuis le 10/09/2024 : aucune n'apparaît dans les journaux 2024 et 2025.

Sheet Paramètres
A1: Paramètres et création du journal dans PCCOMPTA
A2: Cellules jaunes = hypothèses modifiables. Banque (51220, journal 02001) et caisse (53000, journal 04001) : inchangées.
A4: Paramètre | B4: Valeur | C4: Source / commentaire
A5: Taux de TVA (revente en l'état et réparation) | B5: 0.19 | C5: Taux porté sur les G50 2026 (ligne E3B22)
A6: Taux du droit de timbre sur paiements en espèces | B6: 0.01 | C6: Taux appliqué sur la G50 IMPORT de février 2026 (63 720 / 6 372 000) ; barème à confirmer avec l'inspection
A7: Compte client par défaut (vente comptoir) | B7: 41100 | C7: Avec le code auxiliaire CD001 « CLIENTS COMPTOIR DETAIL »
A8: Compte de ventes de marchandises au détail | B8: 70003 | C8: Nouveau compte
A9: Compte de prestations de réparation mécanique | B9: 70604 | C9: Nouveau compte (activité 613204)
A10: Compte de TVA collectée ventes détail | B10: 44519 | C10: Nouveau compte : TVA du détail suivie à part, soldée mensuellement par la G50
A11: Code unité (établissement) | B11: FEN | C11: Code_UNT PCCOMPTA pour isoler Fenaia dans toutes les écritures
A12: Article d'imposition de l'établissement | B12: 06180778071 | C12: Déclaration d'existence du 03/03/2026
A15: Lignes à ajouter dans les tables PCCOMPTA
A16: Table | B16: CODE | C16: LIBELLE | D16: NATURE / Remarque
A17: TAB_JRN | B17: 15001 | C17: VENTES DETAIL FENAIA | D17: Divers
A18: TAB_COM | B18: 70003 | C18: VENTES M/SES DETAIL FENAIA | D18: Produits
A19: TAB_COM | B19: 70604 | C19: PRESTATIONS REPARATION MECANIQUE | D19: Produits (activité 613204)
A20: TAB_COM | B20: 44519 | C20: TVA COLLECTEE VENTES DETAIL | D20: Dette fiscale
A21: TAB_COM | B21: 30003 | C21: STOCK MAGASIN DETAIL FENAIA | D21: Stock du magasin (transferts depuis 30002)
A22: TAB_AUX | B22: CD001 | C22: CLIENTS COMPTOIR DETAIL | D22: Clients de passage ; créer CD002, CD003… pour les clients à crédit
A23: TAB_UNT | B23: FEN | C23: ETABLISSEMENT FENAIA IL MATEN (DETAIL) | D23: Établissement secondaire RC 06/04-0184232 B 03
A24: TAB_UNT | B24: SIE | C24: SIEGE TIZI SMAOUN (IMPORT) | D24: Pour l'activité d'importation

Sheet Brouillard ventes
A1: Brouillard des ventes au détail — établissement de Fenaia Il Maten
A2: Saisir une ligne par facture ou ticket (colonnes jaunes). TVA, TTC et écritures sont calculées. La ligne 6 est un EXEMPLE : la remplacer par la première vraie vente.
A3: Mode de règlement : Espèces / Chèque / Virement / À crédit. Nature : Marchandises / Réparation.
A5: Date | B5: N° facture / ticket | C5: Code client | D5: Nom du client | E5: Nature | F5: Montant HT | G5: Taux TVA | H5: TVA | I5: TTC | J5: Mode de règlement | K5: Observations
A6: =DATE(2026,10,5) | B6: FD-0001 | C6: CD001 | D6: CLIENT COMPTOIR (EXEMPLE) | E6: Marchandises | F6: 10000 | G6: =IF(F6="","",Paramètres!$B$5) | H6: =IF(F6="","",ROUND(F6*G6,2)) | I6: =IF(F6="","",F6+H6) | J6: Espèces | K6: Ligne d'exemple à remplacer
G7: =IF(F7="","",Paramètres!$B$5) | H7: =IF(F7="","",ROUND(F7*G7,2)) | I7: =IF(F7="","",F7+H7)
G8: =IF(F8="","",Paramètres!$B$5) | H8: =IF(F8="","",ROUND(F8*G8,2)) | I8: =IF(F8="","",F8+H8)
G9: =IF(F9="","",Paramètres!$B$5) | H9: =IF(F9="","",ROUND(F9*G9,2)) | I9: =IF(F9="","",F9+H9)
G10: =IF(F10="","",Paramètres!$B$5) | H10: =IF(F10="","",ROUND(F10*G10,2)) | I10: =IF(F10="","",F10+H10)
G11: =IF(F11="","",Paramètres!$B$5) | H11: =IF(F11="","",ROUND(F11*G11,2)) | I11: =IF(F11="","",F11+H11)
G12: =IF(F12="","",Paramètres!$B$5) | H12: =IF(F12="","",ROUND(F12*G12,2)) | I12: =IF(F12="","",F12+H12)
G13: =IF(F13="","",Paramètres!$B$5) | H13: =IF(F13="","",ROUND(F13*G13,2)) | I13: =IF(F13="","",F13+H13)
G14: =IF(F14="","",Paramètres!$B$5) | H14: =IF(F14="","",ROUND(F14*G14,2)) | I14: =IF(F14="","",F14+H14)
G15: =IF(F15="","",Paramètres!$B$5) | H15: =IF(F15="","",ROUND(F15*G15,2)) | I15: =IF(F15="","",F15+H15)
G16: =IF(F16="","",Paramètres!$B$5) | H16: =IF(F16="","",ROUND(F16*G16,2)) | I16: =IF(F16="","",F16+H16)
G17: =IF(F17="","",Paramètres!$B$5) | H17: =IF(F17="","",ROUND(F17*G17,2)) | I17: =IF(F17="","",F17+H17)
G18: =IF(F18="","",Paramètres!$B$5) | H18: =IF(F18="","",ROUND(F18*G18,2)) | I18: =IF(F18="","",F18+H18)
... G305: =IF(F305="","",Paramètres!$B$5) | H305: =IF(F305="","",ROUND(F305*G305,2)) | I305: =IF(F305="","",F305+H305)
E306: TOTAUX | F306: =SUM(F6:F305) | H306: =SUM(H6:H305) | I306: =SUM(I6:I305)

Sheet JOURNAL 15001
A1: FOLIO | B1: PIECE | C1: DATE | D1: REFERENCE | E1: LIBELLE | F1: CODE_JRN | G1: CODE_COM | H1: CODE_AUX | I1: CODE_BDG | J1: CODE_NAT | K1: CODE_UNT | L1: DEBIT | M1: CREDIT | N1: LETTRAGE | O1: LIBELLEA | P1: CTP_COM | Q1: CTP_AUX | R1: ECHEANCE
A2: 1 | B2: =IF('Brouillard ventes'!$F$6="","","VD"&TEXT(ROW('Brouillard ventes'!$F$6)-5,"00000")) | C2: =IF('Brouillard ventes'!$F$6="","",YEAR('Brouillard ventes'!$A$6)*10000+MONTH('Brouillard ventes'!$A$6)*100+DAY('Brouillard ventes'!$A$6)) | D2: =IF('Brouillard ventes'!$F$6="","",'Brouillard ventes'!$B$6) | E2: =IF('Brouillard ventes'!$F$6="","",LEFT('Brouillard ventes'!$D$6,30)) | F2: 15001 | G2: =IF('Brouillard ventes'!$F$6="","",Paramètres!$B$7) | H2: =IF('Brouillard ventes'!$F$6="","",IF('Brouillard ventes'!$C$6="","CD001",'Brouillard ventes'!$C$6)) | K2: =IF('Brouillard ventes'!$F$6="","",Paramètres!$B$11) | L2: =IF('Brouillard ventes'!$F$6="","",'Brouillard ventes'!$I$6) | M2: 0
A3: 1 | B3: =IF('Brouillard ventes'!$F$6="","","VD"&TEXT(ROW('Brouillard ventes'!$F$6)-5,"00000")) | C3: =IF('Brouillard ventes'!$F$6="","",YEAR('Brouillard ventes'!$A$6)*10000+MONTH('Brouillard ventes'!$A$6)*100+DAY('Brouillard ventes'!$A$6)) | D3: =IF('Brouillard ventes'!$F$6="","",'Brouillard ventes'!$B$6) | E3: =IF('Brouillard ventes'!$F$6="","",LEFT('Brouillard ventes'!$D$6,30)) | F3: 15001 | G3: =IF('Brouillard ventes'!$F$6="","",IF('Brouillard ventes'!$E$6="Réparation",Paramètres!$B$9,Paramètres!$B$8)) | K3: =IF('Brouillard ventes'!$F$6="","",Paramètres!$B$11) | L3: 0 | M3: =IF('Brouillard ventes'!$F$6="","",'Brouillard ventes'!$F$6)
A4: 1 | B4: =IF('Brouillard ventes'!$F$6="","","VD"&TEXT(ROW('Brouillard ventes'!$F$6)-5,"00000")) | C4: =IF('Brouillard ventes'!$F$6="","",YEAR('Brouillard ventes'!$A$6)*10000+MONTH('Brouillard ventes'!$A$6)*100+DAY('Brouillard ventes'!$A$6)) | D4: =IF('Brouillard ventes'!$F$6="","",'Brouillard ventes'!$B$6) | E4: =IF('Brouillard ventes'!$F$6="","",LEFT('Brouillard ventes'!$D$6,30)) | F4: 15001 | G4: =IF('Brouillard ventes'!$F$6="","",Paramètres!$B$10) | K4: =IF('Brouillard ventes'!$F$6="","",Paramètres!$B$11) | L4: 0 | M4: =IF('Brouillard ventes'!$F$6="","",'Brouillard ventes'!$H$6)
A5: 1 | B5: =IF('Brouillard ventes'!$F$7="","","VD"&TEXT(ROW('Brouillard ventes'!$F$7)-5,"00000")) | C5: =IF('Brouillard ventes'!$F$7="","",YEAR('Brouillard ventes'!$A$7)*10000+MONTH('Brouillard ventes'!$A$7)*100+DAY('Brouillard ventes'!$A$7)) | D5: =IF('Brouillard ventes'!$F$7="","",'Brouillard ventes'!$B$7) | E5: =IF('Brouillard ventes'!$F$7="","",LEFT('Brouillard ventes'!$D$7,30)) | F5: 15001 | G5: =IF('Brouillard ventes'!$F$7="","",Paramètres!$B$7) | H5: =IF('Brouillard ventes'!$F$7="","",IF('Brouillard ventes'!$C$7="","CD001",'Brouillard ventes'!$C$7)) | K5: =IF('Brouillard ventes'!$F$7="","",Paramètres!$B$11) | L5: =IF('Brouillard ventes'!$F$7="","",'Brouillard ventes'!$I$7) | M5: 0
A6: 1 | B6: =IF('Brouillard ventes'!$F$7="","","VD"&TEXT(ROW('Brouillard ventes'!$F$7)-5,"00000")) | C6: =IF('Brouillard ventes'!$F$7="","",YEAR('Brouillard ventes'!$A$7)*10000+MONTH('Brouillard ventes'!$A$7)*100+DAY('Brouillard ventes'!$A$7)) | D6: =IF('Brouillard ventes'!$F$7="","",'Brouillard ventes'!$B$7) | E6: =IF('Brouillard ventes'!$F$7="","",LEFT('Brouillard ventes'!$D$7,30)) | F6: 15001 | G6: =IF('Brouillard ventes'!$F$7="","",IF('Brouillard ventes'!$E$7="Réparation",Paramètres!$B$9,Paramètres!$B$8)) | K6: =IF('Brouillard ventes'!$F$7="","",Paramètres!$B$11) | L6: 0 | M6: =IF('Brouillard ventes'!$F$7="","",'Brouillard ventes'!$F$7)
A7: 1 | B7: =IF('Brouillard ventes'!$F$7="","","VD"&TEXT(ROW('Brouillard ventes'!$F$7)-5,"00000")) | C7: =IF('Brouillard ventes'!$F$7="","",YEAR('Brouillard ventes'!$A$7)*10000+MONTH('Brouillard ventes'!$A$7)*100+DAY('Brouillard ventes'!$A$7)) | D7: =IF('Brouillard ventes'!$F$7="","",'Brouillard ventes'!$B$7) | E7: =IF('Brouillard ventes'!$F$7="","",LEFT('Brouillard ventes'!$D$7,30)) | F7: 15001 | G7: =IF('Brouillard ventes'!$F$7="","",Paramètres!$B$10) | K7: =IF('Brouillard ventes'!$F$7="","",Paramètres!$B$11) | L7: 0 | M7: =IF('Brouillard ventes'!$F$7="","",'Brouillard ventes'!$H$7)
A8: 1 | B8: =IF('Brouillard ventes'!$F$8="","","VD"&TEXT(ROW('Brouillard ventes'!$F$8)-5,"00000")) | C8: =IF('Brouillard ventes'!$F$8="","",YEAR('Brouillard ventes'!$A$8)*10000+MONTH('Brouillard ventes'!$A$8)*100+DAY('Brouillard ventes'!$A$8)) | D8: =IF('Brouillard ventes'!$F$8="","",'Brouillard ventes'!$B$8) | E8: =IF('Brouillard ventes'!$F$8="","",LEFT('Brouillard ventes'!$D$8,30)) | F8: 15001 | G8: =IF('Brouillard ventes'!$F$8="","",Paramètres!$B$7) | H8: =IF('Brouillard ventes'!$F$8="","",IF('Brouillard ventes'!$C$8="","CD001",'Brouillard ventes'!$C$8)) | K8: =IF('Brouillard ventes'!$F$8="","",Paramètres!$B$11) | L8: =IF('Brouillard ventes'!$F$8="","",'Brouillard ventes'!$I$8) | M8: 0
A9: 1 | B9: =IF('Brouillard ventes'!$F$8="","","VD"&TEXT(ROW('Brouillard ventes'!$F$8)-5,"00000")) | C9: =IF('Brouillard ventes'!$F$8="","",YEAR('Brouillard ventes'!$A$8)*10000+MONTH('Brouillard ventes'!$A$8)*100+DAY('Brouillard ventes'!$A$8)) | D9: =IF('Brouillard ventes'!$F$8="","",'Brouillard ventes'!$B$8) | E9: =IF('Brouillard ventes'!$F$8="","",LEFT('Brouillard ventes'!$D$8,30)) | F9: 15001 | G9: =IF('Brouillard ventes'!$F$8="","",IF('Brouillard ventes'!$E$8="Réparation",Paramètres!$B$9,Paramètres!$B$8)) | K9: =IF('Brouillard ventes'!$F$8="","",Paramètres!$B$11) | L9: 0 | M9: =IF('Brouillard ventes'!$F$8="","",'Brouillard ventes'!$F$8)
A10: 1 | B10: =IF('Brouillard ventes'!$F$8="","","VD"&TEXT(ROW('Brouillard ventes'!$F$8)-5,"00000")) | C10: =IF('Brouillard ventes'!$F$8="","",YEAR('Brouillard ventes'!$A$8)*10000+MONTH('Brouillard ventes'!$A$8)*100+DAY('Brouillard ventes'!$A$8)) | D10: =IF('Brouillard ventes'!$F$8="","",'Brouillard ventes'!$B$8) | E10: =IF('Brouillard ventes'!$F$8="","",LEFT('Brouillard ventes'!$D$8,30)) | F10: 15001 | G10: =IF('Brouillard ventes'!$F$8="","",Paramètres!$B$10) | K10: =IF('Brouillard ventes'!$F$8="","",Paramètres!$B$11) | L10: 0 | M10: =IF('Brouillard ventes'!$F$8="","",'Brouillard ventes'!$H$8)
A11: 1 | B11: =IF('Brouillard ventes'!$F$9="","","VD"&TEXT(ROW('Brouillard ventes'!$F$9)-5,"00000")) | C11: =IF('Brouillard ventes'!$F$9="","",YEAR('Brouillard ventes'!$A$9)*10000+MONTH('Brouillard ventes'!$A$9)*100+DAY('Brouillard ventes'!$A$9)) | D11: =IF('Brouillard ventes'!$F$9="","",'Brouillard ventes'!$B$9) | E11: =IF('Brouillard ventes'!$F$9="","",LEFT('Brouillard ventes'!$D$9,30)) | F11: 15001 | G11: =IF('Brouillard ventes'!$F$9="","",Paramètres!$B$7) | H11: =IF('Brouillard ventes'!$F$9="","",IF('Brouillard ventes'!$C$9="","CD001",'Brouillard ventes'!$C$9)) | K11: =IF('Brouillard ventes'!$F$9="","",Paramètres!$B$11) | L11: =IF('Brouillard ventes'!$F$9="","",'Brouillard ventes'!$I$9) | M11: 0
A12: 1 | B12: =IF('Brouillard ventes'!$F$9="","","VD"&TEXT(ROW('Brouillard ventes'!$F$9)-5,"00000")) | C12: =IF('Brouillard ventes'!$F$9="","",YEAR('Brouillard ventes'!$A$9)*10000+MONTH('Brouillard ventes'!$A$9)*100+DAY('Brouillard ventes'!$A$9)) | D12: =IF('Brouillard ventes'!$F$9="","",'Brouillard ventes'!$B$9) | E12: =IF('Brouillard ventes'!$F$9="","",LEFT('Brouillard ventes'!$D$9,30)) | F12: 15001 | G12: =IF('Brouillard ventes'!$F$9="","",IF('Brouillard ventes'!$E$9="Réparation",Paramètres!$B$9,Paramètres!$B$8)) | K12: =IF('Brouillard ventes'!$F$9="","",Paramètres!$B$11) | L12: 0 | M12: =IF('Brouillard ventes'!$F$9="","",'Brouillard ventes'!$F$9)
A13: 1 | B13: =IF('Brouillard ventes'!$F$9="","","VD"&TEXT(ROW('Brouillard ventes'!$F$9)-5,"00000")) | C13: =IF('Brouillard ventes'!$F$9="","",YEAR('Brouillard ventes'!$A$9)*10000+MONTH('Brouillard ventes'!$A$9)*100+DAY('Brouillard ventes'!$A$9)) | D13: =IF('Brouillard ventes'!$F$9="","",'Brouillard ventes'!$B$9) | E13: =IF('Brouillard ventes'!$F$9="","",LEFT('Brouillard ventes'!$D$9,30)) | F13: 15001 | G13: =IF('Brouillard ventes'!$F$9="","",Paramètres!$B$10) | K13: =IF('Brouillard ventes'!$F$9="","",Paramètres!$B$11) | L13: 0 | M13: =IF('Brouillard ventes'!$F$9="","",'Brouillard ventes'!$H$9)
A14: 1 | B14: =IF('Brouillard ventes'!$F$10="","","VD"&TEXT(ROW('Brouillard ventes'!$F$10)-5,"00000")) | C14: =IF('Brouillard ventes'!$F$10="","",YEAR('Brouillard ventes'!$A$10)*10000+MONTH('Brouillard ventes'!$A$10)*100+DAY('Brouillard ventes'!$A$10)) | D14: =IF('Brouillard ventes'!$F$10="","",'Brouillard ventes'!$B$10) | E14: =IF('Brouillard ventes'!$F$10="","",LEFT('Brouillard ventes'!$D$10,30)) | F14: 15001 | G14: =IF('Brouillard ventes'!$F$10="","",Paramètres!$B$7) | H14: =IF('Brouillard ventes'!$F$10="","",IF('Brouillard ventes'!$C$10="","CD001",'Brouillard ventes'!$C$10)) | K14: =IF('Brouillard ventes'!$F$10="","",Paramètres!$B$11) | L14: =IF('Brouillard ventes'!$F$10="","",'Brouillard ventes'!$I$10) | M14: 0
A15: 1 | B15: =IF('Brouillard ventes'!$F$10="","","VD"&TEXT(ROW('Brouillard ventes'!$F$10)-5,"00000")) | C15: =IF('Brouillard ventes'!$F$10="","",YEAR('Brouillard ventes'!$A$10)*10000+MONTH('Brouillard ventes'!$A$10)*100+DAY('Brouillard ventes'!$A$10)) | D15: =IF('Brouillard ventes'!$F$10="","",'Brouillard ventes'!$B$10) | E15: =IF('Brouillard ventes'!$F$10="","",LEFT('Brouillard ventes'!$D$10,30)) | F15: 15001 | G15: =IF('Brouillard ventes'!$F$10="","",IF('Brouillard ventes'!$E$10="Réparation",Paramètres!$B$9,Paramètres!$B$8)) | K15: =IF('Brouillard ventes'!$F$10="","",Paramètres!$B$11) | L15: 0 | M15: =IF('Brouillard ventes'!$F$10="","",'Brouillard ventes'!$F$10)
A16: 1 | B16: =IF('Brouillard ventes'!$F$10="","","VD"&TEXT(ROW('Brouillard ventes'!$F$10)-5,"00000")) | C16: =IF('Brouillard ventes'!$F$10="","",YEAR('Brouillard ventes'!$A$10)*10000+MONTH('Brouillard ventes'!$A$10)*100+DAY('Brouillard ventes'!$A$10)) | D16: =IF('Brouillard ventes'!$F$10="","",'Brouillard ventes'!$B$10) | E16: =IF('Brouillard ventes'!$F$10="","",LEFT('Brouillard ventes'!$D$10,30)) | F16: 15001 | G16: =IF('Brouillard ventes'!$F$10="","",Paramètres!$B$10) | K16: =IF('Brouillard ventes'!$F$10="","",Paramètres!$B$11) | L16: 0 | M16: =IF('Brouillard ventes'!$F$10="","",'Brouillard ventes'!$H$10)
A17: 1 | B17: =IF('Brouillard ventes'!$F$11="","","VD"&TEXT(ROW('Brouillard ventes'!$F$11)-5,"00000")) | C17: =IF('Brouillard ventes'!$F$11="","",YEAR('Brouillard ventes'!$A$11)*10000+MONTH('Brouillard ventes'!$A$11)*100+DAY('Brouillard ventes'!$A$11)) | D17: =IF('Brouillard ventes'!$F$11="","",'Brouillard ventes'!$B$11) | E17: =IF('Brouillard ventes'!$F$11="","",LEFT('Brouillard ventes'!$D$11,30)) | F17: 15001 | G17: =IF('Brouillard ventes'!$F$11="","",Paramètres!$B$7) | H17: =IF('Brouillard ventes'!$F$11="","",IF('Brouillard ventes'!$C$11="","CD001",'Brouillard ventes'!$C$11)) | K17: =IF('Brouillard ventes'!$F$11="","",Paramètres!$B$11) | L17: =IF('Brouillard ventes'!$F$11="","",'Brouillard ventes'!$I$11) | M17: 0
A18: 1 | B18: =IF('Brouillard ventes'!$F$11="","","VD"&TEXT(ROW('Brouillard ventes'!$F$11)-5,"00000")) | C18: =IF('Brouillard ventes'!$F$11="","",YEAR('Brouillard ventes'!$A$11)*10000+MONTH('Brouillard ventes'!$A$11)*100+DAY('Brouillard ventes'!$A$11)) | D18: =IF('Brouillard ventes'!$F$11="","",'Brouillard ventes'!$B$11) | E18: =IF('Brouillard ventes'!$F$11="","",LEFT('Brouillard ventes'!$D$11,30)) | F18: 15001 | G18: =IF('Brouillard ventes'!$F$11="","",IF('Brouillard ventes'!$E$11="Réparation",Paramètres!$B$9,Paramètres!$B$8)) | K18: =IF('Brouillard ventes'!$F$11="","",Paramètres!$B$11) | L18: 0 | M18: =IF('Brouillard ventes'!$F$11="","",'Brouillard ventes'!$F$11)
A19: 1 | B19: =IF('Brouillard ventes'!$F$11="","","VD"&TEXT(ROW('Brouillard ventes'!$F$11)-5,"00000")) | C19: =IF('Brouillard ventes'!$F$11="","",YEAR('Brouillard ventes'!$A$11)*10000+MONTH('Brouillard ventes'!$A$11)*100+DAY('Brouillard ventes'!$A$11)) | D19: =IF('Brouillard ventes'!$F$11="","",'Brouillard ventes'!$B$11) | E19: =IF('Brouillard ventes'!$F$11="","",LEFT('Brouillard ventes'!$D$11,30)) | F19: 15001 | G19: =IF('Brouillard ventes'!$F$11="","",Paramètres!$B$10) | K19: =IF('Brouillard ventes'!$F$11="","",Paramètres!$B$11) | L19: 0 | M19: =IF('Brouillard ventes'!$F$11="","",'Brouillard ventes'!$H$11)
A20: 1 | B20: =IF('Brouillard ventes'!$F$12="","","VD"&TEXT(ROW('Brouillard ventes'!$F$12)-5,"00000")) | C20: =IF('Brouillard ventes'!$F$12="","",YEAR('Brouillard ventes'!$A$12)*10000+MONTH('Brouillard ventes'!$A$12)*100+DAY('Brouillard ventes'!$A$12)) | D20: =IF('Brouillard ventes'!$F$12="","",'Brouillard ventes'!$B$12) | E20: =IF('Brouillard ventes'!$F$12="","",LEFT('Brouillard ventes'!$D$12,30)) | F20: 15001 | G20: =IF('Brouillard ventes'!$F$12="","",Paramètres!$B$7) | H20: =IF('Brouillard ventes'!$F$12="","",IF('Brouillard ventes'!$C$12="","CD001",'Brouillard ventes'!$C$12)) | K20: =IF('Brouillard ventes'!$F$12="","",Paramètres!$B$11) | L20: =IF('Brouillard ventes'!$F$12="","",'Brouillard ventes'!$I$12) | M20: 0
A21: 1 | B21: =IF('Brouillard ventes'!$F$12="","","VD"&TEXT(ROW('Brouillard ventes'!$F$12)-5,"00000")) | C21: =IF('Brouillard ventes'!$F$12="","",YEAR('Brouillard ventes'!$A$12)*10000+MONTH('Brouillard ventes'!$A$12)*100+DAY('Brouillard ventes'!$A$12)) | D21: =IF('Brouillard ventes'!$F$12="","",'Brouillard ventes'!$B$12) | E21: =IF('Brouillard ventes'!$F$12="","",LEFT('Brouillard ventes'!$D$12,30)) | F21: 15001 | G21: =IF('Brouillard ventes'!$F$12="","",IF('Brouillard ventes'!$E$12="Réparation",Paramètres!$B$9,Paramètres!$B$8)) | K21: =IF('Brouillard ventes'!$F$12="","",Paramètres!$B$11) | L21: 0 | M21: =IF('Brouillard ventes'!$F$12="","",'Brouillard ventes'!$F$12)
A22: 1 | B22: =IF('Brouillard ventes'!$F$12="","","VD"&TEXT(ROW('Brouillard ventes'!$F$12)-5,"00000")) | C22: =IF('Brouillard ventes'!$F$12="","",YEAR('Brouillard ventes'!$A$12)*10000+MONTH('Brouillard ventes'!$A$12)*100+DAY('Brouillard ventes'!$A$12)) | D22: =IF('Brouillard ventes'!$F$12="","",'Brouillard ventes'!$B$12) | E22: =IF('Brouillard ventes'!$F$12="","",LEFT('Brouillard ventes'!$D$12,30)) | F22: 15001 | G22: =IF('Brouillard ventes'!$F$12="","",Paramètres!$B$10) | K22: =IF('Brouillard ventes'!$F$12="","",Paramètres!$B$11) | L22: 0 | M22: =IF('Brouillard ventes'!$F$12="","",'Brouillard ventes'!$H$12)
A23: 1 | B23: =IF('Brouillard ventes'!$F$13="","","VD"&TEXT(ROW('Brouillard ventes'!$F$13)-5,"00000")) | C23: =IF('Brouillard ventes'!$F$13="","",YEAR('Brouillard ventes'!$A$13)*10000+MONTH('Brouillard ventes'!$A$13)*100+DAY('Brouillard ventes'!$A$13)) | D23: =IF('Brouillard ventes'!$F$13="","",'Brouillard ventes'!$B$13) | E23: =IF('Brouillard ventes'!$F$13="","",LEFT('Brouillard ventes'!$D$13,30)) | F23: 15001 | G23: =IF('Brouillard ventes'!$F$13="","",Paramètres!$B$7) | H23: =IF('Brouillard ventes'!$F$13="","",IF('Brouillard ventes'!$C$13="","CD001",'Brouillard ventes'!$C$13)) | K23: =IF('Brouillard ventes'!$F$13="","",Paramètres!$B$11) | L23: =IF('Brouillard ventes'!$F$13="","",'Brouillard ventes'!$I$13) | M23: 0
A24: 1 | B24: =IF('Brouillard ventes'!$F$13="","","VD"&TEXT(ROW('Brouillard ventes'!$F$13)-5,"00000")) | C24: =IF('Brouillard ventes'!$F$13="","",YEAR('Brouillard ventes'!$A$13)*10000+MONTH('Brouillard ventes'!$A$13)*100+DAY('Brouillard ventes'!$A$13)) | D24: =IF('Brouillard ventes'!$F$13="","",'Brouillard ventes'!$B$13) | E24: =IF('Brouillard ventes'!$F$13="","",LEFT('Brouillard ventes'!$D$13,30)) | F24: 15001 | G24: =IF('Brouillard ventes'!$F$13="","",IF('Brouillard ventes'!$E$13="Réparation",Paramètres!$B$9,Paramètres!$B$8)) | K24: =IF('Brouillard ventes'!$F$13="","",Paramètres!$B$11) | L24: 0 | M24: =IF('Brouillard ventes'!$F$13="","",'Brouillard ventes'!$F$13)
A25: 1 | B25: =IF('Brouillard ventes'!$F$13="","","VD"&TEXT(ROW('Brouillard ventes'!$F$13)-5,"00000")) | C25: =IF('Brouillard ventes'!$F$13="","",YEAR('Brouillard ventes'!$A$13)*10000+MONTH('Brouillard ventes'!$A$13)*100+DAY('Brouillard ventes'!$A$13)) | D25: =IF('Brouillard ventes'!$F$13="","",'Brouillard ventes'!$B$13) | E25: =IF('Brouillard ventes'!$F$13="","",LEFT('Brouillard ventes'!$D$13,30)) | F25: 15001 | G25: =IF('Brouillard ventes'!$F$13="","",Paramètres!$B$10) | K25: =IF('Brouillard ventes'!$F$13="","",Paramètres!$B$11) | L25: 0 | M25: =IF('Brouillard ventes'!$F$13="","",'Brouillard ventes'!$H$13)
A26: 1 | B26: =IF('Brouillard ventes'!$F$14="","","VD"&TEXT(ROW('Brouillard ventes'!$F$14)-5,"00000")) | C26: =IF('Brouillard ventes'!$F$14="","",YEAR('Brouillard ventes'!$A$14)*10000+MONTH('Brouillard ventes'!$A$14)*100+DAY('Brouillard ventes'!$A$14)) | D26: =IF('Brouillard ventes'!$F$14="","",'Brouillard ventes'!$B$14) | E26: =IF('Brouillard ventes'!$F$14="","",LEFT('Brouillard ventes'!$D$14,30)) | F26: 15001 | G26: =IF('Brouillard ventes'!$F$14="","",Paramètres!$B$7) | H26: =IF('Brouillard ventes'!$F$14="","",IF('Brouillard ventes'!$C$14="","CD001",'Brouillard ventes'!$C$14)) | K26: =IF('Brouillard ventes'!$F$14="","",Paramètres!$B$11) | L26: =IF('Brouillard ventes'!$F$14="","",'Brouillard ventes'!$I$14) | M26: 0
A27: 1 | B27: =IF('Brouillard ventes'!$F$14="","","VD"&TEXT(ROW('Brouillard ventes'!$F$14)-5,"00000")) | C27: =IF('Brouillard ventes'!$F$14="","",YEAR('Brouillard ventes'!$A$14)*10000+MONTH('Brouillard ventes'!$A$14)*100+DAY('Brouillard ventes'!$A$14)) | D27: =IF('Brouillard ventes'!$F$14="","",'Brouillard ventes'!$B$14) | E27: =IF('Brouillard ventes'!$F$14="","",LEFT('Brouillard ventes'!$D$14,30)) | F27: 15001 | G27: =IF('Brouillard ventes'!$F$14="","",IF('Brouillard ventes'!$E$14="Réparation",Paramètres!$B$9,Paramètres!$B$8)) | K27: =IF('Brouillard ventes'!$F$14="","",Paramètres!$B$11) | L27: 0 | M27: =IF('Brouillard ventes'!$F$14="","",'Brouillard ventes'!$F$14)
A28: 1 | B28: =IF('Brouillard ventes'!$F$14="","","VD"&TEXT(ROW('Brouillard ventes'!$F$14)-5,"00000")) | C28: =IF('Brouillard ventes'!$F$14="","",YEAR('Brouillard ventes'!$A$14)*10000+MONTH('Brouillard ventes'!$A$14)*100+DAY('Brouillard ventes'!$A$14)) | D28: =IF('Brouillard ventes'!$F$14="","",'Brouillard ventes'!$B$14) | E28: =IF('Brouillard ventes'!$F$14="","",LEFT('Brouillard ventes'!$D$14,30)) | F28: 15001 | G28: =IF('Brouillard ventes'!$F$14="","",Paramètres!$B$10) | K28: =IF('Brouillard ventes'!$F$14="","",Paramètres!$B$11) | L28: 0 | M28: =IF('Brouillard ventes'!$F$14="","",'Brouillard ventes'!$H$14)
A29: 1 | B29: =IF('Brouillard ventes'!$F$15="","","VD"&TEXT(ROW('Brouillard ventes'!$F$15)-5,"00000")) | C29: =IF('Brouillard ventes'!$F$15="","",YEAR('Brouillard ventes'!$A$15)*10000+MONTH('Brouillard ventes'!$A$15)*100+DAY('Brouillard ventes'!$A$15)) | D29: =IF('Brouillard ventes'!$F$15="","",'Brouillard ventes'!$B$15) | E29: =IF('Brouillard ventes'!$F$15="","",LEFT('Brouillard ventes'!$D$15,30)) | F29: 15001 | G29: =IF('Brouillard ventes'!$F$15="","",Paramètres!$B$7) | H29: =IF('Brouillard ventes'!$F$15="","",IF('Brouillard ventes'!$C$15="","CD001",'Brouillard ventes'!$C$15)) | K29: =IF('Brouillard ventes'!$F$15="","",Paramètres!$B$11) | L29: =IF('Brouillard ventes'!$F$15="","",'Brouillard ventes'!$I$15) | M29: 0
A30: 1 | B30: =IF('Brouillard ventes'!$F$15="","","VD"&TEXT(ROW('Brouillard ventes'!$F$15)-5,"00000")) | C30: =IF('Brouillard ventes'!$F$15="","",YEAR('Brouillard ventes'!$A$15)*10000+MONTH('Brouillard ventes'!$A$15)*100+DAY('Brouillard ventes'!$A$15)) | D30: =IF('Brouillard ventes'!$F$15="","",'Brouillard ventes'!$B$15) | E30: =IF('Brouillard ventes'!$F$15="","",LEFT('Brouillard ventes'!$D$15,30)) | F30: 15001 | G30: =IF('Brouillard ventes'!$F$15="","",IF('Brouillard ventes'!$E$15="Réparation",Paramètres!$B$9,Paramètres!$B$8)) | K30: =IF('Brouillard ventes'!$F$15="","",Paramètres!$B$11) | L30: 0 | M30: =IF('Brouillard ventes'!$F$15="","",'Brouillard ventes'!$F$15)
A31: 1 | B31: =IF('Brouillard ventes'!$F$15="","","VD"&TEXT(ROW('Brouillard ventes'!$F$15)-5,"00000")) | C31: =IF('Brouillard ventes'!$F$15="","",YEAR('Brouillard ventes'!$A$15)*10000+MONTH('Brouillard ventes'!$A$15)*100+DAY('Brouillard ventes'!$A$15)) | D31: =IF('Brouillard ventes'!$F$15="","",'Brouillard ventes'!$B$15) | E31: =IF('Brouillard ventes'!$F$15="","",LEFT('Brouillard ventes'!$D$15,30)) | F31: 15001 | G31: =IF('Brouillard ventes'!$F$15="","",Paramètres!$B$10) | K31: =IF('Brouillard ventes'!$F$15="","",Paramètres!$B$11) | L31: 0 | M31: =IF('Brouillard ventes'!$F$15="","",'Brouillard ventes'!$H$15)
A32: 1 | B32: =IF('Brouillard ventes'!$F$16="","","VD"&TEXT(ROW('Brouillard ventes'!$F$16)-5,"00000")) | C32: =IF('Brouillard ventes'!$F$16="","",YEAR('Brouillard ventes'!$A$16)*10000+MONTH('Brouillard ventes'!$A$16)*100+DAY('Brouillard ventes'!$A$16)) | D32: =IF('Brouillard ventes'!$F$16="","",'Brouillard ventes'!$B$16) | E32: =IF('Brouillard ventes'!$F$16="","",LEFT('Brouillard ventes'!$D$16,30)) | F32: 15001 | G32: =IF('Brouillard ventes'!$F$16="","",Paramètres!$B$7) | H32: =IF('Brouillard ventes'!$F$16="","",IF('Brouillard ventes'!$C$16="","CD001",'Brouillard ventes'!$C$16)) | K32: =IF('Brouillard ventes'!$F$16="","",Paramètres!$B$11) | L32: =IF('Brouillard ventes'!$F$16="","",'Brouillard ventes'!$I$16) | M32: 0
A33: 1 | B33: =IF('Brouillard ventes'!$F$16="","","VD"&TEXT(ROW('Brouillard ventes'!$F$16)-5,"00000")) | C33: =IF('Brouillard ventes'!$F$16="","",YEAR('Brouillard ventes'!$A$16)*10000+MONTH('Brouillard ventes'!$A$16)*100+DAY('Brouillard ventes'!$A$16)) | D33: =IF('Brouillard ventes'!$F$16="","",'Brouillard ventes'!$B$16) | E33: =IF('Brouillard ventes'!$F$16="","",LEFT('Brouillard ventes'!$D$16,30)) | F33: 15001 | G33: =IF('Brouillard ventes'!$F$16="","",IF('Brouillard ventes'!$E$16="Réparation",Paramètres!$B$9,Paramètres!$B$8)) | K33: =IF('Brouillard ventes'!$F$16="","",Paramètres!$B$11) | L33: 0 | M33: =IF('Brouillard ventes'!$F$16="","",'Brouillard ventes'!$F$16)
A34: 1 | B34: =IF('Brouillard ventes'!$F$16="","","VD"&TEXT(ROW('Brouillard ventes'!$F$16)-5,"00000")) | C34: =IF('Brouillard ventes'!$F$16="","",YEAR('Brouillard ventes'!$A$16)*10000+MONTH('Brouillard ventes'!$A$16)*100+DAY('Brouillard ventes'!$A$16)) | D34: =IF('Brouillard ventes'!$F$16="","",'Brouillard ventes'!$B$16) | E34: =IF('Brouillard ventes'!$F$16="","",LEFT('Brouillard ventes'!$D$16,30)) | F34: 15001 | G34: =IF('Brouillard ventes'!$F$16="","",Paramètres!$B$10) | K34: =IF('Brouillard ventes'!$F$16="","",Paramètres!$B$11) | L34: 0 | M34: =IF('Brouillard ventes'!$F$16="","",'Brouillard ventes'!$H$16)
A35: 1 | B35: =IF('Brouillard ventes'!$F$17="","","VD"&TEXT(ROW('Brouillard ventes'!$F$17)-5,"00000")) | C35: =IF('Brouillard ventes'!$F$17="","",YEAR('Brouillard ventes'!$A$17)*10000+MONTH('Brouillard ventes'!$A$17)*100+DAY('Brouillard ventes'!$A$17)) | D35: =IF('Brouillard ventes'!$F$17="","",'Brouillard ventes'!$B$17) | E35: =IF('Brouillard ventes'!$F$17="","",LEFT('Brouillard ventes'!$D$17,30)) | F35: 15001 | G35: =IF('Brouillard ventes'!$F$17="","",Paramètres!$B$7) | H35: =IF('Brouillard ventes'!$F$17="","",IF('Brouillard ventes'!$C$17="","CD001",'Brouillard ventes'!$C$17)) | K35: =IF('Brouillard ventes'!$F$17="","",Paramètres!$B$11) | L35: =IF('Brouillard ventes'!$F$17="","",'Brouillard ventes'!$I$17) | M35: 0
A36: 1 | B36: =IF('Brouillard ventes'!$F$17="","","VD"&TEXT(ROW('Brouillard ventes'!$F$17)-5,"00000")) | C36: =IF('Brouillard ventes'!$F$17="","",YEAR('Brouillard ventes'!$A$17)*10000+MONTH('Brouillard ventes'!$A$17)*100+DAY('Brouillard ventes'!$A$17)) | D36: =IF('Brouillard ventes'!$F$17="","",'Brouillard ventes'!$B$17) | E36: =IF('Brouillard ventes'!$F$17="","",LEFT('Brouillard ventes'!$D$17,30)) | F36: 15001 | G36: =IF('Brouillard ventes'!$F$17="","",IF('Brouillard ventes'!$E$17="Réparation",Paramètres!$B$9,Paramètres!$B$8)) | K36: =IF('Brouillard ventes'!$F$17="","",Paramètres!$B$11) | L36: 0 | M36: =IF('Brouillard ventes'!$F$17="","",'Brouillard ventes'!$F$17)
A37: 1 | B37: =IF('Brouillard ventes'!$F$17="","","VD"&TEXT(ROW('Brouillard ventes'!$F$17)-5,"00000")) | C37: =IF('Brouillard ventes'!$F$17="","",YEAR('Brouillard ventes'!$A$17)*10000+MONTH('Brouillard ventes'!$A$17)*100+DAY('Brouillard ventes'!$A$17)) | D37: =IF('Brouillard ventes'!$F$17="","",'Brouillard ventes'!$B$17) | E37: =IF('Brouillard ventes'!$F$17="","",LEFT('Brouillard ventes'!$D$17,30)) | F37: 15001 | G37: =IF('Brouillard ventes'!$F$17="","",Paramètres!$B$10) | K37: =IF('Brouillard ventes'!$F$17="","",Paramètres!$B$11) | L37: 0 | M37: =IF('Brouillard ventes'!$F$17="","",'Brouillard ventes'!$H$17)
A38: 1 | B38: =IF('Brouillard ventes'!$F$18="","","VD"&TEXT(ROW('Brouillard ventes'!$F$18)-5,"00000")) | C38: =IF('Brouillard ventes'!$F$18="","",YEAR('Brouillard ventes'!$A$18)*10000+MONTH('Brouillard ventes'!$A$18)*100+DAY('Brouillard ventes'!$A$18)) | D38: =IF('Brouillard ventes'!$F$18="","",'Brouillard ventes'!$B$18) | E38: =IF('Brouillard ventes'!$F$18="","",LEFT('Brouillard ventes'!$D$18,30)) | F38: 15001 | G38: =IF('Brouillard ventes'!$F$18="","",Paramètres!$B$7) | H38: =IF('Brouillard ventes'!$F$18="","",IF('Brouillard ventes'!$C$18="","CD001",'Brouillard ventes'!$C$18)) | K38: =IF('Brouillard ventes'!$F$18="","",Paramètres!$B$11) | L38: =IF('Brouillard ventes'!$F$18="","",'Brouillard ventes'!$I$18) | M38: 0
A39: 1 | B39: =IF('Brouillard ventes'!$F$18="","","VD"&TEXT(ROW('Brouillard ventes'!$F$18)-5,"00000")) | C39: =IF('Brouillard ventes'!$F$18="","",YEAR('Brouillard ventes'!$A$18)*10000+MONTH('Brouillard ventes'!$A$18)*100+DAY('Brouillard ventes'!$A$18)) | D39: =IF('Brouillard ventes'!$F$18="","",'Brouillard ventes'!$B$18) | E39: =IF('Brouillard ventes'!$F$18="","",LEFT('Brouillard ventes'!$D$18,30)) | F39: 15001 | G39: =IF('Brouillard ventes'!$F$18="","",IF('Brouillard ventes'!$E$18="Réparation",Paramètres!$B$9,Paramètres!$B$8)) | K39: =IF('Brouillard ventes'!$F$18="","",Paramètres!$B$11) | L39: 0 | M39: =IF('Brouillard ventes'!$F$18="","",'Brouillard ventes'!$F$18)
A40: 1 | B40: =IF('Brouillard ventes'!$F$18="","","VD"&TEXT(ROW('Brouillard ventes'!$F$18)-5,"00000")) | C40: =IF('Brouillard ventes'!$F$18="","",YEAR('Brouillard ventes'!$A$18)*10000+MONTH('Brouillard ventes'!$A$18)*100+DAY('Brouillard ventes'!$A$18)) | D40: =IF('Brouillard ventes'!$F$18="","",'Brouillard ventes'!$B$18) | E40: =IF('Brouillard ventes'!$F$18="","",LEFT('Brouillard ventes'!$D$18,30)) | F40: 15001 | G40: =IF('Brouillard ventes'!$F$18="","",Paramètres!$B$10) | K40: =IF('Brouillard ventes'!$F$18="","",Paramètres!$B$11) | L40: 0 | M40: =IF('Brouillard ventes'!$F$18="","",'Brouillard ventes'!$H$18)
A41: 1 | B41: =IF('Brouillard ventes'!$F$19="","","VD"&TEXT(ROW('Brouillard ventes'!$F$19)-5,"00000")) | C41: =IF('Brouillard ventes'!$F$19="","",YEAR('Brouillard ventes'!$A$19)*10000+MONTH('Brouillard ventes'!$A$19)*100+DAY('Brouillard ventes'!$A$19)) | D41: =IF('Brouillard ventes'!$F$19="","",'Brouillard ventes'!$B$19) | E41: =IF('Brouillard ventes'!$F$19="","",LEFT('Brouillard ventes'!$D$19,30)) | F41: 15001 | G41: =IF('Brouillard ventes'!$F$19="","",Paramètres!$B$7) | H41: =IF('Brouillard ventes'!$F$19="","",IF('Brouillard ventes'!$C$19="","CD001",'Brouillard ventes'!$C$19)) | K41: =IF('Brouillard ventes'!$F$19="","",Paramètres!$B$11) | L41: =IF('Brouillard ventes'!$F$19="","",'Brouillard ventes'!$I$19) | M41: 0
A42: 1 | B42: =IF('Brouillard ventes'!$F$19="","","VD"&TEXT(ROW('Brouillard ventes'!$F$19)-5,"00000")) | C42: =IF('Brouillard ventes'!$F$19="","",YEAR('Brouillard ventes'!$A$19)*10000+MONTH('Brouillard ventes'!$A$19)*100+DAY('Brouillard ventes'!$A$19)) | D42: =IF('Brouillard ventes'!$F$19="","",'Brouillard ventes'!$B$19) | E42: =IF('Brouillard ventes'!$F$19="","",LEFT('Brouillard ventes'!$D$19,30)) | F42: 15001 | G42: =IF('Brouillard ventes'!$F$19="","",IF('Brouillard ventes'!$E$19="Réparation",Paramètres!$B$9,Paramètres!$B$8)) | K42: =IF('Brouillard ventes'!$F$19="","",Paramètres!$B$11) | L42: 0 | M42: =IF('Brouillard ventes'!$F$19="","",'Brouillard ventes'!$F$19)
A43: 1 | B43: =IF('Brouillard ventes'!$F$19="","","VD"&TEXT(ROW('Brouillard ventes'!$F$19)-5,"00000")) | C43: =IF('Brouillard ventes'!$F$19="","",YEAR('Brouillard ventes'!$A$19)*10000+MONTH('Brouillard ventes'!$A$19)*100+DAY('Brouillard ventes'!$A$19)) | D43: =IF('Brouillard ventes'!$F$19="","",'Brouillard ventes'!$B$19) | E43: =IF('Brouillard ventes'!$F$19="","",LEFT('Brouillard ventes'!$D$19,30)) | F43: 15001 | G43: =IF('Brouillard ventes'!$F$19="","",Paramètres!$B$10) | K43: =IF('Brouillard ventes'!$F$19="","",Paramètres!$B$11) | L43: 0 | M43: =IF('Brouillard ventes'!$F$19="","",'Brouillard ventes'!$H$19)
A44: 1 | B44: =IF('Brouillard ventes'!$F$20="","","VD"&TEXT(ROW('Brouillard ventes'!$F$20)-5,"00000")) | C44: =IF('Brouillard ventes'!$F$20="","",YEAR('Brouillard ventes'!$A$20)*10000+MONTH('Brouillard ventes'!$A$20)*100+DAY('Brouillard ventes'!$A$20)) | D44: =IF('Brouillard ventes'!$F$20="","",'Brouillard ventes'!$B$20) | E44: =IF('Brouillard ventes'!$F$20="","",LEFT('Brouillard ventes'!$D$20,30)) | F44: 15001 | G44: =IF('Brouillard ventes'!$F$20="","",Paramètres!$B$7) | H44: =IF('Brouillard ventes'!$F$20="","",IF('Brouillard ventes'!$C$20="","CD001",'Brouillard ventes'!$C$20)) | K44: =IF('Brouillard ventes'!$F$20="","",Paramètres!$B$11) | L44: =IF('Brouillard ventes'!$F$20="","",'Brouillard ventes'!$I$20) | M44: 0
A45: 1 | B45: =IF('Brouillard ventes'!$F$20="","","VD"&TEXT(ROW('Brouillard ventes'!$F$20)-5,"00000")) | C45: =IF('Brouillard ventes'!$F$20="","",YEAR('Brouillard ventes'!$A$20)*10000+MONTH('Brouillard ventes'!$A$20)*100+DAY('Brouillard ventes'!$A$20)) | D45: =IF('Brouillard ventes'!$F$20="","",'Brouillard ventes'!$B$20) | E45: =IF('Brouillard ventes'!$F$20="","",LEFT('Brouillard ventes'!$D$20,30)) | F45: 15001 | G45: =IF('Brouillard ventes'!$F$20="","",IF('Brouillard ventes'!$E$20="Réparation",Paramètres!$B$9,Paramètres!$B$8)) | K45: =IF('Brouillard ventes'!$F$20="","",Paramètres!$B$11) | L45: 0 | M45: =IF('Brouillard ventes'!$F$20="","",'Brouillard ventes'!$F$20)
A46: 1 | B46: =IF('Brouillard ventes'!$F$20="","","VD"&TEXT(ROW('Brouillard ventes'!$F$20)-5,"00000")) | C46: =IF('Brouillard ventes'!$F$20="","",YEAR('Brouillard ventes'!$A$20)*10000+MONTH('Brouillard ventes'!$A$20)*100+DAY('Brouillard ventes'!$A$20)) | D46: =IF('Brouillard ventes'!$F$20="","",'Brouillard ventes'!$B$20) | E46: =IF('Brouillard ventes'!$F$20="","",LEFT('Brouillard ventes'!$D$20,30)) | F46: 15001 | G46: =IF('Brouillard ventes'!$F$20="","",Paramètres!$B$10) | K46: =IF('Brouillard ventes'!$F$20="","",Paramètres!$B$11) | L46: 0 | M46: =IF('Brouillard ventes'!$F$20="","",'Brouillard ventes'!$H$20)
A47: 1 | B47: =IF('Brouillard ventes'!$F$21="","","VD"&TEXT(ROW('Brouillard ventes'!$F$21)-5,"00000")) | C47: =IF('Brouillard ventes'!$F$21="","",YEAR('Brouillard ventes'!$A$21)*10000+MONTH('Brouillard ventes'!$A$21)*100+DAY('Brouillard ventes'!$A$21)) | D47: =IF('Brouillard ventes'!$F$21="","",'Brouillard ventes'!$B$21) | E47: =IF('Brouillard ventes'!$F$21="","",LEFT('Brouillard ventes'!$D$21,30)) | F47: 15001 | G47: =IF('Brouillard ventes'!$F$21="","",Paramètres!$B$7) | H47: =IF('Brouillard ventes'!$F$21="","",IF('Brouillard ventes'!$C$21="","CD001",'Brouillard ventes'!$C$21)) | K47: =IF('Brouillard ventes'!$F$21="","",Paramètres!$B$11) | L47: =IF('Brouillard ventes'!$F$21="","",'Brouillard ventes'!$I$21) | M47: 0
A48: 1 | B48: =IF('Brouillard ventes'!$F$21="","","VD"&TEXT(ROW('Brouillard ventes'!$F$21)-5,"00000")) | C48: =IF('Brouillard ventes'!$F$21="","",YEAR('Brouillard ventes'!$A$21)*10000+MONTH('Brouillard ventes'!$A$21)*100+DAY('Brouillard ventes'!$A$21)) | D48: =IF('Brouillard ventes'!$F$21="","",'Brouillard ventes'!$B$21) | E48: =IF('Brouillard ventes'!$F$21="","",LEFT('Brouillard ventes'!$D$21,30)) | F48: 15001 | G48: =IF('Brouillard ventes'!$F$21="","",IF('Brouillard ventes'!$E$21="Réparation",Paramètres!$B$9,Paramètres!$B$8)) | K48: =IF('Brouillard ventes'!$F$21="","",Paramètres!$B$11) | L48: 0 | M48: =IF('Brouillard ventes'!$F$21="","",'Brouillard ventes'!$F$21)
A49: 1 | B49: =IF('Brouillard ventes'!$F$21="","","VD"&TEXT(ROW('Brouillard ventes'!$F$21)-5,"00000")) | C49: =IF('Brouillard ventes'!$F$21="","",YEAR('Brouillard ventes'!$A$21)*10000+MONTH('Brouillard ventes'!$A$21)*100+DAY('Brouillard ventes'!$A$21)) | D49: =IF('Brouillard ventes'!$F$21="","",'Brouillard ventes'!$B$21) | E49: =IF('Brouillard ventes'!$F$21="","",LEFT('Brouillard ventes'!$D$21,30)) | F49: 15001 | G49: =IF('Brouillard ventes'!$F$21="","",Paramètres!$B$10) | K49: =IF('Brouillard ventes'!$F$21="","",Paramètres!$B$11) | L49: 0 | M49: =IF('Brouillard ventes'!$F$21="","",'Brouillard ventes'!$H$21)
A50: 1 | B50: =IF('Brouillard ventes'!$F$22="","","VD"&TEXT(ROW('Brouillard ventes'!$F$22)-5,"00000")) | C50: =IF('Brouillard ventes'!$F$22="","",YEAR('Brouillard ventes'!$A$22)*10000+MONTH('Brouillard ventes'!$A$22)*100+DAY('Brouillard ventes'!$A$22)) | D50: =IF('Brouillard ventes'!$F$22="","",'Brouillard ventes'!$B$22) | E50: =IF('Brouillard ventes'!$F$22="","",LEFT('Brouillard ventes'!$D$22,30)) | F50: 15001 | G50: =IF('Brouillard ventes'!$F$22="","",Paramètres!$B$7) | H50: =IF('Brouillard ventes'!$F$22="","",IF('Brouillard ventes'!$C$22="","CD001",'Brouillard ventes'!$C$22)) | K50: =IF('Brouillard ventes'!$F$22="","",Paramètres!$B$11) | L50: =IF('Brouillard ventes'!$F$22="","",'Brouillard ventes'!$I$22) | M50: 0
A51: 1 | B51: =IF('Brouillard ventes'!$F$22="","","VD"&TEXT(ROW('Brouillard ventes'!$F$22)-5,"00000")) | C51: =IF('Brouillard ventes'!$F$22="","",YEAR('Brouillard ventes'!$A$22)*10000+MONTH('Brouillard ventes'!$A$22)*100+DAY('Brouillard ventes'!$A$22)) | D51: =IF('Brouillard ventes'!$F$22="","",'Brouillard ventes'!$B$22) | E51: =IF('Brouillard ventes'!$F$22="","",LEFT('Brouillard ventes'!$D$22,30)) | F51: 15001 | G51: =IF('Brouillard ventes'!$F$22="","",IF('Brouillard ventes'!$E$22="Réparation",Paramètres!$B$9,Paramètres!$B$8)) | K51: =IF('Brouillard ventes'!$F$22="","",Paramètres!$B$11) | L51: 0 | M51: =IF('Brouillard ventes'!$F$22="","",'Brouillard ventes'!$F$22)
A52: 1 | B52: =IF('Brouillard ventes'!$F$22="","","VD"&TEXT(ROW('Brouillard ventes'!$F$22)-5,"00000")) | C52: =IF('Brouillard ventes'!$F$22="","",YEAR('Brouillard ventes'!$A$22)*10000+MONTH('Brouillard ventes'!$A$22)*100+DAY('Brouillard ventes'!$A$22)) | D52: =IF('Brouillard ventes'!$F$22="","",'Brouillard ventes'!$B$22) | E52: =IF('Brouillard ventes'!$F$22="","",LEFT('Brouillard ventes'!$D$22,30)) | F52: 15001 | G52: =IF('Brouillard ventes'!$F$22="","",Paramètres!$B$10) | K52: =IF('Brouillard ventes'!$F$22="","",Paramètres!$B$11) | L52: 0 | M52: =IF('Brouillard ventes'!$F$22="","",'Brouillard ventes'!$H$22)
A53: 1 | B53: =IF('Brouillard ventes'!$F$23="","","VD"&TEXT(ROW('Brouillard ventes'!$F$23)-5,"00000")) | C53: =IF('Brouillard ventes'!$F$23="","",YEAR('Brouillard ventes'!$A$23)*10000+MONTH('Brouillard ventes'!$A$23)*100+DAY('Brouillard ventes'!$A$23)) | D53: =IF('Brouillard ventes'!$F$23="","",'Brouillard ventes'!$B$23) | E53: =IF('Brouillard ventes'!$F$23="","",LEFT('Brouillard ventes'!$D$23,30)) | F53: 15001 | G53: =IF('Brouillard ventes'!$F$23="","",Paramètres!$B$7) | H53: =IF('Brouillard ventes'!$F$23="","",IF('Brouillard ventes'!$C$23="","CD001",'Brouillard ventes'!$C$23)) | K53: =IF('Brouillard ventes'!$F$23="","",Paramètres!$B$11) | L53: =IF('Brouillard ventes'!$F$23="","",'Brouillard ventes'!$I$23) | M53: 0
A54: 1 | B54: =IF('Brouillard ventes'!$F$23="","","VD"&TEXT(ROW('Brouillard ventes'!$F$23)-5,"00000")) | C54: =IF('Brouillard ventes'!$F$23="","",YEAR('Brouillard ventes'!$A$23)*10000+MONTH('Brouillard ventes'!$A$23)*100+DAY('Brouillard ventes'!$A$23)) | D54: =IF('Brouillard ventes'!$F$23="","",'Brouillard ventes'!$B$23) | E54: =IF('Brouillard ventes'!$F$23="","",LEFT('Brouillard ventes'!$D$23,30)) | F54: 15001 | G54: =IF('Brouillard ventes'!$F$23="","",IF('Brouillard ventes'!$E$23="Réparation",Paramètres!$B$9,Paramètres!$B$8)) | K54: =IF('Brouillard ventes'!$F$23="","",Paramètres!$B$11) | L54: 0 | M54: =IF('Brouillard ventes'!$F$23="","",'Brouillard ventes'!$F$23)
A55: 1 | B55: =IF('Brouillard ventes'!$F$23="","","VD"&TEXT(ROW('Brouillard ventes'!$F$23)-5,"00000")) | C55: =IF('Brouillard ventes'!$F$23="","",YEAR('Brouillard ventes'!$A$23)*10000+MONTH('Brouillard ventes'!$A$23)*100+DAY('Brouillard ventes'!$A$23)) | D55: =IF('Brouillard ventes'!$F$23="","",'Brouillard ventes'!$B$23) | E55: =IF('Brouillard ventes'!$F$23="","",LEFT('Brouillard ventes'!$D$23,30)) | F55: 15001 | G55: =IF('Brouillard ventes'!$F$23="","",Paramètres!$B$10) | K55: =IF('Brouillard ventes'!$F$23="","",Paramètres!$B$11) | L55: 0 | M55: =IF('Brouillard ventes'!$F$23="","",'Brouillard ventes'!$H$23)
A56: 1 | B56: =IF('Brouillard ventes'!$F$24="","","VD"&TEXT(ROW('Brouillard ventes'!$F$24)-5,"00000")) | C56: =IF('Brouillard ventes'!$F$24="","",YEAR('Brouillard ventes'!$A$24)*10000+MONTH('Brouillard ventes'!$A$24)*100+DAY('Brouillard ventes'!$A$24)) | D56: =IF('Brouillard ventes'!$F$24="","",'Brouillard ventes'!$B$24) | E56: =IF('Brouillard ventes'!$F$24="","",LEFT('Brouillard ventes'!$D$24,30)) | F56: 15001 | G56: =IF('Brouillard ventes'!$F$24="","",Paramètres!$B$7) | H56: =IF('Brouillard ventes'!$F$24="","",IF('Brouillard ventes'!$C$24="","CD001",'Brouillard ventes'!$C$24)) | K56: =IF('Brouillard ventes'!$F$24="","",Paramètres!$B$11) | L56: =IF('Brouillard ventes'!$F$24="","",'Brouillard ventes'!$I$24) | M56: 0
A57: 1 | B57: =IF('Brouillard ventes'!$F$24="","","VD"&TEXT(ROW('Brouillard ventes'!$F$24)-5,"00000")) | C57: =IF('Brouillard ventes'!$F$24="","",YEAR('Brouillard ventes'!$A$24)*10000+MONTH('Brouillard ventes'!$A$24)*100+DAY('Brouillard ventes'!$A$24)) | D57: =IF('Brouillard ventes'!$F$24="","",'Brouillard ventes'!$B$24) | E57: =IF('Brouillard ventes'!$F$24="","",LEFT('Brouillard ventes'!$D$24,30)) | F57: 15001 | G57: =IF('Brouillard ventes'!$F$24="","",IF('Brouillard ventes'!$E$24="Réparation",Paramètres!$B$9,Paramètres!$B$8)) | K57: =IF('Brouillard ventes'!$F$24="","",Paramètres!$B$11) | L57: 0 | M57: =IF('Brouillard ventes'!$F$24="","",'Brouillard ventes'!$F$24)
A58: 1 | B58: =IF('Brouillard ventes'!$F$24="","","VD"&TEXT(ROW('Brouillard ventes'!$F$24)-5,"00000")) | C58: =IF('Brouillard ventes'!$F$24="","",YEAR('Brouillard ventes'!$A$24)*10000+MONTH('Brouillard ventes'!$A$24)*100+DAY('Brouillard ventes'!$A$24)) | D58: =IF('Brouillard ventes'!$F$24="","",'Brouillard ventes'!$B$24) | E58: =IF('Brouillard ventes'!$F$24="","",LEFT('Brouillard ventes'!$D$24,30)) | F58: 15001 | G58: =IF('Brouillard ventes'!$F$24="","",Paramètres!$B$10) | K58: =IF('Brouillard ventes'!$F$24="","",Paramètres!$B$11) | L58: 0 | M58: =IF('Brouillard ventes'!$F$24="","",'Brouillard ventes'!$H$24)
A59: 1 | B59: =IF('Brouillard ventes'!$F$25="","","VD"&TEXT(ROW('Brouillard ventes'!$F$25)-5,"00000")) | C59: =IF('Brouillard ventes'!$F$25="","",YEAR('Brouillard ventes'!$A$25)*10000+MONTH('Brouillard ventes'!$A$25)*100+DAY('Brouillard ventes'!$A$25)) | D59: =IF('Brouillard ventes'!$F$25="","",'Brouillard ventes'!$B$25) | E59: =IF('Brouillard ventes'!$F$25="","",LEFT('Brouillard ventes'!$D$25,30)) | F59: 15001 | G59: =IF('Brouillard ventes'!$F$25="","",Paramètres!$B$7) | H59: =IF('Brouillard ventes'!$F$25="","",IF('Brouillard ventes'!$C$25="","CD001",'Brouillard ventes'!$C$25)) | K59: =IF('Brouillard ventes'!$F$25="","",Paramètres!$B$11) | L59: =IF('Brouillard ventes'!$F$25="","",'Brouillard ventes'!$I$25) | M59: 0
A60: 1 | B60: =IF('Brouillard ventes'!$F$25="","","VD"&TEXT(ROW('Brouillard ventes'!$F$25)-5,"00000")) | C60: =IF('Brouillard ventes'!$F$25="","",YEAR('Brouillard ventes'!$A$25)*10000+MONTH('Brouillard ventes'!$A$25)*100+DAY('Brouillard ventes'!$A$25)) | D60: =IF('Brouillard ventes'!$F$25="","",'Brouillard ventes'!$B$25) | E60: =IF('Brouillard ventes'!$F$25="","",LEFT('Brouillard ventes'!$D$25,30)) | F60: 15001 | G60: =IF('Brouillard ventes'!$F$25="","",IF('Brouillard ventes'!$E$25="Réparation",Paramètres!$B$9,Paramètres!$B$8)) | K60: =IF('Brouillard ventes'!$F$25="","",Paramètres!$B$11) | L60: 0 | M60: =IF('Brouillard ventes'!$F$25="","",'Brouillard ventes'!$F$25)
A61: 1 | B61: =IF('Brouillard ventes'!$F$25="","","VD"&TEXT(ROW('Brouillard ventes'!$F$25)-5,"00000")) | C61: =IF('Brouillard ventes'!$F$25="","",YEAR('Brouillard ventes'!$A$25)*10000+MONTH('Brouillard ventes'!$A$25)*100+DAY('Brouillard ventes'!$A$25)) | D61: =IF('Brouillard ventes'!$F$25="","",'Brouillard ventes'!$B$25) | E61: =IF('Brouillard ventes'!$F$25="","",LEFT('Brouillard ventes'!$D$25,30)) | F61: 15001 | G61: =IF('Brouillard ventes'!$F$25="","",Paramètres!$B$10) | K61: =IF('Brouillard ventes'!$F$25="","",Paramètres!$B$11) | L61: 0 | M61: =IF('Brouillard ventes'!$F$25="","",'Brouillard ventes'!$H$25)
A62: 1 | B62: =IF('Brouillard ventes'!$F$26="","","VD"&TEXT(ROW('Brouillard ventes'!$F$26)-5,"00000")) | C62: =IF('Brouillard ventes'!$F$26="","",YEAR('Brouillard ventes'!$A$26)*10000+MONTH('Brouillard ventes'!$A$26)*100+DAY('Brouillard ventes'!$A$26)) | D62: =IF('Brouillard ventes'!$F$26="","",'Brouillard ventes'!$B$26) | E62: =IF('Brouillard ventes'!$F$26="","",LEFT('Brouillard ventes'!$D$26,30)) | F62: 15001 | G62: =IF('Brouillard ventes'!$F$26="","",Paramètres!$B$7) | H62: =IF('Brouillard ventes'!$F$26="","",IF('Brouillard ventes'!$C$26="","CD001",'Brouillard ventes'!$C$26)) | K62: =IF('Brouillard ventes'!$F$26="","",Paramètres!$B$11) | L62: =IF('Brouillard ventes'!$F$26="","",'Brouillard ventes'!$I$26) | M62: 0
A63: 1 | B63: =IF('Brouillard ventes'!$F$26="","","VD"&TEXT(ROW('Brouillard ventes'!$F$26)-5,"00000")) | C63: =IF('Brouillard ventes'!$F$26="","",YEAR('Brouillard ventes'!$A$26)*10000+MONTH('Brouillard ventes'!$A$26)*100+DAY('Brouillard ventes'!$A$26)) | D63: =IF('Brouillard ventes'!$F$26="","",'Brouillard ventes'!$B$26) | E63: =IF('Brouillard ventes'!$F$26="","",LEFT('Brouillard ventes'!$D$26,30)) | F63: 15001 | G63: =IF('Brouillard ventes'!$F$26="","",IF('Brouillard ventes'!$E$26="Réparation",Paramètres!$B$9,Paramètres!$B$8)) | K63: =IF('Brouillard ventes'!$F$26="","",Paramètres!$B$11) | L63: 0 | M63: =IF('Brouillard ventes'!$F$26="","",'Brouillard ventes'!$F$26)
A64: 1 | B64: =IF('Brouillard ventes'!$F$26="","","VD"&TEXT(ROW('Brouillard ventes'!$F$26)-5,"00000")) | C64: =IF('Brouillard ventes'!$F$26="","",YEAR('Brouillard ventes'!$A$26)*10000+MONTH('Brouillard ventes'!$A$26)*100+DAY('Brouillard ventes'!$A$26)) | D64: =IF('Brouillard ventes'!$F$26="","",'Brouillard ventes'!$B$26) | E64: =IF('Brouillard ventes'!$F$26="","",LEFT('Brouillard ventes'!$D$26,30)) | F64: 15001 | G64: =IF('Brouillard ventes'!$F$26="","",Paramètres!$B$10) | K64: =IF('Brouillard ventes'!$F$26="","",Paramètres!$B$11) | L64: 0 | M64: =IF('Brouillard ventes'!$F$26="","",'Brouillard ventes'!$H$26)
A65: 1 | B65: =IF('Brouillard ventes'!$F$27="","","VD"&TEXT(ROW('Brouillard ventes'!$F$27)-5,"00000")) | C65: =IF('Brouillard ventes'!$F$27="","",YEAR('Brouillard ventes'!$A$27)*10000+MONTH('Brouillard ventes'!$A$27)*100+DAY('Brouillard ventes'!$A$27)) | D65: =IF('Brouillard ventes'!$F$27="","",'Brouillard ventes'!$B$27) | E65: =IF('Brouillard ventes'!$F$27="","",LEFT('Brouillard ventes'!$D$27,30)) | F65: 15001 | G65: =IF('Brouillard ventes'!$F$27="","",Paramètres!$B$7) | H65: =IF('Brouillard ventes'!$F$27="","",IF('Brouillard ventes'!$C$27="","CD001",'Brouillard ventes'!$C$27)) | K65: =IF('Brouillard ventes'!$F$27="","",Paramètres!$B$11) | L65: =IF('Brouillard ventes'!$F$27="","",'Brouillard ventes'!$I$27) | M65: 0
A66: 1 | B66: =IF('Brouillard ventes'!$F$27="","","VD"&TEXT(ROW('Brouillard ventes'!$F$27)-5,"00000")) | C66: =IF('Brouillard ventes'!$F$27="","",YEAR('Brouillard ventes'!$A$27)*10000+MONTH('Brouillard ventes'!$A$27)*100+DAY('Brouillard ventes'!$A$27)) | D66: =IF('Brouillard ventes'!$F$27="","",'Brouillard ventes'!$B$27) | E66: =IF('Brouillard ventes'!$F$27="","",LEFT('Brouillard ventes'!$D$27,30)) | F66: 15001 | G66: =IF('Brouillard ventes'!$F$27="","",IF('Brouillard ventes'!$E$27="Réparation",Paramètres!$B$9,Paramètres!$B$8)) | K66: =IF('Brouillard ventes'!$F$27="","",Paramètres!$B$11) | L66: 0 | M66: =IF('Brouillard ventes'!$F$27="","",'Brouillard ventes'!$F$27)
A67: 1 | B67: =IF('Brouillard ventes'!$F$27="","","VD"&TEXT(ROW('Brouillard ventes'!$F$27)-5,"00000")) | C67: =IF('Brouillard ventes'!$F$27="","",YEAR('Brouillard ventes'!$A$27)*10000+MONTH('Brouillard ventes'!$A$27)*100+DAY('Brouillard ventes'!$A$27)) | D67: =IF('Brouillard ventes'!$F$27="","",'Brouillard ventes'!$B$27) | E67: =IF('Brouillard ventes'!$F$27="","",LEFT('Brouillard ventes'!$D$27,30)) | F67: 15001 | G67: =IF('Brouillard ventes'!$F$27="","",Paramètres!$B$10) | K67: =IF('Brouillard ventes'!$F$27="","",Paramètres!$B$11) | L67: 0 | M67: =IF('Brouillard ventes'!$F$27="","",'Brouillard ventes'!$H$27)
A68: 1 | B68: =IF('Brouillard ventes'!$F$28="","","VD"&TEXT(ROW('Brouillard ventes'!$F$28)-5,"00000")) | C68: =IF('Brouillard ventes'!$F$28="","",YEAR('Brouillard ventes'!$A$28)*10000+MONTH('Brouillard ventes'!$A$28)*100+DAY('Brouillard ventes'!$A$28)) | D68: =IF('Brouillard ventes'!$F$28="","",'Brouillard ventes'!$B$28) | E68: =IF('Brouillard ventes'!$F$28="","",LEFT('Brouillard ventes'!$D$28,30)) | F68: 15001 | G68: =IF('Brouillard ventes'!$F$28="","",Paramètres!$B$7) | H68: =IF('Brouillard ventes'!$F$28="","",IF('Brouillard ventes'!$C$28="","CD001",'Brouillard ventes'!$C$28)) | K68: =IF('Brouillard ventes'!$F$28="","",Paramètres!$B$11) | L68: =IF('Brouillard ventes'!$F$28="","",'Brouillard ventes'!$I$28) | M68: 0
A69: 1 | B69: =IF('Brouillard ventes'!$F$28="","","VD"&TEXT(ROW('Brouillard ventes'!$F$28)-5,"00000")) | C69: =IF('Brouillard ventes'!$F$28="","",YEAR('Brouillard ventes'!$A$28)*10000+MONTH('Brouillard ventes'!$A$28)*100+DAY('Brouillard ventes'!$A$28)) | D69: =IF('Brouillard ventes'!$F$28="","",'Brouillard ventes'!$B$28) | E69: =IF('Brouillard ventes'!$F$28="","",LEFT('Brouillard ventes'!$D$28,30)) | F69: 15001 | G69: =IF('Brouillard ventes'!$F$28="","",IF('Brouillard ventes'!$E$28="Réparation",Paramètres!$B$9,Paramètres!$B$8)) | K69: =IF('Brouillard ventes'!$F$28="","",Paramètres!$B$11) | L69: 0 | M69: =IF('Brouillard ventes'!$F$28="","",'Brouillard ventes'!$F$28)
A70: 1 | B70: =IF('Brouillard ventes'!$F$28="","","VD"&TEXT(ROW('Brouillard ventes'!$F$28)-5,"00000")) | C70: =IF('Brouillard ventes'!$F$28="","",YEAR('Brouillard ventes'!$A$28)*10000+MONTH('Brouillard ventes'!$A$28)*100+DAY('Brouillard ventes'!$A$28)) | D70: =IF('Brouillard ventes'!$F$28="","",'Brouillard ventes'!$B$28) | E70: =IF('Brouillard ventes'!$F$28="","",LEFT('Brouillard ventes'!$D$28,30)) | F70: 15001 | G70: =IF('Brouillard ventes'!$F$28="","",Paramètres!$B$10) | K70: =IF('Brouillard ventes'!$F$28="","",Paramètres!$B$11) | L70: 0 | M70: =IF('Brouillard ventes'!$F$28="","",'Brouillard ventes'!$H$28)
A71: 1 | B71: =IF('Brouillard ventes'!$F$29="","","VD"&TEXT(ROW('Brouillard ventes'!$F$29)-5,"00000")) | C71: =IF('Brouillard ventes'!$F$29="","",YEAR('Brouillard ventes'!$A$29)*10000+MONTH('Brouillard ventes'!$A$29)*100+DAY('Brouillard ventes'!$A$29)) | D71: =IF('Brouillard ventes'!$F$29="","",'Brouillard ventes'!$B$29) | E71: =IF('Brouillard ventes'!$F$29="","",LEFT('Brouillard ventes'!$D$29,30)) | F71: 15001 | G71: =IF('Brouillard ventes'!$F$29="","",Paramètres!$B$7) | H71: =IF('Brouillard ventes'!$F$29="","",IF('Brouillard ventes'!$C$29="","CD001",'Brouillard ventes'!$C$29)) | K71: =IF('Brouillard ventes'!$F$29="","",Paramètres!$B$11) | L71: =IF('Brouillard ventes'!$F$29="","",'Brouillard ventes'!$I$29) | M71: 0
A72: 1 | B72: =IF('Brouillard ventes'!$F$29="","","VD"&TEXT(ROW('Brouillard ventes'!$F$29)-5,"00000")) | C72: =IF('Brouillard ventes'!$F$29="","",YEAR('Brouillard ventes'!$A$29)*10000+MONTH('Brouillard ventes'!$A$29)*100+DAY('Brouillard ventes'!$A$29)) | D72: =IF('Brouillard ventes'!$F$29="","",'Brouillard ventes'!$B$29) | E72: =IF('Brouillard ventes'!$F$29="","",LEFT('Brouillard ventes'!$D$29,30)) | F72: 15001 | G72: =IF('Brouillard ventes'!$F$29="","",IF('Brouillard ventes'!$E$29="Réparation",Paramètres!$B$9,Paramètres!$B$8)) | K72: =IF('Brouillard ventes'!$F$29="","",Paramètres!$B$11) | L72: 0 | M72: =IF('Brouillard ventes'!$F$29="","",'Brouillard ventes'!$F$29)
A73: 1 | B73: =IF('Brouillard ventes'!$F$29="","","VD"&TEXT(ROW('Brouillard ventes'!$F$29)-5,"00000")) | C73: =IF('Brouillard ventes'!$F$29="","",YEAR('Brouillard ventes'!$A$29)*10000+MONTH('Brouillard ventes'!$A$29)*100+DAY('Brouillard ventes'!$A$29)) | D73: =IF('Brouillard ventes'!$F$29="","",'Brouillard ventes'!$B$29) | E73: =IF('Brouillard ventes'!$F$29="","",LEFT('Brouillard ventes'!$D$29,30)) | F73: 15001 | G73: =IF('Brouillard ventes'!$F$29="","",Paramètres!$B$10) | K73: =IF('Brouillard ventes'!$F$29="","",Paramètres!$B$11) | L73: 0 | M73: =IF('Brouillard ventes'!$F$29="","",'Brouillard ventes'!$H$29)
A74: 1 | B74: =IF('Brouillard ventes'!$F$30="","","VD"&TEXT(ROW('Brouillard ventes'!$F$30)-5,"00000")) | C74: =IF('Brouillard ventes'!$F$30="","",YEAR('Brouillard ventes'!$A$30)*10000+MONTH('Brouillard ventes'!$A$30)*100+DAY('Brouillard ventes'!$A$30)) | D74: =IF('Brouillard ventes'!$F$30="","",'Brouillard ventes'!$B$30) | E74: =IF('Brouillard ventes'!$F$30="","",LEFT('Brouillard ventes'!$D$30,30)) | F74: 15001 | G74: =IF('Brouillard ventes'!$F$30="","",Paramètres!$B$7) | H74: =IF('Brouillard ventes'!$F$30="","",IF('Brouillard ventes'!$C$30="","CD001",'Brouillard ventes'!$C$30)) | K74: =IF('Brouillard ventes'!$F$30="","",Paramètres!$B$11) | L74: =IF('Brouillard ventes'!$F$30="","",'Brouillard ventes'!$I$30) | M74: 0
A75: 1 | B75: =IF('Brouillard ventes'!$F$30="","","VD"&TEXT(ROW('Brouillard ventes'!$F$30)-5,"00000")) | C75: =IF('Brouillard ventes'!$F$30="","",YEAR('Brouillard ventes'!$A$30)*10000+MONTH('Brouillard ventes'!$A$30)*100+DAY('Brouillard ventes'!$A$30)) | D75: =IF('Brouillard ventes'!$F$30="","",'Brouillard ventes'!$B$30) | E75: =IF('Brouillard ventes'!$F$30="","",LEFT('Brouillard ventes'!$D$30,30)) | F75: 15001 | G75: =IF('Brouillard ventes'!$F$30="","",IF('Brouillard ventes'!$E$30="Réparation",Paramètres!$B$9,Paramètres!$B$8)) | K75: =IF('Brouillard ventes'!$F$30="","",Paramètres!$B$11) | L75: 0 | M75: =IF('Brouillard ventes'!$F$30="","",'Brouillard ventes'!$F$30)
A76: 1 | B76: =IF('Brouillard ventes'!$F$30="","","VD"&TEXT(ROW('Brouillard ventes'!$F$30)-5,"00000")) | C76: =IF('Brouillard ventes'!$F$30="","",YEAR('Brouillard ventes'!$A$30)*10000+MONTH('Brouillard ventes'!$A$30)*100+DAY('Brouillard ventes'!$A$30)) | D76: =IF('Brouillard ventes'!$F$30="","",'Brouillard ventes'!$B$30) | E76: =IF('Brouillard ventes'!$F$30="","",LEFT('Brouillard ventes'!$D$30,30)) | F76: 15001 | G76: =IF('Brouillard ventes'!$F$30="","",Paramètres!$B$10) | K76: =IF('Brouillard ventes'!$F$30="","",Paramètres!$B$11) | L76: 0 | M76: =IF('Brouillard ventes'!$F$30="","",'Brouillard ventes'!$H$30)
A77: 1 | B77: =IF('Brouillard ventes'!$F$31="","","VD"&TEXT(ROW('Brouillard ventes'!$F$31)-5,"00000")) | C77: =IF('Brouillard ventes'!$F$31="","",YEAR('Brouillard ventes'!$A$31)*10000+MONTH('Brouillard ventes'!$A$31)*100+DAY('Brouillard ventes'!$A$31)) | D77: =IF('Brouillard ventes'!$F$31="","",'Brouillard ventes'!$B$31) | E77: =IF('Brouillard ventes'!$F$31="","",LEFT('Brouillard ventes'!$D$31,30)) | F77: 15001 | G77: =IF('Brouillard ventes'!$F$31="","",Paramètres!$B$7) | H77: =IF('Brouillard ventes'!$F$31="","",IF('Brouillard ventes'!$C$31="","CD001",'Brouillard ventes'!$C$31)) | K77: =IF('Brouillard ventes'!$F$31="","",Paramètres!$B$11) | L77: =IF('Brouillard ventes'!$F$31="","",'Brouillard ventes'!$I$31) | M77: 0
A78: 1 | B78: =IF('Brouillard ventes'!$F$31="","","VD"&TEXT(ROW('Brouillard ventes'!$F$31)-5,"00000")) | C78: =IF('Brouillard ventes'!$F$31="","",YEAR('Brouillard ventes'!$A$31)*10000+MONTH('Brouillard ventes'!$A$31)*100+DAY('Brouillard ventes'!$A$31)) | D78: =IF('Brouillard ventes'!$F$31="","",'Brouillard ventes'!$B$31) | E78: =IF('Brouillard ventes'!$F$31="","",LEFT('Brouillard ventes'!$D$31,30)) | F78: 15001 | G78: =IF('Brouillard ventes'!$F$31="","",IF('Brouillard ventes'!$E$31="Réparation",Paramètres!$B$9,Paramètres!$B$8)) | K78: =IF('Brouillard ventes'!$F$31="","",Paramètres!$B$11) | L78: 0 | M78: =IF('Brouillard ventes'!$F$31="","",'Brouillard ventes'!$F$31)
A79: 1 | B79: =IF('Brouillard ventes'!$F$31="","","VD"&TEXT(ROW('Brouillard ventes'!$F$31)-5,"00000")) | C79: =IF('Brouillard ventes'!$F$31="","",YEAR('Brouillard ventes'!$A$31)*10000+MONTH('Brouillard ventes'!$A$31)*100+DAY('Brouillard ventes'!$A$31)) | D79: =IF('Brouillard ventes'!$F$31="","",'Brouillard ventes'!$B$31) | E79: =IF('Brouillard ventes'!$F$31="","",LEFT('Brouillard ventes'!$D$31,30)) | F79: 15001 | G79: =IF('Brouillard ventes'!$F$31="","",Paramètres!$B$10) | K79: =IF('Brouillard ventes'!$F$31="","",Paramètres!$B$11) | L79: 0 | M79: =IF('Brouillard ventes'!$F$31="","",'Brouillard ventes'!$H$31)
A80: 1 | B80: =IF('Brouillard ventes'!$F$32="","","VD"&TEXT(ROW('Brouillard ventes'!$F$32)-5,"00000")) | C80: =IF('Brouillard ventes'!$F$32="","",YEAR('Brouillard ventes'!$A$32)*10000+MONTH('Brouillard ventes'!$A$32)*100+DAY('Brouillard ventes'!$A$32)) | D80: =IF('Brouillard ventes'!$F$32="","",'Brouillard ventes'!$B$32) | E80: =IF('Brouillard ventes'!$F$32="","",LEFT('Brouillard ventes'!$D$32,30)) | F80: 15001 | G80: =IF('Brouillard ventes'!$F$32="","",Paramètres!$B$7) | H80: =IF('Brouillard ventes'!$F$32="","",IF('Brouillard ventes'!$C$32="","CD001",'Brouillard ventes'!$C$32)) | K80: =IF('Brouillard ventes'!$F$32="","",Paramètres!$B$11) | L80: =IF('Brouillard ventes'!$F$32="","",'Brouillard ventes'!$I$32) | M80: 0
A81: 1 | B81: =IF('Brouillard ventes'!$F$32="","","VD"&TEXT(ROW('Brouillard ventes'!$F$32)-5,"00000")) | C81: =IF('Brouillard ventes'!$F$32="","",YEAR('Brouillard ventes'!$A$32)*10000+MONTH('Brouillard ventes'!$A$32)*100+DAY('Brouillard ventes'!$A$32)) | D81: =IF('Brouillard ventes'!$F$32="","",'Brouillard ventes'!$B$32) | E81: =IF('Brouillard ventes'!$F$32="","",LEFT('Brouillard ventes'!$D$32,30)) | F81: 15001 | G81: =IF('Brouillard ventes'!$F$32="","",IF('Brouillard ventes'!$E$32="Réparation",Paramètres!$B$9,Paramètres!$B$8)) | K81: =IF('Brouillard ventes'!$F$32="","",Paramètres!$B$11) | L81: 0 | M81: =IF('Brouillard ventes'!$F$32="","",'Brouillard ventes'!$F$32)
A82: 1 | B82: =IF('Brouillard ventes'!$F$32="","","VD"&TEXT(ROW('Brouillard ventes'!$F$32)-5,"00000")) | C82: =IF('Brouillard ventes'!$F$32="","",YEAR('Brouillard ventes'!$A$32)*10000+MONTH('Brouillard ventes'!$A$32)*100+DAY('Brouillard ventes'!$A$32)) | D82: =IF('Brouillard ventes'!$F$32="","",'Brouillard ventes'!$B$32) | E82: =IF('Brouillard ventes'!$F$32="","",LEFT('Brouillard ventes'!$D$32,30)) | F82: 15001 | G82: =IF('Brouillard ventes'!$F$32="","",Paramètres!$B$10) | K82: =IF('Brouillard ventes'!$F$32="","",Paramètres!$B$11) | L82: 0 | M82: =IF('Brouillard ventes'!$F$32="","",'Brouillard ventes'!$H$32)
A83: 1 | B83: =IF('Brouillard ventes'!$F$33="","","VD"&TEXT(ROW('Brouillard ventes'!$F$33)-5,"00000")) | C83: =IF('Brouillard ventes'!$F$33="","",YEAR('Brouillard ventes'!$A$33)*10000+MONTH('Brouillard ventes'!$A$33)*100+DAY('Brouillard ventes'!$A$33)) | D83: =IF('Brouillard ventes'!$F$33="","",'Brouillard ventes'!$B$33) | E83: =IF('Brouillard ventes'!$F$33="","",LEFT('Brouillard ventes'!$D$33,30)) | F83: 15001 | G83: =IF('Brouillard ventes'!$F$33="","",Paramètres!$B$7) | H83: =IF('Brouillard ventes'!$F$33="","",IF('Brouillard ventes'!$C$33="","CD001",'Brouillard ventes'!$C$33)) | K83: =IF('Brouillard ventes'!$F$33="","",Paramètres!$B$11) | L83: =IF('Brouillard ventes'!$F$33="","",'Brouillard ventes'!$I$33) | M83: 0
A84: 1 | B84: =IF('Brouillard ventes'!$F$33="","","VD"&TEXT(ROW('Brouillard ventes'!$F$33)-5,"00000")) | C84: =IF('Brouillard ventes'!$F$33="","",YEAR('Brouillard ventes'!$A$33)*10000+MONTH('Brouillard ventes'!$A$33)*100+DAY('Brouillard ventes'!$A$33)) | D84: =IF('Brouillard ventes'!$F$33="","",'Brouillard ventes'!$B$33) | E84: =IF('Brouillard ventes'!$F$33="","",LEFT('Brouillard ventes'!$D$33,30)) | F84: 15001 | G84: =IF('Brouillard ventes'!$F$33="","",IF('Brouillard ventes'!$E$33="Réparation",Paramètres!$B$9,Paramètres!$B$8)) | K84: =IF('Brouillard ventes'!$F$33="","",Paramètres!$B$11) | L84: 0 | M84: =IF('Brouillard ventes'!$F$33="","",'Brouillard ventes'!$F$33)
A85: 1 | B85: =IF('Brouillard ventes'!$F$33="","","VD"&TEXT(ROW('Brouillard ventes'!$F$33)-5,"00000")) | C85: =IF('Brouillard ventes'!$F$33="","",YEAR('Brouillard ventes'!$A$33)*10000+MONTH('Brouillard ventes'!$A$33)*100+DAY('Brouillard ventes'!$A$33)) | D85: =IF('Brouillard ventes'!$F$33="","",'Brouillard ventes'!$B$33) | E85: =IF('Brouillard ventes'!$F$33="","",LEFT('Brouillard ventes'!$D$33,30)) | F85: 15001 | G85: =IF('Brouillard ventes'!$F$33="","",Paramètres!$B$10) | K85: =IF('Brouillard ventes'!$F$33="","",Paramètres!$B$11) | L85: 0 | M85: =IF('Brouillard ventes'!$F$33="","",'Brouillard ventes'!$H$33)
A86: 1 | B86: =IF('Brouillard ventes'!$F$34="","","VD"&TEXT(ROW('Brouillard ventes'!$F$34)-5,"00000")) | C86: =IF('Brouillard ventes'!$F$34="","",YEAR('Brouillard ventes'!$A$34)*10000+MONTH('Brouillard ventes'!$A$34)*100+DAY('Brouillard ventes'!$A$34)) | D86: =IF('Brouillard ventes'!$F$34="","",'Brouillard ventes'!$B$34) | E86: =IF('Brouillard ventes'!$F$34="","",LEFT('Brouillard ventes'!$D$34,30)) | F86: 15001 | G86: =IF('Brouillard ventes'!$F$34="","",Paramètres!$B$7) | H86: =IF('Brouillard ventes'!$F$34="","",IF('Brouillard ventes'!$C$34="","CD001",'Brouillard ventes'!$C$34)) | K86: =IF('Brouillard ventes'!$F$34="","",Paramètres!$B$11) | L86: =IF('Brouillard ventes'!$F$34="","",'Brouillard ventes'!$I$34) | M86: 0
A87: 1 | B87: =IF('Brouillard ventes'!$F$34="","","VD"&TEXT(ROW('Brouillard ventes'!$F$34)-5,"00000")) | C87: =IF('Brouillard ventes'!$F$34="","",YEAR('Brouillard ventes'!$A$34)*10000+MONTH('Brouillard ventes'!$A$34)*100+DAY('Brouillard ventes'!$A$34)) | D87: =IF('Brouillard ventes'!$F$34="","",'Brouillard ventes'!$B$34) | E87: =IF('Brouillard ventes'!$F$34="","",LEFT('Brouillard ventes'!$D$34,30)) | F87: 15001 | G87: =IF('Brouillard ventes'!$F$34="","",IF('Brouillard ventes'!$E$34="Réparation",Paramètres!$B$9,Paramètres!$B$8)) | K87: =IF('Brouillard ventes'!$F$34="","",Paramètres!$B$11) | L87: 0 | M87: =IF('Brouillard ventes'!$F$34="","",'Brouillard ventes'!$F$34)
A88: 1 | B88: =IF('Brouillard ventes'!$F$34="","","VD"&TEXT(ROW('Brouillard ventes'!$F$34)-5,"00000")) | C88: =IF('Brouillard ventes'!$F$34="","",YEAR('Brouillard ventes'!$A$34)*10000+MONTH('Brouillard ventes'!$A$34)*100+DAY('Brouillard ventes'!$A$34)) | D88: =IF('Brouillard ventes'!$F$34="","",'Brouillard ventes'!$B$34) | E88: =IF('Brouillard ventes'!$F$34="","",LEFT('Brouillard ventes'!$D$34,30)) | F88: 15001 | G88: =IF('Brouillard ventes'!$F$34="","",Paramètres!$B$10) | K88: =IF('Brouillard ventes'!$F$34="","",Paramètres!$B$11) | L88: 0 | M88: =IF('Brouillard ventes'!$F$34="","",'Brouillard ventes'!$H$34)
A89: 1 | B89: =IF('Brouillard ventes'!$F$35="","","VD"&TEXT(ROW('Brouillard ventes'!$F$35)-5,"00000")) | C89: =IF('Brouillard ventes'!$F$35="","",YEAR('Brouillard ventes'!$A$35)*10000+MONTH('Brouillard ventes'!$A$35)*100+DAY('Brouillard ventes'!$A$35)) | D89: =IF('Brouillard ventes'!$F$35="","",'Brouillard ventes'!$B$35) | E89: =IF('Brouillard ventes'!$F$35="","",LEFT('Brouillard ventes'!$D$35,30)) | F89: 15001 | G89: =IF('Brouillard ventes'!$F$35="","",Paramètres!$B$7) | H89: =IF('Brouillard ventes'!$F$35="","",IF('Brouillard ventes'!$C$35="","CD001",'Brouillard ventes'!$C$35)) | K89: =IF('Brouillard ventes'!$F$35="","",Paramètres!$B$11) | L89: =IF('Brouillard ventes'!$F$35="","",'Brouillard ventes'!$I$35) | M89: 0
A90: 1 | B90: =IF('Brouillard ventes'!$F$35="","","VD"&TEXT(ROW('Brouillard ventes'!$F$35)-5,"00000")) | C90: =IF('Brouillard ventes'!$F$35="","",YEAR('Brouillard ventes'!$A$35)*10000+MONTH('Brouillard ventes'!$A$35)*100+DAY('Brouillard ventes'!$A$35)) | D90: =IF('Brouillard ventes'!$F$35="","",'Brouillard ventes'!$B$35) | E90: =IF('Brouillard ventes'!$F$35="","",LEFT('Brouillard ventes'!$D$35,30)) | F90: 15001 | G90: =IF('Brouillard ventes'!$F$35="","",IF('Brouillard ventes'!$E$35="Réparation",Paramètres!$B$9,Paramètres!$B$8)) | K90: =IF('Brouillard ventes'!$F$35="","",Paramètres!$B$11) | L90: 0 | M90: =IF('Brouillard ventes'!$F$35="","",'Brouillard ventes'!$F$35)
A91: 1 | B91: =IF('Brouillard ventes'!$F$35="","","VD"&TEXT(ROW('Brouillard ventes'!$F$35)-5,"00000")) | C91: =IF('Brouillard ventes'!$F$35="","",YEAR('Brouillard ventes'!$A$35)*10000+MONTH('Brouillard ventes'!$A$35)*100+DAY('Brouillard ventes'!$A$35)) | D91: =IF('Brouillard ventes'!$F$35="","",'Brouillard ventes'!$B$35) | E91: =IF('Brouillard ventes'!$F$35="","",LEFT('Brouillard ventes'!$D$35,30)) | F91: 15001 | G91: =IF('Brouillard ventes'!$F$35="","",Paramètres!$B$10) | K91: =IF('Brouillard ventes'!$F$35="","",Paramètres!$B$11) | L91: 0 | M91: =IF('Brouillard ventes'!$F$35="","",'Brouillard ventes'!$H$35)
A92: 1 | B92: =IF('Brouillard ventes'!$F$36="","","VD"&TEXT(ROW('Brouillard ventes'!$F$36)-5,"00000")) | C92: =IF('Brouillard ventes'!$F$36="","",YEAR('Brouillard ventes'!$A$36)*10000+MONTH('Brouillard ventes'!$A$36)*100+DAY('Brouillard ventes'!$A$36)) | D92: =IF('Brouillard ventes'!$F$36="","",'Brouillard ventes'!$B$36) | E92: =IF('Brouillard ventes'!$F$36="","",LEFT('Brouillard ventes'!$D$36,30)) | F92: 15001 | G92: =IF('Brouillard ventes'!$F$36="","",Paramètres!$B$7) | H92: =IF('Brouillard ventes'!$F$36="","",IF('Brouillard ventes'!$C$36="","CD001",'Brouillard ventes'!$C$36)) | K92: =IF('Brouillard ventes'!$F$36="","",Paramètres!$B$11) | L92: =IF('Brouillard ventes'!$F$36="","",'Brouillard ventes'!$I$36) | M92: 0
A93: 1 | B93: =IF('Brouillard ventes'!$F$36="","","VD"&TEXT(ROW('Brouillard ventes'!$F$36)-5,"00000")) | C93: =IF('Brouillard ventes'!$F$36="","",YEAR('Brouillard ventes'!$A$36)*10000+MONTH('Brouillard ventes'!$A$36)*100+DAY('Brouillard ventes'!$A$36)) | D93: =IF('Brouillard ventes'!$F$36="","",'Brouillard ventes'!$B$36) | E93: =IF('Brouillard ventes'!$F$36="","",LEFT('Brouillard ventes'!$D$36,30)) | F93: 15001 | G93: =IF('Brouillard ventes'!$F$36="","",IF('Brouillard ventes'!$E$36="Réparation",Paramètres!$B$9,Paramètres!$B$8)) | K93: =IF('Brouillard ventes'!$F$36="","",Paramètres!$B$11) | L93: 0 | M93: =IF('Brouillard ventes'!$F$36="","",'Brouillard ventes'!$F$36)
A94: 1 | B94: =IF('Brouillard ventes'!$F$36="","","VD"&TEXT(ROW('Brouillard ventes'!$F$36)-5,"00000")) | C94: =IF('Brouillard ventes'!$F$36="","",YEAR('Brouillard ventes'!$A$36)*10000+MONTH('Brouillard ventes'!$A$36)*100+DAY('Brouillard ventes'!$A$36)) | D94: =IF('Brouillard ventes'!$F$36="","",'Brouillard ventes'!$B$36) | E94: =IF('Brouillard ventes'!$F$36="","",LEFT('Brouillard ventes'!$D$36,30)) | F94: 15001 | G94: =IF('Brouillard ventes'!$F$36="","",Paramètres!$B$10) | K94: =IF('Brouillard ventes'!$F$36="","",Paramètres!$B$11) | L94: 0 | M94: =IF('Brouillard ventes'!$F$36="","",'Brouillard ventes'!$H$36)
A95: 1 | B95: =IF('Brouillard ventes'!$F$37="","","VD"&TEXT(ROW('Brouillard ventes'!$F$37)-5,"00000")) | C95: =IF('Brouillard ventes'!$F$37="","",YEAR('Brouillard ventes'!$A$37)*10000+MONTH('Brouillard ventes'!$A$37)*100+DAY('Brouillard ventes'!$A$37)) | D95: =IF('Brouillard ventes'!$F$37="","",'Brouillard ventes'!$B$37) | E95: =IF('Brouillard ventes'!$F$37="","",LEFT('Brouillard ventes'!$D$37,30)) | F95: 15001 | G95: =IF('Brouillard ventes'!$F$37="","",Paramètres!$B$7) | H95: =IF('Brouillard ventes'!$F$37="","",IF('Brouillard ventes'!$C$37="","CD001",'Brouillard ventes'!$C$37)) | K95: =IF('Brouillard ventes'!$F$37="","",Paramètres!$B$11) | L95: =IF('Brouillard ventes'!$F$37="","",'Brouillard ventes'!$I$37) | M95: 0
A96: 1 | B96: =IF('Brouillard ventes'!$F$37="","","VD"&TEXT(ROW('Brouillard ventes'!$F$37)-5,"00000")) | C96: =IF('Brouillard ventes'!$F$37="","",YEAR('Brouillard ventes'!$A$37)*10000+MONTH('Brouillard ventes'!$A$37)*100+DAY('Brouillard ventes'!$A$37)) | D96: =IF('Brouillard ventes'!$F$37="","",'Brouillard ventes'!$B$37) | E96: =IF('Brouillard ventes'!$F$37="","",LEFT('Brouillard ventes'!$D$37,30)) | F96: 15001 | G96: =IF('Brouillard ventes'!$F$37="","",IF('Brouillard ventes'!$E$37="Réparation",Paramètres!$B$9,Paramètres!$B$8)) | K96: =IF('Brouillard ventes'!$F$37="","",Paramètres!$B$11) | L96: 0 | M96: =IF('Brouillard ventes'!$F$37="","",'Brouillard ventes'!$F$37)
A97: 1 | B97: =IF('Brouillard ventes'!$F$37="","","VD"&TEXT(ROW('Brouillard ventes'!$F$37)-5,"00000")) | C97: =IF('Brouillard ventes'!$F$37="","",YEAR('Brouillard ventes'!$A$37)*10000+MONTH('Brouillard ventes'!$A$37)*100+DAY('Brouillard ventes'!$A$37)) | D97: =IF('Brouillard ventes'!$F$37="","",'Brouillard ventes'!$B$37) | E97: =IF('Brouillard ventes'!$F$37="","",LEFT('Brouillard ventes'!$D$37,30)) | F97: 15001 | G97: =IF('Brouillard ventes'!$F$37="","",Paramètres!$B$10) | K97: =IF('Brouillard ventes'!$F$37="","",Paramètres!$B$11) | L97: 0 | M97: =IF('Brouillard ventes'!$F$37="","",'Brouillard ventes'!$H$37)
A98: 1 | B98: =IF('Brouillard ventes'!$F$38="","","VD"&TEXT(ROW('Brouillard ventes'!$F$38)-5,"00000")) | C98: =IF('Brouillard ventes'!$F$38="","",YEAR('Brouillard ventes'!$A$38)*10000+MONTH('Brouillard ventes'!$A$38)*100+DAY('Brouillard ventes'!$A$38)) | D98: =IF('Brouillard ventes'!$F$38="","",'Brouillard ventes'!$B$38) | E98: =IF('Brouillard ventes'!$F$38="","",LEFT('Brouillard ventes'!$D$38,30)) | F98: 15001 | G98: =IF('Brouillard ventes'!$F$38="","",Paramètres!$B$7) | H98: =IF('Brouillard ventes'!$F$38="","",IF('Brouillard ventes'!$C$38="","CD001",'Brouillard ventes'!$C$38)) | K98: =IF('Brouillard ventes'!$F$38="","",Paramètres!$B$11) | L98: =IF('Brouillard ventes'!$F$38="","",'Brouillard ventes'!$I$38) | M98: 0
A99: 1 | B99: =IF('Brouillard ventes'!$F$38="","","VD"&TEXT(ROW('Brouillard ventes'!$F$38)-5,"00000")) | C99: =IF('Brouillard ventes'!$F$38="","",YEAR('Brouillard ventes'!$A$38)*10000+MONTH('Brouillard ventes'!$A$38)*100+DAY('Brouillard ventes'!$A$38)) | D99: =IF('Brouillard ventes'!$F$38="","",'Brouillard ventes'!$B$38) | E99: =IF('Brouillard ventes'!$F$38="","",LEFT('Brouillard ventes'!$D$38,30)) | F99: 15001 | G99: =IF('Brouillard ventes'!$F$38="","",IF('Brouillard ventes'!$E$38="Réparation",Paramètres!$B$9,Paramètres!$B$8)) | K99: =IF('Brouillard ventes'!$F$38="","",Paramètres!$B$11) | L99: 0 | M99: =IF('Brouillard ventes'!$F$38="","",'Brouillard ventes'!$F$38)
A100: 1 | B100: =IF('Brouillard ventes'!$F$38="","","VD"&TEXT(ROW('Brouillard ventes'!$F$38)-5,"00000")) | C100: =IF('Brouillard ventes'!$F$38="","",YEAR('Brouillard ventes'!$A$38)*10000+MONTH('Brouillard ventes'!$A$38)*100+DAY('Brouillard ventes'!$A$38)) | D100: =IF('Brouillard ventes'!$F$38="","",'Brouillard ventes'!$B$38) | E100: =IF('Brouillard ventes'!$F$38="","",LEFT('Brouillard ventes'!$D$38,30)) | F100: 15001 | G100: =IF('Brouillard ventes'!$F$38="","",Paramètres!$B$10) | K100: =IF('Brouillard ventes'!$F$38="","",Paramètres!$B$11) | L100: 0 | M100: =IF('Brouillard ventes'!$F$38="","",'Brouillard ventes'!$H$38)
...

Sheet Encaissements comptant
A1: FOLIO | B1: PIECE | C1: DATE | D1: REFERENCE | E1: LIBELLE | F1: CODE_JRN | G1: CODE_COM | H1: CODE_AUX | I1: CODE_BDG | J1: CODE_NAT | K1: CODE_UNT | L1: DEBIT | M1: CREDIT | N1: LETTRAGE | O1: LIBELLEA | P1: CTP_COM | Q1: CTP_AUX | R1: ECHEANCE
A2: 1 | B2: =IF(OR('Brouillard ventes'!$F$6="",'Brouillard ventes'!$J$6="À crédit",'Brouillard ventes'!$J$6=""),"","EC"&TEXT(ROW('Brouillard ventes'!$F$6)-5,"00000")) | C2: =IF(OR('Brouillard ventes'!$F$6="",'Brouillard ventes'!$J$6="À crédit",'Brouillard ventes'!$J$6=""),"",YEAR('Brouillard ventes'!$A$6)*10000+MONTH('Brouillard ventes'!$A$6)*100+DAY('Brouillard ventes'!$A$6)) | D2: =IF(OR('Brouillard ventes'!$F$6="",'Brouillard ventes'!$J$6="À crédit",'Brouillard ventes'!$J$6=""),"",'Brouillard ventes'!$B$6) | E2: =IF(OR('Brouillard ventes'!$F$6="",'Brouillard ventes'!$J$6="À crédit",'Brouillard ventes'!$J$6=""),"","REGL "&LEFT('Brouillard ventes'!$D$6,25)) | F2: =IF(OR('Brouillard ventes'!$F$6="",'Brouillard ventes'!$J$6="À crédit",'Brouillard ventes'!$J$6=""),"",IF('Brouillard ventes'!$J$6="Espèces","04001","02001")) | G2: =IF(OR('Brouillard ventes'!$F$6="",'Brouillard ventes'!$J$6="À crédit",'Brouillard ventes'!$J$6=""),"",IF('Brouillard ventes'!$J$6="Espèces","53000","51220")) | K2: =IF(OR('Brouillard ventes'!$F$6="",'Brouillard ventes'!$J$6="À crédit",'Brouillard ventes'!$J$6=""),"",Paramètres!$B$11) | L2: =IF(OR('Brouillard ventes'!$F$6="",'Brouillard ventes'!$J$6="À crédit",'Brouillard ventes'!$J$6=""),0,'Brouillard ventes'!$I$6) | M2: 0
A3: 1 | B3: =IF(OR('Brouillard ventes'!$F$6="",'Brouillard ventes'!$J$6="À crédit",'Brouillard ventes'!$J$6=""),"","EC"&TEXT(ROW('Brouillard ventes'!$F$6)-5,"00000")) | C3: =IF(OR('Brouillard ventes'!$F$6="",'Brouillard ventes'!$J$6="À crédit",'Brouillard ventes'!$J$6=""),"",YEAR('Brouillard ventes'!$A$6)*10000+MONTH('Brouillard ventes'!$A$6)*100+DAY('Brouillard ventes'!$A$6)) | D3: =IF(OR('Brouillard ventes'!$F$6="",'Brouillard ventes'!$J$6="À crédit",'Brouillard ventes'!$J$6=""),"",'Brouillard ventes'!$B$6) | E3: =IF(OR('Brouillard ventes'!$F$6="",'Brouillard ventes'!$J$6="À crédit",'Brouillard ventes'!$J$6=""),"","REGL "&LEFT('Brouillard ventes'!$D$6,25)) | F3: =IF(OR('Brouillard ventes'!$F$6="",'Brouillard ventes'!$J$6="À crédit",'Brouillard ventes'!$J$6=""),"",IF('Brouillard ventes'!$J$6="Espèces","04001","02001")) | G3: =IF(OR('Brouillard ventes'!$F$6="",'Brouillard ventes'!$J$6="À crédit",'Brouillard ventes'!$J$6=""),"",Paramètres!$B$7) | H3: =IF(OR('Brouillard ventes'!$F$6="",'Brouillard ventes'!$J$6="À crédit",'Brouillard ventes'!$J$6=""),"",IF('Brouillard ventes'!$C$6="","CD001",'Brouillard ventes'!$C$6)) | K3: =IF(OR('Brouillard ventes'!$F$6="",'Brouillard ventes'!$J$6="À crédit",'Brouillard ventes'!$J$6=""),"",Paramètres!$B$11) | L3: 0 | M3: =IF(OR('Brouillard ventes'!$F$6="",'Brouillard ventes'!$J$6="À crédit",'Brouillard ventes'!$J$6=""),0,'Brouillard ventes'!$I$6)
A4: 1 | B4: =IF(OR('Brouillard ventes'!$F$7="",'Brouillard ventes'!$J$7="À crédit",'Brouillard ventes'!$J$7=""),"","EC"&TEXT(ROW('Brouillard ventes'!$F$7)-5,"00000")) | C4: =IF(OR('Brouillard ventes'!$F$7="",'Brouillard ventes'!$J$7="À crédit",'Brouillard ventes'!$J$7=""),"",YEAR('Brouillard ventes'!$A$7)*10000+MONTH('Brouillard ventes'!$A$7)*100+DAY('Brouillard ventes'!$A$7)) | D4: =IF(OR('Brouillard ventes'!$F$7="",'Brouillard ventes'!$J$7="À crédit",'Brouillard ventes'!$J$7=""),"",'Brouillard ventes'!$B$7) | E4: =IF(OR('Brouillard ventes'!$F$7="",'Brouillard ventes'!$J$7="À crédit",'Brouillard ventes'!$J$7=""),"","REGL "&LEFT('Brouillard ventes'!$D$7,25)) | F4: =IF(OR('Brouillard ventes'!$F$7="",'Brouillard ventes'!$J$7="À crédit",'Brouillard ventes'!$J$7=""),"",IF('Brouillard ventes'!$J$7="Espèces","04001","02001")) | G4: =IF(OR('Brouillard ventes'!$F$7="",'Brouillard ventes'!$J$7="À crédit",'Brouillard ventes'!$J$7=""),"",IF('Brouillard ventes'!$J$7="Espèces","53000","51220")) | K4: =IF(OR('Brouillard ventes'!$F$7="",'Brouillard ventes'!$J$7="À crédit",'Brouillard ventes'!$J$7=""),"",Paramètres!$B$11) | L4: =IF(OR('Brouillard ventes'!$F$7="",'Brouillard ventes'!$J$7="À crédit",'Brouillard ventes'!$J$7=""),0,'Brouillard ventes'!$I$7) | M4: 0
A5: 1 | B5: =IF(OR('Brouillard ventes'!$F$7="",'Brouillard ventes'!$J$7="À crédit",'Brouillard ventes'!$J$7=""),"","EC"&TEXT(ROW('Brouillard ventes'!$F$7)-5,"00000")) | C5: =IF(OR('Brouillard ventes'!$F$7="",'Brouillard ventes'!$J$7="À crédit",'Brouillard ventes'!$J$7=""),"",YEAR('Brouillard ventes'!$A$7)*10000+MONTH('Brouillard ventes'!$A$7)*100+DAY('Brouillard ventes'!$A$7)) | D5: =IF(OR('Brouillard ventes'!$F$7="",'Brouillard ventes'!$J$7="À crédit",'Brouillard ventes'!$J$7=""),"",'Brouillard ventes'!$B$7) | E5: =IF(OR('Brouillard ventes'!$F$7="",'Brouillard ventes'!$J$7="À crédit",'Brouillard ventes'!$J$7=""),"","REGL "&LEFT('Brouillard ventes'!$D$7,25)) | F5: =IF(OR('Brouillard ventes'!$F$7="",'Brouillard ventes'!$J$7="À crédit",'Brouillard ventes'!$J$7=""),"",IF('Brouillard ventes'!$J$7="Espèces","04001","02001")) | G5: =IF(OR('Brouillard ventes'!$F$7="",'Brouillard ventes'!$J$7="À crédit",'Brouillard ventes'!$J$7=""),"",Paramètres!$B$7) | H5: =IF(OR('Brouillard ventes'!$F$7="",'Brouillard ventes'!$J$7="À crédit",'Brouillard ventes'!$J$7=""),"",IF('Brouillard ventes'!$C$7="","CD001",'Brouillard ventes'!$C$7)) | K5: =IF(OR('Brouillard ventes'!$F$7="",'Brouillard ventes'!$J$7="À crédit",'Brouillard ventes'!$J$7=""),"",Paramètres!$B$11) | L5: 0 | M5: =IF(OR('Brouillard ventes'!$F$7="",'Brouillard ventes'!$J$7="À crédit",'Brouillard ventes'!$J$7=""),0,'Brouillard ventes'!$I$7)
A6: 1 | B6: =IF(OR('Brouillard ventes'!$F$8="",'Brouillard ventes'!$J$8="À crédit",'Brouillard ventes'!$J$8=""),"","EC"&TEXT(ROW('Brouillard ventes'!$F$8)-5,"00000")) | C6: =IF(OR('Brouillard ventes'!$F$8="",'Brouillard ventes'!$J$8="À crédit",'Brouillard ventes'!$J$8=""),"",YEAR('Brouillard ventes'!$A$8)*10000+MONTH('Brouillard ventes'!$A$8)*100+DAY('Brouillard ventes'!$A$8)) | D6: =IF(OR('Brouillard ventes'!$F$8="",'Brouillard ventes'!$J$8="À crédit",'Brouillard ventes'!$J$8=""),"",'Brouillard ventes'!$B$8) | E6: =IF(OR('Brouillard ventes'!$F$8="",'Brouillard ventes'!$J$8="À crédit",'Brouillard ventes'!$J$8=""),"","REGL "&LEFT('Brouillard ventes'!$D$8,25)) | F6: =IF(OR('Brouillard ventes'!$F$8="",'Brouillard ventes'!$J$8="À crédit",'Brouillard ventes'!$J$8=""),"",IF('Brouillard ventes'!$J$8="Espèces","04001","02001")) | G6: =IF(OR('Brouillard ventes'!$F$8="",'Brouillard ventes'!$J$8="À crédit",'Brouillard ventes'!$J$8=""),"",IF('Brouillard ventes'!$J$8="Espèces","53000","51220")) | K6: =IF(OR('Brouillard ventes'!$F$8="",'Brouillard ventes'!$J$8="À crédit",'Brouillard ventes'!$J$8=""),"",Paramètres!$B$11) | L6: =IF(OR('Brouillard ventes'!$F$8="",'Brouillard ventes'!$J$8="À crédit",'Brouillard ventes'!$J$8=""),0,'Brouillard ventes'!$I$8) | M6: 0
A7: 1 | B7: =IF(OR('Brouillard ventes'!$F$8="",'Brouillard ventes'!$J$8="À crédit",'Brouillard ventes'!$J$8=""),"","EC"&TEXT(ROW('Brouillard ventes'!$F$8)-5,"00000")) | C7: =IF(OR('Brouillard ventes'!$F$8="",'Brouillard ventes'!$J$8="À crédit",'Brouillard ventes'!$J$8=""),"",YEAR('Brouillard ventes'!$A$8)*10000+MONTH('Brouillard ventes'!$A$8)*100+DAY('Brouillard ventes'!$A$8)) | D7: =IF(OR('Brouillard ventes'!$F$8="",'Brouillard ventes'!$J$8="À crédit",'Brouillard ventes'!$J$8=""),"",'Brouillard ventes'!$B$8) | E7: =IF(OR('Brouillard ventes'!$F$8="",'Brouillard ventes'!$J$8="À crédit",'Brouillard ventes'!$J$8=""),"","REGL "&LEFT('Brouillard ventes'!$D$8,25)) | F7: =IF(OR('Brouillard ventes'!$F$8="",'Brouillard ventes'!$J$8="À crédit",'Brouillard ventes'!$J$8=""),"",IF('Brouillard ventes'!$J$8="Espèces","04001","02001")) | G7: =IF(OR('Brouillard ventes'!$F$8="",'Brouillard ventes'!$J$8="À crédit",'Brouillard ventes'!$J$8=""),"",Paramètres!$B$7) | H7: =IF(OR('Brouillard ventes'!$F$8="",'Brouillard ventes'!$J$8="À crédit",'Brouillard ventes'!$J$8=""),"",IF('Brouillard ventes'!$C$8="","CD001",'Brouillard ventes'!$C$8)) | K7: =IF(OR('Brouillard ventes'!$F$8="",'Brouillard ventes'!$J$8="À crédit",'Brouillard ventes'!$J$8=""),"",Paramètres!$B$11) | L7: 0 | M7: =IF(OR('Brouillard ventes'!$F$8="",'Brouillard ventes'!$J$8="À crédit",'Brouillard ventes'!$J$8=""),0,'Brouillard ventes'!$I$8)
A8: 1 | B8: =IF(OR('Brouillard ventes'!$F$9="",'Brouillard ventes'!$J$9="À crédit",'Brouillard ventes'!$J$9=""),"","EC"&TEXT(ROW('Brouillard ventes'!$F$9)-5,"00000")) | C8: =IF(OR('Brouillard ventes'!$F$9="",'Brouillard ventes'!$J$9="À crédit",'Brouillard ventes'!$J$9=""),"",YEAR('Brouillard ventes'!$A$9)*10000+MONTH('Brouillard ventes'!$A$9)*100+DAY('Brouillard ventes'!$A$9)) | D8: =IF(OR('Brouillard ventes'!$F$9="",'Brouillard ventes'!$J$9="À crédit",'Brouillard ventes'!$J$9=""),"",'Brouillard ventes'!$B$9) | E8: =IF(OR('Brouillard ventes'!$F$9="",'Brouillard ventes'!$J$9="À crédit",'Brouillard ventes'!$J$9=""),"","REGL "&LEFT('Brouillard ventes'!$D$9,25)) | F8: =IF(OR('Brouillard ventes'!$F$9="",'Brouillard ventes'!$J$9="À crédit",'Brouillard ventes'!$J$9=""),"",IF('Brouillard ventes'!$J$9="Espèces","04001","02001")) | G8: =IF(OR('Brouillard ventes'!$F$9="",'Brouillard ventes'!$J$9="À crédit",'Brouillard ventes'!$J$9=""),"",IF('Brouillard ventes'!$J$9="Espèces","53000","51220")) | K8: =IF(OR('Brouillard ventes'!$F$9="",'Brouillard ventes'!$J$9="À crédit",'Brouillard ventes'!$J$9=""),"",Paramètres!$B$11) | L8: =IF(OR('Brouillard ventes'!$F$9="",'Brouillard ventes'!$J$9="À crédit",'Brouillard ventes'!$J$9=""),0,'Brouillard ventes'!$I$9) | M8: 0
A9: 1 | B9: =IF(OR('Brouillard ventes'!$F$9="",'Brouillard ventes'!$J$9="À crédit",'Brouillard ventes'!$J$9=""),"","EC"&TEXT(ROW('Brouillard ventes'!$F$9)-5,"00000")) | C9: =IF(OR('Brouillard ventes'!$F$9="",'Brouillard ventes'!$J$9="À crédit",'Brouillard ventes'!$J$9=""),"",YEAR('Brouillard ventes'!$A$9)*10000+MONTH('Brouillard ventes'!$A$9)*100+DAY('Brouillard ventes'!$A$9)) | D9: =IF(OR('Brouillard ventes'!$F$9="",'Brouillard ventes'!$J$9="À crédit",'Brouillard ventes'!$J$9=""),"",'Brouillard ventes'!$B$9) | E9: =IF(OR('Brouillard ventes'!$F$9="",'Brouillard ventes'!$J$9="À crédit",'Brouillard ventes'!$J$9=""),"","REGL "&LEFT('Brouillard ventes'!$D$9,25)) | F9: =IF(OR('Brouillard ventes'!$F$9="",'Brouillard ventes'!$J$9="À crédit",'Brouillard ventes'!$J$9=""),"",IF('Brouillard ventes'!$J$9="Espèces","04001","02001")) | G9: =IF(OR('Brouillard ventes'!$F$9="",'Brouillard ventes'!$J$9="À crédit",'Brouillard ventes'!$J$9=""),"",Paramètres!$B$7) | H9: =IF(OR('Brouillard ventes'!$F$9="",'Brouillard ventes'!$J$9="À crédit",'Brouillard ventes'!$J$9=""),"",IF('Brouillard ventes'!$C$9="","CD001",'Brouillard ventes'!$C$9)) | K9: =IF(OR('Brouillard ventes'!$F$9="",'Brouillard ventes'!$J$9="À crédit",'Brouillard ventes'!$J$9=""),"",Paramètres!$B$11) | L9: 0 | M9: =IF(OR('Brouillard ventes'!$F$9="",'Brouillard ventes'!$J$9="À crédit",'Brouillard ventes'!$J$9=""),0,'Brouillard ventes'!$I$9)
A10: 1 | B10: =IF(OR('Brouillard ventes'!$F$10="",'Brouillard ventes'!$J$10="À crédit",'Brouillard ventes'!$J$10=""),"","EC"&TEXT(ROW('Brouillard ventes'!$F$10)-5,"00000")) | C10: =IF(OR('Brouillard ventes'!$F$10="",'Brouillard ventes'!$J$10="À crédit",'Brouillard ventes'!$J$10=""),"",YEAR('Brouillard ventes'!$A$10)*10000+MONTH('Brouillard ventes'!$A$10)*100+DAY('Brouillard ventes'!$A$10)) | D10: =IF(OR('Brouillard ventes'!$F$10="",'Brouillard ventes'!$J$10="À crédit",'Brouillard ventes'!$J$10=""),"",'Brouillard ventes'!$B$10) | E10: =IF(OR('Brouillard ventes'!$F$10="",'Brouillard ventes'!$J$10="À crédit",'Brouillard ventes'!$J$10=""),"","REGL "&LEFT('Brouillard ventes'!$D$10,25)) | F10: =IF(OR('Brouillard ventes'!$F$10="",'Brouillard ventes'!$J$10="À crédit",'Brouillard ventes'!$J$10=""),"",IF('Brouillard ventes'!$J$10="Espèces","04001","02001")) | G10: =IF(OR('Brouillard ventes'!$F$10="",'Brouillard ventes'!$J$10="À crédit",'Brouillard ventes'!$J$10=""),"",IF('Brouillard ventes'!$J$10="Espèces","53000","51220")) | K10: =IF(OR('Brouillard ventes'!$F$10="",'Brouillard ventes'!$J$10="À crédit",'Brouillard ventes'!$J$10=""),"",Paramètres!$B$11) | L10: =IF(OR('Brouillard ventes'!$F$10="",'Brouillard ventes'!$J$10="À crédit",'Brouillard ventes'!$J$10=""),0,'Brouillard ventes'!$I$10) | M10: 0
A11: 1 | B11: =IF(OR('Brouillard ventes'!$F$10="",'Brouillard ventes'!$J$10="À crédit",'Brouillard ventes'!$J$10=""),"","EC"&TEXT(ROW('Brouillard ventes'!$F$10)-5,"00000")) | C11: =IF(OR('Brouillard ventes'!$F$10="",'Brouillard ventes'!$J$10="À crédit",'Brouillard ventes'!$J$10=""),"",YEAR('Brouillard ventes'!$A$10)*10000+MONTH('Brouillard ventes'!$A$10)*100+DAY('Brouillard ventes'!$A$10)) | D11: =IF(OR('Brouillard ventes'!$F$10="",'Brouillard ventes'!$J$10="À crédit",'Brouillard ventes'!$J$10=""),"",'Brouillard ventes'!$B$10) | E11: =IF(OR('Brouillard ventes'!$F$10="",'Brouillard ventes'!$J$10="À crédit",'Brouillard ventes'!$J$10=""),"","REGL "&LEFT('Brouillard ventes'!$D$10,25)) | F11: =IF(OR('Brouillard ventes'!$F$10="",'Brouillard ventes'!$J$10="À crédit",'Brouillard ventes'!$J$10=""),"",IF('Brouillard ventes'!$J$10="Espèces","04001","02001")) | G11: =IF(OR('Brouillard ventes'!$F$10="",'Brouillard ventes'!$J$10="À crédit",'Brouillard ventes'!$J$10=""),"",Paramètres!$B$7) | H11: =IF(OR('Brouillard ventes'!$F$10="",'Brouillard ventes'!$J$10="À crédit",'Brouillard ventes'!$J$10=""),"",IF('Brouillard ventes'!$C$10="","CD001",'Brouillard ventes'!$C$10)) | K11: =IF(OR('Brouillard ventes'!$F$10="",'Brouillard ventes'!$J$10="À crédit",'Brouillard ventes'!$J$10=""),"",Paramètres!$B$11) | L11: 0 | M11: =IF(OR('Brouillard ventes'!$F$10="",'Brouillard ventes'!$J$10="À crédit",'Brouillard ventes'!$J$10=""),0,'Brouillard ventes'!$I$10)
A12: 1 | B12: =IF(OR('Brouillard ventes'!$F$11="",'Brouillard ventes'!$J$11="À crédit",'Brouillard ventes'!$J$11=""),"","EC"&TEXT(ROW('Brouillard ventes'!$F$11)-5,"00000")) | C12: =IF(OR('Brouillard ventes'!$F$11="",'Brouillard ventes'!$J$11="À crédit",'Brouillard ventes'!$J$11=""),"",YEAR('Brouillard ventes'!$A$11)*10000+MONTH('Brouillard ventes'!$A$11)*100+DAY('Brouillard ventes'!$A$11)) | D12: =IF(OR('Brouillard ventes'!$F$11="",'Brouillard ventes'!$J$11="À crédit",'Brouillard ventes'!$J$11=""),"",'Brouillard ventes'!$B$11) | E12: =IF(OR('Brouillard ventes'!$F$11="",'Brouillard ventes'!$J$11="À crédit",'Brouillard ventes'!$J$11=""),"","REGL "&LEFT('Brouillard ventes'!$D$11,25)) | F12: =IF(OR('Brouillard ventes'!$F$11="",'Brouillard ventes'!$J$11="À crédit",'Brouillard ventes'!$J$11=""),"",IF('Brouillard ventes'!$J$11="Espèces","04001","02001")) | G12: =IF(OR('Brouillard ventes'!$F$11="",'Brouillard ventes'!$J$11="À crédit",'Brouillard ventes'!$J$11=""),"",IF('Brouillard ventes'!$J$11="Espèces","53000","51220")) | K12: =IF(OR('Brouillard ventes'!$F$11="",'Brouillard ventes'!$J$11="À crédit",'Brouillard ventes'!$J$11=""),"",Paramètres!$B$11) | L12: =IF(OR('Brouillard ventes'!$F$11="",'Brouillard ventes'!$J$11="À crédit",'Brouillard ventes'!$J$11=""),0,'Brouillard ventes'!$I$11) | M12: 0
A13: 1 | B13: =IF(OR('Brouillard ventes'!$F$11="",'Brouillard ventes'!$J$11="À crédit",'Brouillard ventes'!$J$11=""),"","EC"&TEXT(ROW('Brouillard ventes'!$F$11)-5,"00000")) | C13: =IF(OR('Brouillard ventes'!$F$11="",'Brouillard ventes'!$J$11="À crédit",'Brouillard ventes'!$J$11=""),"",YEAR('Brouillard ventes'!$A$11)*10000+MONTH('Brouillard ventes'!$A$11)*100+DAY('Brouillard ventes'!$A$11)) | D13: =IF(OR('Brouillard ventes'!$F$11="",'Brouillard ventes'!$J$11="À crédit",'Brouillard ventes'!$J$11=""),"",'Brouillard ventes'!$B$11) | E13: =IF(OR('Brouillard ventes'!$F$11="",'Brouillard ventes'!$J$11="À crédit",'Brouillard ventes'!$J$11=""),"","REGL "&LEFT('Brouillard ventes'!$D$11,25)) | F13: =IF(OR('Brouillard ventes'!$F$11="",'Brouillard ventes'!$J$11="À crédit",'Brouillard ventes'!$J$11=""),"",IF('Brouillard ventes'!$J$11="Espèces","04001","02001")) | G13: =IF(OR('Brouillard ventes'!$F$11="",'Brouillard ventes'!$J$11="À crédit",'Brouillard ventes'!$J$11=""),"",Paramètres!$B$7) | H13: =IF(OR('Brouillard ventes'!$F$11="",'Brouillard ventes'!$J$11="À crédit",'Brouillard ventes'!$J$11=""),"",IF('Brouillard ventes'!$C$11="","CD001",'Brouillard ventes'!$C$11)) | K13: =IF(OR('Brouillard ventes'!$F$11="",'Brouillard ventes'!$J$11="À crédit",'Brouillard ventes'!$J$11=""),"",Paramètres!$B$11) | L13: 0 | M13: =IF(OR('Brouillard ventes'!$F$11="",'Brouillard ventes'!$J$11="À crédit",'Brouillard ventes'!$J$11=""),0,'Brouillard ventes'!$I$11)
A14: 1 | B14: =IF(OR('Brouillard ventes'!$F$12="",'Brouillard ventes'!$J$12="À crédit",'Brouillard ventes'!$J$12=""),"","EC"&TEXT(ROW('Brouillard ventes'!$F$12)-5,"00000")) | C14: =IF(OR('Brouillard ventes'!$F$12="",'Brouillard ventes'!$J$12="À crédit",'Brouillard ventes'!$J$12=""),"",YEAR('Brouillard ventes'!$A$12)*10000+MONTH('Brouillard ventes'!$A$12)*100+DAY('Brouillard ventes'!$A$12)) | D14: =IF(OR('Brouillard ventes'!$F$12="",'Brouillard ventes'!$J$12="À crédit",'Brouillard ventes'!$J$12=""),"",'Brouillard ventes'!$B$12) | E14: =IF(OR('Brouillard ventes'!$F$12="",'Brouillard ventes'!$J$12="À crédit",'Brouillard ventes'!$J$12=""),"","REGL "&LEFT('Brouillard ventes'!$D$12,25)) | F14: =IF(OR('Brouillard ventes'!$F$12="",'Brouillard ventes'!$J$12="À crédit",'Brouillard ventes'!$J$12=""),"",IF('Brouillard ventes'!$J$12="Espèces","04001","02001")) | G14: =IF(OR('Brouillard ventes'!$F$12="",'Brouillard ventes'!$J$12="À crédit",'Brouillard ventes'!$J$12=""),"",IF('Brouillard ventes'!$J$12="Espèces","53000","51220")) | K14: =IF(OR('Brouillard ventes'!$F$12="",'Brouillard ventes'!$J$12="À crédit",'Brouillard ventes'!$J$12=""),"",Paramètres!$B$11) | L14: =IF(OR('Brouillard ventes'!$F$12="",'Brouillard ventes'!$J$12="À crédit",'Brouillard ventes'!$J$12=""),0,'Brouillard ventes'!$I$12) | M14: 0
A15: 1 | B15: =IF(OR('Brouillard ventes'!$F$12="",'Brouillard ventes'!$J$12="À crédit",'Brouillard ventes'!$J$12=""),"","EC"&TEXT(ROW('Brouillard ventes'!$F$12)-5,"00000")) | C15: =IF(OR('Brouillard ventes'!$F$12="",'Brouillard ventes'!$J$12="À crédit",'Brouillard ventes'!$J$12=""),"",YEAR('Brouillard ventes'!$A$12)*10000+MONTH('Brouillard ventes'!$A$12)*100+DAY('Brouillard ventes'!$A$12)) | D15: =IF(OR('Brouillard ventes'!$F$12="",'Brouillard ventes'!$J$12="À crédit",'Brouillard ventes'!$J$12=""),"",'Brouillard ventes'!$B$12) | E15: =IF(OR('Brouillard ventes'!$F$12="",'Brouillard ventes'!$J$12="À crédit",'Brouillard ventes'!$J$12=""),"","REGL "&LEFT('Brouillard ventes'!$D$12,25)) | F15: =IF(OR('Brouillard ventes'!$F$12="",'Brouillard ventes'!$J$12="À crédit",'Brouillard ventes'!$J$12=""),"",IF('Brouillard ventes'!$J$12="Espèces","04001","02001")) | G15: =IF(OR('Brouillard ventes'!$F$12="",'Brouillard ventes'!$J$12="À crédit",'Brouillard ventes'!$J$12=""),"",Paramètres!$B$7) | H15: =IF(OR('Brouillard ventes'!$F$12="",'Brouillard ventes'!$J$12="À crédit",'Brouillard ventes'!$J$12=""),"",IF('Brouillard ventes'!$C$12="","CD001",'Brouillard ventes'!$C$12)) | K15: =IF(OR('Brouillard ventes'!$F$12="",'Brouillard ventes'!$J$12="À crédit",'Brouillard ventes'!$J$12=""),"",Paramètres!$B$11) | L15: 0 | M15: =IF(OR('Brouillard ventes'!$F$12="",'Brouillard ventes'!$J$12="À crédit",'Brouillard ventes'!$J$12=""),0,'Brouillard ventes'!$I$12)
A16: 1 | B16: =IF(OR('Brouillard ventes'!$F$13="",'Brouillard ventes'!$J$13="À crédit",'Brouillard ventes'!$J$13=""),"","EC"&TEXT(ROW('Brouillard ventes'!$F$13)-5,"00000")) | C16: =IF(OR('Brouillard ventes'!$F$13="",'Brouillard ventes'!$J$13="À crédit",'Brouillard ventes'!$J$13=""),"",YEAR('Brouillard ventes'!$A$13)*10000+MONTH('Brouillard ventes'!$A$13)*100+DAY('Brouillard ventes'!$A$13)) | D16: =IF(OR('Brouillard ventes'!$F$13="",'Brouillard ventes'!$J$13="À crédit",'Brouillard ventes'!$J$13=""),"",'Brouillard ventes'!$B$13) | E16: =IF(OR('Brouillard ventes'!$F$13="",'Brouillard ventes'!$J$13="À crédit",'Brouillard ventes'!$J$13=""),"","REGL "&LEFT('Brouillard ventes'!$D$13,25)) | F16: =IF(OR('Brouillard ventes'!$F$13="",'Brouillard ventes'!$J$13="À crédit",'Brouillard ventes'!$J$13=""),"",IF('Brouillard ventes'!$J$13="Espèces","04001","02001")) | G16: =IF(OR('Brouillard ventes'!$F$13="",'Brouillard ventes'!$J$13="À crédit",'Brouillard ventes'!$J$13=""),"",IF('Brouillard ventes'!$J$13="Espèces","53000","51220")) | K16: =IF(OR('Brouillard ventes'!$F$13="",'Brouillard ventes'!$J$13="À crédit",'Brouillard ventes'!$J$13=""),"",Paramètres!$B$11) | L16: =IF(OR('Brouillard ventes'!$F$13="",'Brouillard ventes'!$J$13="À crédit",'Brouillard ventes'!$J$13=""),0,'Brouillard ventes'!$I$13) | M16: 0
A17: 1 | B17: =IF(OR('Brouillard ventes'!$F$13="",'Brouillard ventes'!$J$13="À crédit",'Brouillard ventes'!$J$13=""),"","EC"&TEXT(ROW('Brouillard ventes'!$F$13)-5,"00000")) | C17: =IF(OR('Brouillard ventes'!$F$13="",'Brouillard ventes'!$J$13="À crédit",'Brouillard ventes'!$J$13=""),"",YEAR('Brouillard ventes'!$A$13)*10000+MONTH('Brouillard ventes'!$A$13)*100+DAY('Brouillard ventes'!$A$13)) | D17: =IF(OR('Brouillard ventes'!$F$13="",'Brouillard ventes'!$J$13="À crédit",'Brouillard ventes'!$J$13=""),"",'Brouillard ventes'!$B$13) | E17: =IF(OR('Brouillard ventes'!$F$13="",'Brouillard ventes'!$J$13="À crédit",'Brouillard ventes'!$J$13=""),"","REGL "&LEFT('Brouillard ventes'!$D$13,25)) | F17: =IF(OR('Brouillard ventes'!$F$13="",'Brouillard ventes'!$J$13="À crédit",'Brouillard ventes'!$J$13=""),"",IF('Brouillard ventes'!$J$13="Espèces","04001","02001")) | G17: =IF(OR('Brouillard ventes'!$F$13="",'Brouillard ventes'!$J$13="À crédit",'Brouillard ventes'!$J$13=""),"",Paramètres!$B$7) | H17: =IF(OR('Brouillard ventes'!$F$13="",'Brouillard ventes'!$J$13="À crédit",'Brouillard ventes'!$J$13=""),"",IF('Brouillard ventes'!$C$13="","CD001",'Brouillard ventes'!$C$13)) | K17: =IF(OR('Brouillard ventes'!$F$13="",'Brouillard ventes'!$J$13="À crédit",'Brouillard ventes'!$J$13=""),"",Paramètres!$B$11) | L17: 0 | M17: =IF(OR('Brouillard ventes'!$F$13="",'Brouillard ventes'!$J$13="À crédit",'Brouillard ventes'!$J$13=""),0,'Brouillard ventes'!$I$13)
A18: 1 | B18: =IF(OR('Brouillard ventes'!$F$14="",'Brouillard ventes'!$J$14="À crédit",'Brouillard ventes'!$J$14=""),"","EC"&TEXT(ROW('Brouillard ventes'!$F$14)-5,"00000")) | C18: =IF(OR('Brouillard ventes'!$F$14="",'Brouillard ventes'!$J$14="À crédit",'Brouillard ventes'!$J$14=""),"",YEAR('Brouillard ventes'!$A$14)*10000+MONTH('Brouillard ventes'!$A$14)*100+DAY('Brouillard ventes'!$A$14)) | D18: =IF(OR('Brouillard ventes'!$F$14="",'Brouillard ventes'!$J$14="À crédit",'Brouillard ventes'!$J$14=""),"",'Brouillard ventes'!$B$14) | E18: =IF(OR('Brouillard ventes'!$F$14="",'Brouillard ventes'!$J$14="À crédit",'Brouillard ventes'!$J$14=""),"","REGL "&LEFT('Brouillard ventes'!$D$14,25)) | F18: =IF(OR('Brouillard ventes'!$F$14="",'Brouillard ventes'!$J$14="À crédit",'Brouillard ventes'!$J$14=""),"",IF('Brouillard ventes'!$J$14="Espèces","04001","02001")) | G18: =IF(OR('Brouillard ventes'!$F$14="",'Brouillard ventes'!$J$14="À crédit",'Brouillard ventes'!$J$14=""),"",IF('Brouillard ventes'!$J$14="Espèces","53000","51220")) | K18: =IF(OR('Brouillard ventes'!$F$14="",'Brouillard ventes'!$J$14="À crédit",'Brouillard ventes'!$J$14=""),"",Paramètres!$B$11) | L18: =IF(OR('Brouillard ventes'!$F$14="",'Brouillard ventes'!$J$14="À crédit",'Brouillard ventes'!$J$14=""),0,'Brouillard ventes'!$I$14) | M18: 0
A19: 1 | B19: =IF(OR('Brouillard ventes'!$F$14="",'Brouillard ventes'!$J$14="À crédit",'Brouillard ventes'!$J$14=""),"","EC"&TEXT(ROW('Brouillard ventes'!$F$14)-5,"00000")) | C19: =IF(OR('Brouillard ventes'!$F$14="",'Brouillard ventes'!$J$14="À crédit",'Brouillard ventes'!$J$14=""),"",YEAR('Brouillard ventes'!$A$14)*10000+MONTH('Brouillard ventes'!$A$14)*100+DAY('Brouillard ventes'!$A$14)) | D19: =IF(OR('Brouillard ventes'!$F$14="",'Brouillard ventes'!$J$14="À crédit",'Brouillard ventes'!$J$14=""),"",'Brouillard ventes'!$B$14) | E19: =IF(OR('Brouillard ventes'!$F$14="",'Brouillard ventes'!$J$14="À crédit",'Brouillard ventes'!$J$14=""),"","REGL "&LEFT('Brouillard ventes'!$D$14,25)) | F19: =IF(OR('Brouillard ventes'!$F$14="",'Brouillard ventes'!$J$14="À crédit",'Brouillard ventes'!$J$14=""),"",IF('Brouillard ventes'!$J$14="Espèces","04001","02001")) | G19: =IF(OR('Brouillard ventes'!$F$14="",'Brouillard ventes'!$J$14="À crédit",'Brouillard ventes'!$J$14=""),"",Paramètres!$B$7) | H19: =IF(OR('Brouillard ventes'!$F$14="",'Brouillard ventes'!$J$14="À crédit",'Brouillard ventes'!$J$14=""),"",IF('Brouillard ventes'!$C$14="","CD001",'Brouillard ventes'!$C$14)) | K19: =IF(OR('Brouillard ventes'!$F$14="",'Brouillard ventes'!$J$14="À crédit",'Brouillard ventes'!$J$14=""),"",Paramètres!$B$11) | L19: 0 | M19: =IF(OR('Brouillard ventes'!$F$14="",'Brouillard ventes'!$J$14="À crédit",'Brouillard ventes'!$J$14=""),0,'Brouillard ventes'!$I$14)
A20: 1 | B20: =IF(OR('Brouillard ventes'!$F$15="",'Brouillard ventes'!$J$15="À crédit",'Brouillard ventes'!$J$15=""),"","EC"&TEXT(ROW('Brouillard ventes'!$F$15)-5,"00000")) | C20: =IF(OR('Brouillard ventes'!$F$15="",'Brouillard ventes'!$J$15="À crédit",'Brouillard ventes'!$J$15=""),"",YEAR('Brouillard ventes'!$A$15)*10000+MONTH('Brouillard ventes'!$A$15)*100+DAY('Brouillard ventes'!$A$15)) | D20: =IF(OR('Brouillard ventes'!$F$15="",'Brouillard ventes'!$J$15="À crédit",'Brouillard ventes'!$J$15=""),"",'Brouillard ventes'!$B$15) | E20: =IF(OR('Brouillard ventes'!$F$15="",'Brouillard ventes'!$J$15="À crédit",'Brouillard ventes'!$J$15=""),"","REGL "&LEFT('Brouillard ventes'!$D$15,25)) | F20: =IF(OR('Brouillard ventes'!$F$15="",'Brouillard ventes'!$J$15="À crédit",'Brouillard ventes'!$J$15=""),"",IF('Brouillard ventes'!$J$15="Espèces","04001","02001")) | G20: =IF(OR('Brouillard ventes'!$F$15="",'Brouillard ventes'!$J$15="À crédit",'Brouillard ventes'!$J$15=""),"",IF('Brouillard ventes'!$J$15="Espèces","53000","51220")) | K20: =IF(OR('Brouillard ventes'!$F$15="",'Brouillard ventes'!$J$15="À crédit",'Brouillard ventes'!$J$15=""),"",Paramètres!$B$11) | L20: =IF(OR('Brouillard ventes'!$F$15="",'Brouillard ventes'!$J$15="À crédit",'Brouillard ventes'!$J$15=""),0,'Brouillard ventes'!$I$15) | M20: 0
A21: 1 | B21: =IF(OR('Brouillard ventes'!$F$15="",'Brouillard ventes'!$J$15="À crédit",'Brouillard ventes'!$J$15=""),"","EC"&TEXT(ROW('Brouillard ventes'!$F$15)-5,"00000")) | C21: =IF(OR('Brouillard ventes'!$F$15="",'Brouillard ventes'!$J$15="À crédit",'Brouillard ventes'!$J$15=""),"",YEAR('Brouillard ventes'!$A$15)*10000+MONTH('Brouillard ventes'!$A$15)*100+DAY('Brouillard ventes'!$A$15)) | D21: =IF(OR('Brouillard ventes'!$F$15="",'Brouillard ventes'!$J$15="À crédit",'Brouillard ventes'!$J$15=""),"",'Brouillard ventes'!$B$15) | E21: =IF(OR('Brouillard ventes'!$F$15="",'Brouillard ventes'!$J$15="À crédit",'Brouillard ventes'!$J$15=""),"","REGL "&LEFT('Brouillard ventes'!$D$15,25)) | F21: =IF(OR('Brouillard ventes'!$F$15="",'Brouillard ventes'!$J$15="À crédit",'Brouillard ventes'!$J$15=""),"",IF('Brouillard ventes'!$J$15="Espèces","04001","02001")) | G21: =IF(OR('Brouillard ventes'!$F$15="",'Brouillard ventes'!$J$15="À crédit",'Brouillard ventes'!$J$15=""),"",Paramètres!$B$7) | H21: =IF(OR('Brouillard ventes'!$F$15="",'Brouillard ventes'!$J$15="À crédit",'Brouillard ventes'!$J$15=""),"",IF('Brouillard ventes'!$C$15="","CD001",'Brouillard ventes'!$C$15)) | K21: =IF(OR('Brouillard ventes'!$F$15="",'Brouillard ventes'!$J$15="À crédit",'Brouillard ventes'!$J$15=""),"",Paramètres!$B$11) | L21: 0 | M21: =IF(OR('Brouillard ventes'!$F$15="",'Brouillard ventes'!$J$15="À crédit",'Brouillard ventes'!$J$15=""),0,'Brouillard ventes'!$I$15)
A22: 1 | B22: =IF(OR('Brouillard ventes'!$F$16="",'Brouillard ventes'!$J$16="À crédit",'Brouillard ventes'!$J$16=""),"","EC"&TEXT(ROW('Brouillard ventes'!$F$16)-5,"00000")) | C22: =IF(OR('Brouillard ventes'!$F$16="",'Brouillard ventes'!$J$16="À crédit",'Brouillard ventes'!$J$16=""),"",YEAR('Brouillard ventes'!$A$16)*10000+MONTH('Brouillard ventes'!$A$16)*100+DAY('Brouillard ventes'!$A$16)) | D22: =IF(OR('Brouillard ventes'!$F$16="",'Brouillard ventes'!$J$16="À crédit",'Brouillard ventes'!$J$16=""),"",'Brouillard ventes'!$B$16) | E22: =IF(OR('Brouillard ventes'!$F$16="",'Brouillard ventes'!$J$16="À crédit",'Brouillard ventes'!$J$16=""),"","REGL "&LEFT('Brouillard ventes'!$D$16,25)) | F22: =IF(OR('Brouillard ventes'!$F$16="",'Brouillard ventes'!$J$16="À crédit",'Brouillard ventes'!$J$16=""),"",IF('Brouillard ventes'!$J$16="Espèces","04001","02001")) | G22: =IF(OR('Brouillard ventes'!$F$16="",'Brouillard ventes'!$J$16="À crédit",'Brouillard ventes'!$J$16=""),"",IF('Brouillard ventes'!$J$16="Espèces","53000","51220")) | K22: =IF(OR('Brouillard ventes'!$F$16="",'Brouillard ventes'!$J$16="À crédit",'Brouillard ventes'!$J$16=""),"",Paramètres!$B$11) | L22: =IF(OR('Brouillard ventes'!$F$16="",'Brouillard ventes'!$J$16="À crédit",'Brouillard ventes'!$J$16=""),0,'Brouillard ventes'!$I$16) | M22: 0
A23: 1 | B23: =IF(OR('Brouillard ventes'!$F$16="",'Brouillard ventes'!$J$16="À crédit",'Brouillard ventes'!$J$16=""),"","EC"&TEXT(ROW('Brouillard ventes'!$F$16)-5,"00000")) | C23: =IF(OR('Brouillard ventes'!$F$16="",'Brouillard ventes'!$J$16="À crédit",'Brouillard ventes'!$J$16=""),"",YEAR('Brouillard ventes'!$A$16)*10000+MONTH('Brouillard ventes'!$A$16)*100+DAY('Brouillard ventes'!$A$16)) | D23: =IF(OR('Brouillard ventes'!$F$16="",'Brouillard ventes'!$J$16="À crédit",'Brouillard ventes'!$J$16=""),"",'Brouillard ventes'!$B$16) | E23: =IF(OR('Brouillard ventes'!$F$16="",'Brouillard ventes'!$J$16="À crédit",'Brouillard ventes'!$J$16=""),"","REGL "&LEFT('Brouillard ventes'!$D$16,25)) | F23: =IF(OR('Brouillard ventes'!$F$16="",'Brouillard ventes'!$J$16="À crédit",'Brouillard ventes'!$J$16=""),"",IF('Brouillard ventes'!$J$16="Espèces","04001","02001")) | G23: =IF(OR('Brouillard ventes'!$F$16="",'Brouillard ventes'!$J$16="À crédit",'Brouillard ventes'!$J$16=""),"",Paramètres!$B$7) | H23: =IF(OR('Brouillard ventes'!$F$16="",'Brouillard ventes'!$J$16="À crédit",'Brouillard ventes'!$J$16=""),"",IF('Brouillard ventes'!$C$16="","CD001",'Brouillard ventes'!$C$16)) | K23: =IF(OR('Brouillard ventes'!$F$16="",'Brouillard ventes'!$J$16="À crédit",'Brouillard ventes'!$J$16=""),"",Paramètres!$B$11) | L23: 0 | M23: =IF(OR('Brouillard ventes'!$F$16="",'Brouillard ventes'!$J$16="À crédit",'Brouillard ventes'!$J$16=""),0,'Brouillard ventes'!$I$16)
A24: 1 | B24: =IF(OR('Brouillard ventes'!$F$17="",'Brouillard ventes'!$J$17="À crédit",'Brouillard ventes'!$J$17=""),"","EC"&TEXT(ROW('Brouillard ventes'!$F$17)-5,"00000")) | C24: =IF(OR('Brouillard ventes'!$F$17="",'Brouillard ventes'!$J$17="À crédit",'Brouillard ventes'!$J$17=""),"",YEAR('Brouillard ventes'!$A$17)*10000+MONTH('Brouillard ventes'!$A$17)*100+DAY('Brouillard ventes'!$A$17)) | D24: =IF(OR('Brouillard ventes'!$F$17="",'Brouillard ventes'!$J$17="À crédit",'Brouillard ventes'!$J$17=""),"",'Brouillard ventes'!$B$17) | E24: =IF(OR('Brouillard ventes'!$F$17="",'Brouillard ventes'!$J$17="À crédit",'Brouillard ventes'!$J$17=""),"","REGL "&LEFT('Brouillard ventes'!$D$17,25)) | F24: =IF(OR('Brouillard ventes'!$F$17="",'Brouillard ventes'!$J$17="À crédit",'Brouillard ventes'!$J$17=""),"",IF('Brouillard ventes'!$J$17="Espèces","04001","02001")) | G24: =IF(OR('Brouillard ventes'!$F$17="",'Brouillard ventes'!$J$17="À crédit",'Brouillard ventes'!$J$17=""),"",IF('Brouillard ventes'!$J$17="Espèces","53000","51220")) | K24: =IF(OR('Brouillard ventes'!$F$17="",'Brouillard ventes'!$J$17="À crédit",'Brouillard ventes'!$J$17=""),"",Paramètres!$B$11) | L24: =IF(OR('Brouillard ventes'!$F$17="",'Brouillard ventes'!$J$17="À crédit",'Brouillard ventes'!$J$17=""),0,'Brouillard ventes'!$I$17) | M24: 0
A25: 1 | B25: =IF(OR('Brouillard ventes'!$F$17="",'Brouillard ventes'!$J$17="À crédit",'Brouillard ventes'!$J$17=""),"","EC"&TEXT(ROW('Brouillard ventes'!$F$17)-5,"00000")) | C25: =IF(OR('Brouillard ventes'!$F$17="",'Brouillard ventes'!$J$17="À crédit",'Brouillard ventes'!$J$17=""),"",YEAR('Brouillard ventes'!$A$17)*10000+MONTH('Brouillard ventes'!$A$17)*100+DAY('Brouillard ventes'!$A$17)) | D25: =IF(OR('Brouillard ventes'!$F$17="",'Brouillard ventes'!$J$17="À crédit",'Brouillard ventes'!$J$17=""),"",'Brouillard ventes'!$B$17) | E25: =IF(OR('Brouillard ventes'!$F$17="",'Brouillard ventes'!$J$17="À crédit",'Brouillard ventes'!$J$17=""),"","REGL "&LEFT('Brouillard ventes'!$D$17,25)) | F25: =IF(OR('Brouillard ventes'!$F$17="",'Brouillard ventes'!$J$17="À crédit",'Brouillard ventes'!$J$17=""),"",IF('Brouillard ventes'!$J$17="Espèces","04001","02001")) | G25: =IF(OR('Brouillard ventes'!$F$17="",'Brouillard ventes'!$J$17="À crédit",'Brouillard ventes'!$J$17=""),"",Paramètres!$B$7) | H25: =IF(OR('Brouillard ventes'!$F$17="",'Brouillard ventes'!$J$17="À crédit",'Brouillard ventes'!$J$17=""),"",IF('Brouillard ventes'!$C$17="","CD001",'Brouillard ventes'!$C$17)) | K25: =IF(OR('Brouillard ventes'!$F$17="",'Brouillard ventes'!$J$17="À crédit",'Brouillard ventes'!$J$17=""),"",Paramètres!$B$11) | L25: 0 | M25: =IF(OR('Brouillard ventes'!$F$17="",'Brouillard ventes'!$J$17="À crédit",'Brouillard ventes'!$J$17=""),0,'Brouillard ventes'!$I$17)
A26: 1 | B26: =IF(OR('Brouillard ventes'!$F$18="",'Brouillard ventes'!$J$18="À crédit",'Brouillard ventes'!$J$18=""),"","EC"&TEXT(ROW('Brouillard ventes'!$F$18)-5,"00000")) | C26: =IF(OR('Brouillard ventes'!$F$18="",'Brouillard ventes'!$J$18="À crédit",'Brouillard ventes'!$J$18=""),"",YEAR('Brouillard ventes'!$A$18)*10000+MONTH('Brouillard ventes'!$A$18)*100+DAY('Brouillard ventes'!$A$18)) | D26: =IF(OR('Brouillard ventes'!$F$18="",'Brouillard ventes'!$J$18="À crédit",'Brouillard ventes'!$J$18=""),"",'Brouillard ventes'!$B$18) | E26: =IF(OR('Brouillard ventes'!$F$18="",'Brouillard ventes'!$J$18="À crédit",'Brouillard ventes'!$J$18=""),"","REGL "&LEFT('Brouillard ventes'!$D$18,25)) | F26: =IF(OR('Brouillard ventes'!$F$18="",'Brouillard ventes'!$J$18="À crédit",'Brouillard ventes'!$J$18=""),"",IF('Brouillard ventes'!$J$18="Espèces","04001","02001")) | G26: =IF(OR('Brouillard ventes'!$F$18="",'Brouillard ventes'!$J$18="À crédit",'Brouillard ventes'!$J$18=""),"",IF('Brouillard ventes'!$J$18="Espèces","53000","51220")) | K26: =IF(OR('Brouillard ventes'!$F$18="",'Brouillard ventes'!$J$18="À crédit",'Brouillard ventes'!$J$18=""),"",Paramètres!$B$11) | L26: =IF(OR('Brouillard ventes'!$F$18="",'Brouillard ventes'!$J$18="À crédit",'Brouillard ventes'!$J$18=""),0,'Brouillard ventes'!$I$18) | M26: 0
A27: 1 | B27: =IF(OR('Brouillard ventes'!$F$18="",'Brouillard ventes'!$J$18="À crédit",'Brouillard ventes'!$J$18=""),"","EC"&TEXT(ROW('Brouillard ventes'!$F$18)-5,"00000")) | C27: =IF(OR('Brouillard ventes'!$F$18="",'Brouillard ventes'!$J$18="À crédit",'Brouillard ventes'!$J$18=""),"",YEAR('Brouillard ventes'!$A$18)*10000+MONTH('Brouillard ventes'!$A$18)*100+DAY('Brouillard ventes'!$A$18)) | D27: =IF(OR('Brouillard ventes'!$F$18="",'Brouillard ventes'!$J$18="À crédit",'Brouillard ventes'!$J$18=""),"",'Brouillard ventes'!$B$18) | E27: =IF(OR('Brouillard ventes'!$F$18="",'Brouillard ventes'!$J$18="À crédit",'Brouillard ventes'!$J$18=""),"","REGL "&LEFT('Brouillard ventes'!$D$18,25)) | F27: =IF(OR('Brouillard ventes'!$F$18="",'Brouillard ventes'!$J$18="À crédit",'Brouillard ventes'!$J$18=""),"",IF('Brouillard ventes'!$J$18="Espèces","04001","02001")) | G27: =IF(OR('Brouillard ventes'!$F$18="",'Brouillard ventes'!$J$18="À crédit",'Brouillard ventes'!$J$18=""),"",Paramètres!$B$7) | H27: =IF(OR('Brouillard ventes'!$F$18="",'Brouillard ventes'!$J$18="À crédit",'Brouillard ventes'!$J$18=""),"",IF('Brouillard ventes'!$C$18="","CD001",'Brouillard ventes'!$C$18)) | K27: =IF(OR('Brouillard ventes'!$F$18="",'Brouillard ventes'!$J$18="À crédit",'Brouillard ventes'!$J$18=""),"",Paramètres!$B$11) | L27: 0 | M27: =IF(OR('Brouillard ventes'!$F$18="",'Brouillard ventes'!$J$18="À crédit",'Brouillard ventes'!$J$18=""),0,'Brouillard ventes'!$I$18)
A28: 1 | B28: =IF(OR('Brouillard ventes'!$F$19="",'Brouillard ventes'!$J$19="À crédit",'Brouillard ventes'!$J$19=""),"","EC"&TEXT(ROW('Brouillard ventes'!$F$19)-5,"00000")) | C28: =IF(OR('Brouillard ventes'!$F$19="",'Brouillard ventes'!$J$19="À crédit",'Brouillard ventes'!$J$19=""),"",YEAR('Brouillard ventes'!$A$19)*10000+MONTH('Brouillard ventes'!$A$19)*100+DAY('Brouillard ventes'!$A$19)) | D28: =IF(OR('Brouillard ventes'!$F$19="",'Brouillard ventes'!$J$19="À crédit",'Brouillard ventes'!$J$19=""),"",'Brouillard ventes'!$B$19) | E28: =IF(OR('Brouillard ventes'!$F$19="",'Brouillard ventes'!$J$19="À crédit",'Brouillard ventes'!$J$19=""),"","REGL "&LEFT('Brouillard ventes'!$D$19,25)) | F28: =IF(OR('Brouillard ventes'!$F$19="",'Brouillard ventes'!$J$19="À crédit",'Brouillard ventes'!$J$19=""),"",IF('Brouillard ventes'!$J$19="Espèces","04001","02001")) | G28: =IF(OR('Brouillard ventes'!$F$19="",'Brouillard ventes'!$J$19="À crédit",'Brouillard ventes'!$J$19=""),"",IF('Brouillard ventes'!$J$19="Espèces","53000","51220")) | K28: =IF(OR('Brouillard ventes'!$F$19="",'Brouillard ventes'!$J$19="À crédit",'Brouillard ventes'!$J$19=""),"",Paramètres!$B$11) | L28: =IF(OR('Brouillard ventes'!$F$19="",'Brouillard ventes'!$J$19="À crédit",'Brouillard ventes'!$J$19=""),0,'Brouillard ventes'!$I$19) | M28: 0
A29: 1 | B29: =IF(OR('Brouillard ventes'!$F$19="",'Brouillard ventes'!$J$19="À crédit",'Brouillard ventes'!$J$19=""),"","EC"&TEXT(ROW('Brouillard ventes'!$F$19)-5,"00000")) | C29: =IF(OR('Brouillard ventes'!$F$19="",'Brouillard ventes'!$J$19="À crédit",'Brouillard ventes'!$J$19=""),"",YEAR('Brouillard ventes'!$A$19)*10000+MONTH('Brouillard ventes'!$A$19)*100+DAY('Brouillard ventes'!$A$19)) | D29: =IF(OR('Brouillard ventes'!$F$19="",'Brouillard ventes'!$J$19="À crédit",'Brouillard ventes'!$J$19=""),"",'Brouillard ventes'!$B$19) | E29: =IF(OR('Brouillard ventes'!$F$19="",'Brouillard ventes'!$J$19="À crédit",'Brouillard ventes'!$J$19=""),"","REGL "&LEFT('Brouillard ventes'!$D$19,25)) | F29: =IF(OR('Brouillard ventes'!$F$19="",'Brouillard ventes'!$J$19="À crédit",'Brouillard ventes'!$J$19=""),"",IF('Brouillard ventes'!$J$19="Espèces","04001","02001")) | G29: =IF(OR('Brouillard ventes'!$F$19="",'Brouillard ventes'!$J$19="À crédit",'Brouillard ventes'!$J$19=""),"",Paramètres!$B$7) | H29: =IF(OR('Brouillard ventes'!$F$19="",'Brouillard ventes'!$J$19="À crédit",'Brouillard ventes'!$J$19=""),"",IF('Brouillard ventes'!$C$19="","CD001",'Brouillard ventes'!$C$19)) | K29: =IF(OR('Brouillard ventes'!$F$19="",'Brouillard ventes'!$J$19="À crédit",'Brouillard ventes'!$J$19=""),"",Paramètres!$B$11) | L29: 0 | M29: =IF(OR('Brouillard ventes'!$F$19="",'Brouillard ventes'!$J$19="À crédit",'Brouillard ventes'!$J$19=""),0,'Brouillard ventes'!$I$19)
A30: 1 | B30: =IF(OR('Brouillard ventes'!$F$20="",'Brouillard ventes'!$J$20="À crédit",'Brouillard ventes'!$J$20=""),"","EC"&TEXT(ROW('Brouillard ventes'!$F$20)-5,"00000")) | C30: =IF(OR('Brouillard ventes'!$F$20="",'Brouillard ventes'!$J$20="À crédit",'Brouillard ventes'!$J$20=""),"",YEAR('Brouillard ventes'!$A$20)*10000+MONTH('Brouillard ventes'!$A$20)*100+DAY('Brouillard ventes'!$A$20)) | D30: =IF(OR('Brouillard ventes'!$F$20="",'Brouillard ventes'!$J$20="À crédit",'Brouillard ventes'!$J$20=""),"",'Brouillard ventes'!$B$20) | E30: =IF(OR('Brouillard ventes'!$F$20="",'Brouillard ventes'!$J$20="À crédit",'Brouillard ventes'!$J$20=""),"","REGL "&LEFT('Brouillard ventes'!$D$20,25)) | F30: =IF(OR('Brouillard ventes'!$F$20="",'Brouillard ventes'!$J$20="À crédit",'Brouillard ventes'!$J$20=""),"",IF('Brouillard ventes'!$J$20="Espèces","04001","02001")) | G30: =IF(OR('Brouillard ventes'!$F$20="",'Brouillard ventes'!$J$20="À crédit",'Brouillard ventes'!$J$20=""),"",IF('Brouillard ventes'!$J$20="Espèces","53000","51220")) | K30: =IF(OR('Brouillard ventes'!$F$20="",'Brouillard ventes'!$J$20="À crédit",'Brouillard ventes'!$J$20=""),"",Paramètres!$B$11) | L30: =IF(OR('Brouillard ventes'!$F$20="",'Brouillard ventes'!$J$20="À crédit",'Brouillard ventes'!$J$20=""),0,'Brouillard ventes'!$I$20) | M30: 0
A31: 1 | B31: =IF(OR('Brouillard ventes'!$F$20="",'Brouillard ventes'!$J$20="À crédit",'Brouillard ventes'!$J$20=""),"","EC"&TEXT(ROW('Brouillard ventes'!$F$20)-5,"00000")) | C31: =IF(OR('Brouillard ventes'!$F$20="",'Brouillard ventes'!$J$20="À crédit",'Brouillard ventes'!$J$20=""),"",YEAR('Brouillard ventes'!$A$20)*10000+MONTH('Brouillard ventes'!$A$20)*100+DAY('Brouillard ventes'!$A$20)) | D31: =IF(OR('Brouillard ventes'!$F$20="",'Brouillard ventes'!$J$20="À crédit",'Brouillard ventes'!$J$20=""),"",'Brouillard ventes'!$B$20) | E31: =IF(OR('Brouillard ventes'!$F$20="",'Brouillard ventes'!$J$20="À crédit",'Brouillard ventes'!$J$20=""),"","REGL "&LEFT('Brouillard ventes'!$D$20,25)) | F31: =IF(OR('Brouillard ventes'!$F$20="",'Brouillard ventes'!$J$20="À crédit",'Brouillard ventes'!$J$20=""),"",IF('Brouillard ventes'!$J$20="Espèces","04001","02001")) | G31: =IF(OR('Brouillard ventes'!$F$20="",'Brouillard ventes'!$J$20="À crédit",'Brouillard ventes'!$J$20=""),"",Paramètres!$B$7) | H31: =IF(OR('Brouillard ventes'!$F$20="",'Brouillard ventes'!$J$20="À crédit",'Brouillard ventes'!$J$20=""),"",IF('Brouillard ventes'!$C$20="","CD001",'Brouillard ventes'!$C$20)) | K31: =IF(OR('Brouillard ventes'!$F$20="",'Brouillard ventes'!$J$20="À crédit",'Brouillard ventes'!$J$20=""),"",Paramètres!$B$11) | L31: 0 | M31: =IF(OR('Brouillard ventes'!$F$20="",'Brouillard ventes'!$J$20="À crédit",'Brouillard ventes'!$J$20=""),0,'Brouillard ventes'!$I$20)
A32: 1 | B32: =IF(OR('Brouillard ventes'!$F$21="",'Brouillard ventes'!$J$21="À crédit",'Brouillard ventes'!$J$21=""),"","EC"&TEXT(ROW('Brouillard ventes'!$F$21)-5,"00000")) | C32: =IF(OR('Brouillard ventes'!$F$21="",'Brouillard ventes'!$J$21="À crédit",'Brouillard ventes'!$J$21=""),"",YEAR('Brouillard ventes'!$A$21)*10000+MONTH('Brouillard ventes'!$A$21)*100+DAY('Brouillard ventes'!$A$21)) | D32: =IF(OR('Brouillard ventes'!$F$21="",'Brouillard ventes'!$J$21="À crédit",'Brouillard ventes'!$J$21=""),"",'Brouillard ventes'!$B$21) | E32: =IF(OR('Brouillard ventes'!$F$21="",'Brouillard ventes'!$J$21="À crédit",'Brouillard ventes'!$J$21=""),"","REGL "&LEFT('Brouillard ventes'!$D$21,25)) | F32: =IF(OR('Brouillard ventes'!$F$21="",'Brouillard ventes'!$J$21="À crédit",'Brouillard ventes'!$J$21=""),"",IF('Brouillard ventes'!$J$21="Espèces","04001","02001")) | G32: =IF(OR('Brouillard ventes'!$F$21="",'Brouillard ventes'!$J$21="À crédit",'Brouillard ventes'!$J$21=""),"",IF('Brouillard ventes'!$J$21="Espèces","53000","51220")) | K32: =IF(OR('Brouillard ventes'!$F$21="",'Brouillard ventes'!$J$21="À crédit",'Brouillard ventes'!$J$21=""),"",Paramètres!$B$11) | L32: =IF(OR('Brouillard ventes'!$F$21="",'Brouillard ventes'!$J$21="À crédit",'Brouillard ventes'!$J$21=""),0,'Brouillard ventes'!$I$21) | M32: 0
A33: 1 | B33: =IF(OR('Brouillard ventes'!$F$21="",'Brouillard ventes'!$J$21="À crédit",'Brouillard ventes'!$J$21=""),"","EC"&TEXT(ROW('Brouillard ventes'!$F$21)-5,"00000")) | C33: =IF(OR('Brouillard ventes'!$F$21="",'Brouillard ventes'!$J$21="À crédit",'Brouillard ventes'!$J$21=""),"",YEAR('Brouillard ventes'!$A$21)*10000+MONTH('Brouillard ventes'!$A$21)*100+DAY('Brouillard ventes'!$A$21)) | D33: =IF(OR('Brouillard ventes'!$F$21="",'Brouillard ventes'!$J$21="À crédit",'Brouillard ventes'!$J$21=""),"",'Brouillard ventes'!$B$21) | E33: =IF(OR('Brouillard ventes'!$F$21="",'Brouillard ventes'!$J$21="À crédit",'Brouillard ventes'!$J$21=""),"","REGL "&LEFT('Brouillard ventes'!$D$21,25)) | F33: =IF(OR('Brouillard ventes'!$F$21="",'Brouillard ventes'!$J$21="À crédit",'Brouillard ventes'!$J$21=""),"",IF('Brouillard ventes'!$J$21="Espèces","04001","02001")) | G33: =IF(OR('Brouillard ventes'!$F$21="",'Brouillard ventes'!$J$21="À crédit",'Brouillard ventes'!$J$21=""),"",Paramètres!$B$7) | H33: =IF(OR('Brouillard ventes'!$F$21="",'Brouillard ventes'!$J$21="À crédit",'Brouillard ventes'!$J$21=""),"",IF('Brouillard ventes'!$C$21="","CD001",'Brouillard ventes'!$C$21)) | K33: =IF(OR('Brouillard ventes'!$F$21="",'Brouillard ventes'!$J$21="À crédit",'Brouillard ventes'!$J$21=""),"",Paramètres!$B$11) | L33: 0 | M33: =IF(OR('Brouillard ventes'!$F$21="",'Brouillard ventes'!$J$21="À crédit",'Brouillard ventes'!$J$21=""),0,'Brouillard ventes'!$I$21)
A34: 1 | B34: =IF(OR('Brouillard ventes'!$F$22="",'Brouillard ventes'!$J$22="À crédit",'Brouillard ventes'!$J$22=""),"","EC"&TEXT(ROW('Brouillard ventes'!$F$22)-5,"00000")) | C34: =IF(OR('Brouillard ventes'!$F$22="",'Brouillard ventes'!$J$22="À crédit",'Brouillard ventes'!$J$22=""),"",YEAR('Brouillard ventes'!$A$22)*10000+MONTH('Brouillard ventes'!$A$22)*100+DAY('Brouillard ventes'!$A$22)) | D34: =IF(OR('Brouillard ventes'!$F$22="",'Brouillard ventes'!$J$22="À crédit",'Brouillard ventes'!$J$22=""),"",'Brouillard ventes'!$B$22) | E34: =IF(OR('Brouillard ventes'!$F$22="",'Brouillard ventes'!$J$22="À crédit",'Brouillard ventes'!$J$22=""),"","REGL "&LEFT('Brouillard ventes'!$D$22,25)) | F34: =IF(OR('Brouillard ventes'!$F$22="",'Brouillard ventes'!$J$22="À crédit",'Brouillard ventes'!$J$22=""),"",IF('Brouillard ventes'!$J$22="Espèces","04001","02001")) | G34: =IF(OR('Brouillard ventes'!$F$22="",'Brouillard ventes'!$J$22="À crédit",'Brouillard ventes'!$J$22=""),"",IF('Brouillard ventes'!$J$22="Espèces","53000","51220")) | K34: =IF(OR('Brouillard ventes'!$F$22="",'Brouillard ventes'!$J$22="À crédit",'Brouillard ventes'!$J$22=""),"",Paramètres!$B$11) | L34: =IF(OR('Brouillard ventes'!$F$22="",'Brouillard ventes'!$J$22="À crédit",'Brouillard ventes'!$J$22=""),0,'Brouillard ventes'!$I$22) | M34: 0
A35: 1 | B35: =IF(OR('Brouillard ventes'!$F$22="",'Brouillard ventes'!$J$22="À crédit",'Brouillard ventes'!$J$22=""),"","EC"&TEXT(ROW('Brouillard ventes'!$F$22)-5,"00000")) | C35: =IF(OR('Brouillard ventes'!$F$22="",'Brouillard ventes'!$J$22="À crédit",'Brouillard ventes'!$J$22=""),"",YEAR('Brouillard ventes'!$A$22)*10000+MONTH('Brouillard ventes'!$A$22)*100+DAY('Brouillard ventes'!$A$22)) | D35: =IF(OR('Brouillard ventes'!$F$22="",'Brouillard ventes'!$J$22="À crédit",'Brouillard ventes'!$J$22=""),"",'Brouillard ventes'!$B$22) | E35: =IF(OR('Brouillard ventes'!$F$22="",'Brouillard ventes'!$J$22="À crédit",'Brouillard ventes'!$J$22=""),"","REGL "&LEFT('Brouillard ventes'!$D$22,25)) | F35: =IF(OR('Brouillard ventes'!$F$22="",'Brouillard ventes'!$J$22="À crédit",'Brouillard ventes'!$J$22=""),"",IF('Brouillard ventes'!$J$22="Espèces","04001","02001")) | G35: =IF(OR('Brouillard ventes'!$F$22="",'Brouillard ventes'!$J$22="À crédit",'Brouillard ventes'!$J$22=""),"",Paramètres!$B$7) | H35: =IF(OR('Brouillard ventes'!$F$22="",'Brouillard ventes'!$J$22="À crédit",'Brouillard ventes'!$J$22=""),"",IF('Brouillard ventes'!$C$22="","CD001",'Brouillard ventes'!$C$22)) | K35: =IF(OR('Brouillard ventes'!$F$22="",'Brouillard ventes'!$J$22="À crédit",'Brouillard ventes'!$J$22=""),"",Paramètres!$B$11) | L35: 0 | M35: =IF(OR('Brouillard ventes'!$F$22="",'Brouillard ventes'!$J$22="À crédit",'Brouillard ventes'!$J$22=""),0,'Brouillard ventes'!$I$22)
A36: 1 | B36: =IF(OR('Brouillard ventes'!$F$23="",'Brouillard ventes'!$J$23="À crédit",'Brouillard ventes'!$J$23=""),"","EC"&TEXT(ROW('Brouillard ventes'!$F$23)-5,"00000")) | C36: =IF(OR('Brouillard ventes'!$F$23="",'Brouillard ventes'!$J$23="À crédit",'Brouillard ventes'!$J$23=""),"",YEAR('Brouillard ventes'!$A$23)*10000+MONTH('Brouillard ventes'!$A$23)*100+DAY('Brouillard ventes'!$A$23)) | D36: =IF(OR('Brouillard ventes'!$F$23="",'Brouillard ventes'!$J$23="À crédit",'Brouillard ventes'!$J$23=""),"",'Brouillard ventes'!$B$23) | E36: =IF(OR('Brouillard ventes'!$F$23="",'Brouillard ventes'!$J$23="À crédit",'Brouillard ventes'!$J$23=""),"","REGL "&LEFT('Brouillard ventes'!$D$23,25)) | F36: =IF(OR('Brouillard ventes'!$F$23="",'Brouillard ventes'!$J$23="À crédit",'Brouillard ventes'!$J$23=""),"",IF('Brouillard ventes'!$J$23="Espèces","04001","02001")) | G36: =IF(OR('Brouillard ventes'!$F$23="",'Brouillard ventes'!$J$23="À crédit",'Brouillard ventes'!$J$23=""),"",IF('Brouillard ventes'!$J$23="Espèces","53000","51220")) | K36: =IF(OR('Brouillard ventes'!$F$23="",'Brouillard ventes'!$J$23="À crédit",'Brouillard ventes'!$J$23=""),"",Paramètres!$B$11) | L36: =IF(OR('Brouillard ventes'!$F$23="",'Brouillard ventes'!$J$23="À crédit",'Brouillard ventes'!$J$23=""),0,'Brouillard ventes'!$I$23) | M36: 0
A37: 1 | B37: =IF(OR('Brouillard ventes'!$F$23="",'Brouillard ventes'!$J$23="À crédit",'Brouillard ventes'!$J$23=""),"","EC"&TEXT(ROW('Brouillard ventes'!$F$23)-5,"00000")) | C37: =IF(OR('Brouillard ventes'!$F$23="",'Brouillard ventes'!$J$23="À crédit",'Brouillard ventes'!$J$23=""),"",YEAR('Brouillard ventes'!$A$23)*10000+MONTH('Brouillard ventes'!$A$23)*100+DAY('Brouillard ventes'!$A$23)) | D37: =IF(OR('Brouillard ventes'!$F$23="",'Brouillard ventes'!$J$23="À crédit",'Brouillard ventes'!$J$23=""),"",'Brouillard ventes'!$B$23) | E37: =IF(OR('Brouillard ventes'!$F$23="",'Brouillard ventes'!$J$23="À crédit",'Brouillard ventes'!$J$23=""),"","REGL "&LEFT('Brouillard ventes'!$D$23,25)) | F37: =IF(OR('Brouillard ventes'!$F$23="",'Brouillard ventes'!$J$23="À crédit",'Brouillard ventes'!$J$23=""),"",IF('Brouillard ventes'!$J$23="Espèces","04001","02001")) | G37: =IF(OR('Brouillard ventes'!$F$23="",'Brouillard ventes'!$J$23="À crédit",'Brouillard ventes'!$J$23=""),"",Paramètres!$B$7) | H37: =IF(OR('Brouillard ventes'!$F$23="",'Brouillard ventes'!$J$23="À crédit",'Brouillard ventes'!$J$23=""),"",IF('Brouillard ventes'!$C$23="","CD001",'Brouillard ventes'!$C$23)) | K37: =IF(OR('Brouillard ventes'!$F$23="",'Brouillard ventes'!$J$23="À crédit",'Brouillard ventes'!$J$23=""),"",Paramètres!$B$11) | L37: 0 | M37: =IF(OR('Brouillard ventes'!$F$23="",'Brouillard ventes'!$J$23="À crédit",'Brouillard ventes'!$J$23=""),0,'Brouillard ventes'!$I$23)
A38: 1 | B38: =IF(OR('Brouillard ventes'!$F$24="",'Brouillard ventes'!$J$24="À crédit",'Brouillard ventes'!$J$24=""),"","EC"&TEXT(ROW('Brouillard ventes'!$F$24)-5,"00000")) | C38: =IF(OR('Brouillard ventes'!$F$24="",'Brouillard ventes'!$J$24="À crédit",'Brouillard ventes'!$J$24=""),"",YEAR('Brouillard ventes'!$A$24)*10000+MONTH('Brouillard ventes'!$A$24)*100+DAY('Brouillard ventes'!$A$24)) | D38: =IF(OR('Brouillard ventes'!$F$24="",'Brouillard ventes'!$J$24="À crédit",'Brouillard ventes'!$J$24=""),"",'Brouillard ventes'!$B$24) | E38: =IF(OR('Brouillard ventes'!$F$24="",'Brouillard ventes'!$J$24="À crédit",'Brouillard ventes'!$J$24=""),"","REGL "&LEFT('Brouillard ventes'!$D$24,25)) | F38: =IF(OR('Brouillard ventes'!$F$24="",'Brouillard ventes'!$J$24="À crédit",'Brouillard ventes'!$J$24=""),"",IF('Brouillard ventes'!$J$24="Espèces","04001","02001")) | G38: =IF(OR('Brouillard ventes'!$F$24="",'Brouillard ventes'!$J$24="À crédit",'Brouillard ventes'!$J$24=""),"",IF('Brouillard ventes'!$J$24="Espèces","53000","51220")) | K38: =IF(OR('Brouillard ventes'!$F$24="",'Brouillard ventes'!$J$24="À crédit",'Brouillard ventes'!$J$24=""),"",Paramètres!$B$11) | L38: =IF(OR('Brouillard ventes'!$F$24="",'Brouillard ventes'!$J$24="À crédit",'Brouillard ventes'!$J$24=""),0,'Brouillard ventes'!$I$24) | M38: 0
A39: 1 | B39: =IF(OR('Brouillard ventes'!$F$24="",'Brouillard ventes'!$J$24="À crédit",'Brouillard ventes'!$J$24=""),"","EC"&TEXT(ROW('Brouillard ventes'!$F$24)-5,"00000")) | C39: =IF(OR('Brouillard ventes'!$F$24="",'Brouillard ventes'!$J$24="À crédit",'Brouillard ventes'!$J$24=""),"",YEAR('Brouillard ventes'!$A$24)*10000+MONTH('Brouillard ventes'!$A$24)*100+DAY('Brouillard ventes'!$A$24)) | D39: =IF(OR('Brouillard ventes'!$F$24="",'Brouillard ventes'!$J$24="À crédit",'Brouillard ventes'!$J$24=""),"",'Brouillard ventes'!$B$24) | E39: =IF(OR('Brouillard ventes'!$F$24="",'Brouillard ventes'!$J$24="À crédit",'Brouillard ventes'!$J$24=""),"","REGL "&LEFT('Brouillard ventes'!$D$24,25)) | F39: =IF(OR('Brouillard ventes'!$F$24="",'Brouillard ventes'!$J$24="À crédit",'Brouillard ventes'!$J$24=""),"",IF('Brouillard ventes'!$J$24="Espèces","04001","02001")) | G39: =IF(OR('Brouillard ventes'!$F$24="",'Brouillard ventes'!$J$24="À crédit",'Brouillard ventes'!$J$24=""),"",Paramètres!$B$7) | H39: =IF(OR('Brouillard ventes'!$F$24="",'Brouillard ventes'!$J$24="À crédit",'Brouillard ventes'!$J$24=""),"",IF('Brouillard ventes'!$C$24="","CD001",'Brouillard ventes'!$C$24)) | K39: =IF(OR('Brouillard ventes'!$F$24="",'Brouillard ventes'!$J$24="À crédit",'Brouillard ventes'!$J$24=""),"",Paramètres!$B$11) | L39: 0 | M39: =IF(OR('Brouillard ventes'!$F$24="",'Brouillard ventes'!$J$24="À crédit",'Brouillard ventes'!$J$24=""),0,'Brouillard ventes'!$I$24)
A40: 1 | B40: =IF(OR('Brouillard ventes'!$F$25="",'Brouillard ventes'!$J$25="À crédit",'Brouillard ventes'!$J$25=""),"","EC"&TEXT(ROW('Brouillard ventes'!$F$25)-5,"00000")) | C40: =IF(OR('Brouillard ventes'!$F$25="",'Brouillard ventes'!$J$25="À crédit",'Brouillard ventes'!$J$25=""),"",YEAR('Brouillard ventes'!$A$25)*10000+MONTH('Brouillard ventes'!$A$25)*100+DAY('Brouillard ventes'!$A$25)) | D40: =IF(OR('Brouillard ventes'!$F$25="",'Brouillard ventes'!$J$25="À crédit",'Brouillard ventes'!$J$25=""),"",'Brouillard ventes'!$B$25) | E40: =IF(OR('Brouillard ventes'!$F$25="",'Brouillard ventes'!$J$25="À crédit",'Brouillard ventes'!$J$25=""),"","REGL "&LEFT('Brouillard ventes'!$D$25,25)) | F40: =IF(OR('Brouillard ventes'!$F$25="",'Brouillard ventes'!$J$25="À crédit",'Brouillard ventes'!$J$25=""),"",IF('Brouillard ventes'!$J$25="Espèces","04001","02001")) | G40: =IF(OR('Brouillard ventes'!$F$25="",'Brouillard ventes'!$J$25="À crédit",'Brouillard ventes'!$J$25=""),"",IF('Brouillard ventes'!$J$25="Espèces","53000","51220")) | K40: =IF(OR('Brouillard ventes'!$F$25="",'Brouillard ventes'!$J$25="À crédit",'Brouillard ventes'!$J$25=""),"",Paramètres!$B$11) | L40: =IF(OR('Brouillard ventes'!$F$25="",'Brouillard ventes'!$J$25="À crédit",'Brouillard ventes'!$J$25=""),0,'Brouillard ventes'!$I$25) | M40: 0
A41: 1 | B41: =IF(OR('Brouillard ventes'!$F$25="",'Brouillard ventes'!$J$25="À crédit",'Brouillard ventes'!$J$25=""),"","EC"&TEXT(ROW('Brouillard ventes'!$F$25)-5,"00000")) | C41: =IF(OR('Brouillard ventes'!$F$25="",'Brouillard ventes'!$J$25="À crédit",'Brouillard ventes'!$J$25=""),"",YEAR('Brouillard ventes'!$A$25)*10000+MONTH('Brouillard ventes'!$A$25)*100+DAY('Brouillard ventes'!$A$25)) | D41: =IF(OR('Brouillard ventes'!$F$25="",'Brouillard ventes'!$J$25="À crédit",'Brouillard ventes'!$J$25=""),"",'Brouillard ventes'!$B$25) | E41: =IF(OR('Brouillard ventes'!$F$25="",'Brouillard ventes'!$J$25="À crédit",'Brouillard ventes'!$J$25=""),"","REGL "&LEFT('Brouillard ventes'!$D$25,25)) | F41: =IF(OR('Brouillard ventes'!$F$25="",'Brouillard ventes'!$J$25="À crédit",'Brouillard ventes'!$J$25=""),"",IF('Brouillard ventes'!$J$25="Espèces","04001","02001")) | G41: =IF(OR('Brouillard ventes'!$F$25="",'Brouillard ventes'!$J$25="À crédit",'Brouillard ventes'!$J$25=""),"",Paramètres!$B$7) | H41: =IF(OR('Brouillard ventes'!$F$25="",'Brouillard ventes'!$J$25="À crédit",'Brouillard ventes'!$J$25=""),"",IF('Brouillard ventes'!$C$25="","CD001",'Brouillard ventes'!$C$25)) | K41: =IF(OR('Brouillard ventes'!$F$25="",'Brouillard ventes'!$J$25="À crédit",'Brouillard ventes'!$J$25=""),"",Paramètres!$B$11) | L41: 0 | M41: =IF(OR('Brouillard ventes'!$F$25="",'Brouillard ventes'!$J$25="À crédit",'Brouillard ventes'!$J$25=""),0,'Brouillard ventes'!$I$25)
A42: 1 | B42: =IF(OR('Brouillard ventes'!$F$26="",'Brouillard ventes'!$J$26="À crédit",'Brouillard ventes'!$J$26=""),"","EC"&TEXT(ROW('Brouillard ventes'!$F$26)-5,"00000")) | C42: =IF(OR('Brouillard ventes'!$F$26="",'Brouillard ventes'!$J$26="À crédit",'Brouillard ventes'!$J$26=""),"",YEAR('Brouillard ventes'!$A$26)*10000+MONTH('Brouillard ventes'!$A$26)*100+DAY('Brouillard ventes'!$A$26)) | D42: =IF(OR('Brouillard ventes'!$F$26="",'Brouillard ventes'!$J$26="À crédit",'Brouillard ventes'!$J$26=""),"",'Brouillard ventes'!$B$26) | E42: =IF(OR('Brouillard ventes'!$F$26="",'Brouillard ventes'!$J$26="À crédit",'Brouillard ventes'!$J$26=""),"","REGL "&LEFT('Brouillard ventes'!$D$26,25)) | F42: =IF(OR('Brouillard ventes'!$F$26="",'Brouillard ventes'!$J$26="À crédit",'Brouillard ventes'!$J$26=""),"",IF('Brouillard ventes'!$J$26="Espèces","04001","02001")) | G42: =IF(OR('Brouillard ventes'!$F$26="",'Brouillard ventes'!$J$26="À crédit",'Brouillard ventes'!$J$26=""),"",IF('Brouillard ventes'!$J$26="Espèces","53000","51220")) | K42: =IF(OR('Brouillard ventes'!$F$26="",'Brouillard ventes'!$J$26="À crédit",'Brouillard ventes'!$J$26=""),"",Paramètres!$B$11) | L42: =IF(OR('Brouillard ventes'!$F$26="",'Brouillard ventes'!$J$26="À crédit",'Brouillard ventes'!$J$26=""),0,'Brouillard ventes'!$I$26) | M42: 0
A43: 1 | B43: =IF(OR('Brouillard ventes'!$F$26="",'Brouillard ventes'!$J$26="À crédit",'Brouillard ventes'!$J$26=""),"","EC"&TEXT(ROW('Brouillard ventes'!$F$26)-5,"00000")) | C43: =IF(OR('Brouillard ventes'!$F$26="",'Brouillard ventes'!$J$26="À crédit",'Brouillard ventes'!$J$26=""),"",YEAR('Brouillard ventes'!$A$26)*10000+MONTH('Brouillard ventes'!$A$26)*100+DAY('Brouillard ventes'!$A$26)) | D43: =IF(OR('Brouillard ventes'!$F$26="",'Brouillard ventes'!$J$26="À crédit",'Brouillard ventes'!$J$26=""),"",'Brouillard ventes'!$B$26) | E43: =IF(OR('Brouillard ventes'!$F$26="",'Brouillard ventes'!$J$26="À crédit",'Brouillard ventes'!$J$26=""),"","REGL "&LEFT('Brouillard ventes'!$D$26,25)) | F43: =IF(OR('Brouillard ventes'!$F$26="",'Brouillard ventes'!$J$26="À crédit",'Brouillard ventes'!$J$26=""),"",IF('Brouillard ventes'!$J$26="Espèces","04001","02001")) | G43: =IF(OR('Brouillard ventes'!$F$26="",'Brouillard ventes'!$J$26="À crédit",'Brouillard ventes'!$J$26=""),"",Paramètres!$B$7) | H43: =IF(OR('Brouillard ventes'!$F$26="",'Brouillard ventes'!$J$26="À crédit",'Brouillard ventes'!$J$26=""),"",IF('Brouillard ventes'!$C$26="","CD001",'Brouillard ventes'!$C$26)) | K43: =IF(OR('Brouillard ventes'!$F$26="",'Brouillard ventes'!$J$26="À crédit",'Brouillard ventes'!$J$26=""),"",Paramètres!$B$11) | L43: 0 | M43: =IF(OR('Brouillard ventes'!$F$26="",'Brouillard ventes'!$J$26="À crédit",'Brouillard ventes'!$J$26=""),0,'Brouillard ventes'!$I$26)
A44: 1 | B44: =IF(OR('Brouillard ventes'!$F$27="",'Brouillard ventes'!$J$27="À crédit",'Brouillard ventes'!$J$27=""),"","EC"&TEXT(ROW('Brouillard ventes'!$F$27)-5,"00000")) | C44: =IF(OR('Brouillard ventes'!$F$27="",'Brouillard ventes'!$J$27="À crédit",'Brouillard ventes'!$J$27=""),"",YEAR('Brouillard ventes'!$A$27)*10000+MONTH('Brouillard ventes'!$A$27)*100+DAY('Brouillard ventes'!$A$27)) | D44: =IF(OR('Brouillard ventes'!$F$27="",'Brouillard ventes'!$J$27="À crédit",'Brouillard ventes'!$J$27=""),"",'Brouillard ventes'!$B$27) | E44: =IF(OR('Brouillard ventes'!$F$27="",'Brouillard ventes'!$J$27="À crédit",'Brouillard ventes'!$J$27=""),"","REGL "&LEFT('Brouillard ventes'!$D$27,25)) | F44: =IF(OR('Brouillard ventes'!$F$27="",'Brouillard ventes'!$J$27="À crédit",'Brouillard ventes'!$J$27=""),"",IF('Brouillard ventes'!$J$27="Espèces","04001","02001")) | G44: =IF(OR('Brouillard ventes'!$F$27="",'Brouillard ventes'!$J$27="À crédit",'Brouillard ventes'!$J$27=""),"",IF('Brouillard ventes'!$J$27="Espèces","53000","51220")) | K44: =IF(OR('Brouillard ventes'!$F$27="",'Brouillard ventes'!$J$27="À crédit",'Brouillard ventes'!$J$27=""),"",Paramètres!$B$11) | L44: =IF(OR('Brouillard ventes'!$F$27="",'Brouillard ventes'!$J$27="À crédit",'Brouillard ventes'!$J$27=""),0,'Brouillard ventes'!$I$27) | M44: 0
A45: 1 | B45: =IF(OR('Brouillard ventes'!$F$27="",'Brouillard ventes'!$J$27="À crédit",'Brouillard ventes'!$J$27=""),"","EC"&TEXT(ROW('Brouillard ventes'!$F$27)-5,"00000")) | C45: =IF(OR('Brouillard ventes'!$F$27="",'Brouillard ventes'!$J$27="À crédit",'Brouillard ventes'!$J$27=""),"",YEAR('Brouillard ventes'!$A$27)*10000+MONTH('Brouillard ventes'!$A$27)*100+DAY('Brouillard ventes'!$A$27)) | D45: =IF(OR('Brouillard ventes'!$F$27="",'Brouillard ventes'!$J$27="À crédit",'Brouillard ventes'!$J$27=""),"",'Brouillard ventes'!$B$27) | E45: =IF(OR('Brouillard ventes'!$F$27="",'Brouillard ventes'!$J$27="À crédit",'Brouillard ventes'!$J$27=""),"","REGL "&LEFT('Brouillard ventes'!$D$27,25)) | F45: =IF(OR('Brouillard ventes'!$F$27="",'Brouillard ventes'!$J$27="À crédit",'Brouillard ventes'!$J$27=""),"",IF('Brouillard ventes'!$J$27="Espèces","04001","02001")) | G45: =IF(OR('Brouillard ventes'!$F$27="",'Brouillard ventes'!$J$27="À crédit",'Brouillard ventes'!$J$27=""),"",Paramètres!$B$7) | H45: =IF(OR('Brouillard ventes'!$F$27="",'Brouillard ventes'!$J$27="À crédit",'Brouillard ventes'!$J$27=""),"",IF('Brouillard ventes'!$C$27="","CD001",'Brouillard ventes'!$C$27)) | K45: =IF(OR('Brouillard ventes'!$F$27="",'Brouillard ventes'!$J$27="À crédit",'Brouillard ventes'!$J$27=""),"",Paramètres!$B$11) | L45: 0 | M45: =IF(OR('Brouillard ventes'!$F$27="",'Brouillard ventes'!$J$27="À crédit",'Brouillard ventes'!$J$27=""),0,'Brouillard ventes'!$I$27)
A46: 1 | B46: =IF(OR('Brouillard ventes'!$F$28="",'Brouillard ventes'!$J$28="À crédit",'Brouillard ventes'!$J$28=""),"","EC"&TEXT(ROW('Brouillard ventes'!$F$28)-5,"00000")) | C46: =IF(OR('Brouillard ventes'!$F$28="",'Brouillard ventes'!$J$28="À crédit",'Brouillard ventes'!$J$28=""),"",YEAR('Brouillard ventes'!$A$28)*10000+MONTH('Brouillard ventes'!$A$28)*100+DAY('Brouillard ventes'!$A$28)) | D46: =IF(OR('Brouillard ventes'!$F$28="",'Brouillard ventes'!$J$28="À crédit",'Brouillard ventes'!$J$28=""),"",'Brouillard ventes'!$B$28) | E46: =IF(OR('Brouillard ventes'!$F$28="",'Brouillard ventes'!$J$28="À crédit",'Brouillard ventes'!$J$28=""),"","REGL "&LEFT('Brouillard ventes'!$D$28,25)) | F46: =IF(OR('Brouillard ventes'!$F$28="",'Brouillard ventes'!$J$28="À crédit",'Brouillard ventes'!$J$28=""),"",IF('Brouillard ventes'!$J$28="Espèces","04001","02001")) | G46: =IF(OR('Brouillard ventes'!$F$28="",'Brouillard ventes'!$J$28="À crédit",'Brouillard ventes'!$J$28=""),"",IF('Brouillard ventes'!$J$28="Espèces","53000","51220")) | K46: =IF(OR('Brouillard ventes'!$F$28="",'Brouillard ventes'!$J$28="À crédit",'Brouillard ventes'!$J$28=""),"",Paramètres!$B$11) | L46: =IF(OR('Brouillard ventes'!$F$28="",'Brouillard ventes'!$J$28="À crédit",'Brouillard ventes'!$J$28=""),0,'Brouillard ventes'!$I$28) | M46: 0
A47: 1 | B47: =IF(OR('Brouillard ventes'!$F$28="",'Brouillard ventes'!$J$28="À crédit",'Brouillard ventes'!$J$28=""),"","EC"&TEXT(ROW('Brouillard ventes'!$F$28)-5,"00000")) | C47: =IF(OR('Brouillard ventes'!$F$28="",'Brouillard ventes'!$J$28="À crédit",'Brouillard ventes'!$J$28=""),"",YEAR('Brouillard ventes'!$A$28)*10000+MONTH('Brouillard ventes'!$A$28)*100+DAY('Brouillard ventes'!$A$28)) | D47: =IF(OR('Brouillard ventes'!$F$28="",'Brouillard ventes'!$J$28="À crédit",'Brouillard ventes'!$J$28=""),"",'Brouillard ventes'!$B$28) | E47: =IF(OR('Brouillard ventes'!$F$28="",'Brouillard ventes'!$J$28="À crédit",'Brouillard ventes'!$J$28=""),"","REGL "&LEFT('Brouillard ventes'!$D$28,25)) | F47: =IF(OR('Brouillard ventes'!$F$28="",'Brouillard ventes'!$J$28="À crédit",'Brouillard ventes'!$J$28=""),"",IF('Brouillard ventes'!$J$28="Espèces","04001","02001")) | G47: =IF(OR('Brouillard ventes'!$F$28="",'Brouillard ventes'!$J$28="À crédit",'Brouillard ventes'!$J$28=""),"",Paramètres!$B$7) | H47: =IF(OR('Brouillard ventes'!$F$28="",'Brouillard ventes'!$J$28="À crédit",'Brouillard ventes'!$J$28=""),"",IF('Brouillard ventes'!$C$28="","CD001",'Brouillard ventes'!$C$28)) | K47: =IF(OR('Brouillard ventes'!$F$28="",'Brouillard ventes'!$J$28="À crédit",'Brouillard ventes'!$J$28=""),"",Paramètres!$B$11) | L47: 0 | M47: =IF(OR('Brouillard ventes'!$F$28="",'Brouillard ventes'!$J$28="À crédit",'Brouillard ventes'!$J$28=""),0,'Brouillard ventes'!$I$28)
A48: 1 | B48: =IF(OR('Brouillard ventes'!$F$29="",'Brouillard ventes'!$J$29="À crédit",'Brouillard ventes'!$J$29=""),"","EC"&TEXT(ROW('Brouillard ventes'!$F$29)-5,"00000")) | C48: =IF(OR('Brouillard ventes'!$F$29="",'Brouillard ventes'!$J$29="À crédit",'Brouillard ventes'!$J$29=""),"",YEAR('Brouillard ventes'!$A$29)*10000+MONTH('Brouillard ventes'!$A$29)*100+DAY('Brouillard ventes'!$A$29)) | D48: =IF(OR('Brouillard ventes'!$F$29="",'Brouillard ventes'!$J$29="À crédit",'Brouillard ventes'!$J$29=""),"",'Brouillard ventes'!$B$29) | E48: =IF(OR('Brouillard ventes'!$F$29="",'Brouillard ventes'!$J$29="À crédit",'Brouillard ventes'!$J$29=""),"","REGL "&LEFT('Brouillard ventes'!$D$29,25)) | F48: =IF(OR('Brouillard ventes'!$F$29="",'Brouillard ventes'!$J$29="À crédit",'Brouillard ventes'!$J$29=""),"",IF('Brouillard ventes'!$J$29="Espèces","04001","02001")) | G48: =IF(OR('Brouillard ventes'!$F$29="",'Brouillard ventes'!$J$29="À crédit",'Brouillard ventes'!$J$29=""),"",IF('Brouillard ventes'!$J$29="Espèces","53000","51220")) | K48: =IF(OR('Brouillard ventes'!$F$29="",'Brouillard ventes'!$J$29="À crédit",'Brouillard ventes'!$J$29=""),"",Paramètres!$B$11) | L48: =IF(OR('Brouillard ventes'!$F$29="",'Brouillard ventes'!$J$29="À crédit",'Brouillard ventes'!$J$29=""),0,'Brouillard ventes'!$I$29) | M48: 0
A49: 1 | B49: =IF(OR('Brouillard ventes'!$F$29="",'Brouillard ventes'!$J$29="À crédit",'Brouillard ventes'!$J$29=""),"","EC"&TEXT(ROW('Brouillard ventes'!$F$29)-5,"00000")) | C49: =IF(OR('Brouillard ventes'!$F$29="",'Brouillard ventes'!$J$29="À crédit",'Brouillard ventes'!$J$29=""),"",YEAR('Brouillard ventes'!$A$29)*10000+MONTH('Brouillard ventes'!$A$29)*100+DAY('Brouillard ventes'!$A$29)) | D49: =IF(OR('Brouillard ventes'!$F$29="",'Brouillard ventes'!$J$29="À crédit",'Brouillard ventes'!$J$29=""),"",'Brouillard ventes'!$B$29) | E49: =IF(OR('Brouillard ventes'!$F$29="",'Brouillard ventes'!$J$29="À crédit",'Brouillard ventes'!$J$29=""),"","REGL "&LEFT('Brouillard ventes'!$D$29,25)) | F49: =IF(OR('Brouillard ventes'!$F$29="",'Brouillard ventes'!$J$29="À crédit",'Brouillard ventes'!$J$29=""),"",IF('Brouillard ventes'!$J$29="Espèces","04001","02001")) | G49: =IF(OR('Brouillard ventes'!$F$29="",'Brouillard ventes'!$J$29="À crédit",'Brouillard ventes'!$J$29=""),"",Paramètres!$B$7) | H49: =IF(OR('Brouillard ventes'!$F$29="",'Brouillard ventes'!$J$29="À crédit",'Brouillard ventes'!$J$29=""),"",IF('Brouillard ventes'!$C$29="","CD001",'Brouillard ventes'!$C$29)) | K49: =IF(OR('Brouillard ventes'!$F$29="",'Brouillard ventes'!$J$29="À crédit",'Brouillard ventes'!$J$29=""),"",Paramètres!$B$11) | L49: 0 | M49: =IF(OR('Brouillard ventes'!$F$29="",'Brouillard ventes'!$J$29="À crédit",'Brouillard ventes'!$J$29=""),0,'Brouillard ventes'!$I$29)
A50: 1 | B50: =IF(OR('Brouillard ventes'!$F$30="",'Brouillard ventes'!$J$30="À crédit",'Brouillard ventes'!$J$30=""),"","EC"&TEXT(ROW('Brouillard ventes'!$F$30)-5,"00000")) | C50: =IF(OR('Brouillard ventes'!$F$30="",'Brouillard ventes'!$J$30="À crédit",'Brouillard ventes'!$J$30=""),"",YEAR('Brouillard ventes'!$A$30)*10000+MONTH('Brouillard ventes'!$A$30)*100+DAY('Brouillard ventes'!$A$30)) | D50: =IF(OR('Brouillard ventes'!$F$30="",'Brouillard ventes'!$J$30="À crédit",'Brouillard ventes'!$J$30=""),"",'Brouillard ventes'!$B$30) | E50: =IF(OR('Brouillard ventes'!$F$30="",'Brouillard ventes'!$J$30="À crédit",'Brouillard ventes'!$J$30=""),"","REGL "&LEFT('Brouillard ventes'!$D$30,25)) | F50: =IF(OR('Brouillard ventes'!$F$30="",'Brouillard ventes'!$J$30="À crédit",'Brouillard ventes'!$J$30=""),"",IF('Brouillard ventes'!$J$30="Espèces","04001","02001")) | G50: =IF(OR('Brouillard ventes'!$F$30="",'Brouillard ventes'!$J$30="À crédit",'Brouillard ventes'!$J$30=""),"",IF('Brouillard ventes'!$J$30="Espèces","53000","51220")) | K50: =IF(OR('Brouillard ventes'!$F$30="",'Brouillard ventes'!$J$30="À crédit",'Brouillard ventes'!$J$30=""),"",Paramètres!$B$11) | L50: =IF(OR('Brouillard ventes'!$F$30="",'Brouillard ventes'!$J$30="À crédit",'Brouillard ventes'!$J$30=""),0,'Brouillard ventes'!$I$30) | M50: 0
A51: 1 | B51: =IF(OR('Brouillard ventes'!$F$30="",'Brouillard ventes'!$J$30="À crédit",'Brouillard ventes'!$J$30=""),"","EC"&TEXT(ROW('Brouillard ventes'!$F$30)-5,"00000")) | C51: =IF(OR('Brouillard ventes'!$F$30="",'Brouillard ventes'!$J$30="À crédit",'Brouillard ventes'!$J$30=""),"",YEAR('Brouillard ventes'!$A$30)*10000+MONTH('Brouillard ventes'!$A$30)*100+DAY('Brouillard ventes'!$A$30)) | D51: =IF(OR('Brouillard ventes'!$F$30="",'Brouillard ventes'!$J$30="À crédit",'Brouillard ventes'!$J$30=""),"",'Brouillard ventes'!$B$30) | E51: =IF(OR('Brouillard ventes'!$F$30="",'Brouillard ventes'!$J$30="À crédit",'Brouillard ventes'!$J$30=""),"","REGL "&LEFT('Brouillard ventes'!$D$30,25)) | F51: =IF(OR('Brouillard ventes'!$F$30="",'Brouillard ventes'!$J$30="À crédit",'Brouillard ventes'!$J$30=""),"",IF('Brouillard ventes'!$J$30="Espèces","04001","02001")) | G51: =IF(OR('Brouillard ventes'!$F$30="",'Brouillard ventes'!$J$30="À crédit",'Brouillard ventes'!$J$30=""),"",Paramètres!$B$7) | H51: =IF(OR('Brouillard ventes'!$F$30="",'Brouillard ventes'!$J$30="À crédit",'Brouillard ventes'!$J$30=""),"",IF('Brouillard ventes'!$C$30="","CD001",'Brouillard ventes'!$C$30)) | K51: =IF(OR('Brouillard ventes'!$F$30="",'Brouillard ventes'!$J$30="À crédit",'Brouillard ventes'!$J$30=""),"",Paramètres!$B$11) | L51: 0 | M51: =IF(OR('Brouillard ventes'!$F$30="",'Brouillard ventes'!$J$30="À crédit",'Brouillard ventes'!$J$30=""),0,'Brouillard ventes'!$I$30)
A52: 1 | B52: =IF(OR('Brouillard ventes'!$F$31="",'Brouillard ventes'!$J$31="À crédit",'Brouillard ventes'!$J$31=""),"","EC"&TEXT(ROW('Brouillard ventes'!$F$31)-5,"00000")) | C52: =IF(OR('Brouillard ventes'!$F$31="",'Brouillard ventes'!$J$31="À crédit",'Brouillard ventes'!$J$31=""),"",YEAR('Brouillard ventes'!$A$31)*10000+MONTH('Brouillard ventes'!$A$31)*100+DAY('Brouillard ventes'!$A$31)) | D52: =IF(OR('Brouillard ventes'!$F$31="",'Brouillard ventes'!$J$31="À crédit",'Brouillard ventes'!$J$31=""),"",'Brouillard ventes'!$B$31) | E52: =IF(OR('Brouillard ventes'!$F$31="",'Brouillard ventes'!$J$31="À crédit",'Brouillard ventes'!$J$31=""),"","REGL "&LEFT('Brouillard ventes'!$D$31,25)) | F52: =IF(OR('Brouillard ventes'!$F$31="",'Brouillard ventes'!$J$31="À crédit",'Brouillard ventes'!$J$31=""),"",IF('Brouillard ventes'!$J$31="Espèces","04001","02001")) | G52: =IF(OR('Brouillard ventes'!$F$31="",'Brouillard ventes'!$J$31="À crédit",'Brouillard ventes'!$J$31=""),"",IF('Brouillard ventes'!$J$31="Espèces","53000","51220")) | K52: =IF(OR('Brouillard ventes'!$F$31="",'Brouillard ventes'!$J$31="À crédit",'Brouillard ventes'!$J$31=""),"",Paramètres!$B$11) | L52: =IF(OR('Brouillard ventes'!$F$31="",'Brouillard ventes'!$J$31="À crédit",'Brouillard ventes'!$J$31=""),0,'Brouillard ventes'!$I$31) | M52: 0
A53: 1 | B53: =IF(OR('Brouillard ventes'!$F$31="",'Brouillard ventes'!$J$31="À crédit",'Brouillard ventes'!$J$31=""),"","EC"&TEXT(ROW('Brouillard ventes'!$F$31)-5,"00000")) | C53: =IF(OR('Brouillard ventes'!$F$31="",'Brouillard ventes'!$J$31="À crédit",'Brouillard ventes'!$J$31=""),"",YEAR('Brouillard ventes'!$A$31)*10000+MONTH('Brouillard ventes'!$A$31)*100+DAY('Brouillard ventes'!$A$31)) | D53: =IF(OR('Brouillard ventes'!$F$31="",'Brouillard ventes'!$J$31="À crédit",'Brouillard ventes'!$J$31=""),"",'Brouillard ventes'!$B$31) | E53: =IF(OR('Brouillard ventes'!$F$31="",'Brouillard ventes'!$J$31="À crédit",'Brouillard ventes'!$J$31=""),"","REGL "&LEFT('Brouillard ventes'!$D$31,25)) | F53: =IF(OR('Brouillard ventes'!$F$31="",'Brouillard ventes'!$J$31="À crédit",'Brouillard ventes'!$J$31=""),"",IF('Brouillard ventes'!$J$31="Espèces","04001","02001")) | G53: =IF(OR('Brouillard ventes'!$F$31="",'Brouillard ventes'!$J$31="À crédit",'Brouillard ventes'!$J$31=""),"",Paramètres!$B$7) | H53: =IF(OR('Brouillard ventes'!$F$31="",'Brouillard ventes'!$J$31="À crédit",'Brouillard ventes'!$J$31=""),"",IF('Brouillard ventes'!$C$31="","CD001",'Brouillard ventes'!$C$31)) | K53: =IF(OR('Brouillard ventes'!$F$31="",'Brouillard ventes'!$J$31="À crédit",'Brouillard ventes'!$J$31=""),"",Paramètres!$B$11) | L53: 0 | M53: =IF(OR('Brouillard ventes'!$F$31="",'Brouillard ventes'!$J$31="À crédit",'Brouillard ventes'!$J$31=""),0,'Brouillard ventes'!$I$31)
A54: 1 | B54: =IF(OR('Brouillard ventes'!$F$32="",'Brouillard ventes'!$J$32="À crédit",'Brouillard ventes'!$J$32=""),"","EC"&TEXT(ROW('Brouillard ventes'!$F$32)-5,"00000")) | C54: =IF(OR('Brouillard ventes'!$F$32="",'Brouillard ventes'!$J$32="À crédit",'Brouillard ventes'!$J$32=""),"",YEAR('Brouillard ventes'!$A$32)*10000+MONTH('Brouillard ventes'!$A$32)*100+DAY('Brouillard ventes'!$A$32)) | D54: =IF(OR('Brouillard ventes'!$F$32="",'Brouillard ventes'!$J$32="À crédit",'Brouillard ventes'!$J$32=""),"",'Brouillard ventes'!$B$32) | E54: =IF(OR('Brouillard ventes'!$F$32="",'Brouillard ventes'!$J$32="À crédit",'Brouillard ventes'!$J$32=""),"","REGL "&LEFT('Brouillard ventes'!$D$32,25)) | F54: =IF(OR('Brouillard ventes'!$F$32="",'Brouillard ventes'!$J$32="À crédit",'Brouillard ventes'!$J$32=""),"",IF('Brouillard ventes'!$J$32="Espèces","04001","02001")) | G54: =IF(OR('Brouillard ventes'!$F$32="",'Brouillard ventes'!$J$32="À crédit",'Brouillard ventes'!$J$32=""),"",IF('Brouillard ventes'!$J$32="Espèces","53000","51220")) | K54: =IF(OR('Brouillard ventes'!$F$32="",'Brouillard ventes'!$J$32="À crédit",'Brouillard ventes'!$J$32=""),"",Paramètres!$B$11) | L54: =IF(OR('Brouillard ventes'!$F$32="",'Brouillard ventes'!$J$32="À crédit",'Brouillard ventes'!$J$32=""),0,'Brouillard ventes'!$I$32) | M54: 0
A55: 1 | B55: =IF(OR('Brouillard ventes'!$F$32="",'Brouillard ventes'!$J$32="À crédit",'Brouillard ventes'!$J$32=""),"","EC"&TEXT(ROW('Brouillard ventes'!$F$32)-5,"00000")) | C55: =IF(OR('Brouillard ventes'!$F$32="",'Brouillard ventes'!$J$32="À crédit",'Brouillard ventes'!$J$32=""),"",YEAR('Brouillard ventes'!$A$32)*10000+MONTH('Brouillard ventes'!$A$32)*100+DAY('Brouillard ventes'!$A$32)) | D55: =IF(OR('Brouillard ventes'!$F$32="",'Brouillard ventes'!$J$32="À crédit",'Brouillard ventes'!$J$32=""),"",'Brouillard ventes'!$B$32) | E55: =IF(OR('Brouillard ventes'!$F$32="",'Brouillard ventes'!$J$32="À crédit",'Brouillard ventes'!$J$32=""),"","REGL "&LEFT('Brouillard ventes'!$D$32,25)) | F55: =IF(OR('Brouillard ventes'!$F$32="",'Brouillard ventes'!$J$32="À crédit",'Brouillard ventes'!$J$32=""),"",IF('Brouillard ventes'!$J$32="Espèces","04001","02001")) | G55: =IF(OR('Brouillard ventes'!$F$32="",'Brouillard ventes'!$J$32="À crédit",'Brouillard ventes'!$J$32=""),"",Paramètres!$B$7) | H55: =IF(OR('Brouillard ventes'!$F$32="",'Brouillard ventes'!$J$32="À crédit",'Brouillard ventes'!$J$32=""),"",IF('Brouillard ventes'!$C$32="","CD001",'Brouillard ventes'!$C$32)) | K55: =IF(OR('Brouillard ventes'!$F$32="",'Brouillard ventes'!$J$32="À crédit",'Brouillard ventes'!$J$32=""),"",Paramètres!$B$11) | L55: 0 | M55: =IF(OR('Brouillard ventes'!$F$32="",'Brouillard ventes'!$J$32="À crédit",'Brouillard ventes'!$J$32=""),0,'Brouillard ventes'!$I$32)
A56: 1 | B56: =IF(OR('Brouillard ventes'!$F$33="",'Brouillard ventes'!$J$33="À crédit",'Brouillard ventes'!$J$33=""),"","EC"&TEXT(ROW('Brouillard ventes'!$F$33)-5,"00000")) | C56: =IF(OR('Brouillard ventes'!$F$33="",'Brouillard ventes'!$J$33="À crédit",'Brouillard ventes'!$J$33=""),"",YEAR('Brouillard ventes'!$A$33)*10000+MONTH('Brouillard ventes'!$A$33)*100+DAY('Brouillard ventes'!$A$33)) | D56: =IF(OR('Brouillard ventes'!$F$33="",'Brouillard ventes'!$J$33="À crédit",'Brouillard ventes'!$J$33=""),"",'Brouillard ventes'!$B$33) | E56: =IF(OR('Brouillard ventes'!$F$33="",'Brouillard ventes'!$J$33="À crédit",'Brouillard ventes'!$J$33=""),"","REGL "&LEFT('Brouillard ventes'!$D$33,25)) | F56: =IF(OR('Brouillard ventes'!$F$33="",'Brouillard ventes'!$J$33="À crédit",'Brouillard ventes'!$J$33=""),"",IF('Brouillard ventes'!$J$33="Espèces","04001","02001")) | G56: =IF(OR('Brouillard ventes'!$F$33="",'Brouillard ventes'!$J$33="À crédit",'Brouillard ventes'!$J$33=""),"",IF('Brouillard ventes'!$J$33="Espèces","53000","51220")) | K56: =IF(OR('Brouillard ventes'!$F$33="",'Brouillard ventes'!$J$33="À crédit",'Brouillard ventes'!$J$33=""),"",Paramètres!$B$11) | L56: =IF(OR('Brouillard ventes'!$F$33="",'Brouillard ventes'!$J$33="À crédit",'Brouillard ventes'!$J$33=""),0,'Brouillard ventes'!$I$33) | M56: 0
A57: 1 | B57: =IF(OR('Brouillard ventes'!$F$33="",'Brouillard ventes'!$J$33="À crédit",'Brouillard ventes'!$J$33=""),"","EC"&TEXT(ROW('Brouillard ventes'!$F$33)-5,"00000")) | C57: =IF(OR('Brouillard ventes'!$F$33="",'Brouillard ventes'!$J$33="À crédit",'Brouillard ventes'!$J$33=""),"",YEAR('Brouillard ventes'!$A$33)*10000+MONTH('Brouillard ventes'!$A$33)*100+DAY('Brouillard ventes'!$A$33)) | D57: =IF(OR('Brouillard ventes'!$F$33="",'Brouillard ventes'!$J$33="À crédit",'Brouillard ventes'!$J$33=""),"",'Brouillard ventes'!$B$33) | E57: =IF(OR('Brouillard ventes'!$F$33="",'Brouillard ventes'!$J$33="À crédit",'Brouillard ventes'!$J$33=""),"","REGL "&LEFT('Brouillard ventes'!$D$33,25)) | F57: =IF(OR('Brouillard ventes'!$F$33="",'Brouillard ventes'!$J$33="À crédit",'Brouillard ventes'!$J$33=""),"",IF('Brouillard ventes'!$J$33="Espèces","04001","02001")) | G57: =IF(OR('Brouillard ventes'!$F$33="",'Brouillard ventes'!$J$33="À crédit",'Brouillard ventes'!$J$33=""),"",Paramètres!$B$7) | H57: =IF(OR('Brouillard ventes'!$F$33="",'Brouillard ventes'!$J$33="À crédit",'Brouillard ventes'!$J$33=""),"",IF('Brouillard ventes'!$C$33="","CD001",'Brouillard ventes'!$C$33)) | K57: =IF(OR('Brouillard ventes'!$F$33="",'Brouillard ventes'!$J$33="À crédit",'Brouillard ventes'!$J$33=""),"",Paramètres!$B$11) | L57: 0 | M57: =IF(OR('Brouillard ventes'!$F$33="",'Brouillard ventes'!$J$33="À crédit",'Brouillard ventes'!$J$33=""),0,'Brouillard ventes'!$I$33)
A58: 1 | B58: =IF(OR('Brouillard ventes'!$F$34="",'Brouillard ventes'!$J$34="À crédit",'Brouillard ventes'!$J$34=""),"","EC"&TEXT(ROW('Brouillard ventes'!$F$34)-5,"00000")) | C58: =IF(OR('Brouillard ventes'!$F$34="",'Brouillard ventes'!$J$34="À crédit",'Brouillard ventes'!$J$34=""),"",YEAR('Brouillard ventes'!$A$34)*10000+MONTH('Brouillard ventes'!$A$34)*100+DAY('Brouillard ventes'!$A$34)) | D58: =IF(OR('Brouillard ventes'!$F$34="",'Brouillard ventes'!$J$34="À crédit",'Brouillard ventes'!$J$34=""),"",'Brouillard ventes'!$B$34) | E58: =IF(OR('Brouillard ventes'!$F$34="",'Brouillard ventes'!$J$34="À crédit",'Brouillard ventes'!$J$34=""),"","REGL "&LEFT('Brouillard ventes'!$D$34,25)) | F58: =IF(OR('Brouillard ventes'!$F$34="",'Brouillard ventes'!$J$34="À crédit",'Brouillard ventes'!$J$34=""),"",IF('Brouillard ventes'!$J$34="Espèces","04001","02001")) | G58: =IF(OR('Brouillard ventes'!$F$34="",'Brouillard ventes'!$J$34="À crédit",'Brouillard ventes'!$J$34=""),"",IF('Brouillard ventes'!$J$34="Espèces","53000","51220")) | K58: =IF(OR('Brouillard ventes'!$F$34="",'Brouillard ventes'!$J$34="À crédit",'Brouillard ventes'!$J$34=""),"",Paramètres!$B$11) | L58: =IF(OR('Brouillard ventes'!$F$34="",'Brouillard ventes'!$J$34="À crédit",'Brouillard ventes'!$J$34=""),0,'Brouillard ventes'!$I$34) | M58: 0
A59: 1 | B59: =IF(OR('Brouillard ventes'!$F$34="",'Brouillard ventes'!$J$34="À crédit",'Brouillard ventes'!$J$34=""),"","EC"&TEXT(ROW('Brouillard ventes'!$F$34)-5,"00000")) | C59: =IF(OR('Brouillard ventes'!$F$34="",'Brouillard ventes'!$J$34="À crédit",'Brouillard ventes'!$J$34=""),"",YEAR('Brouillard ventes'!$A$34)*10000+MONTH('Brouillard ventes'!$A$34)*100+DAY('Brouillard ventes'!$A$34)) | D59: =IF(OR('Brouillard ventes'!$F$34="",'Brouillard ventes'!$J$34="À crédit",'Brouillard ventes'!$J$34=""),"",'Brouillard ventes'!$B$34) | E59: =IF(OR('Brouillard ventes'!$F$34="",'Brouillard ventes'!$J$34="À crédit",'Brouillard ventes'!$J$34=""),"","REGL "&LEFT('Brouillard ventes'!$D$34,25)) | F59: =IF(OR('Brouillard ventes'!$F$34="",'Brouillard ventes'!$J$34="À crédit",'Brouillard ventes'!$J$34=""),"",IF('Brouillard ventes'!$J$34="Espèces","04001","02001")) | G59: =IF(OR('Brouillard ventes'!$F$34="",'Brouillard ventes'!$J$34="À crédit",'Brouillard ventes'!$J$34=""),"",Paramètres!$B$7) | H59: =IF(OR('Brouillard ventes'!$F$34="",'Brouillard ventes'!$J$34="À crédit",'Brouillard ventes'!$J$34=""),"",IF('Brouillard ventes'!$C$34="","CD001",'Brouillard ventes'!$C$34)) | K59: =IF(OR('Brouillard ventes'!$F$34="",'Brouillard ventes'!$J$34="À crédit",'Brouillard ventes'!$J$34=""),"",Paramètres!$B$11) | L59: 0 | M59: =IF(OR('Brouillard ventes'!$F$34="",'Brouillard ventes'!$J$34="À crédit",'Brouillard ventes'!$J$34=""),0,'Brouillard ventes'!$I$34)
A60: 1 | B60: =IF(OR('Brouillard ventes'!$F$35="",'Brouillard ventes'!$J$35="À crédit",'Brouillard ventes'!$J$35=""),"","EC"&TEXT(ROW('Brouillard ventes'!$F$35)-5,"00000")) | C60: =IF(OR('Brouillard ventes'!$F$35="",'Brouillard ventes'!$J$35="À crédit",'Brouillard ventes'!$J$35=""),"",YEAR('Brouillard ventes'!$A$35)*10000+MONTH('Brouillard ventes'!$A$35)*100+DAY('Brouillard ventes'!$A$35)) | D60: =IF(OR('Brouillard ventes'!$F$35="",'Brouillard ventes'!$J$35="À crédit",'Brouillard ventes'!$J$35=""),"",'Brouillard ventes'!$B$35) | E60: =IF(OR('Brouillard ventes'!$F$35="",'Brouillard ventes'!$J$35="À crédit",'Brouillard ventes'!$J$35=""),"","REGL "&LEFT('Brouillard ventes'!$D$35,25)) | F60: =IF(OR('Brouillard ventes'!$F$35="",'Brouillard ventes'!$J$35="À crédit",'Brouillard ventes'!$J$35=""),"",IF('Brouillard ventes'!$J$35="Espèces","04001","02001")) | G60: =IF(OR('Brouillard ventes'!$F$35="",'Brouillard ventes'!$J$35="À crédit",'Brouillard ventes'!$J$35=""),"",IF('Brouillard ventes'!$J$35="Espèces","53000","51220")) | K60: =IF(OR('Brouillard ventes'!$F$35="",'Brouillard ventes'!$J$35="À crédit",'Brouillard ventes'!$J$35=""),"",Paramètres!$B$11) | L60: =IF(OR('Brouillard ventes'!$F$35="",'Brouillard ventes'!$J$35="À crédit",'Brouillard ventes'!$J$35=""),0,'Brouillard ventes'!$I$35) | M60: 0
A61: 1 | B61: =IF(OR('Brouillard ventes'!$F$35="",'Brouillard ventes'!$J$35="À crédit",'Brouillard ventes'!$J$35=""),"","EC"&TEXT(ROW('Brouillard ventes'!$F$35)-5,"00000")) | C61: =IF(OR('Brouillard ventes'!$F$35="",'Brouillard ventes'!$J$35="À crédit",'Brouillard ventes'!$J$35=""),"",YEAR('Brouillard ventes'!$A$35)*10000+MONTH('Brouillard ventes'!$A$35)*100+DAY('Brouillard ventes'!$A$35)) | D61: =IF(OR('Brouillard ventes'!$F$35="",'Brouillard ventes'!$J$35="À crédit",'Brouillard ventes'!$J$35=""),"",'Brouillard ventes'!$B$35) | E61: =IF(OR('Brouillard ventes'!$F$35="",'Brouillard ventes'!$J$35="À crédit",'Brouillard ventes'!$J$35=""),"","REGL "&LEFT('Brouillard ventes'!$D$35,25)) | F61: =IF(OR('Brouillard ventes'!$F$35="",'Brouillard ventes'!$J$35="À crédit",'Brouillard ventes'!$J$35=""),"",IF('Brouillard ventes'!$J$35="Espèces","04001","02001")) | G61: =IF(OR('Brouillard ventes'!$F$35="",'Brouillard ventes'!$J$35="À crédit",'Brouillard ventes'!$J$35=""),"",Paramètres!$B$7) | H61: =IF(OR('Brouillard ventes'!$F$35="",'Brouillard ventes'!$J$35="À crédit",'Brouillard ventes'!$J$35=""),"",IF('Brouillard ventes'!$C$35="","CD001",'Brouillard ventes'!$C$35)) | K61: =IF(OR('Brouillard ventes'!$F$35="",'Brouillard ventes'!$J$35="À crédit",'Brouillard ventes'!$J$35=""),"",Paramètres!$B$11) | L61: 0 | M61: =IF(OR('Brouillard ventes'!$F$35="",'Brouillard ventes'!$J$35="À crédit",'Brouillard ventes'!$J$35=""),0,'Brouillard ventes'!$I$35)
A62: 1 | B62: =IF(OR('Brouillard ventes'!$F$36="",'Brouillard ventes'!$J$36="À crédit",'Brouillard ventes'!$J$36=""),"","EC"&TEXT(ROW('Brouillard ventes'!$F$36)-5,"00000")) | C62: =IF(OR('Brouillard ventes'!$F$36="",'Brouillard ventes'!$J$36="À crédit",'Brouillard ventes'!$J$36=""),"",YEAR('Brouillard ventes'!$A$36)*10000+MONTH('Brouillard ventes'!$A$36)*100+DAY('Brouillard ventes'!$A$36)) | D62: =IF(OR('Brouillard ventes'!$F$36="",'Brouillard ventes'!$J$36="À crédit",'Brouillard ventes'!$J$36=""),"",'Brouillard ventes'!$B$36) | E62: =IF(OR('Brouillard ventes'!$F$36="",'Brouillard ventes'!$J$36="À crédit",'Brouillard ventes'!$J$36=""),"","REGL "&LEFT('Brouillard ventes'!$D$36,25)) | F62: =IF(OR('Brouillard ventes'!$F$36="",'Brouillard ventes'!$J$36="À crédit",'Brouillard ventes'!$J$36=""),"",IF('Brouillard ventes'!$J$36="Espèces","04001","02001")) | G62: =IF(OR('Brouillard ventes'!$F$36="",'Brouillard ventes'!$J$36="À crédit",'Brouillard ventes'!$J$36=""),"",IF('Brouillard ventes'!$J$36="Espèces","53000","51220")) | K62: =IF(OR('Brouillard ventes'!$F$36="",'Brouillard ventes'!$J$36="À crédit",'Brouillard ventes'!$J$36=""),"",Paramètres!$B$11) | L62: =IF(OR('Brouillard ventes'!$F$36="",'Brouillard ventes'!$J$36="À crédit",'Brouillard ventes'!$J$36=""),0,'Brouillard ventes'!$I$36) | M62: 0
A63: 1 | B63: =IF(OR('Brouillard ventes'!$F$36="",'Brouillard ventes'!$J$36="À crédit",'Brouillard ventes'!$J$36=""),"","EC"&TEXT(ROW('Brouillard ventes'!$F$36)-5,"00000")) | C63: =IF(OR('Brouillard ventes'!$F$36="",'Brouillard ventes'!$J$36="À crédit",'Brouillard ventes'!$J$36=""),"",YEAR('Brouillard ventes'!$A$36)*10000+MONTH('Brouillard ventes'!$A$36)*100+DAY('Brouillard ventes'!$A$36)) | D63: =IF(OR('Brouillard ventes'!$F$36="",'Brouillard ventes'!$J$36="À crédit",'Brouillard ventes'!$J$36=""),"",'Brouillard ventes'!$B$36) | E63: =IF(OR('Brouillard ventes'!$F$36="",'Brouillard ventes'!$J$36="À crédit",'Brouillard ventes'!$J$36=""),"","REGL "&LEFT('Brouillard ventes'!$D$36,25)) | F63: =IF(OR('Brouillard ventes'!$F$36="",'Brouillard ventes'!$J$36="À crédit",'Brouillard ventes'!$J$36=""),"",IF('Brouillard ventes'!$J$36="Espèces","04001","02001")) | G63: =IF(OR('Brouillard ventes'!$F$36="",'Brouillard ventes'!$J$36="À crédit",'Brouillard ventes'!$J$36=""),"",Paramètres!$B$7) | H63: =IF(OR('Brouillard ventes'!$F$36="",'Brouillard ventes'!$J$36="À crédit",'Brouillard ventes'!$J$36=""),"",IF('Brouillard ventes'!$C$36="","CD001",'Brouillard ventes'!$C$36)) | K63: =IF(OR('Brouillard ventes'!$F$36="",'Brouillard ventes'!$J$36="À crédit",'Brouillard ventes'!$J$36=""),"",Paramètres!$B$11) | L63: 0 | M63: =IF(OR('Brouillard ventes'!$F$36="",'Brouillard ventes'!$J$36="À crédit",'Brouillard ventes'!$J$36=""),0,'Brouillard ventes'!$I$36)
A64: 1 | B64: =IF(OR('Brouillard ventes'!$F$37="",'Brouillard ventes'!$J$37="À crédit",'Brouillard ventes'!$J$37=""),"","EC"&TEXT(ROW('Brouillard ventes'!$F$37)-5,"00000")) | C64: =IF(OR('Brouillard ventes'!$F$37="",'Brouillard ventes'!$J$37="À crédit",'Brouillard ventes'!$J$37=""),"",YEAR('Brouillard ventes'!$A$37)*10000+MONTH('Brouillard ventes'!$A$37)*100+DAY('Brouillard ventes'!$A$37)) | D64: =IF(OR('Brouillard ventes'!$F$37="",'Brouillard ventes'!$J$37="À crédit",'Brouillard ventes'!$J$37=""),"",'Brouillard ventes'!$B$37) | E64: =IF(OR('Brouillard ventes'!$F$37="",'Brouillard ventes'!$J$37="À crédit",'Brouillard ventes'!$J$37=""),"","REGL "&LEFT('Brouillard ventes'!$D$37,25)) | F64: =IF(OR('Brouillard ventes'!$F$37="",'Brouillard ventes'!$J$37="À crédit",'Brouillard ventes'!$J$37=""),"",IF('Brouillard ventes'!$J$37="Espèces","04001","02001")) | G64: =IF(OR('Brouillard ventes'!$F$37="",'Brouillard ventes'!$J$37="À crédit",'Brouillard ventes'!$J$37=""),"",IF('Brouillard ventes'!$J$37="Espèces","53000","51220")) | K64: =IF(OR('Brouillard ventes'!$F$37="",'Brouillard ventes'!$J$37="À crédit",'Brouillard ventes'!$J$37=""),"",Paramètres!$B$11) | L64: =IF(OR('Brouillard ventes'!$F$37="",'Brouillard ventes'!$J$37="À crédit",'Brouillard ventes'!$J$37=""),0,'Brouillard ventes'!$I$37) | M64: 0
A65: 1 | B65: =IF(OR('Brouillard ventes'!$F$37="",'Brouillard ventes'!$J$37="À crédit",'Brouillard ventes'!$J$37=""),"","EC"&TEXT(ROW('Brouillard ventes'!$F$37)-5,"00000")) | C65: =IF(OR('Brouillard ventes'!$F$37="",'Brouillard ventes'!$J$37="À crédit",'Brouillard ventes'!$J$37=""),"",YEAR('Brouillard ventes'!$A$37)*10000+MONTH('Brouillard ventes'!$A$37)*100+DAY('Brouillard ventes'!$A$37)) | D65: =IF(OR('Brouillard ventes'!$F$37="",'Brouillard ventes'!$J$37="À crédit",'Brouillard ventes'!$J$37=""),"",'Brouillard ventes'!$B$37) | E65: =IF(OR('Brouillard ventes'!$F$37="",'Brouillard ventes'!$J$37="À crédit",'Brouillard ventes'!$J$37=""),"","REGL "&LEFT('Brouillard ventes'!$D$37,25)) | F65: =IF(OR('Brouillard ventes'!$F$37="",'Brouillard ventes'!$J$37="À crédit",'Brouillard ventes'!$J$37=""),"",IF('Brouillard ventes'!$J$37="Espèces","04001","02001")) | G65: =IF(OR('Brouillard ventes'!$F$37="",'Brouillard ventes'!$J$37="À crédit",'Brouillard ventes'!$J$37=""),"",Paramètres!$B$7) | H65: =IF(OR('Brouillard ventes'!$F$37="",'Brouillard ventes'!$J$37="À crédit",'Brouillard ventes'!$J$37=""),"",IF('Brouillard ventes'!$C$37="","CD001",'Brouillard ventes'!$C$37)) | K65: =IF(OR('Brouillard ventes'!$F$37="",'Brouillard ventes'!$J$37="À crédit",'Brouillard ventes'!$J$37=""),"",Paramètres!$B$11) | L65: 0 | M65: =IF(OR('Brouillard ventes'!$F$37="",'Brouillard ventes'!$J$37="À crédit",'Brouillard ventes'!$J$37=""),0,'Brouillard ventes'!$I$37)
A66: 1 | B66: =IF(OR('Brouillard ventes'!$F$38="",'Brouillard ventes'!$J$38="À crédit",'Brouillard ventes'!$J$38=""),"","EC"&TEXT(ROW('Brouillard ventes'!$F$38)-5,"00000")) | C66: =IF(OR('Brouillard ventes'!$F$38="",'Brouillard ventes'!$J$38="À crédit",'Brouillard ventes'!$J$38=""),"",YEAR('Brouillard ventes'!$A$38)*10000+MONTH('Brouillard ventes'!$A$38)*100+DAY('Brouillard ventes'!$A$38)) | D66: =IF(OR('Brouillard ventes'!$F$38="",'Brouillard ventes'!$J$38="À crédit",'Brouillard ventes'!$J$38=""),"",'Brouillard ventes'!$B$38) | E66: =IF(OR('Brouillard ventes'!$F$38="",'Brouillard ventes'!$J$38="À crédit",'Brouillard ventes'!$J$38=""),"","REGL "&LEFT('Brouillard ventes'!$D$38,25)) | F66: =IF(OR('Brouillard ventes'!$F$38="",'Brouillard ventes'!$J$38="À crédit",'Brouillard ventes'!$J$38=""),"",IF('Brouillard ventes'!$J$38="Espèces","04001","02001")) | G66: =IF(OR('Brouillard ventes'!$F$38="",'Brouillard ventes'!$J$38="À crédit",'Brouillard ventes'!$J$38=""),"",IF('Brouillard ventes'!$J$38="Espèces","53000","51220")) | K66: =IF(OR('Brouillard ventes'!$F$38="",'Brouillard ventes'!$J$38="À crédit",'Brouillard ventes'!$J$38=""),"",Paramètres!$B$11) | L66: =IF(OR('Brouillard ventes'!$F$38="",'Brouillard ventes'!$J$38="À crédit",'Brouillard ventes'!$J$38=""),0,'Brouillard ventes'!$I$38) | M66: 0
A67: 1 | B67: =IF(OR('Brouillard ventes'!$F$38="",'Brouillard ventes'!$J$38="À crédit",'Brouillard ventes'!$J$38=""),"","EC"&TEXT(ROW('Brouillard ventes'!$F$38)-5,"00000")) | C67: =IF(OR('Brouillard ventes'!$F$38="",'Brouillard ventes'!$J$38="À crédit",'Brouillard ventes'!$J$38=""),"",YEAR('Brouillard ventes'!$A$38)*10000+MONTH('Brouillard ventes'!$A$38)*100+DAY('Brouillard ventes'!$A$38)) | D67: =IF(OR('Brouillard ventes'!$F$38="",'Brouillard ventes'!$J$38="À crédit",'Brouillard ventes'!$J$38=""),"",'Brouillard ventes'!$B$38) | E67: =IF(OR('Brouillard ventes'!$F$38="",'Brouillard ventes'!$J$38="À crédit",'Brouillard ventes'!$J$38=""),"","REGL "&LEFT('Brouillard ventes'!$D$38,25)) | F67: =IF(OR('Brouillard ventes'!$F$38="",'Brouillard ventes'!$J$38="À crédit",'Brouillard ventes'!$J$38=""),"",IF('Brouillard ventes'!$J$38="Espèces","04001","02001")) | G67: =IF(OR('Brouillard ventes'!$F$38="",'Brouillard ventes'!$J$38="À crédit",'Brouillard ventes'!$J$38=""),"",Paramètres!$B$7) | H67: =IF(OR('Brouillard ventes'!$F$38="",'Brouillard ventes'!$J$38="À crédit",'Brouillard ventes'!$J$38=""),"",IF('Brouillard ventes'!$C$38="","CD001",'Brouillard ventes'!$C$38)) | K67: =IF(OR('Brouillard ventes'!$F$38="",'Brouillard ventes'!$J$38="À crédit",'Brouillard ventes'!$J$38=""),"",Paramètres!$B$11) | L67: 0 | M67: =IF(OR('Brouillard ventes'!$F$38="",'Brouillard ventes'!$J$38="À crédit",'Brouillard ventes'!$J$38=""),0,'Brouillard ventes'!$I$38)
A68: 1 | B68: =IF(OR('Brouillard ventes'!$F$39="",'Brouillard ventes'!$J$39="À crédit",'Brouillard ventes'!$J$39=""),"","EC"&TEXT(ROW('Brouillard ventes'!$F$39)-5,"00000")) | C68: =IF(OR('Brouillard ventes'!$F$39="",'Brouillard ventes'!$J$39="À crédit",'Brouillard ventes'!$J$39=""),"",YEAR('Brouillard ventes'!$A$39)*10000+MONTH('Brouillard ventes'!$A$39)*100+DAY('Brouillard ventes'!$A$39)) | D68: =IF(OR('Brouillard ventes'!$F$39="",'Brouillard ventes'!$J$39="À crédit",'Brouillard ventes'!$J$39=""),"",'Brouillard ventes'!$B$39) | E68: =IF(OR('Brouillard ventes'!$F$39="",'Brouillard ventes'!$J$39="À crédit",'Brouillard ventes'!$J$39=""),"","REGL "&LEFT('Brouillard ventes'!$D$39,25)) | F68: =IF(OR('Brouillard ventes'!$F$39="",'Brouillard ventes'!$J$39="À crédit",'Brouillard ventes'!$J$39=""),"",IF('Brouillard ventes'!$J$39="Espèces","04001","02001")) | G68: =IF(OR('Brouillard ventes'!$F$39="",'Brouillard ventes'!$J$39="À crédit",'Brouillard ventes'!$J$39=""),"",IF('Brouillard ventes'!$J$39="Espèces","53000","51220")) | K68: =IF(OR('Brouillard ventes'!$F$39="",'Brouillard ventes'!$J$39="À crédit",'Brouillard ventes'!$J$39=""),"",Paramètres!$B$11) | L68: =IF(OR('Brouillard ventes'!$F$39="",'Brouillard ventes'!$J$39="À crédit",'Brouillard ventes'!$J$39=""),0,'Brouillard ventes'!$I$39) | M68: 0
A69: 1 | B69: =IF(OR('Brouillard ventes'!$F$39="",'Brouillard ventes'!$J$39="À crédit",'Brouillard ventes'!$J$39=""),"","EC"&TEXT(ROW('Brouillard ventes'!$F$39)-5,"00000")) | C69: =IF(OR('Brouillard ventes'!$F$39="",'Brouillard ventes'!$J$39="À crédit",'Brouillard ventes'!$J$39=""),"",YEAR('Brouillard ventes'!$A$39)*10000+MONTH('Brouillard ventes'!$A$39)*100+DAY('Brouillard ventes'!$A$39)) | D69: =IF(OR('Brouillard ventes'!$F$39="",'Brouillard ventes'!$J$39="À crédit",'Brouillard ventes'!$J$39=""),"",'Brouillard ventes'!$B$39) | E69: =IF(OR('Brouillard ventes'!$F$39="",'Brouillard ventes'!$J$39="À crédit",'Brouillard ventes'!$J$39=""),"","REGL "&LEFT('Brouillard ventes'!$D$39,25)) | F69: =IF(OR('Brouillard ventes'!$F$39="",'Brouillard ventes'!$J$39="À crédit",'Brouillard ventes'!$J$39=""),"",IF('Brouillard ventes'!$J$39="Espèces","04001","02001")) | G69: =IF(OR('Brouillard ventes'!$F$39="",'Brouillard ventes'!$J$39="À crédit",'Brouillard ventes'!$J$39=""),"",Paramètres!$B$7) | H69: =IF(OR('Brouillard ventes'!$F$39="",'Brouillard ventes'!$J$39="À crédit",'Brouillard ventes'!$J$39=""),"",IF('Brouillard ventes'!$C$39="","CD001",'Brouillard ventes'!$C$39)) | K69: =IF(OR('Brouillard ventes'!$F$39="",'Brouillard ventes'!$J$39="À crédit",'Brouillard ventes'!$J$39=""),"",Paramètres!$B$11) | L69: 0 | M69: =IF(OR('Brouillard ventes'!$F$39="",'Brouillard ventes'!$J$39="À crédit",'Brouillard ventes'!$J$39=""),0,'Brouillard ventes'!$I$39)
A70: 1 | B70: =IF(OR('Brouillard ventes'!$F$40="",'Brouillard ventes'!$J$40="À crédit",'Brouillard ventes'!$J$40=""),"","EC"&TEXT(ROW('Brouillard ventes'!$F$40)-5,"00000")) | C70: =IF(OR('Brouillard ventes'!$F$40="",'Brouillard ventes'!$J$40="À crédit",'Brouillard ventes'!$J$40=""),"",YEAR('Brouillard ventes'!$A$40)*10000+MONTH('Brouillard ventes'!$A$40)*100+DAY('Brouillard ventes'!$A$40)) | D70: =IF(OR('Brouillard ventes'!$F$40="",'Brouillard ventes'!$J$40="À crédit",'Brouillard ventes'!$J$40=""),"",'Brouillard ventes'!$B$40) | E70: =IF(OR('Brouillard ventes'!$F$40="",'Brouillard ventes'!$J$40="À crédit",'Brouillard ventes'!$J$40=""),"","REGL "&LEFT('Brouillard ventes'!$D$40,25)) | F70: =IF(OR('Brouillard ventes'!$F$40="",'Brouillard ventes'!$J$40="À crédit",'Brouillard ventes'!$J$40=""),"",IF('Brouillard ventes'!$J$40="Espèces","04001","02001")) | G70: =IF(OR('Brouillard ventes'!$F$40="",'Brouillard ventes'!$J$40="À crédit",'Brouillard ventes'!$J$40=""),"",IF('Brouillard ventes'!$J$40="Espèces","53000","51220")) | K70: =IF(OR('Brouillard ventes'!$F$40="",'Brouillard ventes'!$J$40="À crédit",'Brouillard ventes'!$J$40=""),"",Paramètres!$B$11) | L70: =IF(OR('Brouillard ventes'!$F$40="",'Brouillard ventes'!$J$40="À crédit",'Brouillard ventes'!$J$40=""),0,'Brouillard ventes'!$I$40) | M70: 0
A71: 1 | B71: =IF(OR('Brouillard ventes'!$F$40="",'Brouillard ventes'!$J$40="À crédit",'Brouillard ventes'!$J$40=""),"","EC"&TEXT(ROW('Brouillard ventes'!$F$40)-5,"00000")) | C71: =IF(OR('Brouillard ventes'!$F$40="",'Brouillard ventes'!$J$40="À crédit",'Brouillard ventes'!$J$40=""),"",YEAR('Brouillard ventes'!$A$40)*10000+MONTH('Brouillard ventes'!$A$40)*100+DAY('Brouillard ventes'!$A$40)) | D71: =IF(OR('Brouillard ventes'!$F$40="",'Brouillard ventes'!$J$40="À crédit",'Brouillard ventes'!$J$40=""),"",'Brouillard ventes'!$B$40) | E71: =IF(OR('Brouillard ventes'!$F$40="",'Brouillard ventes'!$J$40="À crédit",'Brouillard ventes'!$J$40=""),"","REGL "&LEFT('Brouillard ventes'!$D$40,25)) | F71: =IF(OR('Brouillard ventes'!$F$40="",'Brouillard ventes'!$J$40="À crédit",'Brouillard ventes'!$J$40=""),"",IF('Brouillard ventes'!$J$40="Espèces","04001","02001")) | G71: =IF(OR('Brouillard ventes'!$F$40="",'Brouillard ventes'!$J$40="À crédit",'Brouillard ventes'!$J$40=""),"",Paramètres!$B$7) | H71: =IF(OR('Brouillard ventes'!$F$40="",'Brouillard ventes'!$J$40="À crédit",'Brouillard ventes'!$J$40=""),"",IF('Brouillard ventes'!$C$40="","CD001",'Brouillard ventes'!$C$40)) | K71: =IF(OR('Brouillard ventes'!$F$40="",'Brouillard ventes'!$J$40="À crédit",'Brouillard ventes'!$J$40=""),"",Paramètres!$B$11) | L71: 0 | M71: =IF(OR('Brouillard ventes'!$F$40="",'Brouillard ventes'!$J$40="À crédit",'Brouillard ventes'!$J$40=""),0,'Brouillard ventes'!$I$40)
A72: 1 | B72: =IF(OR('Brouillard ventes'!$F$41="",'Brouillard ventes'!$J$41="À crédit",'Brouillard ventes'!$J$41=""),"","EC"&TEXT(ROW('Brouillard ventes'!$F$41)-5,"00000")) | C72: =IF(OR('Brouillard ventes'!$F$41="",'Brouillard ventes'!$J$41="À crédit",'Brouillard ventes'!$J$41=""),"",YEAR('Brouillard ventes'!$A$41)*10000+MONTH('Brouillard ventes'!$A$41)*100+DAY('Brouillard ventes'!$A$41)) | D72: =IF(OR('Brouillard ventes'!$F$41="",'Brouillard ventes'!$J$41="À crédit",'Brouillard ventes'!$J$41=""),"",'Brouillard ventes'!$B$41) | E72: =IF(OR('Brouillard ventes'!$F$41="",'Brouillard ventes'!$J$41="À crédit",'Brouillard ventes'!$J$41=""),"","REGL "&LEFT('Brouillard ventes'!$D$41,25)) | F72: =IF(OR('Brouillard ventes'!$F$41="",'Brouillard ventes'!$J$41="À crédit",'Brouillard ventes'!$J$41=""),"",IF('Brouillard ventes'!$J$41="Espèces","04001","02001")) | G72: =IF(OR('Brouillard ventes'!$F$41="",'Brouillard ventes'!$J$41="À crédit",'Brouillard ventes'!$J$41=""),"",IF('Brouillard ventes'!$J$41="Espèces","53000","51220")) | K72: =IF(OR('Brouillard ventes'!$F$41="",'Brouillard ventes'!$J$41="À crédit",'Brouillard ventes'!$J$41=""),"",Paramètres!$B$11) | L72: =IF(OR('Brouillard ventes'!$F$41="",'Brouillard ventes'!$J$41="À crédit",'Brouillard ventes'!$J$41=""),0,'Brouillard ventes'!$I$41) | M72: 0
A73: 1 | B73: =IF(OR('Brouillard ventes'!$F$41="",'Brouillard ventes'!$J$41="À crédit",'Brouillard ventes'!$J$41=""),"","EC"&TEXT(ROW('Brouillard ventes'!$F$41)-5,"00000")) | C73: =IF(OR('Brouillard ventes'!$F$41="",'Brouillard ventes'!$J$41="À crédit",'Brouillard ventes'!$J$41=""),"",YEAR('Brouillard ventes'!$A$41)*10000+MONTH('Brouillard ventes'!$A$41)*100+DAY('Brouillard ventes'!$A$41)) | D73: =IF(OR('Brouillard ventes'!$F$41="",'Brouillard ventes'!$J$41="À crédit",'Brouillard ventes'!$J$41=""),"",'Brouillard ventes'!$B$41) | E73: =IF(OR('Brouillard ventes'!$F$41="",'Brouillard ventes'!$J$41="À crédit",'Brouillard ventes'!$J$41=""),"","REGL "&LEFT('Brouillard ventes'!$D$41,25)) | F73: =IF(OR('Brouillard ventes'!$F$41="",'Brouillard ventes'!$J$41="À crédit",'Brouillard ventes'!$J$41=""),"",IF('Brouillard ventes'!$J$41="Espèces","04001","02001")) | G73: =IF(OR('Brouillard ventes'!$F$41="",'Brouillard ventes'!$J$41="À crédit",'Brouillard ventes'!$J$41=""),"",Paramètres!$B$7) | H73: =IF(OR('Brouillard ventes'!$F$41="",'Brouillard ventes'!$J$41="À crédit",'Brouillard ventes'!$J$41=""),"",IF('Brouillard ventes'!$C$41="","CD001",'Brouillard ventes'!$C$41)) | K73: =IF(OR('Brouillard ventes'!$F$41="",'Brouillard ventes'!$J$41="À crédit",'Brouillard ventes'!$J$41=""),"",Paramètres!$B$11) | L73: 0 | M73: =IF(OR('Brouillard ventes'!$F$41="",'Brouillard ventes'!$J$41="À crédit",'Brouillard ventes'!$J$41=""),0,'Brouillard ventes'!$I$41)
A74: 1 | B74: =IF(OR('Brouillard ventes'!$F$42="",'Brouillard ventes'!$J$42="À crédit",'Brouillard ventes'!$J$42=""),"","EC"&TEXT(ROW('Brouillard ventes'!$F$42)-5,"00000")) | C74: =IF(OR('Brouillard ventes'!$F$42="",'Brouillard ventes'!$J$42="À crédit",'Brouillard ventes'!$J$42=""),"",YEAR('Brouillard ventes'!$A$42)*10000+MONTH('Brouillard ventes'!$A$42)*100+DAY('Brouillard ventes'!$A$42)) | D74: =IF(OR('Brouillard ventes'!$F$42="",'Brouillard ventes'!$J$42="À crédit",'Brouillard ventes'!$J$42=""),"",'Brouillard ventes'!$B$42) | E74: =IF(OR('Brouillard ventes'!$F$42="",'Brouillard ventes'!$J$42="À crédit",'Brouillard ventes'!$J$42=""),"","REGL "&LEFT('Brouillard ventes'!$D$42,25)) | F74: =IF(OR('Brouillard ventes'!$F$42="",'Brouillard ventes'!$J$42="À crédit",'Brouillard ventes'!$J$42=""),"",IF('Brouillard ventes'!$J$42="Espèces","04001","02001")) | G74: =IF(OR('Brouillard ventes'!$F$42="",'Brouillard ventes'!$J$42="À crédit",'Brouillard ventes'!$J$42=""),"",IF('Brouillard ventes'!$J$42="Espèces","53000","51220")) | K74: =IF(OR('Brouillard ventes'!$F$42="",'Brouillard ventes'!$J$42="À crédit",'Brouillard ventes'!$J$42=""),"",Paramètres!$B$11) | L74: =IF(OR('Brouillard ventes'!$F$42="",'Brouillard ventes'!$J$42="À crédit",'Brouillard ventes'!$J$42=""),0,'Brouillard ventes'!$I$42) | M74: 0
A75: 1 | B75: =IF(OR('Brouillard ventes'!$F$42="",'Brouillard ventes'!$J$42="À crédit",'Brouillard ventes'!$J$42=""),"","EC"&TEXT(ROW('Brouillard ventes'!$F$42)-5,"00000")) | C75: =IF(OR('Brouillard ventes'!$F$42="",'Brouillard ventes'!$J$42="À crédit",'Brouillard ventes'!$J$42=""),"",YEAR('Brouillard ventes'!$A$42)*10000+MONTH('Brouillard ventes'!$A$42)*100+DAY('Brouillard ventes'!$A$42)) | D75: =IF(OR('Brouillard ventes'!$F$42="",'Brouillard ventes'!$J$42="À crédit",'Brouillard ventes'!$J$42=""),"",'Brouillard ventes'!$B$42) | E75: =IF(OR('Brouillard ventes'!$F$42="",'Brouillard ventes'!$J$42="À crédit",'Brouillard ventes'!$J$42=""),"","REGL "&LEFT('Brouillard ventes'!$D$42,25)) | F75: =IF(OR('Brouillard ventes'!$F$42="",'Brouillard ventes'!$J$42="À crédit",'Brouillard ventes'!$J$42=""),"",IF('Brouillard ventes'!$J$42="Espèces","04001","02001")) | G75: =IF(OR('Brouillard ventes'!$F$42="",'Brouillard ventes'!$J$42="À crédit",'Brouillard ventes'!$J$42=""),"",Paramètres!$B$7) | H75: =IF(OR('Brouillard ventes'!$F$42="",'Brouillard ventes'!$J$42="À crédit",'Brouillard ventes'!$J$42=""),"",IF('Brouillard ventes'!$C$42="","CD001",'Brouillard ventes'!$C$42)) | K75: =IF(OR('Brouillard ventes'!$F$42="",'Brouillard ventes'!$J$42="À crédit",'Brouillard ventes'!$J$42=""),"",Paramètres!$B$11) | L75: 0 | M75: =IF(OR('Brouillard ventes'!$F$42="",'Brouillard ventes'!$J$42="À crédit",'Brouillard ventes'!$J$42=""),0,'Brouillard ventes'!$I$42)
A76: 1 | B76: =IF(OR('Brouillard ventes'!$F$43="",'Brouillard ventes'!$J$43="À crédit",'Brouillard ventes'!$J$43=""),"","EC"&TEXT(ROW('Brouillard ventes'!$F$43)-5,"00000")) | C76: =IF(OR('Brouillard ventes'!$F$43="",'Brouillard ventes'!$J$43="À crédit",'Brouillard ventes'!$J$43=""),"",YEAR('Brouillard ventes'!$A$43)*10000+MONTH('Brouillard ventes'!$A$43)*100+DAY('Brouillard ventes'!$A$43)) | D76: =IF(OR('Brouillard ventes'!$F$43="",'Brouillard ventes'!$J$43="À crédit",'Brouillard ventes'!$J$43=""),"",'Brouillard ventes'!$B$43) | E76: =IF(OR('Brouillard ventes'!$F$43="",'Brouillard ventes'!$J$43="À crédit",'Brouillard ventes'!$J$43=""),"","REGL "&LEFT('Brouillard ventes'!$D$43,25)) | F76: =IF(OR('Brouillard ventes'!$F$43="",'Brouillard ventes'!$J$43="À crédit",'Brouillard ventes'!$J$43=""),"",IF('Brouillard ventes'!$J$43="Espèces","04001","02001")) | G76: =IF(OR('Brouillard ventes'!$F$43="",'Brouillard ventes'!$J$43="À crédit",'Brouillard ventes'!$J$43=""),"",IF('Brouillard ventes'!$J$43="Espèces","53000","51220")) | K76: =IF(OR('Brouillard ventes'!$F$43="",'Brouillard ventes'!$J$43="À crédit",'Brouillard ventes'!$J$43=""),"",Paramètres!$B$11) | L76: =IF(OR('Brouillard ventes'!$F$43="",'Brouillard ventes'!$J$43="À crédit",'Brouillard ventes'!$J$43=""),0,'Brouillard ventes'!$I$43) | M76: 0
A77: 1 | B77: =IF(OR('Brouillard ventes'!$F$43="",'Brouillard ventes'!$J$43="À crédit",'Brouillard ventes'!$J$43=""),"","EC"&TEXT(ROW('Brouillard ventes'!$F$43)-5,"00000")) | C77: =IF(OR('Brouillard ventes'!$F$43="",'Brouillard ventes'!$J$43="À crédit",'Brouillard ventes'!$J$43=""),"",YEAR('Brouillard ventes'!$A$43)*10000+MONTH('Brouillard ventes'!$A$43)*100+DAY('Brouillard ventes'!$A$43)) | D77: =IF(OR('Brouillard ventes'!$F$43="",'Brouillard ventes'!$J$43="À crédit",'Brouillard ventes'!$J$43=""),"",'Brouillard ventes'!$B$43) | E77: =IF(OR('Brouillard ventes'!$F$43="",'Brouillard ventes'!$J$43="À crédit",'Brouillard ventes'!$J$43=""),"","REGL "&LEFT('Brouillard ventes'!$D$43,25)) | F77: =IF(OR('Brouillard ventes'!$F$43="",'Brouillard ventes'!$J$43="À crédit",'Brouillard ventes'!$J$43=""),"",IF('Brouillard ventes'!$J$43="Espèces","04001","02001")) | G77: =IF(OR('Brouillard ventes'!$F$43="",'Brouillard ventes'!$J$43="À crédit",'Brouillard ventes'!$J$43=""),"",Paramètres!$B$7) | H77: =IF(OR('Brouillard ventes'!$F$43="",'Brouillard ventes'!$J$43="À crédit",'Brouillard ventes'!$J$43=""),"",IF('Brouillard ventes'!$C$43="","CD001",'Brouillard ventes'!$C$43)) | K77: =IF(OR('Brouillard ventes'!$F$43="",'Brouillard ventes'!$J$43="À crédit",'Brouillard ventes'!$J$43=""),"",Paramètres!$B$11) | L77: 0 | M77: =IF(OR('Brouillard ventes'!$F$43="",'Brouillard ventes'!$J$43="À crédit",'Brouillard ventes'!$J$43=""),0,'Brouillard ventes'!$I$43)
A78: 1 | B78: =IF(OR('Brouillard ventes'!$F$44="",'Brouillard ventes'!$J$44="À crédit",'Brouillard ventes'!$J$44=""),"","EC"&TEXT(ROW('Brouillard ventes'!$F$44)-5,"00000")) | C78: =IF(OR('Brouillard ventes'!$F$44="",'Brouillard ventes'!$J$44="À crédit",'Brouillard ventes'!$J$44=""),"",YEAR('Brouillard ventes'!$A$44)*10000+MONTH('Brouillard ventes'!$A$44)*100+DAY('Brouillard ventes'!$A$44)) | D78: =IF(OR('Brouillard ventes'!$F$44="",'Brouillard ventes'!$J$44="À crédit",'Brouillard ventes'!$J$44=""),"",'Brouillard ventes'!$B$44) | E78: =IF(OR('Brouillard ventes'!$F$44="",'Brouillard ventes'!$J$44="À crédit",'Brouillard ventes'!$J$44=""),"","REGL "&LEFT('Brouillard ventes'!$D$44,25)) | F78: =IF(OR('Brouillard ventes'!$F$44="",'Brouillard ventes'!$J$44="À crédit",'Brouillard ventes'!$J$44=""),"",IF('Brouillard ventes'!$J$44="Espèces","04001","02001")) | G78: =IF(OR('Brouillard ventes'!$F$44="",'Brouillard ventes'!$J$44="À crédit",'Brouillard ventes'!$J$44=""),"",IF('Brouillard ventes'!$J$44="Espèces","53000","51220")) | K78: =IF(OR('Brouillard ventes'!$F$44="",'Brouillard ventes'!$J$44="À crédit",'Brouillard ventes'!$J$44=""),"",Paramètres!$B$11) | L78: =IF(OR('Brouillard ventes'!$F$44="",'Brouillard ventes'!$J$44="À crédit",'Brouillard ventes'!$J$44=""),0,'Brouillard ventes'!$I$44) | M78: 0
A79: 1 | B79: =IF(OR('Brouillard ventes'!$F$44="",'Brouillard ventes'!$J$44="À crédit",'Brouillard ventes'!$J$44=""),"","EC"&TEXT(ROW('Brouillard ventes'!$F$44)-5,"00000")) | C79: =IF(OR('Brouillard ventes'!$F$44="",'Brouillard ventes'!$J$44="À crédit",'Brouillard ventes'!$J$44=""),"",YEAR('Brouillard ventes'!$A$44)*10000+MONTH('Brouillard ventes'!$A$44)*100+DAY('Brouillard ventes'!$A$44)) | D79: =IF(OR('Brouillard ventes'!$F$44="",'Brouillard ventes'!$J$44="À crédit",'Brouillard ventes'!$J$44=""),"",'Brouillard ventes'!$B$44) | E79: =IF(OR('Brouillard ventes'!$F$44="",'Brouillard ventes'!$J$44="À crédit",'Brouillard ventes'!$J$44=""),"","REGL "&LEFT('Brouillard ventes'!$D$44,25)) | F79: =IF(OR('Brouillard ventes'!$F$44="",'Brouillard ventes'!$J$44="À crédit",'Brouillard ventes'!$J$44=""),"",IF('Brouillard ventes'!$J$44="Espèces","04001","02001")) | G79: =IF(OR('Brouillard ventes'!$F$44="",'Brouillard ventes'!$J$44="À crédit",'Brouillard ventes'!$J$44=""),"",Paramètres!$B$7) | H79: =IF(OR('Brouillard ventes'!$F$44="",'Brouillard ventes'!$J$44="À crédit",'Brouillard ventes'!$J$44=""),"",IF('Brouillard ventes'!$C$44="","CD001",'Brouillard ventes'!$C$44)) | K79: =IF(OR('Brouillard ventes'!$F$44="",'Brouillard ventes'!$J$44="À crédit",'Brouillard ventes'!$J$44=""),"",Paramètres!$B$11) | L79: 0 | M79: =IF(OR('Brouillard ventes'!$F$44="",'Brouillard ventes'!$J$44="À crédit",'Brouillard ventes'!$J$44=""),0,'Brouillard ventes'!$I$44)
A80: 1 | B80: =IF(OR('Brouillard ventes'!$F$45="",'Brouillard ventes'!$J$45="À crédit",'Brouillard ventes'!$J$45=""),"","EC"&TEXT(ROW('Brouillard ventes'!$F$45)-5,"00000")) | C80: =IF(OR('Brouillard ventes'!$F$45="",'Brouillard ventes'!$J$45="À crédit",'Brouillard ventes'!$J$45=""),"",YEAR('Brouillard ventes'!$A$45)*10000+MONTH('Brouillard ventes'!$A$45)*100+DAY('Brouillard ventes'!$A$45)) | D80: =IF(OR('Brouillard ventes'!$F$45="",'Brouillard ventes'!$J$45="À crédit",'Brouillard ventes'!$J$45=""),"",'Brouillard ventes'!$B$45) | E80: =IF(OR('Brouillard ventes'!$F$45="",'Brouillard ventes'!$J$45="À crédit",'Brouillard ventes'!$J$45=""),"","REGL "&LEFT('Brouillard ventes'!$D$45,25)) | F80: =IF(OR('Brouillard ventes'!$F$45="",'Brouillard ventes'!$J$45="À crédit",'Brouillard ventes'!$J$45=""),"",IF('Brouillard ventes'!$J$45="Espèces","04001","02001")) | G80: =IF(OR('Brouillard ventes'!$F$45="",'Brouillard ventes'!$J$45="À crédit",'Brouillard ventes'!$J$45=""),"",IF('Brouillard ventes'!$J$45="Espèces","53000","51220")) | K80: =IF(OR('Brouillard ventes'!$F$45="",'Brouillard ventes'!$J$45="À crédit",'Brouillard ventes'!$J$45=""),"",Paramètres!$B$11) | L80: =IF(OR('Brouillard ventes'!$F$45="",'Brouillard ventes'!$J$45="À crédit",'Brouillard ventes'!$J$45=""),0,'Brouillard ventes'!$I$45) | M80: 0
A81: 1 | B81: =IF(OR('Brouillard ventes'!$F$45="",'Brouillard ventes'!$J$45="À crédit",'Brouillard ventes'!$J$45=""),"","EC"&TEXT(ROW('Brouillard ventes'!$F$45)-5,"00000")) | C81: =IF(OR('Brouillard ventes'!$F$45="",'Brouillard ventes'!$J$45="À crédit",'Brouillard ventes'!$J$45=""),"",YEAR('Brouillard ventes'!$A$45)*10000+MONTH('Brouillard ventes'!$A$45)*100+DAY('Brouillard ventes'!$A$45)) | D81: =IF(OR('Brouillard ventes'!$F$45="",'Brouillard ventes'!$J$45="À crédit",'Brouillard ventes'!$J$45=""),"",'Brouillard ventes'!$B$45) | E81: =IF(OR('Brouillard ventes'!$F$45="",'Brouillard ventes'!$J$45="À crédit",'Brouillard ventes'!$J$45=""),"","REGL "&LEFT('Brouillard ventes'!$D$45,25)) | F81: =IF(OR('Brouillard ventes'!$F$45="",'Brouillard ventes'!$J$45="À crédit",'Brouillard ventes'!$J$45=""),"",IF('Brouillard ventes'!$J$45="Espèces","04001","02001")) | G81: =IF(OR('Brouillard ventes'!$F$45="",'Brouillard ventes'!$J$45="À crédit",'Brouillard ventes'!$J$45=""),"",Paramètres!$B$7) | H81: =IF(OR('Brouillard ventes'!$F$45="",'Brouillard ventes'!$J$45="À crédit",'Brouillard ventes'!$J$45=""),"",IF('Brouillard ventes'!$C$45="","CD001",'Brouillard ventes'!$C$45)) | K81: =IF(OR('Brouillard ventes'!$F$45="",'Brouillard ventes'!$J$45="À crédit",'Brouillard ventes'!$J$45=""),"",Paramètres!$B$11) | L81: 0 | M81: =IF(OR('Brouillard ventes'!$F$45="",'Brouillard ventes'!$J$45="À crédit",'Brouillard ventes'!$J$45=""),0,'Brouillard ventes'!$I$45)
A82: 1 | B82: =IF(OR('Brouillard ventes'!$F$46="",'Brouillard ventes'!$J$46="À crédit",'Brouillard ventes'!$J$46=""),"","EC"&TEXT(ROW('Brouillard ventes'!$F$46)-5,"00000")) | C82: =IF(OR('Brouillard ventes'!$F$46="",'Brouillard ventes'!$J$46="À crédit",'Brouillard ventes'!$J$46=""),"",YEAR('Brouillard ventes'!$A$46)*10000+MONTH('Brouillard ventes'!$A$46)*100+DAY('Brouillard ventes'!$A$46)) | D82: =IF(OR('Brouillard ventes'!$F$46="",'Brouillard ventes'!$J$46="À crédit",'Brouillard ventes'!$J$46=""),"",'Brouillard ventes'!$B$46) | E82: =IF(OR('Brouillard ventes'!$F$46="",'Brouillard ventes'!$J$46="À crédit",'Brouillard ventes'!$J$46=""),"","REGL "&LEFT('Brouillard ventes'!$D$46,25)) | F82: =IF(OR('Brouillard ventes'!$F$46="",'Brouillard ventes'!$J$46="À crédit",'Brouillard ventes'!$J$46=""),"",IF('Brouillard ventes'!$J$46="Espèces","04001","02001")) | G82: =IF(OR('Brouillard ventes'!$F$46="",'Brouillard ventes'!$J$46="À crédit",'Brouillard ventes'!$J$46=""),"",IF('Brouillard ventes'!$J$46="Espèces","53000","51220")) | K82: =IF(OR('Brouillard ventes'!$F$46="",'Brouillard ventes'!$J$46="À crédit",'Brouillard ventes'!$J$46=""),"",Paramètres!$B$11) | L82: =IF(OR('Brouillard ventes'!$F$46="",'Brouillard ventes'!$J$46="À crédit",'Brouillard ventes'!$J$46=""),0,'Brouillard ventes'!$I$46) | M82: 0
A83: 1 | B83: =IF(OR('Brouillard ventes'!$F$46="",'Brouillard ventes'!$J$46="À crédit",'Brouillard ventes'!$J$46=""),"","EC"&TEXT(ROW('Brouillard ventes'!$F$46)-5,"00000")) | C83: =IF(OR('Brouillard ventes'!$F$46="",'Brouillard ventes'!$J$46="À crédit",'Brouillard ventes'!$J$46=""),"",YEAR('Brouillard ventes'!$A$46)*10000+MONTH('Brouillard ventes'!$A$46)*100+DAY('Brouillard ventes'!$A$46)) | D83: =IF(OR('Brouillard ventes'!$F$46="",'Brouillard ventes'!$J$46="À crédit",'Brouillard ventes'!$J$46=""),"",'Brouillard ventes'!$B$46) | E83: =IF(OR('Brouillard ventes'!$F$46="",'Brouillard ventes'!$J$46="À crédit",'Brouillard ventes'!$J$46=""),"","REGL "&LEFT('Brouillard ventes'!$D$46,25)) | F83: =IF(OR('Brouillard ventes'!$F$46="",'Brouillard ventes'!$J$46="À crédit",'Brouillard ventes'!$J$46=""),"",IF('Brouillard ventes'!$J$46="Espèces","04001","02001")) | G83: =IF(OR('Brouillard ventes'!$F$46="",'Brouillard ventes'!$J$46="À crédit",'Brouillard ventes'!$J$46=""),"",Paramètres!$B$7) | H83: =IF(OR('Brouillard ventes'!$F$46="",'Brouillard ventes'!$J$46="À crédit",'Brouillard ventes'!$J$46=""),"",IF('Brouillard ventes'!$C$46="","CD001",'Brouillard ventes'!$C$46)) | K83: =IF(OR('Brouillard ventes'!$F$46="",'Brouillard ventes'!$J$46="À crédit",'Brouillard ventes'!$J$46=""),"",Paramètres!$B$11) | L83: 0 | M83: =IF(OR('Brouillard ventes'!$F$46="",'Brouillard ventes'!$J$46="À crédit",'Brouillard ventes'!$J$46=""),0,'Brouillard ventes'!$I$46)
A84: 1 | B84: =IF(OR('Brouillard ventes'!$F$47="",'Brouillard ventes'!$J$47="À crédit",'Brouillard ventes'!$J$47=""),"","EC"&TEXT(ROW('Brouillard ventes'!$F$47)-5,"00000")) | C84: =IF(OR('Brouillard ventes'!$F$47="",'Brouillard ventes'!$J$47="À crédit",'Brouillard ventes'!$J$47=""),"",YEAR('Brouillard ventes'!$A$47)*10000+MONTH('Brouillard ventes'!$A$47)*100+DAY('Brouillard ventes'!$A$47)) | D84: =IF(OR('Brouillard ventes'!$F$47="",'Brouillard ventes'!$J$47="À crédit",'Brouillard ventes'!$J$47=""),"",'Brouillard ventes'!$B$47) | E84: =IF(OR('Brouillard ventes'!$F$47="",'Brouillard ventes'!$J$47="À crédit",'Brouillard ventes'!$J$47=""),"","REGL "&LEFT('Brouillard ventes'!$D$47,25)) | F84: =IF(OR('Brouillard ventes'!$F$47="",'Brouillard ventes'!$J$47="À crédit",'Brouillard ventes'!$J$47=""),"",IF('Brouillard ventes'!$J$47="Espèces","04001","02001")) | G84: =IF(OR('Brouillard ventes'!$F$47="",'Brouillard ventes'!$J$47="À crédit",'Brouillard ventes'!$J$47=""),"",IF('Brouillard ventes'!$J$47="Espèces","53000","51220")) | K84: =IF(OR('Brouillard ventes'!$F$47="",'Brouillard ventes'!$J$47="À crédit",'Brouillard ventes'!$J$47=""),"",Paramètres!$B$11) | L84: =IF(OR('Brouillard ventes'!$F$47="",'Brouillard ventes'!$J$47="À crédit",'Brouillard ventes'!$J$47=""),0,'Brouillard ventes'!$I$47) | M84: 0
A85: 1 | B85: =IF(OR('Brouillard ventes'!$F$47="",'Brouillard ventes'!$J$47="À crédit",'Brouillard ventes'!$J$47=""),"","EC"&TEXT(ROW('Brouillard ventes'!$F$47)-5,"00000")) | C85: =IF(OR('Brouillard ventes'!$F$47="",'Brouillard ventes'!$J$47="À crédit",'Brouillard ventes'!$J$47=""),"",YEAR('Brouillard ventes'!$A$47)*10000+MONTH('Brouillard ventes'!$A$47)*100+DAY('Brouillard ventes'!$A$47)) | D85: =IF(OR('Brouillard ventes'!$F$47="",'Brouillard ventes'!$J$47="À crédit",'Brouillard ventes'!$J$47=""),"",'Brouillard ventes'!$B$47) | E85: =IF(OR('Brouillard ventes'!$F$47="",'Brouillard ventes'!$J$47="À crédit",'Brouillard ventes'!$J$47=""),"","REGL "&LEFT('Brouillard ventes'!$D$47,25)) | F85: =IF(OR('Brouillard ventes'!$F$47="",'Brouillard ventes'!$J$47="À crédit",'Brouillard ventes'!$J$47=""),"",IF('Brouillard ventes'!$J$47="Espèces","04001","02001")) | G85: =IF(OR('Brouillard ventes'!$F$47="",'Brouillard ventes'!$J$47="À crédit",'Brouillard ventes'!$J$47=""),"",Paramètres!$B$7) | H85: =IF(OR('Brouillard ventes'!$F$47="",'Brouillard ventes'!$J$47="À crédit",'Brouillard ventes'!$J$47=""),"",IF('Brouillard ventes'!$C$47="","CD001",'Brouillard ventes'!$C$47)) | K85: =IF(OR('Brouillard ventes'!$F$47="",'Brouillard ventes'!$J$47="À crédit",'Brouillard ventes'!$J$47=""),"",Paramètres!$B$11) | L85: 0 | M85: =IF(OR('Brouillard ventes'!$F$47="",'Brouillard ventes'!$J$47="À crédit",'Brouillard ventes'!$J$47=""),0,'Brouillard ventes'!$I$47)
A86: 1 | B86: =IF(OR('Brouillard ventes'!$F$48="",'Brouillard ventes'!$J$48="À crédit",'Brouillard ventes'!$J$48=""),"","EC"&TEXT(ROW('Brouillard ventes'!$F$48)-5,"00000")) | C86: =IF(OR('Brouillard ventes'!$F$48="",'Brouillard ventes'!$J$48="À crédit",'Brouillard ventes'!$J$48=""),"",YEAR('Brouillard ventes'!$A$48)*10000+MONTH('Brouillard ventes'!$A$48)*100+DAY('Brouillard ventes'!$A$48)) | D86: =IF(OR('Brouillard ventes'!$F$48="",'Brouillard ventes'!$J$48="À crédit",'Brouillard ventes'!$J$48=""),"",'Brouillard ventes'!$B$48) | E86: =IF(OR('Brouillard ventes'!$F$48="",'Brouillard ventes'!$J$48="À crédit",'Brouillard ventes'!$J$48=""),"","REGL "&LEFT('Brouillard ventes'!$D$48,25)) | F86: =IF(OR('Brouillard ventes'!$F$48="",'Brouillard ventes'!$J$48="À crédit",'Brouillard ventes'!$J$48=""),"",IF('Brouillard ventes'!$J$48="Espèces","04001","02001")) | G86: =IF(OR('Brouillard ventes'!$F$48="",'Brouillard ventes'!$J$48="À crédit",'Brouillard ventes'!$J$48=""),"",IF('Brouillard ventes'!$J$48="Espèces","53000","51220")) | K86: =IF(OR('Brouillard ventes'!$F$48="",'Brouillard ventes'!$J$48="À crédit",'Brouillard ventes'!$J$48=""),"",Paramètres!$B$11) | L86: =IF(OR('Brouillard ventes'!$F$48="",'Brouillard ventes'!$J$48="À crédit",'Brouillard ventes'!$J$48=""),0,'Brouillard ventes'!$I$48) | M86: 0
A87: 1 | B87: =IF(OR('Brouillard ventes'!$F$48="",'Brouillard ventes'!$J$48="À crédit",'Brouillard ventes'!$J$48=""),"","EC"&TEXT(ROW('Brouillard ventes'!$F$48)-5,"00000")) | C87: =IF(OR('Brouillard ventes'!$F$48="",'Brouillard ventes'!$J$48="À crédit",'Brouillard ventes'!$J$48=""),"",YEAR('Brouillard ventes'!$A$48)*10000+MONTH('Brouillard ventes'!$A$48)*100+DAY('Brouillard ventes'!$A$48)) | D87: =IF(OR('Brouillard ventes'!$F$48="",'Brouillard ventes'!$J$48="À crédit",'Brouillard ventes'!$J$48=""),"",'Brouillard ventes'!$B$48) | E87: =IF(OR('Brouillard ventes'!$F$48="",'Brouillard ventes'!$J$48="À crédit",'Brouillard ventes'!$J$48=""),"","REGL "&LEFT('Brouillard ventes'!$D$48,25)) | F87: =IF(OR('Brouillard ventes'!$F$48="",'Brouillard ventes'!$J$48="À crédit",'Brouillard ventes'!$J$48=""),"",IF('Brouillard ventes'!$J$48="Espèces","04001","02001")) | G87: =IF(OR('Brouillard ventes'!$F$48="",'Brouillard ventes'!$J$48="À crédit",'Brouillard ventes'!$J$48=""),"",Paramètres!$B$7) | H87: =IF(OR('Brouillard ventes'!$F$48="",'Brouillard ventes'!$J$48="À crédit",'Brouillard ventes'!$J$48=""),"",IF('Brouillard ventes'!$C$48="","CD001",'Brouillard ventes'!$C$48)) | K87: =IF(OR('Brouillard ventes'!$F$48="",'Brouillard ventes'!$J$48="À crédit",'Brouillard ventes'!$J$48=""),"",Paramètres!$B$11) | L87: 0 | M87: =IF(OR('Brouillard ventes'!$F$48="",'Brouillard ventes'!$J$48="À crédit",'Brouillard ventes'!$J$48=""),0,'Brouillard ventes'!$I$48)
A88: 1 | B88: =IF(OR('Brouillard ventes'!$F$49="",'Brouillard ventes'!$J$49="À crédit",'Brouillard ventes'!$J$49=""),"","EC"&TEXT(ROW('Brouillard ventes'!$F$49)-5,"00000")) | C88: =IF(OR('Brouillard ventes'!$F$49="",'Brouillard ventes'!$J$49="À crédit",'Brouillard ventes'!$J$49=""),"",YEAR('Brouillard ventes'!$A$49)*10000+MONTH('Brouillard ventes'!$A$49)*100+DAY('Brouillard ventes'!$A$49)) | D88: =IF(OR('Brouillard ventes'!$F$49="",'Brouillard ventes'!$J$49="À crédit",'Brouillard ventes'!$J$49=""),"",'Brouillard ventes'!$B$49) | E88: =IF(OR('Brouillard ventes'!$F$49="",'Brouillard ventes'!$J$49="À crédit",'Brouillard ventes'!$J$49=""),"","REGL "&LEFT('Brouillard ventes'!$D$49,25)) | F88: =IF(OR('Brouillard ventes'!$F$49="",'Brouillard ventes'!$J$49="À crédit",'Brouillard ventes'!$J$49=""),"",IF('Brouillard ventes'!$J$49="Espèces","04001","02001")) | G88: =IF(OR('Brouillard ventes'!$F$49="",'Brouillard ventes'!$J$49="À crédit",'Brouillard ventes'!$J$49=""),"",IF('Brouillard ventes'!$J$49="Espèces","53000","51220")) | K88: =IF(OR('Brouillard ventes'!$F$49="",'Brouillard ventes'!$J$49="À crédit",'Brouillard ventes'!$J$49=""),"",Paramètres!$B$11) | L88: =IF(OR('Brouillard ventes'!$F$49="",'Brouillard ventes'!$J$49="À crédit",'Brouillard ventes'!$J$49=""),0,'Brouillard ventes'!$I$49) | M88: 0
A89: 1 | B89: =IF(OR('Brouillard ventes'!$F$49="",'Brouillard ventes'!$J$49="À crédit",'Brouillard ventes'!$J$49=""),"","EC"&TEXT(ROW('Brouillard ventes'!$F$49)-5,"00000")) | C89: =IF(OR('Brouillard ventes'!$F$49="",'Brouillard ventes'!$J$49="À crédit",'Brouillard ventes'!$J$49=""),"",YEAR('Brouillard ventes'!$A$49)*10000+MONTH('Brouillard ventes'!$A$49)*100+DAY('Brouillard ventes'!$A$49)) | D89: =IF(OR('Brouillard ventes'!$F$49="",'Brouillard ventes'!$J$49="À crédit",'Brouillard ventes'!$J$49=""),"",'Brouillard ventes'!$B$49) | E89: =IF(OR('Brouillard ventes'!$F$49="",'Brouillard ventes'!$J$49="À crédit",'Brouillard ventes'!$J$49=""),"","REGL "&LEFT('Brouillard ventes'!$D$49,25)) | F89: =IF(OR('Brouillard ventes'!$F$49="",'Brouillard ventes'!$J$49="À crédit",'Brouillard ventes'!$J$49=""),"",IF('Brouillard ventes'!$J$49="Espèces","04001","02001")) | G89: =IF(OR('Brouillard ventes'!$F$49="",'Brouillard ventes'!$J$49="À crédit",'Brouillard ventes'!$J$49=""),"",Paramètres!$B$7) | H89: =IF(OR('Brouillard ventes'!$F$49="",'Brouillard ventes'!$J$49="À crédit",'Brouillard ventes'!$J$49=""),"",IF('Brouillard ventes'!$C$49="","CD001",'Brouillard ventes'!$C$49)) | K89: =IF(OR('Brouillard ventes'!$F$49="",'Brouillard ventes'!$J$49="À crédit",'Brouillard ventes'!$J$49=""),"",Paramètres!$B$11) | L89: 0 | M89: =IF(OR('Brouillard ventes'!$F$49="",'Brouillard ventes'!$J$49="À crédit",'Brouillard ventes'!$J$49=""),0,'Brouillard ventes'!$I$49)
A90: 1 | B90: =IF(OR('Brouillard ventes'!$F$50="",'Brouillard ventes'!$J$50="À crédit",'Brouillard ventes'!$J$50=""),"","EC"&TEXT(ROW('Brouillard ventes'!$F$50)-5,"00000")) | C90: =IF(OR('Brouillard ventes'!$F$50="",'Brouillard ventes'!$J$50="À crédit",'Brouillard ventes'!$J$50=""),"",YEAR('Brouillard ventes'!$A$50)*10000+MONTH('Brouillard ventes'!$A$50)*100+DAY('Brouillard ventes'!$A$50)) | D90: =IF(OR('Brouillard ventes'!$F$50="",'Brouillard ventes'!$J$50="À crédit",'Brouillard ventes'!$J$50=""),"",'Brouillard ventes'!$B$50) | E90: =IF(OR('Brouillard ventes'!$F$50="",'Brouillard ventes'!$J$50="À crédit",'Brouillard ventes'!$J$50=""),"","REGL "&LEFT('Brouillard ventes'!$D$50,25)) | F90: =IF(OR('Brouillard ventes'!$F$50="",'Brouillard ventes'!$J$50="À crédit",'Brouillard ventes'!$J$50=""),"",IF('Brouillard ventes'!$J$50="Espèces","04001","02001")) | G90: =IF(OR('Brouillard ventes'!$F$50="",'Brouillard ventes'!$J$50="À crédit",'Brouillard ventes'!$J$50=""),"",IF('Brouillard ventes'!$J$50="Espèces","53000","51220")) | K90: =IF(OR('Brouillard ventes'!$F$50="",'Brouillard ventes'!$J$50="À crédit",'Brouillard ventes'!$J$50=""),"",Paramètres!$B$11) | L90: =IF(OR('Brouillard ventes'!$F$50="",'Brouillard ventes'!$J$50="À crédit",'Brouillard ventes'!$J$50=""),0,'Brouillard ventes'!$I$50) | M90: 0
A91: 1 | B91: =IF(OR('Brouillard ventes'!$F$50="",'Brouillard ventes'!$J$50="À crédit",'Brouillard ventes'!$J$50=""),"","EC"&TEXT(ROW('Brouillard ventes'!$F$50)-5,"00000")) | C91: =IF(OR('Brouillard ventes'!$F$50="",'Brouillard ventes'!$J$50="À crédit",'Brouillard ventes'!$J$50=""),"",YEAR('Brouillard ventes'!$A$50)*10000+MONTH('Brouillard ventes'!$A$50)*100+DAY('Brouillard ventes'!$A$50)) | D91: =IF(OR('Brouillard ventes'!$F$50="",'Brouillard ventes'!$J$50="À crédit",'Brouillard ventes'!$J$50=""),"",'Brouillard ventes'!$B$50) | E91: =IF(OR('Brouillard ventes'!$F$50="",'Brouillard ventes'!$J$50="À crédit",'Brouillard ventes'!$J$50=""),"","REGL "&LEFT('Brouillard ventes'!$D$50,25)) | F91: =IF(OR('Brouillard ventes'!$F$50="",'Brouillard ventes'!$J$50="À crédit",'Brouillard ventes'!$J$50=""),"",IF('Brouillard ventes'!$J$50="Espèces","04001","02001")) | G91: =IF(OR('Brouillard ventes'!$F$50="",'Brouillard ventes'!$J$50="À crédit",'Brouillard ventes'!$J$50=""),"",Paramètres!$B$7) | H91: =IF(OR('Brouillard ventes'!$F$50="",'Brouillard ventes'!$J$50="À crédit",'Brouillard ventes'!$J$50=""),"",IF('Brouillard ventes'!$C$50="","CD001",'Brouillard ventes'!$C$50)) | K91: =IF(OR('Brouillard ventes'!$F$50="",'Brouillard ventes'!$J$50="À crédit",'Brouillard ventes'!$J$50=""),"",Paramètres!$B$11) | L91: 0 | M91: =IF(OR('Brouillard ventes'!$F$50="",'Brouillard ventes'!$J$50="À crédit",'Brouillard ventes'!$J$50=""),0,'Brouillard ventes'!$I$50)
A92: 1 | B92: =IF(OR('Brouillard ventes'!$F$51="",'Brouillard ventes'!$J$51="À crédit",'Brouillard ventes'!$J$51=""),"","EC"&TEXT(ROW('Brouillard ventes'!$F$51)-5,"00000")) | C92: =IF(OR('Brouillard ventes'!$F$51="",'Brouillard ventes'!$J$51="À crédit",'Brouillard ventes'!$J$51=""),"",YEAR('Brouillard ventes'!$A$51)*10000+MONTH('Brouillard ventes'!$A$51)*100+DAY('Brouillard ventes'!$A$51)) | D92: =IF(OR('Brouillard ventes'!$F$51="",'Brouillard ventes'!$J$51="À crédit",'Brouillard ventes'!$J$51=""),"",'Brouillard ventes'!$B$51) | E92: =IF(OR('Brouillard ventes'!$F$51="",'Brouillard ventes'!$J$51="À crédit",'Brouillard ventes'!$J$51=""),"","REGL "&LEFT('Brouillard ventes'!$D$51,25)) | F92: =IF(OR('Brouillard ventes'!$F$51="",'Brouillard ventes'!$J$51="À crédit",'Brouillard ventes'!$J$51=""),"",IF('Brouillard ventes'!$J$51="Espèces","04001","02001")) | G92: =IF(OR('Brouillard ventes'!$F$51="",'Brouillard ventes'!$J$51="À crédit",'Brouillard ventes'!$J$51=""),"",IF('Brouillard ventes'!$J$51="Espèces","53000","51220")) | K92: =IF(OR('Brouillard ventes'!$F$51="",'Brouillard ventes'!$J$51="À crédit",'Brouillard ventes'!$J$51=""),"",Paramètres!$B$11) | L92: =IF(OR('Brouillard ventes'!$F$51="",'Brouillard ventes'!$J$51="À crédit",'Brouillard ventes'!$J$51=""),0,'Brouillard ventes'!$I$51) | M92: 0
